Workbook
Name YearList: Lists!$A$1:$A$15
Name MonthList: Lists!$C$1:$C$12
Name ChannelList: OFFSET(Lists!$E$1,0,0,COUNTIF(Lists!$E$1:$E$40,"?*"),1)

Sheet Dashboard
B2: SCB Video Library
B3: =IF(Settings!$C$5="","","Last updated "&TEXT(Settings!$C$5,"d mmm yyyy h:mm AM/PM")&" · "&TODAY()-INT(Settings!$C$5)&" day(s) ago")
B4: =HYPERLINK("#Library!A1","Library") | C4: =HYPERLINK("#Queue!A1","Queue") | D4: =HYPERLINK("#Calendar!A1","Calendar") | E4: =HYPERLINK("#History!A1","History") | F4: =HYPERLINK("#Stats!A1","Stats") | G4: =HYPERLINK("#Channels!A1","Channels") | H4: =HYPERLINK("#Settings!A1","Settings")
B6: TOTAL VIDEOS | D6: WATCHED | F6: BACKLOG | H6: % WATCHED | J6: HOURS WATCHED | L6: HOURS REMAINING
B7: =Stats!C14 | D7: =Stats!D14 | F7: =Stats!E14+Stats!F14 | H7: =Stats!H14 | J7: =Stats!J14 | L7: =Stats!K14
B8: ="across "&6&" channels" | D8: ="of "&TEXT(Stats!C14-Stats!G14,"#,##0")&" tracked" | F8: =TEXT(Stats!E14,"#,##0")&" watch-later" | H8: =TEXT(Stats!L14,"0.0%")&" of runtime" | J8: ="of "&TEXT(Stats!I14,"#,##0")&" h total" | L8: ="≈ "&TEXT(Stats!K14/24,"#,##0")&" days of video"
B10: By channel
B11: Channel | E11: Videos | F11: Watched | G11: Backlog | H11: % Watched | I11: Hours left | J11: Latest upload | L11: Days since
B12: =Stats!B8 | E12: =Stats!C8 | F12: =Stats!D8 | G12: =Stats!E8+Stats!F8 | H12: =Stats!H8 | I12: =Stats!K8 | J12: =Stats!D20 | L12: =IF(J12="","",TODAY()-J12)
B13: =Stats!B9 | E13: =Stats!C9 | F13: =Stats!D9 | G13: =Stats!E9+Stats!F9 | H13: =Stats!H9 | I13: =Stats!K9 | J13: =Stats!D21 | L13: =IF(J13="","",TODAY()-J13)
B14: =Stats!B10 | E14: =Stats!C10 | F14: =Stats!D10 | G14: =Stats!E10+Stats!F10 | H14: =Stats!H10 | I14: =Stats!K10 | J14: =Stats!D22 | L14: =IF(J14="","",TODAY()-J14)
B15: =Stats!B11 | E15: =Stats!C11 | F15: =Stats!D11 | G15: =Stats!E11+Stats!F11 | H15: =Stats!H11 | I15: =Stats!K11 | J15: =Stats!D23 | L15: =IF(J15="","",TODAY()-J15)
B16: =Stats!B12 | E16: =Stats!C12 | F16: =Stats!D12 | G16: =Stats!E12+Stats!F12 | H16: =Stats!H12 | I16: =Stats!K12 | J16: =Stats!D24 | L16: =IF(J16="","",TODAY()-J16)
B17: =Stats!B13 | E17: =Stats!C13 | F17: =Stats!D13 | G17: =Stats!E13+Stats!F13 | H17: =Stats!H13 | I17: =Stats!K13 | J17: =Stats!D25 | L17: =IF(J17="","",TODAY()-J17)
B18: All channels | E18: =Stats!C14 | F18: =Stats!D14 | G18: =Stats!E14+Stats!F14 | H18: =Stats!H14 | I18: =Stats!K14
B36: Up next - oldest unwatched video in each channel
B37: Channel | E37: Video | L37: Length | M37: Published
B38: =Channels!$C$6 | E38: =IF($O38="","All caught up ✓",IF(INDEX(tblVideos[Video ID],$O38)="",INDEX(tblVideos[Title],$O38),HYPERLINK("https://www.youtube.com/watch?v="&INDEX(tblVideos[Video ID],$O38),INDEX(tblVideos[Title],$O38)))) | L38: =IF($O38="","",INDEX(tblVideos[Length],$O38)) | M38: =IF($O38="","",INDEX(tblVideos[Day],$O38)) | O38: =IF(_xlfn.MINIFS(tblVideos[Seq],tblVideos[Channel ID],Channels!$E$6,tblVideos[Status],"Unwatched")=0,"",MATCH(_xlfn.MINIFS(tblVideos[Seq],tblVideos[Channel ID],Channels!$E$6,tblVideos[Status],"Unwatched"),tblVideos[Seq],0))
B39: =Channels!$C$7 | E39: =IF($O39="","All caught up ✓",IF(INDEX(tblVideos[Video ID],$O39)="",INDEX(tblVideos[Title],$O39),HYPERLINK("https://www.youtube.com/watch?v="&INDEX(tblVideos[Video ID],$O39),INDEX(tblVideos[Title],$O39)))) | L39: =IF($O39="","",INDEX(tblVideos[Length],$O39)) | M39: =IF($O39="","",INDEX(tblVideos[Day],$O39)) | O39: =IF(_xlfn.MINIFS(tblVideos[Seq],tblVideos[Channel ID],Channels!$E$7,tblVideos[Status],"Unwatched")=0,"",MATCH(_xlfn.MINIFS(tblVideos[Seq],tblVideos[Channel ID],Channels!$E$7,tblVideos[Status],"Unwatched"),tblVideos[Seq],0))
B40: =Channels!$C$8 | E40: =IF($O40="","All caught up ✓",IF(INDEX(tblVideos[Video ID],$O40)="",INDEX(tblVideos[Title],$O40),HYPERLINK("https://www.youtube.com/watch?v="&INDEX(tblVideos[Video ID],$O40),INDEX(tblVideos[Title],$O40)))) | L40: =IF($O40="","",INDEX(tblVideos[Length],$O40)) | M40: =IF($O40="","",INDEX(tblVideos[Day],$O40)) | O40: =IF(_xlfn.MINIFS(tblVideos[Seq],tblVideos[Channel ID],Channels!$E$8,tblVideos[Status],"Unwatched")=0,"",MATCH(_xlfn.MINIFS(tblVideos[Seq],tblVideos[Channel ID],Channels!$E$8,tblVideos[Status],"Unwatched"),tblVideos[Seq],0))
B41: =Channels!$C$9 | E41: =IF($O41="","All caught up ✓",IF(INDEX(tblVideos[Video ID],$O41)="",INDEX(tblVideos[Title],$O41),HYPERLINK("https://www.youtube.com/watch?v="&INDEX(tblVideos[Video ID],$O41),INDEX(tblVideos[Title],$O41)))) | L41: =IF($O41="","",INDEX(tblVideos[Length],$O41)) | M41: =IF($O41="","",INDEX(tblVideos[Day],$O41)) | O41: =IF(_xlfn.MINIFS(tblVideos[Seq],tblVideos[Channel ID],Channels!$E$9,tblVideos[Status],"Unwatched")=0,"",MATCH(_xlfn.MINIFS(tblVideos[Seq],tblVideos[Channel ID],Channels!$E$9,tblVideos[Status],"Unwatched"),tblVideos[Seq],0))
B42: =Channels!$C$10 | E42: =IF($O42="","All caught up ✓",IF(INDEX(tblVideos[Video ID],$O42)="",INDEX(tblVideos[Title],$O42),HYPERLINK("https://www.youtube.com/watch?v="&INDEX(tblVideos[Video ID],$O42),INDEX(tblVideos[Title],$O42)))) | L42: =IF($O42="","",INDEX(tblVideos[Length],$O42)) | M42: =IF($O42="","",INDEX(tblVideos[Day],$O42)) | O42: =IF(_xlfn.MINIFS(tblVideos[Seq],tblVideos[Channel ID],Channels!$E$10,tblVideos[Status],"Unwatched")=0,"",MATCH(_xlfn.MINIFS(tblVideos[Seq],tblVideos[Channel ID],Channels!$E$10,tblVideos[Status],"Unwatched"),tblVideos[Seq],0))
B43: =Channels!$C$11 | E43: =IF($O43="","All caught up ✓",IF(INDEX(tblVideos[Video ID],$O43)="",INDEX(tblVideos[Title],$O43),HYPERLINK("https://www.youtube.com/watch?v="&INDEX(tblVideos[Video ID],$O43),INDEX(tblVideos[Title],$O43)))) | L43: =IF($O43="","",INDEX(tblVideos[Length],$O43)) | M43: =IF($O43="","",INDEX(tblVideos[Day],$O43)) | O43: =IF(_xlfn.MINIFS(tblVideos[Seq],tblVideos[Channel ID],Channels!$E$11,tblVideos[Status],"Unwatched")=0,"",MATCH(_xlfn.MINIFS(tblVideos[Seq],tblVideos[Channel ID],Channels!$E$11,tblVideos[Status],"Unwatched"),tblVideos[Seq],0))
B46: Newest uploads
B47: Published | D47: Channel | F47: Title | L47: Length | M47: Status
B48: =IF($O48="","",INDEX(tblVideos[Day],$O48)) | D48: =IF($O48="","",INDEX(tblVideos[Channel],$O48)) | F48: =IF($O48="","",IF(INDEX(tblVideos[Video ID],$O48)="",INDEX(tblVideos[Title],$O48),HYPERLINK("https://www.youtube.com/watch?v="&INDEX(tblVideos[Video ID],$O48),INDEX(tblVideos[Title],$O48)))) | L48: =IF($O48="","",INDEX(tblVideos[Length],$O48)) | M48: =IF($O48="","",INDEX(tblVideos[Status],$O48)) | O48: =IFERROR(MATCH(MAX(tblVideos[Seq])-0,tblVideos[Seq],0),"")
B49: =IF($O49="","",INDEX(tblVideos[Day],$O49)) | D49: =IF($O49="","",INDEX(tblVideos[Channel],$O49)) | F49: =IF($O49="","",IF(INDEX(tblVideos[Video ID],$O49)="",INDEX(tblVideos[Title],$O49),HYPERLINK("https://www.youtube.com/watch?v="&INDEX(tblVideos[Video ID],$O49),INDEX(tblVideos[Title],$O49)))) | L49: =IF($O49="","",INDEX(tblVideos[Length],$O49)) | M49: =IF($O49="","",INDEX(tblVideos[Status],$O49)) | O49: =IFERROR(MATCH(MAX(tblVideos[Seq])-1,tblVideos[Seq],0),"")
B50: =IF($O50="","",INDEX(tblVideos[Day],$O50)) | D50: =IF($O50="","",INDEX(tblVideos[Channel],$O50)) | F50: =IF($O50="","",IF(INDEX(tblVideos[Video ID],$O50)="",INDEX(tblVideos[Title],$O50),HYPERLINK("https://www.youtube.com/watch?v="&INDEX(tblVideos[Video ID],$O50),INDEX(tblVideos[Title],$O50)))) | L50: =IF($O50="","",INDEX(tblVideos[Length],$O50)) | M50: =IF($O50="","",INDEX(tblVideos[Status],$O50)) | O50: =IFERROR(MATCH(MAX(tblVideos[Seq])-2,tblVideos[Seq],0),"")
B51: =IF($O51="","",INDEX(tblVideos[Day],$O51)) | D51: =IF($O51="","",INDEX(tblVideos[Channel],$O51)) | F51: =IF($O51="","",IF(INDEX(tblVideos[Video ID],$O51)="",INDEX(tblVideos[Title],$O51),HYPERLINK("https://www.youtube.com/watch?v="&INDEX(tblVideos[Video ID],$O51),INDEX(tblVideos[Title],$O51)))) | L51: =IF($O51="","",INDEX(tblVideos[Length],$O51)) | M51: =IF($O51="","",INDEX(tblVideos[Status],$O51)) | O51: =IFERROR(MATCH(MAX(tblVideos[Seq])-3,tblVideos[Seq],0),"")
B52: =IF($O52="","",INDEX(tblVideos[Day],$O52)) | D52: =IF($O52="","",INDEX(tblVideos[Channel],$O52)) | F52: =IF($O52="","",IF(INDEX(tblVideos[Video ID],$O52)="",INDEX(tblVideos[Title],$O52),HYPERLINK("https://www.youtube.com/watch?v="&INDEX(tblVideos[Video ID],$O52),INDEX(tblVideos[Title],$O52)))) | L52: =IF($O52="","",INDEX(tblVideos[Length],$O52)) | M52: =IF($O52="","",INDEX(tblVideos[Status],$O52)) | O52: =IFERROR(MATCH(MAX(tblVideos[Seq])-4,tblVideos[Seq],0),"")
B53: =IF($O53="","",INDEX(tblVideos[Day],$O53)) | D53: =IF($O53="","",INDEX(tblVideos[Channel],$O53)) | F53: =IF($O53="","",IF(INDEX(tblVideos[Video ID],$O53)="",INDEX(tblVideos[Title],$O53),HYPERLINK("https://www.youtube.com/watch?v="&INDEX(tblVideos[Video ID],$O53),INDEX(tblVideos[Title],$O53)))) | L53: =IF($O53="","",INDEX(tblVideos[Length],$O53)) | M53: =IF($O53="","",INDEX(tblVideos[Status],$O53)) | O53: =IFERROR(MATCH(MAX(tblVideos[Seq])-5,tblVideos[Seq],0),"")
B54: =IF($O54="","",INDEX(tblVideos[Day],$O54)) | D54: =IF($O54="","",INDEX(tblVideos[Channel],$O54)) | F54: =IF($O54="","",IF(INDEX(tblVideos[Video ID],$O54)="",INDEX(tblVideos[Title],$O54),HYPERLINK("https://www.youtube.com/watch?v="&INDEX(tblVideos[Video ID],$O54),INDEX(tblVideos[Title],$O54)))) | L54: =IF($O54="","",INDEX(tblVideos[Length],$O54)) | M54: =IF($O54="","",INDEX(tblVideos[Status],$O54)) | O54: =IFERROR(MATCH(MAX(tblVideos[Seq])-6,tblVideos[Seq],0),"")
B55: =IF($O55="","",INDEX(tblVideos[Day],$O55)) | D55: =IF($O55="","",INDEX(tblVideos[Channel],$O55)) | F55: =IF($O55="","",IF(INDEX(tblVideos[Video ID],$O55)="",INDEX(tblVideos[Title],$O55),HYPERLINK("https://www.youtube.com/watch?v="&INDEX(tblVideos[Video ID],$O55),INDEX(tblVideos[Title],$O55)))) | L55: =IF($O55="","",INDEX(tblVideos[Length],$O55)) | M55: =IF($O55="","",INDEX(tblVideos[Status],$O55)) | O55: =IFERROR(MATCH(MAX(tblVideos[Seq])-7,tblVideos[Seq],0),"")
B56: =IF($O56="","",INDEX(tblVideos[Day],$O56)) | D56: =IF($O56="","",INDEX(tblVideos[Channel],$O56)) | F56: =IF($O56="","",IF(INDEX(tblVideos[Video ID],$O56)="",INDEX(tblVideos[Title],$O56),HYPERLINK("https://www.youtube.com/watch?v="&INDEX(tblVideos[Video ID],$O56),INDEX(tblVideos[Title],$O56)))) | L56: =IF($O56="","",INDEX(tblVideos[Length],$O56)) | M56: =IF($O56="","",INDEX(tblVideos[Status],$O56)) | O56: =IFERROR(MATCH(MAX(tblVideos[Seq])-8,tblVideos[Seq],0),"")
B57: =IF($O57="","",INDEX(tblVideos[Day],$O57)) | D57: =IF($O57="","",INDEX(tblVideos[Channel],$O57)) | F57: =IF($O57="","",IF(INDEX(tblVideos[Video ID],$O57)="",INDEX(tblVideos[Title],$O57),HYPERLINK("https://www.youtube.com/watch?v="&INDEX(tblVideos[Video ID],$O57),INDEX(tblVideos[Title],$O57)))) | L57: =IF($O57="","",INDEX(tblVideos[Length],$O57)) | M57: =IF($O57="","",INDEX(tblVideos[Status],$O57)) | O57: =IFERROR(MATCH(MAX(tblVideos[Seq])-9,tblVideos[Seq],0),"")

Sheet Library
A1: Video Library
A2: Slate columns come from YouTube and are refreshed by the updater. Teal columns are calculated. Gold columns (Mark, Watched On, Notes) are YOURS and are never overwritten.
A3: =HYPERLINK("#Dashboard!A1","◄ Dashboard")
A5: Open | B5: Status | C5: Mark | D5: Watched On | E5: Published | F5: Channel | G5: Title | H5: Length | I5: Views | J5: Likes | K5: Comments | L5: Notes | M5: Video ID | N5: Channel ID | O5: Published UTC | P5: Day | Q5: Seq | R5: Availability | S5: First Seen | T5: Last Seen | U5: Description | V5: Cal Key | W5: Queue Key
A6: =IF(M6="","",HYPERLINK("https://www.youtube.com/watch?v="&M6,"▶")) | B6: =IF(C6<>"",C6,IF(P6<=IFERROR(INDEX(tblChannels[Watched Through],MATCH(N6,tblChannels[Channel ID],0)),0),"Watched","Unwatched")) | E6: 46297.417 | F6: Popcorn Culture | G6: Top 100 TV Shows! | Popcorn Culture | H6: 0.077893519 | I6: 209 | J6: 16 | K6: 7 | N6: UCHfIbq9thHPC8yrKjAdJgDA | O6: 46297.583 | P6: 46297 | Q6: 3266 | R6: No Video ID yet | V6: =IF(AND(P6>=Calendar!$K$2,P6<EDATE(Calendar!$K$2,1),OR(Calendar!$K$4="*",N6=Calendar!$K$4)),P6*100+COUNTIFS($P$6:$P$3271,P6,$Q$6:$Q$3271,"<="&Q6,$N$6:$N$3271,Calendar!$K$4),"") | W6: =IF(AND(B6=Queue!$C$4,OR(Queue!$K$4="*",N6=Queue!$K$4)),Q6,"")
A7: =IF(M7="","",HYPERLINK("https://www.youtube.com/watch?v="&M7,"▶")) | B7: =IF(C7<>"",C7,IF(P7<=IFERROR(INDEX(tblChannels[Watched Through],MATCH(N7,tblChannels[Channel ID],0)),0),"Watched","Unwatched")) | E7: 46295.649 | F7: Super Carlin Brothers | G7: Slughorn’s SECRET Son Revealed | H7: 0.011087963 | I7: 62777 | J7: 1573 | K7: 250 | N7: UCKZo4N0lVPccBkSiuyVh4yg | O7: 46295.815 | P7: 46295 | Q7: 3265 | R7: No Video ID yet | V7: =IF(AND(P7>=Calendar!$K$2,P7<EDATE(Calendar!$K$2,1),OR(Calendar!$K$4="*",N7=Calendar!$K$4)),P7*100+COUNTIFS($P$6:$P$3271,P7,$Q$6:$Q$3271,"<="&Q7,$N$6:$N$3271,Calendar!$K$4),"") | W7: =IF(AND(B7=Queue!$C$4,OR(Queue!$K$4="*",N7=Queue!$K$4)),Q7,"")
A8: =IF(M8="","",HYPERLINK("https://www.youtube.com/watch?v="&M8,"▶")) | B8: =IF(C8<>"",C8,IF(P8<=IFERROR(INDEX(tblChannels[Watched Through],MATCH(N8,tblChannels[Channel ID],0)),0),"Watched","Unwatched")) | E8: 46292.417 | F8: Through The Griffin Door | G8: Chapter 15: The Unbreakable Vow | Half-Blood Prince | H8: 0.076793981 | I8: 41173 | J8: 692 | K8: 303 | N8: UCEscP6ETYXWSSvsNrDHekMQ | O8: 46292.583 | P8: 46292 | Q8: 3264 | R8: No Video ID yet | V8: =IF(AND(P8>=Calendar!$K$2,P8<EDATE(Calendar!$K$2,1),OR(Calendar!$K$4="*",N8=Calendar!$K$4)),P8*100+COUNTIFS($P$6:$P$3271,P8,$Q$6:$Q$3271,"<="&Q8,$N$6:$N$3271,Calendar!$K$4),"") | W8: =IF(AND(B8=Queue!$C$4,OR(Queue!$K$4="*",N8=Queue!$K$4)),Q8,"")
A9: =IF(M9="","",HYPERLINK("https://www.youtube.com/watch?v="&M9,"▶")) | B9: =IF(C9<>"",C9,IF(P9<=IFERROR(INDEX(tblChannels[Watched Through],MATCH(N9,tblChannels[Channel ID],0)),0),"Watched","Unwatched")) | E9: 46290.682 | F9: Super Carlin Brothers | G9: J vs Ben: How Well Do We Know The Boy Who Lived (MAX DIFFICULTY) | H9: 0.034791667 | I9: 102063 | J9: 1791 | K9: 297 | N9: UCKZo4N0lVPccBkSiuyVh4yg | O9: 46290.849 | P9: 46290 | Q9: 3263 | R9: No Video ID yet | V9: =IF(AND(P9>=Calendar!$K$2,P9<EDATE(Calendar!$K$2,1),OR(Calendar!$K$4="*",N9=Calendar!$K$4)),P9*100+COUNTIFS($P$6:$P$3271,P9,$Q$6:$Q$3271,"<="&Q9,$N$6:$N$3271,Calendar!$K$4),"") | W9: =IF(AND(B9=Queue!$C$4,OR(Queue!$K$4="*",N9=Queue!$K$4)),Q9,"")
A10: =IF(M10="","",HYPERLINK("https://www.youtube.com/watch?v="&M10,"▶")) | B10: =IF(C10<>"",C10,IF(P10<=IFERROR(INDEX(tblChannels[Watched Through],MATCH(N10,tblChannels[Channel ID],0)),0),"Watched","Unwatched")) | E10: 46290.417 | F10: Popcorn Culture | G10: Tour in a Podshell | Popcorn Culture | H10: 0.047337963 | I10: 3615 | J10: 90 | K10: 18 | N10: UCHfIbq9thHPC8yrKjAdJgDA | O10: 46290.583 | P10: 46290 | Q10: 3262 | R10: No Video ID yet | V10: =IF(AND(P10>=Calendar!$K$2,P10<EDATE(Calendar!$K$2,1),OR(Calendar!$K$4="*",N10=Calendar!$K$4)),P10*100+COUNTIFS($P$6:$P$3271,P10,$Q$6:$Q$3271,"<="&Q10,$N$6:$N$3271,Calendar!$K$4),"") | W10: =IF(AND(B10=Queue!$C$4,OR(Queue!$K$4="*",N10=Queue!$K$4)),Q10,"")
A11: =IF(M11="","",HYPERLINK("https://www.youtube.com/watch?v="&M11,"▶")) | B11: =IF(C11<>"",C11,IF(P11<=IFERROR(INDEX(tblChannels[Watched Through],MATCH(N11,tblChannels[Channel ID],0)),0),"Watched","Unwatched")) | E11: 46289.653 | F11: Popcorn Culture | G11: Mr. Ben's Worst Day Ever | Popcorn Culture | H11: 0.0026273148 | I11: 2235 | J11: 118 | K11: 27 | N11: UCHfIbq9thHPC8yrKjAdJgDA | O11: 46289.82 | P11: 46289 | Q11: 3261 | R11: No Video ID yet | V11: =IF(AND(P11>=Calendar!$K$2,P11<EDATE(Calendar!$K$2,1),OR(Calendar!$K$4="*",N11=Calendar!$K$4)),P11*100+COUNTIFS($P$6:$P$3271,P11,$Q$6:$Q$3271,"<="&Q11,$N$6:$N$3271,Calendar!$K$4),"") | W11: =IF(AND(B11=Queue!$C$4,OR(Queue!$K$4="*",N11=Queue!$K$4)),Q11,"")
A12: =IF(M12="","",HYPERLINK("https://www.youtube.com/watch?v="&M12,"▶")) | B12: =IF(C12<>"",C12,IF(P12<=IFERROR(INDEX(tblChannels[Watched Through],MATCH(N12,tblChannels[Channel ID],0)),0),"Watched","Unwatched")) | E12: 46288.674 | F12: Super Carlin Brothers | G12: Slughorn’s SECRET Role In Creating Voldemort | H12: 0.011018519 | I12: 188618 | J12: 3039 | K12: 280 | N12: UCKZo4N0lVPccBkSiuyVh4yg | O12: 46288.841 | P12: 46288 | Q12: 3260 | R12: No Video ID yet | V12: =IF(AND(P12>=Calendar!$K$2,P12<EDATE(Calendar!$K$2,1),OR(Calendar!$K$4="*",N12=Calendar!$K$4)),P12*100+COUNTIFS($P$6:$P$3271,P12,$Q$6:$Q$3271,"<="&Q12,$N$6:$N$3271,Calendar!$K$4),"") | W12: =IF(AND(B12=Queue!$C$4,OR(Queue!$K$4="*",N12=Queue!$K$4)),Q12,"")
A13: =IF(M13="","",HYPERLINK("https://www.youtube.com/watch?v="&M13,"▶")) | B13: =IF(C13<>"",C13,IF(P13<=IFERROR(INDEX(tblChannels[Watched Through],MATCH(N13,tblChannels[Channel ID],0)),0),"Watched","Unwatched")) | E13: 46285.417 | F13: Through The Griffin Door | G13: The Owlery Special Part 5! | H13: 0.054189815 | I13: 25554 | J13: 452 | K13: 122 | N13: UCEscP6ETYXWSSvsNrDHekMQ | O13: 46285.583 | P13: 46285 | Q13: 3259 | R13: No Video ID yet | V13: =IF(AND(P13>=Calendar!$K$2,P13<EDATE(Calendar!$K$2,1),OR(Calendar!$K$4="*",N13=Calendar!$K$4)),P13*100+COUNTIFS($P$6:$P$3271,P13,$Q$6:$Q$3271,"<="&Q13,$N$6:$N$3271,Calendar!$K$4),"") | W13: =IF(AND(B13=Queue!$C$4,OR(Queue!$K$4="*",N13=Queue!$K$4)),Q13,"")
A14: =IF(M14="","",HYPERLINK("https://www.youtube.com/watch?v="&M14,"▶")) | B14: =IF(C14<>"",C14,IF(P14<=IFERROR(INDEX(tblChannels[Watched Through],MATCH(N14,tblChannels[Channel ID],0)),0),"Watched","Unwatched")) | E14: 46283.625 | F14: Super Carlin Brothers | G14: J & Ben VS AI - Harry Potter Trivia | H14: 0.031261574 | I14: 115261 | J14: 2389 | K14: 450 | N14: UCKZo4N0lVPccBkSiuyVh4yg | O14: 46283.792 | P14: 46283 | Q14: 3258 | R14: No Video ID yet | V14: =IF(AND(P14>=Calendar!$K$2,P14<EDATE(Calendar!$K$2,1),OR(Calendar!$K$4="*",N14=Calendar!$K$4)),P14*100+COUNTIFS($P$6:$P$3271,P14,$Q$6:$Q$3271,"<="&Q14,$N$6:$N$3271,Calendar!$K$4),"") | W14: =IF(AND(B14=Queue!$C$4,OR(Queue!$K$4="*",N14=Queue!$K$4)),Q14,"")
A15: =IF(M15="","",HYPERLINK("https://www.youtube.com/watch?v="&M15,"▶")) | B15: =IF(C15<>"",C15,IF(P15<=IFERROR(INDEX(tblChannels[Watched Through],MATCH(N15,tblChannels[Channel ID],0)),0),"Watched","Unwatched")) | E15: 46283.417 | F15: Popcorn Culture | G15: The Roanoke Bracket | Popcorn Culture | H15: 0.050405093 | I15: 3167 | J15: 96 | K15: 22 | N15: UCHfIbq9thHPC8yrKjAdJgDA | O15: 46283.583 | P15: 46283 | Q15: 3257 | R15: No Video ID yet | V15: =IF(AND(P15>=Calendar!$K$2,P15<EDATE(Calendar!$K$2,1),OR(Calendar!$K$4="*",N15=Calendar!$K$4)),P15*100+COUNTIFS($P$6:$P$3271,P15,$Q$6:$Q$3271,"<="&Q15,$N$6:$N$3271,Calendar!$K$4),"") | W15: =IF(AND(B15=Queue!$C$4,OR(Queue!$K$4="*",N15=Queue!$K$4)),Q15,"")
A16: =IF(M16="","",HYPERLINK("https://www.youtube.com/watch?v="&M16,"▶")) | B16: =IF(C16<>"",C16,IF(P16<=IFERROR(INDEX(tblChannels[Watched Through],MATCH(N16,tblChannels[Channel ID],0)),0),"Watched","Unwatched")) | E16: 46281.625 | F16: Super Carlin Brothers | G16: Theories From A Hat: Defending MORE Wild Harry Potter Theories | H16: 0.0271875 | I16: 104475 | J16: 1972 | K16: 409 | N16: UCKZo4N0lVPccBkSiuyVh4yg | O16: 46281.792 | P16: 46281 | Q16: 3256 | R16: No Video ID yet | V16: =IF(AND(P16>=Calendar!$K$2,P16<EDATE(Calendar!$K$2,1),OR(Calendar!$K$4="*",N16=Calendar!$K$4)),P16*100+COUNTIFS($P$6:$P$3271,P16,$Q$6:$Q$3271,"<="&Q16,$N$6:$N$3271,Calendar!$K$4),"") | W16: =IF(AND(B16=Queue!$C$4,OR(Queue!$K$4="*",N16=Queue!$K$4)),Q16,"")
A17: =IF(M17="","",HYPERLINK("https://www.youtube.com/watch?v="&M17,"▶")) | B17: =IF(C17<>"",C17,IF(P17<=IFERROR(INDEX(tblChannels[Watched Through],MATCH(N17,tblChannels[Channel ID],0)),0),"Watched","Unwatched")) | E17: 46278.476 | F17: Through The Griffin Door | G17: Chapter 14: Felix Felicis | Half-Blood Prince | H17: 0.079710648 | I17: 38643 | J17: 813 | K17: 243 | N17: UCEscP6ETYXWSSvsNrDHekMQ | O17: 46278.642 | P17: 46278 | Q17: 3255 | R17: No Video ID yet | V17: =IF(AND(P17>=Calendar!$K$2,P17<EDATE(Calendar!$K$2,1),OR(Calendar!$K$4="*",N17=Calendar!$K$4)),P17*100+COUNTIFS($P$6:$P$3271,P17,$Q$6:$Q$3271,"<="&Q17,$N$6:$N$3271,Calendar!$K$4),"") | W17: =IF(AND(B17=Queue!$C$4,OR(Queue!$K$4="*",N17=Queue!$K$4)),Q17,"")
... A3271: =IF(M3271="","",HYPERLINK("https://www.youtube.com/watch?v="&M3271,"▶")) | B3271: =IF(C3271<>"",C3271,IF(P3271<=IFERROR(INDEX(tblChannels[Watched Through],MATCH(N3271,tblChannels[Channel ID],0)),0),"Watched","Unwatched")) | E3271: 41058.985 | F3271: Super Carlin Brothers | G3271: Super Carlin Brothers Teaser | H3271: 0.00025462963 | I3271: 146050 | J3271: 2475 | K3271: 271 | N3271: UCKZo4N0lVPccBkSiuyVh4yg | O3271: 41059.151 | P3271: 41058 | Q3271: 1 | R3271: No Video ID yet | V3271: =IF(AND(P3271>=Calendar!$K$2,P3271<EDATE(Calendar!$K$2,1),OR(Calendar!$K$4="*",N3271=Calendar!$K$4)),P3271*100+COUNTIFS($P$6:$P$3271,P3271,$Q$6:$Q$3271,"<="&Q3271,$N$6:$N$3271,Calendar!$K$4),"") | W3271: =IF(AND(B3271=Queue!$C$4,OR(Queue!$K$4="*",N3271=Queue!$K$4)),Q3271,"")

Sheet Queue
B2: Watch Queue
C3: Show | D3: Channel | E3: Order
B4: =HYPERLINK("#Dashboard!A1","◄ Dashboard") | C4: Unwatched | D4: All channels | E4: Oldest first | K4: =IF($D$4="All channels","*",IFERROR(INDEX(tblChannels[Channel ID],MATCH($D$4,tblChannels[Display Name],0)),"none"))
B5: =COUNT(tblVideos[Queue Key])&" videos match · "&TEXT(SUMIFS(tblVideos[Length],tblVideos[Queue Key],">0"),"[h]:mm")&" of runtime"
B6: Your next videos. Click a title to open it on YouTube; mark it watched in the Library.
B7: # | C7: Published | D7: Channel | E7: Title | F7: Length | G7: Status
B8: =IF($I8="","",1) | C8: =IF($I8="","",INDEX(tblVideos[Day],$I8)) | D8: =IF($I8="","",INDEX(tblVideos[Channel],$I8)) | E8: =IF($I8="","",IF(INDEX(tblVideos[Video ID],$I8)="",INDEX(tblVideos[Title],$I8),HYPERLINK("https://www.youtube.com/watch?v="&INDEX(tblVideos[Video ID],$I8),INDEX(tblVideos[Title],$I8)))) | F8: =IF($I8="","",INDEX(tblVideos[Length],$I8)) | G8: =IF($I8="","",INDEX(tblVideos[Status],$I8)) | I8: =IFERROR(MATCH(IF($E$4="Newest first",LARGE(tblVideos[Queue Key],1),SMALL(tblVideos[Queue Key],1)),tblVideos[Seq],0),"")
B9: =IF($I9="","",2) | C9: =IF($I9="","",INDEX(tblVideos[Day],$I9)) | D9: =IF($I9="","",INDEX(tblVideos[Channel],$I9)) | E9: =IF($I9="","",IF(INDEX(tblVideos[Video ID],$I9)="",INDEX(tblVideos[Title],$I9),HYPERLINK("https://www.youtube.com/watch?v="&INDEX(tblVideos[Video ID],$I9),INDEX(tblVideos[Title],$I9)))) | F9: =IF($I9="","",INDEX(tblVideos[Length],$I9)) | G9: =IF($I9="","",INDEX(tblVideos[Status],$I9)) | I9: =IFERROR(MATCH(IF($E$4="Newest first",LARGE(tblVideos[Queue Key],2),SMALL(tblVideos[Queue Key],2)),tblVideos[Seq],0),"")
B10: =IF($I10="","",3) | C10: =IF($I10="","",INDEX(tblVideos[Day],$I10)) | D10: =IF($I10="","",INDEX(tblVideos[Channel],$I10)) | E10: =IF($I10="","",IF(INDEX(tblVideos[Video ID],$I10)="",INDEX(tblVideos[Title],$I10),HYPERLINK("https://www.youtube.com/watch?v="&INDEX(tblVideos[Video ID],$I10),INDEX(tblVideos[Title],$I10)))) | F10: =IF($I10="","",INDEX(tblVideos[Length],$I10)) | G10: =IF($I10="","",INDEX(tblVideos[Status],$I10)) | I10: =IFERROR(MATCH(IF($E$4="Newest first",LARGE(tblVideos[Queue Key],3),SMALL(tblVideos[Queue Key],3)),tblVideos[Seq],0),"")
B11: =IF($I11="","",4) | C11: =IF($I11="","",INDEX(tblVideos[Day],$I11)) | D11: =IF($I11="","",INDEX(tblVideos[Channel],$I11)) | E11: =IF($I11="","",IF(INDEX(tblVideos[Video ID],$I11)="",INDEX(tblVideos[Title],$I11),HYPERLINK("https://www.youtube.com/watch?v="&INDEX(tblVideos[Video ID],$I11),INDEX(tblVideos[Title],$I11)))) | F11: =IF($I11="","",INDEX(tblVideos[Length],$I11)) | G11: =IF($I11="","",INDEX(tblVideos[Status],$I11)) | I11: =IFERROR(MATCH(IF($E$4="Newest first",LARGE(tblVideos[Queue Key],4),SMALL(tblVideos[Queue Key],4)),tblVideos[Seq],0),"")
B12: =IF($I12="","",5) | C12: =IF($I12="","",INDEX(tblVideos[Day],$I12)) | D12: =IF($I12="","",INDEX(tblVideos[Channel],$I12)) | E12: =IF($I12="","",IF(INDEX(tblVideos[Video ID],$I12)="",INDEX(tblVideos[Title],$I12),HYPERLINK("https://www.youtube.com/watch?v="&INDEX(tblVideos[Video ID],$I12),INDEX(tblVideos[Title],$I12)))) | F12: =IF($I12="","",INDEX(tblVideos[Length],$I12)) | G12: =IF($I12="","",INDEX(tblVideos[Status],$I12)) | I12: =IFERROR(MATCH(IF($E$4="Newest first",LARGE(tblVideos[Queue Key],5),SMALL(tblVideos[Queue Key],5)),tblVideos[Seq],0),"")
B13: =IF($I13="","",6) | C13: =IF($I13="","",INDEX(tblVideos[Day],$I13)) | D13: =IF($I13="","",INDEX(tblVideos[Channel],$I13)) | E13: =IF($I13="","",IF(INDEX(tblVideos[Video ID],$I13)="",INDEX(tblVideos[Title],$I13),HYPERLINK("https://www.youtube.com/watch?v="&INDEX(tblVideos[Video ID],$I13),INDEX(tblVideos[Title],$I13)))) | F13: =IF($I13="","",INDEX(tblVideos[Length],$I13)) | G13: =IF($I13="","",INDEX(tblVideos[Status],$I13)) | I13: =IFERROR(MATCH(IF($E$4="Newest first",LARGE(tblVideos[Queue Key],6),SMALL(tblVideos[Queue Key],6)),tblVideos[Seq],0),"")
B14: =IF($I14="","",7) | C14: =IF($I14="","",INDEX(tblVideos[Day],$I14)) | D14: =IF($I14="","",INDEX(tblVideos[Channel],$I14)) | E14: =IF($I14="","",IF(INDEX(tblVideos[Video ID],$I14)="",INDEX(tblVideos[Title],$I14),HYPERLINK("https://www.youtube.com/watch?v="&INDEX(tblVideos[Video ID],$I14),INDEX(tblVideos[Title],$I14)))) | F14: =IF($I14="","",INDEX(tblVideos[Length],$I14)) | G14: =IF($I14="","",INDEX(tblVideos[Status],$I14)) | I14: =IFERROR(MATCH(IF($E$4="Newest first",LARGE(tblVideos[Queue Key],7),SMALL(tblVideos[Queue Key],7)),tblVideos[Seq],0),"")
B15: =IF($I15="","",8) | C15: =IF($I15="","",INDEX(tblVideos[Day],$I15)) | D15: =IF($I15="","",INDEX(tblVideos[Channel],$I15)) | E15: =IF($I15="","",IF(INDEX(tblVideos[Video ID],$I15)="",INDEX(tblVideos[Title],$I15),HYPERLINK("https://www.youtube.com/watch?v="&INDEX(tblVideos[Video ID],$I15),INDEX(tblVideos[Title],$I15)))) | F15: =IF($I15="","",INDEX(tblVideos[Length],$I15)) | G15: =IF($I15="","",INDEX(tblVideos[Status],$I15)) | I15: =IFERROR(MATCH(IF($E$4="Newest first",LARGE(tblVideos[Queue Key],8),SMALL(tblVideos[Queue Key],8)),tblVideos[Seq],0),"")
B16: =IF($I16="","",9) | C16: =IF($I16="","",INDEX(tblVideos[Day],$I16)) | D16: =IF($I16="","",INDEX(tblVideos[Channel],$I16)) | E16: =IF($I16="","",IF(INDEX(tblVideos[Video ID],$I16)="",INDEX(tblVideos[Title],$I16),HYPERLINK("https://www.youtube.com/watch?v="&INDEX(tblVideos[Video ID],$I16),INDEX(tblVideos[Title],$I16)))) | F16: =IF($I16="","",INDEX(tblVideos[Length],$I16)) | G16: =IF($I16="","",INDEX(tblVideos[Status],$I16)) | I16: =IFERROR(MATCH(IF($E$4="Newest first",LARGE(tblVideos[Queue Key],9),SMALL(tblVideos[Queue Key],9)),tblVideos[Seq],0),"")
B17: =IF($I17="","",10) | C17: =IF($I17="","",INDEX(tblVideos[Day],$I17)) | D17: =IF($I17="","",INDEX(tblVideos[Channel],$I17)) | E17: =IF($I17="","",IF(INDEX(tblVideos[Video ID],$I17)="",INDEX(tblVideos[Title],$I17),HYPERLINK("https://www.youtube.com/watch?v="&INDEX(tblVideos[Video ID],$I17),INDEX(tblVideos[Title],$I17)))) | F17: =IF($I17="","",INDEX(tblVideos[Length],$I17)) | G17: =IF($I17="","",INDEX(tblVideos[Status],$I17)) | I17: =IFERROR(MATCH(IF($E$4="Newest first",LARGE(tblVideos[Queue Key],10),SMALL(tblVideos[Queue Key],10)),tblVideos[Seq],0),"")
B18: =IF($I18="","",11) | C18: =IF($I18="","",INDEX(tblVideos[Day],$I18)) | D18: =IF($I18="","",INDEX(tblVideos[Channel],$I18)) | E18: =IF($I18="","",IF(INDEX(tblVideos[Video ID],$I18)="",INDEX(tblVideos[Title],$I18),HYPERLINK("https://www.youtube.com/watch?v="&INDEX(tblVideos[Video ID],$I18),INDEX(tblVideos[Title],$I18)))) | F18: =IF($I18="","",INDEX(tblVideos[Length],$I18)) | G18: =IF($I18="","",INDEX(tblVideos[Status],$I18)) | I18: =IFERROR(MATCH(IF($E$4="Newest first",LARGE(tblVideos[Queue Key],11),SMALL(tblVideos[Queue Key],11)),tblVideos[Seq],0),"")
B19: =IF($I19="","",12) | C19: =IF($I19="","",INDEX(tblVideos[Day],$I19)) | D19: =IF($I19="","",INDEX(tblVideos[Channel],$I19)) | E19: =IF($I19="","",IF(INDEX(tblVideos[Video ID],$I19)="",INDEX(tblVideos[Title],$I19),HYPERLINK("https://www.youtube.com/watch?v="&INDEX(tblVideos[Video ID],$I19),INDEX(tblVideos[Title],$I19)))) | F19: =IF($I19="","",INDEX(tblVideos[Length],$I19)) | G19: =IF($I19="","",INDEX(tblVideos[Status],$I19)) | I19: =IFERROR(MATCH(IF($E$4="Newest first",LARGE(tblVideos[Queue Key],12),SMALL(tblVideos[Queue Key],12)),tblVideos[Seq],0),"")
B20: =IF($I20="","",13) | C20: =IF($I20="","",INDEX(tblVideos[Day],$I20)) | D20: =IF($I20="","",INDEX(tblVideos[Channel],$I20)) | E20: =IF($I20="","",IF(INDEX(tblVideos[Video ID],$I20)="",INDEX(tblVideos[Title],$I20),HYPERLINK("https://www.youtube.com/watch?v="&INDEX(tblVideos[Video ID],$I20),INDEX(tblVideos[Title],$I20)))) | F20: =IF($I20="","",INDEX(tblVideos[Length],$I20)) | G20: =IF($I20="","",INDEX(tblVideos[Status],$I20)) | I20: =IFERROR(MATCH(IF($E$4="Newest first",LARGE(tblVideos[Queue Key],13),SMALL(tblVideos[Queue Key],13)),tblVideos[Seq],0),"")
B21: =IF($I21="","",14) | C21: =IF($I21="","",INDEX(tblVideos[Day],$I21)) | D21: =IF($I21="","",INDEX(tblVideos[Channel],$I21)) | E21: =IF($I21="","",IF(INDEX(tblVideos[Video ID],$I21)="",INDEX(tblVideos[Title],$I21),HYPERLINK("https://www.youtube.com/watch?v="&INDEX(tblVideos[Video ID],$I21),INDEX(tblVideos[Title],$I21)))) | F21: =IF($I21="","",INDEX(tblVideos[Length],$I21)) | G21: =IF($I21="","",INDEX(tblVideos[Status],$I21)) | I21: =IFERROR(MATCH(IF($E$4="Newest first",LARGE(tblVideos[Queue Key],14),SMALL(tblVideos[Queue Key],14)),tblVideos[Seq],0),"")
B22: =IF($I22="","",15) | C22: =IF($I22="","",INDEX(tblVideos[Day],$I22)) | D22: =IF($I22="","",INDEX(tblVideos[Channel],$I22)) | E22: =IF($I22="","",IF(INDEX(tblVideos[Video ID],$I22)="",INDEX(tblVideos[Title],$I22),HYPERLINK("https://www.youtube.com/watch?v="&INDEX(tblVideos[Video ID],$I22),INDEX(tblVideos[Title],$I22)))) | F22: =IF($I22="","",INDEX(tblVideos[Length],$I22)) | G22: =IF($I22="","",INDEX(tblVideos[Status],$I22)) | I22: =IFERROR(MATCH(IF($E$4="Newest first",LARGE(tblVideos[Queue Key],15),SMALL(tblVideos[Queue Key],15)),tblVideos[Seq],0),"")
B23: =IF($I23="","",16) | C23: =IF($I23="","",INDEX(tblVideos[Day],$I23)) | D23: =IF($I23="","",INDEX(tblVideos[Channel],$I23)) | E23: =IF($I23="","",IF(INDEX(tblVideos[Video ID],$I23)="",INDEX(tblVideos[Title],$I23),HYPERLINK("https://www.youtube.com/watch?v="&INDEX(tblVideos[Video ID],$I23),INDEX(tblVideos[Title],$I23)))) | F23: =IF($I23="","",INDEX(tblVideos[Length],$I23)) | G23: =IF($I23="","",INDEX(tblVideos[Status],$I23)) | I23: =IFERROR(MATCH(IF($E$4="Newest first",LARGE(tblVideos[Queue Key],16),SMALL(tblVideos[Queue Key],16)),tblVideos[Seq],0),"")
B24: =IF($I24="","",17) | C24: =IF($I24="","",INDEX(tblVideos[Day],$I24)) | D24: =IF($I24="","",INDEX(tblVideos[Channel],$I24)) | E24: =IF($I24="","",IF(INDEX(tblVideos[Video ID],$I24)="",INDEX(tblVideos[Title],$I24),HYPERLINK("https://www.youtube.com/watch?v="&INDEX(tblVideos[Video ID],$I24),INDEX(tblVideos[Title],$I24)))) | F24: =IF($I24="","",INDEX(tblVideos[Length],$I24)) | G24: =IF($I24="","",INDEX(tblVideos[Status],$I24)) | I24: =IFERROR(MATCH(IF($E$4="Newest first",LARGE(tblVideos[Queue Key],17),SMALL(tblVideos[Queue Key],17)),tblVideos[Seq],0),"")
B25: =IF($I25="","",18) | C25: =IF($I25="","",INDEX(tblVideos[Day],$I25)) | D25: =IF($I25="","",INDEX(tblVideos[Channel],$I25)) | E25: =IF($I25="","",IF(INDEX(tblVideos[Video ID],$I25)="",INDEX(tblVideos[Title],$I25),HYPERLINK("https://www.youtube.com/watch?v="&INDEX(tblVideos[Video ID],$I25),INDEX(tblVideos[Title],$I25)))) | F25: =IF($I25="","",INDEX(tblVideos[Length],$I25)) | G25: =IF($I25="","",INDEX(tblVideos[Status],$I25)) | I25: =IFERROR(MATCH(IF($E$4="Newest first",LARGE(tblVideos[Queue Key],18),SMALL(tblVideos[Queue Key],18)),tblVideos[Seq],0),"")
B26: =IF($I26="","",19) | C26: =IF($I26="","",INDEX(tblVideos[Day],$I26)) | D26: =IF($I26="","",INDEX(tblVideos[Channel],$I26)) | E26: =IF($I26="","",IF(INDEX(tblVideos[Video ID],$I26)="",INDEX(tblVideos[Title],$I26),HYPERLINK("https://www.youtube.com/watch?v="&INDEX(tblVideos[Video ID],$I26),INDEX(tblVideos[Title],$I26)))) | F26: =IF($I26="","",INDEX(tblVideos[Length],$I26)) | G26: =IF($I26="","",INDEX(tblVideos[Status],$I26)) | I26: =IFERROR(MATCH(IF($E$4="Newest first",LARGE(tblVideos[Queue Key],19),SMALL(tblVideos[Queue Key],19)),tblVideos[Seq],0),"")
B27: =IF($I27="","",20) | C27: =IF($I27="","",INDEX(tblVideos[Day],$I27)) | D27: =IF($I27="","",INDEX(tblVideos[Channel],$I27)) | E27: =IF($I27="","",IF(INDEX(tblVideos[Video ID],$I27)="",INDEX(tblVideos[Title],$I27),HYPERLINK("https://www.youtube.com/watch?v="&INDEX(tblVideos[Video ID],$I27),INDEX(tblVideos[Title],$I27)))) | F27: =IF($I27="","",INDEX(tblVideos[Length],$I27)) | G27: =IF($I27="","",INDEX(tblVideos[Status],$I27)) | I27: =IFERROR(MATCH(IF($E$4="Newest first",LARGE(tblVideos[Queue Key],20),SMALL(tblVideos[Queue Key],20)),tblVideos[Seq],0),"")
B28: =IF($I28="","",21) | C28: =IF($I28="","",INDEX(tblVideos[Day],$I28)) | D28: =IF($I28="","",INDEX(tblVideos[Channel],$I28)) | E28: =IF($I28="","",IF(INDEX(tblVideos[Video ID],$I28)="",INDEX(tblVideos[Title],$I28),HYPERLINK("https://www.youtube.com/watch?v="&INDEX(tblVideos[Video ID],$I28),INDEX(tblVideos[Title],$I28)))) | F28: =IF($I28="","",INDEX(tblVideos[Length],$I28)) | G28: =IF($I28="","",INDEX(tblVideos[Status],$I28)) | I28: =IFERROR(MATCH(IF($E$4="Newest first",LARGE(tblVideos[Queue Key],21),SMALL(tblVideos[Queue Key],21)),tblVideos[Seq],0),"")
B29: =IF($I29="","",22) | C29: =IF($I29="","",INDEX(tblVideos[Day],$I29)) | D29: =IF($I29="","",INDEX(tblVideos[Channel],$I29)) | E29: =IF($I29="","",IF(INDEX(tblVideos[Video ID],$I29)="",INDEX(tblVideos[Title],$I29),HYPERLINK("https://www.youtube.com/watch?v="&INDEX(tblVideos[Video ID],$I29),INDEX(tblVideos[Title],$I29)))) | F29: =IF($I29="","",INDEX(tblVideos[Length],$I29)) | G29: =IF($I29="","",INDEX(tblVideos[Status],$I29)) | I29: =IFERROR(MATCH(IF($E$4="Newest first",LARGE(tblVideos[Queue Key],22),SMALL(tblVideos[Queue Key],22)),tblVideos[Seq],0),"")
B30: =IF($I30="","",23) | C30: =IF($I30="","",INDEX(tblVideos[Day],$I30)) | D30: =IF($I30="","",INDEX(tblVideos[Channel],$I30)) | E30: =IF($I30="","",IF(INDEX(tblVideos[Video ID],$I30)="",INDEX(tblVideos[Title],$I30),HYPERLINK("https://www.youtube.com/watch?v="&INDEX(tblVideos[Video ID],$I30),INDEX(tblVideos[Title],$I30)))) | F30: =IF($I30="","",INDEX(tblVideos[Length],$I30)) | G30: =IF($I30="","",INDEX(tblVideos[Status],$I30)) | I30: =IFERROR(MATCH(IF($E$4="Newest first",LARGE(tblVideos[Queue Key],23),SMALL(tblVideos[Queue Key],23)),tblVideos[Seq],0),"")
B31: =IF($I31="","",24) | C31: =IF($I31="","",INDEX(tblVideos[Day],$I31)) | D31: =IF($I31="","",INDEX(tblVideos[Channel],$I31)) | E31: =IF($I31="","",IF(INDEX(tblVideos[Video ID],$I31)="",INDEX(tblVideos[Title],$I31),HYPERLINK("https://www.youtube.com/watch?v="&INDEX(tblVideos[Video ID],$I31),INDEX(tblVideos[Title],$I31)))) | F31: =IF($I31="","",INDEX(tblVideos[Length],$I31)) | G31: =IF($I31="","",INDEX(tblVideos[Status],$I31)) | I31: =IFERROR(MATCH(IF($E$4="Newest first",LARGE(tblVideos[Queue Key],24),SMALL(tblVideos[Queue Key],24)),tblVideos[Seq],0),"")
B32: =IF($I32="","",25) | C32: =IF($I32="","",INDEX(tblVideos[Day],$I32)) | D32: =IF($I32="","",INDEX(tblVideos[Channel],$I32)) | E32: =IF($I32="","",IF(INDEX(tblVideos[Video ID],$I32)="",INDEX(tblVideos[Title],$I32),HYPERLINK("https://www.youtube.com/watch?v="&INDEX(tblVideos[Video ID],$I32),INDEX(tblVideos[Title],$I32)))) | F32: =IF($I32="","",INDEX(tblVideos[Length],$I32)) | G32: =IF($I32="","",INDEX(tblVideos[Status],$I32)) | I32: =IFERROR(MATCH(IF($E$4="Newest first",LARGE(tblVideos[Queue Key],25),SMALL(tblVideos[Queue Key],25)),tblVideos[Seq],0),"")
B33: =IF($I33="","",26) | C33: =IF($I33="","",INDEX(tblVideos[Day],$I33)) | D33: =IF($I33="","",INDEX(tblVideos[Channel],$I33)) | E33: =IF($I33="","",IF(INDEX(tblVideos[Video ID],$I33)="",INDEX(tblVideos[Title],$I33),HYPERLINK("https://www.youtube.com/watch?v="&INDEX(tblVideos[Video ID],$I33),INDEX(tblVideos[Title],$I33)))) | F33: =IF($I33="","",INDEX(tblVideos[Length],$I33)) | G33: =IF($I33="","",INDEX(tblVideos[Status],$I33)) | I33: =IFERROR(MATCH(IF($E$4="Newest first",LARGE(tblVideos[Queue Key],26),SMALL(tblVideos[Queue Key],26)),tblVideos[Seq],0),"")
B34: =IF($I34="","",27) | C34: =IF($I34="","",INDEX(tblVideos[Day],$I34)) | D34: =IF($I34="","",INDEX(tblVideos[Channel],$I34)) | E34: =IF($I34="","",IF(INDEX(tblVideos[Video ID],$I34)="",INDEX(tblVideos[Title],$I34),HYPERLINK("https://www.youtube.com/watch?v="&INDEX(tblVideos[Video ID],$I34),INDEX(tblVideos[Title],$I34)))) | F34: =IF($I34="","",INDEX(tblVideos[Length],$I34)) | G34: =IF($I34="","",INDEX(tblVideos[Status],$I34)) | I34: =IFERROR(MATCH(IF($E$4="Newest first",LARGE(tblVideos[Queue Key],27),SMALL(tblVideos[Queue Key],27)),tblVideos[Seq],0),"")
B35: =IF($I35="","",28) | C35: =IF($I35="","",INDEX(tblVideos[Day],$I35)) | D35: =IF($I35="","",INDEX(tblVideos[Channel],$I35)) | E35: =IF($I35="","",IF(INDEX(tblVideos[Video ID],$I35)="",INDEX(tblVideos[Title],$I35),HYPERLINK("https://www.youtube.com/watch?v="&INDEX(tblVideos[Video ID],$I35),INDEX(tblVideos[Title],$I35)))) | F35: =IF($I35="","",INDEX(tblVideos[Length],$I35)) | G35: =IF($I35="","",INDEX(tblVideos[Status],$I35)) | I35: =IFERROR(MATCH(IF($E$4="Newest first",LARGE(tblVideos[Queue Key],28),SMALL(tblVideos[Queue Key],28)),tblVideos[Seq],0),"")
B36: =IF($I36="","",29) | C36: =IF($I36="","",INDEX(tblVideos[Day],$I36)) | D36: =IF($I36="","",INDEX(tblVideos[Channel],$I36)) | E36: =IF($I36="","",IF(INDEX(tblVideos[Video ID],$I36)="",INDEX(tblVideos[Title],$I36),HYPERLINK("https://www.youtube.com/watch?v="&INDEX(tblVideos[Video ID],$I36),INDEX(tblVideos[Title],$I36)))) | F36: =IF($I36="","",INDEX(tblVideos[Length],$I36)) | G36: =IF($I36="","",INDEX(tblVideos[Status],$I36)) | I36: =IFERROR(MATCH(IF($E$4="Newest first",LARGE(tblVideos[Queue Key],29),SMALL(tblVideos[Queue Key],29)),tblVideos[Seq],0),"")
B37: =IF($I37="","",30) | C37: =IF($I37="","",INDEX(tblVideos[Day],$I37)) | D37: =IF($I37="","",INDEX(tblVideos[Channel],$I37)) | E37: =IF($I37="","",IF(INDEX(tblVideos[Video ID],$I37)="",INDEX(tblVideos[Title],$I37),HYPERLINK("https://www.youtube.com/watch?v="&INDEX(tblVideos[Video ID],$I37),INDEX(tblVideos[Title],$I37)))) | F37: =IF($I37="","",INDEX(tblVideos[Length],$I37)) | G37: =IF($I37="","",INDEX(tblVideos[Status],$I37)) | I37: =IFERROR(MATCH(IF($E$4="Newest first",LARGE(tblVideos[Queue Key],30),SMALL(tblVideos[Queue Key],30)),tblVideos[Seq],0),"")

Sheet Calendar
B2: Upload Calendar | J2: month start | K2: =DATE($C$4,MATCH($E$4,MonthList,0),1)
C3: Year | E3: Month | G3: Channel | J3: grid start | K3: =K2-(WEEKDAY(K2,2)-1)
B4: =HYPERLINK("#Dashboard!A1","◄ Dashboard") | C4: 2026 | E4: October | G4: All channels | J4: channel crit | K4: =IF($G$4="All channels","*",IFERROR(INDEX(tblChannels[Channel ID],MATCH($G$4,tblChannels[Display Name],0)),"none"))
B5: Pick a year, month and (optionally) a channel with the dropdowns. Click a title to open it on YouTube. ✓ = watched, dimmed.
B6: ="Videos: "&COUNTIFS(tblVideos[Day],">="&$K$2,tblVideos[Day],"<"&EDATE($K$2,1),tblVideos[Channel ID],$K$4)&" Runtime: "&TEXT(SUMIFS(tblVideos[Length],tblVideos[Day],">="&$K$2,tblVideos[Day],"<"&EDATE($K$2,1),tblVideos[Channel ID],$K$4),"[h]:mm")&" Watched: "&COUNTIFS(tblVideos[Day],">="&$K$2,tblVideos[Day],"<"&EDATE($K$2,1),tblVideos[Channel ID],$K$4,tblVideos[Status],"Watched")&" of "&COUNTIFS(tblVideos[Day],">="&$K$2,tblVideos[Day],"<"&EDATE($K$2,1),tblVideos[Channel ID],$K$4)
B7: =Channels!$C$6&" ("&COUNTIFS(tblVideos[Day],">="&$K$2,tblVideos[Day],"<"&EDATE($K$2,1),tblVideos[Channel ID],Channels!$E$6)&")" | C7: =Channels!$C$7&" ("&COUNTIFS(tblVideos[Day],">="&$K$2,tblVideos[Day],"<"&EDATE($K$2,1),tblVideos[Channel ID],Channels!$E$7)&")" | D7: =Channels!$C$8&" ("&COUNTIFS(tblVideos[Day],">="&$K$2,tblVideos[Day],"<"&EDATE($K$2,1),tblVideos[Channel ID],Channels!$E$8)&")" | E7: =Channels!$C$9&" ("&COUNTIFS(tblVideos[Day],">="&$K$2,tblVideos[Day],"<"&EDATE($K$2,1),tblVideos[Channel ID],Channels!$E$9)&")" | F7: =Channels!$C$10&" ("&COUNTIFS(tblVideos[Day],">="&$K$2,tblVideos[Day],"<"&EDATE($K$2,1),tblVideos[Channel ID],Channels!$E$10)&")" | G7: =Channels!$C$11&" ("&COUNTIFS(tblVideos[Day],">="&$K$2,tblVideos[Day],"<"&EDATE($K$2,1),tblVideos[Channel ID],Channels!$E$11)&")"
B9: Monday | C9: Tuesday | D9: Wednesday | E9: Thursday | F9: Friday | G9: Saturday | H9: Sunday
B10: =IF(MONTH(K10)=MONTH($K$2),DAY(K10)&IF(S10>0," · "&S10&IF(S10=1," video"," videos")&" · "&TEXT(AA10,"[h]:mm")&IF(S10>5," (+"&(S10-5)&" more)",""),""),"") | C10: =IF(MONTH(L10)=MONTH($K$2),DAY(L10)&IF(T10>0," · "&T10&IF(T10=1," video"," videos")&" · "&TEXT(AB10,"[h]:mm")&IF(T10>5," (+"&(T10-5)&" more)",""),""),"") | D10: =IF(MONTH(M10)=MONTH($K$2),DAY(M10)&IF(U10>0," · "&U10&IF(U10=1," video"," videos")&" · "&TEXT(AC10,"[h]:mm")&IF(U10>5," (+"&(U10-5)&" more)",""),""),"") | E10: =IF(MONTH(N10)=MONTH($K$2),DAY(N10)&IF(V10>0," · "&V10&IF(V10=1," video"," videos")&" · "&TEXT(AD10,"[h]:mm")&IF(V10>5," (+"&(V10-5)&" more)",""),""),"") | F10: =IF(MONTH(O10)=MONTH($K$2),DAY(O10)&IF(W10>0," · "&W10&IF(W10=1," video"," videos")&" · "&TEXT(AE10,"[h]:mm")&IF(W10>5," (+"&(W10-5)&" more)",""),""),"") | G10: =IF(MONTH(P10)=MONTH($K$2),DAY(P10)&IF(X10>0," · "&X10&IF(X10=1," video"," videos")&" · "&TEXT(AF10,"[h]:mm")&IF(X10>5," (+"&(X10-5)&" more)",""),""),"") | H10: =IF(MONTH(Q10)=MONTH($K$2),DAY(Q10)&IF(Y10>0," · "&Y10&IF(Y10=1," video"," videos")&" · "&TEXT(AG10,"[h]:mm")&IF(Y10>5," (+"&(Y10-5)&" more)",""),""),"") | K10: =$K$3+0 | L10: =$K$3+1 | M10: =$K$3+2 | N10: =$K$3+3 | O10: =$K$3+4 | P10: =$K$3+5 | Q10: =$K$3+6 | S10: =IF(MONTH(K10)=MONTH($K$2),COUNTIFS(tblVideos[Day],K10,tblVideos[Channel ID],$K$4),0) | T10: =IF(MONTH(L10)=MONTH($K$2),COUNTIFS(tblVideos[Day],L10,tblVideos[Channel ID],$K$4),0) | U10: =IF(MONTH(M10)=MONTH($K$2),COUNTIFS(tblVideos[Day],M10,tblVideos[Channel ID],$K$4),0) | V10: =IF(MONTH(N10)=MONTH($K$2),COUNTIFS(tblVideos[Day],N10,tblVideos[Channel ID],$K$4),0) | W10: =IF(MONTH(O10)=MONTH($K$2),COUNTIFS(tblVideos[Day],O10,tblVideos[Channel ID],$K$4),0) | X10: =IF(MONTH(P10)=MONTH($K$2),COUNTIFS(tblVideos[Day],P10,tblVideos[Channel ID],$K$4),0) | Y10: =IF(MONTH(Q10)=MONTH($K$2),COUNTIFS(tblVideos[Day],Q10,tblVideos[Channel ID],$K$4),0) | AA10: =IF(S10>0,SUMIFS(tblVideos[Length],tblVideos[Day],K10,tblVideos[Channel ID],$K$4),0) | AB10: =IF(T10>0,SUMIFS(tblVideos[Length],tblVideos[Day],L10,tblVideos[Channel ID],$K$4),0) | AC10: =IF(U10>0,SUMIFS(tblVideos[Length],tblVideos[Day],M10,tblVideos[Channel ID],$K$4),0) | AD10: =IF(V10>0,SUMIFS(tblVideos[Length],tblVideos[Day],N10,tblVideos[Channel ID],$K$4),0) | AE10: =IF(W10>0,SUMIFS(tblVideos[Length],tblVideos[Day],O10,tblVideos[Channel ID],$K$4),0) | AF10: =IF(X10>0,SUMIFS(tblVideos[Length],tblVideos[Day],P10,tblVideos[Channel ID],$K$4),0) | AG10: =IF(Y10>0,SUMIFS(tblVideos[Length],tblVideos[Day],Q10,tblVideos[Channel ID],$K$4),0)
B11: =IF(K11="","",IF(INDEX(tblVideos[Video ID],K11)="",IF(INDEX(tblVideos[Status],K11)="Watched","✓ ","▸ ")&INDEX(tblVideos[Title],K11),HYPERLINK("https://www.youtube.com/watch?v="&INDEX(tblVideos[Video ID],K11),IF(INDEX(tblVideos[Status],K11)="Watched","✓ ","▸ ")&INDEX(tblVideos[Title],K11)))) | C11: =IF(L11="","",IF(INDEX(tblVideos[Video ID],L11)="",IF(INDEX(tblVideos[Status],L11)="Watched","✓ ","▸ ")&INDEX(tblVideos[Title],L11),HYPERLINK("https://www.youtube.com/watch?v="&INDEX(tblVideos[Video ID],L11),IF(INDEX(tblVideos[Status],L11)="Watched","✓ ","▸ ")&INDEX(tblVideos[Title],L11)))) | D11: =IF(M11="","",IF(INDEX(tblVideos[Video ID],M11)="",IF(INDEX(tblVideos[Status],M11)="Watched","✓ ","▸ ")&INDEX(tblVideos[Title],M11),HYPERLINK("https://www.youtube.com/watch?v="&INDEX(tblVideos[Video ID],M11),IF(INDEX(tblVideos[Status],M11)="Watched","✓ ","▸ ")&INDEX(tblVideos[Title],M11)))) | E11: =IF(N11="","",IF(INDEX(tblVideos[Video ID],N11)="",IF(INDEX(tblVideos[Status],N11)="Watched","✓ ","▸ ")&INDEX(tblVideos[Title],N11),HYPERLINK("https://www.youtube.com/watch?v="&INDEX(tblVideos[Video ID],N11),IF(INDEX(tblVideos[Status],N11)="Watched","✓ ","▸ ")&INDEX(tblVideos[Title],N11)))) | F11: =IF(O11="","",IF(INDEX(tblVideos[Video ID],O11)="",IF(INDEX(tblVideos[Status],O11)="Watched","✓ ","▸ ")&INDEX(tblVideos[Title],O11),HYPERLINK("https://www.youtube.com/watch?v="&INDEX(tblVideos[Video ID],O11),IF(INDEX(tblVideos[Status],O11)="Watched","✓ ","▸ ")&INDEX(tblVideos[Title],O11)))) | G11: =IF(P11="","",IF(INDEX(tblVideos[Video ID],P11)="",IF(INDEX(tblVideos[Status],P11)="Watched","✓ ","▸ ")&INDEX(tblVideos[Title],P11),HYPERLINK("https://www.youtube.com/watch?v="&INDEX(tblVideos[Video ID],P11),IF(INDEX(tblVideos[Status],P11)="Watched","✓ ","▸ ")&INDEX(tblVideos[Title],P11)))) | H11: =IF(Q11="","",IF(INDEX(tblVideos[Video ID],Q11)="",IF(INDEX(tblVideos[Status],Q11)="Watched","✓ ","▸ ")&INDEX(tblVideos[Title],Q11),HYPERLINK("https://www.youtube.com/watch?v="&INDEX(tblVideos[Video ID],Q11),IF(INDEX(tblVideos[Status],Q11)="Watched","✓ ","▸ ")&INDEX(tblVideos[Title],Q11)))) | K11: =IF(S10>=1,MATCH(K10*100+1,tblVideos[Cal Key],0),"") | L11: =IF(T10>=1,MATCH(L10*100+1,tblVideos[Cal Key],0),"") | M11: =IF(U10>=1,MATCH(M10*100+1,tblVideos[Cal Key],0),"") | N11: =IF(V10>=1,MATCH(N10*100+1,tblVideos[Cal Key],0),"") | O11: =IF(W10>=1,MATCH(O10*100+1,tblVideos[Cal Key],0),"") | P11: =IF(X10>=1,MATCH(P10*100+1,tblVideos[Cal Key],0),"") | Q11: =IF(Y10>=1,MATCH(Q10*100+1,tblVideos[Cal Key],0),"") | S11: =IF(K11="","",IFERROR(MATCH(INDEX(tblVideos[Channel ID],K11),tblChannels[Channel ID],0),"")) | T11: =IF(L11="","",IFERROR(MATCH(INDEX(tblVideos[Channel ID],L11),tblChannels[Channel ID],0),"")) | U11: =IF(M11="","",IFERROR(MATCH(INDEX(tblVideos[Channel ID],M11),tblChannels[Channel ID],0),"")) | V11: =IF(N11="","",IFERROR(MATCH(INDEX(tblVideos[Channel ID],N11),tblChannels[Channel ID],0),"")) | W11: =IF(O11="","",IFERROR(MATCH(INDEX(tblVideos[Channel ID],O11),tblChannels[Channel ID],0),"")) | X11: =IF(P11="","",IFERROR(MATCH(INDEX(tblVideos[Channel ID],P11),tblChannels[Channel ID],0),"")) | Y11: =IF(Q11="","",IFERROR(MATCH(INDEX(tblVideos[Channel ID],Q11),tblChannels[Channel ID],0),""))
B12: =IF(K12="","",IF(INDEX(tblVideos[Video ID],K12)="",IF(INDEX(tblVideos[Status],K12)="Watched","✓ ","▸ ")&INDEX(tblVideos[Title],K12),HYPERLINK("https://www.youtube.com/watch?v="&INDEX(tblVideos[Video ID],K12),IF(INDEX(tblVideos[Status],K12)="Watched","✓ ","▸ ")&INDEX(tblVideos[Title],K12)))) | C12: =IF(L12="","",IF(INDEX(tblVideos[Video ID],L12)="",IF(INDEX(tblVideos[Status],L12)="Watched","✓ ","▸ ")&INDEX(tblVideos[Title],L12),HYPERLINK("https://www.youtube.com/watch?v="&INDEX(tblVideos[Video ID],L12),IF(INDEX(tblVideos[Status],L12)="Watched","✓ ","▸ ")&INDEX(tblVideos[Title],L12)))) | D12: =IF(M12="","",IF(INDEX(tblVideos[Video ID],M12)="",IF(INDEX(tblVideos[Status],M12)="Watched","✓ ","▸ ")&INDEX(tblVideos[Title],M12),HYPERLINK("https://www.youtube.com/watch?v="&INDEX(tblVideos[Video ID],M12),IF(INDEX(tblVideos[Status],M12)="Watched","✓ ","▸ ")&INDEX(tblVideos[Title],M12)))) | E12: =IF(N12="","",IF(INDEX(tblVideos[Video ID],N12)="",IF(INDEX(tblVideos[Status],N12)="Watched","✓ ","▸ ")&INDEX(tblVideos[Title],N12),HYPERLINK("https://www.youtube.com/watch?v="&INDEX(tblVideos[Video ID],N12),IF(INDEX(tblVideos[Status],N12)="Watched","✓ ","▸ ")&INDEX(tblVideos[Title],N12)))) | F12: =IF(O12="","",IF(INDEX(tblVideos[Video ID],O12)="",IF(INDEX(tblVideos[Status],O12)="Watched","✓ ","▸ ")&INDEX(tblVideos[Title],O12),HYPERLINK("https://www.youtube.com/watch?v="&INDEX(tblVideos[Video ID],O12),IF(INDEX(tblVideos[Status],O12)="Watched","✓ ","▸ ")&INDEX(tblVideos[Title],O12)))) | G12: =IF(P12="","",IF(INDEX(tblVideos[Video ID],P12)="",IF(INDEX(tblVideos[Status],P12)="Watched","✓ ","▸ ")&INDEX(tblVideos[Title],P12),HYPERLINK("https://www.youtube.com/watch?v="&INDEX(tblVideos[Video ID],P12),IF(INDEX(tblVideos[Status],P12)="Watched","✓ ","▸ ")&INDEX(tblVideos[Title],P12)))) | H12: =IF(Q12="","",IF(INDEX(tblVideos[Video ID],Q12)="",IF(INDEX(tblVideos[Status],Q12)="Watched","✓ ","▸ ")&INDEX(tblVideos[Title],Q12),HYPERLINK("https://www.youtube.com/watch?v="&INDEX(tblVideos[Video ID],Q12),IF(INDEX(tblVideos[Status],Q12)="Watched","✓ ","▸ ")&INDEX(tblVideos[Title],Q12)))) | K12: =IF(S10>=2,MATCH(K10*100+2,tblVideos[Cal Key],0),"") | L12: =IF(T10>=2,MATCH(L10*100+2,tblVideos[Cal Key],0),"") | M12: =IF(U10>=2,MATCH(M10*100+2,tblVideos[Cal Key],0),"") | N12: =IF(V10>=2,MATCH(N10*100+2,tblVideos[Cal Key],0),"") | O12: =IF(W10>=2,MATCH(O10*100+2,tblVideos[Cal Key],0),"") | P12: =IF(X10>=2,MATCH(P10*100+2,tblVideos[Cal Key],0),"") | Q12: =IF(Y10>=2,MATCH(Q10*100+2,tblVideos[Cal Key],0),"") | S12: =IF(K12="","",IFERROR(MATCH(INDEX(tblVideos[Channel ID],K12),tblChannels[Channel ID],0),"")) | T12: =IF(L12="","",IFERROR(MATCH(INDEX(tblVideos[Channel ID],L12),tblChannels[Channel ID],0),"")) | U12: =IF(M12="","",IFERROR(MATCH(INDEX(tblVideos[Channel ID],M12),tblChannels[Channel ID],0),"")) | V12: =IF(N12="","",IFERROR(MATCH(INDEX(tblVideos[Channel ID],N12),tblChannels[Channel ID],0),"")) | W12: =IF(O12="","",IFERROR(MATCH(INDEX(tblVideos[Channel ID],O12),tblChannels[Channel ID],0),"")) | X12: =IF(P12="","",IFERROR(MATCH(INDEX(tblVideos[Channel ID],P12),tblChannels[Channel ID],0),"")) | Y12: =IF(Q12="","",IFERROR(MATCH(INDEX(tblVideos[Channel ID],Q12),tblChannels[Channel ID],0),""))
B13: =IF(K13="","",IF(INDEX(tblVideos[Video ID],K13)="",IF(INDEX(tblVideos[Status],K13)="Watched","✓ ","▸ ")&INDEX(tblVideos[Title],K13),HYPERLINK("https://www.youtube.com/watch?v="&INDEX(tblVideos[Video ID],K13),IF(INDEX(tblVideos[Status],K13)="Watched","✓ ","▸ ")&INDEX(tblVideos[Title],K13)))) | C13: =IF(L13="","",IF(INDEX(tblVideos[Video ID],L13)="",IF(INDEX(tblVideos[Status],L13)="Watched","✓ ","▸ ")&INDEX(tblVideos[Title],L13),HYPERLINK("https://www.youtube.com/watch?v="&INDEX(tblVideos[Video ID],L13),IF(INDEX(tblVideos[Status],L13)="Watched","✓ ","▸ ")&INDEX(tblVideos[Title],L13)))) | D13: =IF(M13="","",IF(INDEX(tblVideos[Video ID],M13)="",IF(INDEX(tblVideos[Status],M13)="Watched","✓ ","▸ ")&INDEX(tblVideos[Title],M13),HYPERLINK("https://www.youtube.com/watch?v="&INDEX(tblVideos[Video ID],M13),IF(INDEX(tblVideos[Status],M13)="Watched","✓ ","▸ ")&INDEX(tblVideos[Title],M13)))) | E13: =IF(N13="","",IF(INDEX(tblVideos[Video ID],N13)="",IF(INDEX(tblVideos[Status],N13)="Watched","✓ ","▸ ")&INDEX(tblVideos[Title],N13),HYPERLINK("https://www.youtube.com/watch?v="&INDEX(tblVideos[Video ID],N13),IF(INDEX(tblVideos[Status],N13)="Watched","✓ ","▸ ")&INDEX(tblVideos[Title],N13)))) | F13: =IF(O13="","",IF(INDEX(tblVideos[Video ID],O13)="",IF(INDEX(tblVideos[Status],O13)="Watched","✓ ","▸ ")&INDEX(tblVideos[Title],O13),HYPERLINK("https://www.youtube.com/watch?v="&INDEX(tblVideos[Video ID],O13),IF(INDEX(tblVideos[Status],O13)="Watched","✓ ","▸ ")&INDEX(tblVideos[Title],O13)))) | G13: =IF(P13="","",IF(INDEX(tblVideos[Video ID],P13)="",IF(INDEX(tblVideos[Status],P13)="Watched","✓ ","▸ ")&INDEX(tblVideos[Title],P13),HYPERLINK("https://www.youtube.com/watch?v="&INDEX(tblVideos[Video ID],P13),IF(INDEX(tblVideos[Status],P13)="Watched","✓ ","▸ ")&INDEX(tblVideos[Title],P13)))) | H13: =IF(Q13="","",IF(INDEX(tblVideos[Video ID],Q13)="",IF(INDEX(tblVideos[Status],Q13)="Watched","✓ ","▸ ")&INDEX(tblVideos[Title],Q13),HYPERLINK("https://www.youtube.com/watch?v="&INDEX(tblVideos[Video ID],Q13),IF(INDEX(tblVideos[Status],Q13)="Watched","✓ ","▸ ")&INDEX(tblVideos[Title],Q13)))) | K13: =IF(S10>=3,MATCH(K10*100+3,tblVideos[Cal Key],0),"") | L13: =IF(T10>=3,MATCH(L10*100+3,tblVideos[Cal Key],0),"") | M13: =IF(U10>=3,MATCH(M10*100+3,tblVideos[Cal Key],0),"") | N13: =IF(V10>=3,MATCH(N10*100+3,tblVideos[Cal Key],0),"") | O13: =IF(W10>=3,MATCH(O10*100+3,tblVideos[Cal Key],0),"") | P13: =IF(X10>=3,MATCH(P10*100+3,tblVideos[Cal Key],0),"") | Q13: =IF(Y10>=3,MATCH(Q10*100+3,tblVideos[Cal Key],0),"") | S13: =IF(K13="","",IFERROR(MATCH(INDEX(tblVideos[Channel ID],K13),tblChannels[Channel ID],0),"")) | T13: =IF(L13="","",IFERROR(MATCH(INDEX(tblVideos[Channel ID],L13),tblChannels[Channel ID],0),"")) | U13: =IF(M13="","",IFERROR(MATCH(INDEX(tblVideos[Channel ID],M13),tblChannels[Channel ID],0),"")) | V13: =IF(N13="","",IFERROR(MATCH(INDEX(tblVideos[Channel ID],N13),tblChannels[Channel ID],0),"")) | W13: =IF(O13="","",IFERROR(MATCH(INDEX(tblVideos[Channel ID],O13),tblChannels[Channel ID],0),"")) | X13: =IF(P13="","",IFERROR(MATCH(INDEX(tblVideos[Channel ID],P13),tblChannels[Channel ID],0),"")) | Y13: =IF(Q13="","",IFERROR(MATCH(INDEX(tblVideos[Channel ID],Q13),tblChannels[Channel ID],0),""))
B14: =IF(K14="","",IF(INDEX(tblVideos[Video ID],K14)="",IF(INDEX(tblVideos[Status],K14)="Watched","✓ ","▸ ")&INDEX(tblVideos[Title],K14),HYPERLINK("https://www.youtube.com/watch?v="&INDEX(tblVideos[Video ID],K14),IF(INDEX(tblVideos[Status],K14)="Watched","✓ ","▸ ")&INDEX(tblVideos[Title],K14)))) | C14: =IF(L14="","",IF(INDEX(tblVideos[Video ID],L14)="",IF(INDEX(tblVideos[Status],L14)="Watched","✓ ","▸ ")&INDEX(tblVideos[Title],L14),HYPERLINK("https://www.youtube.com/watch?v="&INDEX(tblVideos[Video ID],L14),IF(INDEX(tblVideos[Status],L14)="Watched","✓ ","▸ ")&INDEX(tblVideos[Title],L14)))) | D14: =IF(M14="","",IF(INDEX(tblVideos[Video ID],M14)="",IF(INDEX(tblVideos[Status],M14)="Watched","✓ ","▸ ")&INDEX(tblVideos[Title],M14),HYPERLINK("https://www.youtube.com/watch?v="&INDEX(tblVideos[Video ID],M14),IF(INDEX(tblVideos[Status],M14)="Watched","✓ ","▸ ")&INDEX(tblVideos[Title],M14)))) | E14: =IF(N14="","",IF(INDEX(tblVideos[Video ID],N14)="",IF(INDEX(tblVideos[Status],N14)="Watched","✓ ","▸ ")&INDEX(tblVideos[Title],N14),HYPERLINK("https://www.youtube.com/watch?v="&INDEX(tblVideos[Video ID],N14),IF(INDEX(tblVideos[Status],N14)="Watched","✓ ","▸ ")&INDEX(tblVideos[Title],N14)))) | F14: =IF(O14="","",IF(INDEX(tblVideos[Video ID],O14)="",IF(INDEX(tblVideos[Status],O14)="Watched","✓ ","▸ ")&INDEX(tblVideos[Title],O14),HYPERLINK("https://www.youtube.com/watch?v="&INDEX(tblVideos[Video ID],O14),IF(INDEX(tblVideos[Status],O14)="Watched","✓ ","▸ ")&INDEX(tblVideos[Title],O14)))) | G14: =IF(P14="","",IF(INDEX(tblVideos[Video ID],P14)="",IF(INDEX(tblVideos[Status],P14)="Watched","✓ ","▸ ")&INDEX(tblVideos[Title],P14),HYPERLINK("https://www.youtube.com/watch?v="&INDEX(tblVideos[Video ID],P14),IF(INDEX(tblVideos[Status],P14)="Watched","✓ ","▸ ")&INDEX(tblVideos[Title],P14)))) | H14: =IF(Q14="","",IF(INDEX(tblVideos[Video ID],Q14)="",IF(INDEX(tblVideos[Status],Q14)="Watched","✓ ","▸ ")&INDEX(tblVideos[Title],Q14),HYPERLINK("https://www.youtube.com/watch?v="&INDEX(tblVideos[Video ID],Q14),IF(INDEX(tblVideos[Status],Q14)="Watched","✓ ","▸ ")&INDEX(tblVideos[Title],Q14)))) | K14: =IF(S10>=4,MATCH(K10*100+4,tblVideos[Cal Key],0),"") | L14: =IF(T10>=4,MATCH(L10*100+4,tblVideos[Cal Key],0),"") | M14: =IF(U10>=4,MATCH(M10*100+4,tblVideos[Cal Key],0),"") | N14: =IF(V10>=4,MATCH(N10*100+4,tblVideos[Cal Key],0),"") | O14: =IF(W10>=4,MATCH(O10*100+4,tblVideos[Cal Key],0),"") | P14: =IF(X10>=4,MATCH(P10*100+4,tblVideos[Cal Key],0),"") | Q14: =IF(Y10>=4,MATCH(Q10*100+4,tblVideos[Cal Key],0),"") | S14: =IF(K14="","",IFERROR(MATCH(INDEX(tblVideos[Channel ID],K14),tblChannels[Channel ID],0),"")) | T14: =IF(L14="","",IFERROR(MATCH(INDEX(tblVideos[Channel ID],L14),tblChannels[Channel ID],0),"")) | U14: =IF(M14="","",IFERROR(MATCH(INDEX(tblVideos[Channel ID],M14),tblChannels[Channel ID],0),"")) | V14: =IF(N14="","",IFERROR(MATCH(INDEX(tblVideos[Channel ID],N14),tblChannels[Channel ID],0),"")) | W14: =IF(O14="","",IFERROR(MATCH(INDEX(tblVideos[Channel ID],O14),tblChannels[Channel ID],0),"")) | X14: =IF(P14="","",IFERROR(MATCH(INDEX(tblVideos[Channel ID],P14),tblChannels[Channel ID],0),"")) | Y14: =IF(Q14="","",IFERROR(MATCH(INDEX(tblVideos[Channel ID],Q14),tblChannels[Channel ID],0),""))
B15: =IF(K15="","",IF(INDEX(tblVideos[Video ID],K15)="",IF(INDEX(tblVideos[Status],K15)="Watched","✓ ","▸ ")&INDEX(tblVideos[Title],K15),HYPERLINK("https://www.youtube.com/watch?v="&INDEX(tblVideos[Video ID],K15),IF(INDEX(tblVideos[Status],K15)="Watched","✓ ","▸ ")&INDEX(tblVideos[Title],K15)))) | C15: =IF(L15="","",IF(INDEX(tblVideos[Video ID],L15)="",IF(INDEX(tblVideos[Status],L15)="Watched","✓ ","▸ ")&INDEX(tblVideos[Title],L15),HYPERLINK("https://www.youtube.com/watch?v="&INDEX(tblVideos[Video ID],L15),IF(INDEX(tblVideos[Status],L15)="Watched","✓ ","▸ ")&INDEX(tblVideos[Title],L15)))) | D15: =IF(M15="","",IF(INDEX(tblVideos[Video ID],M15)="",IF(INDEX(tblVideos[Status],M15)="Watched","✓ ","▸ ")&INDEX(tblVideos[Title],M15),HYPERLINK("https://www.youtube.com/watch?v="&INDEX(tblVideos[Video ID],M15),IF(INDEX(tblVideos[Status],M15)="Watched","✓ ","▸ ")&INDEX(tblVideos[Title],M15)))) | E15: =IF(N15="","",IF(INDEX(tblVideos[Video ID],N15)="",IF(INDEX(tblVideos[Status],N15)="Watched","✓ ","▸ ")&INDEX(tblVideos[Title],N15),HYPERLINK("https://www.youtube.com/watch?v="&INDEX(tblVideos[Video ID],N15),IF(INDEX(tblVideos[Status],N15)="Watched","✓ ","▸ ")&INDEX(tblVideos[Title],N15)))) | F15: =IF(O15="","",IF(INDEX(tblVideos[Video ID],O15)="",IF(INDEX(tblVideos[Status],O15)="Watched","✓ ","▸ ")&INDEX(tblVideos[Title],O15),HYPERLINK("https://www.youtube.com/watch?v="&INDEX(tblVideos[Video ID],O15),IF(INDEX(tblVideos[Status],O15)="Watched","✓ ","▸ ")&INDEX(tblVideos[Title],O15)))) | G15: =IF(P15="","",IF(INDEX(tblVideos[Video ID],P15)="",IF(INDEX(tblVideos[Status],P15)="Watched","✓ ","▸ ")&INDEX(tblVideos[Title],P15),HYPERLINK("https://www.youtube.com/watch?v="&INDEX(tblVideos[Video ID],P15),IF(INDEX(tblVideos[Status],P15)="Watched","✓ ","▸ ")&INDEX(tblVideos[Title],P15)))) | H15: =IF(Q15="","",IF(INDEX(tblVideos[Video ID],Q15)="",IF(INDEX(tblVideos[Status],Q15)="Watched","✓ ","▸ ")&INDEX(tblVideos[Title],Q15),HYPERLINK("https://www.youtube.com/watch?v="&INDEX(tblVideos[Video ID],Q15),IF(INDEX(tblVideos[Status],Q15)="Watched","✓ ","▸ ")&INDEX(tblVideos[Title],Q15)))) | K15: =IF(S10>=5,MATCH(K10*100+5,tblVideos[Cal Key],0),"") | L15: =IF(T10>=5,MATCH(L10*100+5,tblVideos[Cal Key],0),"") | M15: =IF(U10>=5,MATCH(M10*100+5,tblVideos[Cal Key],0),"") | N15: =IF(V10>=5,MATCH(N10*100+5,tblVideos[Cal Key],0),"") | O15: =IF(W10>=5,MATCH(O10*100+5,tblVideos[Cal Key],0),"") | P15: =IF(X10>=5,MATCH(P10*100+5,tblVideos[Cal Key],0),"") | Q15: =IF(Y10>=5,MATCH(Q10*100+5,tblVideos[Cal Key],0),"") | S15: =IF(K15="","",IFERROR(MATCH(INDEX(tblVideos[Channel ID],K15),tblChannels[Channel ID],0),"")) | T15: =IF(L15="","",IFERROR(MATCH(INDEX(tblVideos[Channel ID],L15),tblChannels[Channel ID],0),"")) | U15: =IF(M15="","",IFERROR(MATCH(INDEX(tblVideos[Channel ID],M15),tblChannels[Channel ID],0),"")) | V15: =IF(N15="","",IFERROR(MATCH(INDEX(tblVideos[Channel ID],N15),tblChannels[Channel ID],0),"")) | W15: =IF(O15="","",IFERROR(MATCH(INDEX(tblVideos[Channel ID],O15),tblChannels[Channel ID],0),"")) | X15: =IF(P15="","",IFERROR(MATCH(INDEX(tblVideos[Channel ID],P15),tblChannels[Channel ID],0),"")) | Y15: =IF(Q15="","",IFERROR(MATCH(INDEX(tblVideos[Channel ID],Q15),tblChannels[Channel ID],0),""))
B16: =IF(MONTH(K16)=MONTH($K$2),DAY(K16)&IF(S16>0," · "&S16&IF(S16=1," video"," videos")&" · "&TEXT(AA16,"[h]:mm")&IF(S16>5," (+"&(S16-5)&" more)",""),""),"") | C16: =IF(MONTH(L16)=MONTH($K$2),DAY(L16)&IF(T16>0," · "&T16&IF(T16=1," video"," videos")&" · "&TEXT(AB16,"[h]:mm")&IF(T16>5," (+"&(T16-5)&" more)",""),""),"") | D16: =IF(MONTH(M16)=MONTH($K$2),DAY(M16)&IF(U16>0," · "&U16&IF(U16=1," video"," videos")&" · "&TEXT(AC16,"[h]:mm")&IF(U16>5," (+"&(U16-5)&" more)",""),""),"") | E16: =IF(MONTH(N16)=MONTH($K$2),DAY(N16)&IF(V16>0," · "&V16&IF(V16=1," video"," videos")&" · "&TEXT(AD16,"[h]:mm")&IF(V16>5," (+"&(V16-5)&" more)",""),""),"") | F16: =IF(MONTH(O16)=MONTH($K$2),DAY(O16)&IF(W16>0," · "&W16&IF(W16=1," video"," videos")&" · "&TEXT(AE16,"[h]:mm")&IF(W16>5," (+"&(W16-5)&" more)",""),""),"") | G16: =IF(MONTH(P16)=MONTH($K$2),DAY(P16)&IF(X16>0," · "&X16&IF(X16=1," video"," videos")&" · "&TEXT(AF16,"[h]:mm")&IF(X16>5," (+"&(X16-5)&" more)",""),""),"") | H16: =IF(MONTH(Q16)=MONTH($K$2),DAY(Q16)&IF(Y16>0," · "&Y16&IF(Y16=1," video"," videos")&" · "&TEXT(AG16,"[h]:mm")&IF(Y16>5," (+"&(Y16-5)&" more)",""),""),"") | K16: =$K$3+7 | L16: =$K$3+8 | M16: =$K$3+9 | N16: =$K$3+10 | O16: =$K$3+11 | P16: =$K$3+12 | Q16: =$K$3+13 | S16: =IF(MONTH(K16)=MONTH($K$2),COUNTIFS(tblVideos[Day],K16,tblVideos[Channel ID],$K$4),0) | T16: =IF(MONTH(L16)=MONTH($K$2),COUNTIFS(tblVideos[Day],L16,tblVideos[Channel ID],$K$4),0) | U16: =IF(MONTH(M16)=MONTH($K$2),COUNTIFS(tblVideos[Day],M16,tblVideos[Channel ID],$K$4),0) | V16: =IF(MONTH(N16)=MONTH($K$2),COUNTIFS(tblVideos[Day],N16,tblVideos[Channel ID],$K$4),0) | W16: =IF(MONTH(O16)=MONTH($K$2),COUNTIFS(tblVideos[Day],O16,tblVideos[Channel ID],$K$4),0) | X16: =IF(MONTH(P16)=MONTH($K$2),COUNTIFS(tblVideos[Day],P16,tblVideos[Channel ID],$K$4),0) | Y16: =IF(MONTH(Q16)=MONTH($K$2),COUNTIFS(tblVideos[Day],Q16,tblVideos[Channel ID],$K$4),0) | AA16: =IF(S16>0,SUMIFS(tblVideos[Length],tblVideos[Day],K16,tblVideos[Channel ID],$K$4),0) | AB16: =IF(T16>0,SUMIFS(tblVideos[Length],tblVideos[Day],L16,tblVideos[Channel ID],$K$4),0) | AC16: =IF(U16>0,SUMIFS(tblVideos[Length],tblVideos[Day],M16,tblVideos[Channel ID],$K$4),0) | AD16: =IF(V16>0,SUMIFS(tblVideos[Length],tblVideos[Day],N16,tblVideos[Channel ID],$K$4),0) | AE16: =IF(W16>0,SUMIFS(tblVideos[Length],tblVideos[Day],O16,tblVideos[Channel ID],$K$4),0) | AF16: =IF(X16>0,SUMIFS(tblVideos[Length],tblVideos[Day],P16,tblVideos[Channel ID],$K$4),0) | AG16: =IF(Y16>0,SUMIFS(tblVideos[Length],tblVideos[Day],Q16,tblVideos[Channel ID],$K$4),0)
B17: =IF(K17="","",IF(INDEX(tblVideos[Video ID],K17)="",IF(INDEX(tblVideos[Status],K17)="Watched","✓ ","▸ ")&INDEX(tblVideos[Title],K17),HYPERLINK("https://www.youtube.com/watch?v="&INDEX(tblVideos[Video ID],K17),IF(INDEX(tblVideos[Status],K17)="Watched","✓ ","▸ ")&INDEX(tblVideos[Title],K17)))) | C17: =IF(L17="","",IF(INDEX(tblVideos[Video ID],L17)="",IF(INDEX(tblVideos[Status],L17)="Watched","✓ ","▸ ")&INDEX(tblVideos[Title],L17),HYPERLINK("https://www.youtube.com/watch?v="&INDEX(tblVideos[Video ID],L17),IF(INDEX(tblVideos[Status],L17)="Watched","✓ ","▸ ")&INDEX(tblVideos[Title],L17)))) | D17: =IF(M17="","",IF(INDEX(tblVideos[Video ID],M17)="",IF(INDEX(tblVideos[Status],M17)="Watched","✓ ","▸ ")&INDEX(tblVideos[Title],M17),HYPERLINK("https://www.youtube.com/watch?v="&INDEX(tblVideos[Video ID],M17),IF(INDEX(tblVideos[Status],M17)="Watched","✓ ","▸ ")&INDEX(tblVideos[Title],M17)))) | E17: =IF(N17="","",IF(INDEX(tblVideos[Video ID],N17)="",IF(INDEX(tblVideos[Status],N17)="Watched","✓ ","▸ ")&INDEX(tblVideos[Title],N17),HYPERLINK("https://www.youtube.com/watch?v="&INDEX(tblVideos[Video ID],N17),IF(INDEX(tblVideos[Status],N17)="Watched","✓ ","▸ ")&INDEX(tblVideos[Title],N17)))) | F17: =IF(O17="","",IF(INDEX(tblVideos[Video ID],O17)="",IF(INDEX(tblVideos[Status],O17)="Watched","✓ ","▸ ")&INDEX(tblVideos[Title],O17),HYPERLINK("https://www.youtube.com/watch?v="&INDEX(tblVideos[Video ID],O17),IF(INDEX(tblVideos[Status],O17)="Watched","✓ ","▸ ")&INDEX(tblVideos[Title],O17)))) | G17: =IF(P17="","",IF(INDEX(tblVideos[Video ID],P17)="",IF(INDEX(tblVideos[Status],P17)="Watched","✓ ","▸ ")&INDEX(tblVideos[Title],P17),HYPERLINK("https://www.youtube.com/watch?v="&INDEX(tblVideos[Video ID],P17),IF(INDEX(tblVideos[Status],P17)="Watched","✓ ","▸ ")&INDEX(tblVideos[Title],P17)))) | H17: =IF(Q17="","",IF(INDEX(tblVideos[Video ID],Q17)="",IF(INDEX(tblVideos[Status],Q17)="Watched","✓ ","▸ ")&INDEX(tblVideos[Title],Q17),HYPERLINK("https://www.youtube.com/watch?v="&INDEX(tblVideos[Video ID],Q17),IF(INDEX(tblVideos[Status],Q17)="Watched","✓ ","▸ ")&INDEX(tblVideos[Title],Q17)))) | K17: =IF(S16>=1,MATCH(K16*100+1,tblVideos[Cal Key],0),"") | L17: =IF(T16>=1,MATCH(L16*100+1,tblVideos[Cal Key],0),"") | M17: =IF(U16>=1,MATCH(M16*100+1,tblVideos[Cal Key],0),"") | N17: =IF(V16>=1,MATCH(N16*100+1,tblVideos[Cal Key],0),"") | O17: =IF(W16>=1,MATCH(O16*100+1,tblVideos[Cal Key],0),"") | P17: =IF(X16>=1,MATCH(P16*100+1,tblVideos[Cal Key],0),"") | Q17: =IF(Y16>=1,MATCH(Q16*100+1,tblVideos[Cal Key],0),"") | S17: =IF(K17="","",IFERROR(MATCH(INDEX(tblVideos[Channel ID],K17),tblChannels[Channel ID],0),"")) | T17: =IF(L17="","",IFERROR(MATCH(INDEX(tblVideos[Channel ID],L17),tblChannels[Channel ID],0),"")) | U17: =IF(M17="","",IFERROR(MATCH(INDEX(tblVideos[Channel ID],M17),tblChannels[Channel ID],0),"")) | V17: =IF(N17="","",IFERROR(MATCH(INDEX(tblVideos[Channel ID],N17),tblChannels[Channel ID],0),"")) | W17: =IF(O17="","",IFERROR(MATCH(INDEX(tblVideos[Channel ID],O17),tblChannels[Channel ID],0),"")) | X17: =IF(P17="","",IFERROR(MATCH(INDEX(tblVideos[Channel ID],P17),tblChannels[Channel ID],0),"")) | Y17: =IF(Q17="","",IFERROR(MATCH(INDEX(tblVideos[Channel ID],Q17),tblChannels[Channel ID],0),""))
B18: =IF(K18="","",IF(INDEX(tblVideos[Video ID],K18)="",IF(INDEX(tblVideos[Status],K18)="Watched","✓ ","▸ ")&INDEX(tblVideos[Title],K18),HYPERLINK("https://www.youtube.com/watch?v="&INDEX(tblVideos[Video ID],K18),IF(INDEX(tblVideos[Status],K18)="Watched","✓ ","▸ ")&INDEX(tblVideos[Title],K18)))) | C18: =IF(L18="","",IF(INDEX(tblVideos[Video ID],L18)="",IF(INDEX(tblVideos[Status],L18)="Watched","✓ ","▸ ")&INDEX(tblVideos[Title],L18),HYPERLINK("https://www.youtube.com/watch?v="&INDEX(tblVideos[Video ID],L18),IF(INDEX(tblVideos[Status],L18)="Watched","✓ ","▸ ")&INDEX(tblVideos[Title],L18)))) | D18: =IF(M18="","",IF(INDEX(tblVideos[Video ID],M18)="",IF(INDEX(tblVideos[Status],M18)="Watched","✓ ","▸ ")&INDEX(tblVideos[Title],M18),HYPERLINK("https://www.youtube.com/watch?v="&INDEX(tblVideos[Video ID],M18),IF(INDEX(tblVideos[Status],M18)="Watched","✓ ","▸ ")&INDEX(tblVideos[Title],M18)))) | E18: =IF(N18="","",IF(INDEX(tblVideos[Video ID],N18)="",IF(INDEX(tblVideos[Status],N18)="Watched","✓ ","▸ ")&INDEX(tblVideos[Title],N18),HYPERLINK("https://www.youtube.com/watch?v="&INDEX(tblVideos[Video ID],N18),IF(INDEX(tblVideos[Status],N18)="Watched","✓ ","▸ ")&INDEX(tblVideos[Title],N18)))) | F18: =IF(O18="","",IF(INDEX(tblVideos[Video ID],O18)="",IF(INDEX(tblVideos[Status],O18)="Watched","✓ ","▸ ")&INDEX(tblVideos[Title],O18),HYPERLINK("https://www.youtube.com/watch?v="&INDEX(tblVideos[Video ID],O18),IF(INDEX(tblVideos[Status],O18)="Watched","✓ ","▸ ")&INDEX(tblVideos[Title],O18)))) | G18: =IF(P18="","",IF(INDEX(tblVideos[Video ID],P18)="",IF(INDEX(tblVideos[Status],P18)="Watched","✓ ","▸ ")&INDEX(tblVideos[Title],P18),HYPERLINK("https://www.youtube.com/watch?v="&INDEX(tblVideos[Video ID],P18),IF(INDEX(tblVideos[Status],P18)="Watched","✓ ","▸ ")&INDEX(tblVideos[Title],P18)))) | H18: =IF(Q18="","",IF(INDEX(tblVideos[Video ID],Q18)="",IF(INDEX(tblVideos[Status],Q18)="Watched","✓ ","▸ ")&INDEX(tblVideos[Title],Q18),HYPERLINK("https://www.youtube.com/watch?v="&INDEX(tblVideos[Video ID],Q18),IF(INDEX(tblVideos[Status],Q18)="Watched","✓ ","▸ ")&INDEX(tblVideos[Title],Q18)))) | K18: =IF(S16>=2,MATCH(K16*100+2,tblVideos[Cal Key],0),"") | L18: =IF(T16>=2,MATCH(L16*100+2,tblVideos[Cal Key],0),"") | M18: =IF(U16>=2,MATCH(M16*100+2,tblVideos[Cal Key],0),"") | N18: =IF(V16>=2,MATCH(N16*100+2,tblVideos[Cal Key],0),"") | O18: =IF(W16>=2,MATCH(O16*100+2,tblVideos[Cal Key],0),"") | P18: =IF(X16>=2,MATCH(P16*100+2,tblVideos[Cal Key],0),"") | Q18: =IF(Y16>=2,MATCH(Q16*100+2,tblVideos[Cal Key],0),"") | S18: =IF(K18="","",IFERROR(MATCH(INDEX(tblVideos[Channel ID],K18),tblChannels[Channel ID],0),"")) | T18: =IF(L18="","",IFERROR(MATCH(INDEX(tblVideos[Channel ID],L18),tblChannels[Channel ID],0),"")) | U18: =IF(M18="","",IFERROR(MATCH(INDEX(tblVideos[Channel ID],M18),tblChannels[Channel ID],0),"")) | V18: =IF(N18="","",IFERROR(MATCH(INDEX(tblVideos[Channel ID],N18),tblChannels[Channel ID],0),"")) | W18: =IF(O18="","",IFERROR(MATCH(INDEX(tblVideos[Channel ID],O18),tblChannels[Channel ID],0),"")) | X18: =IF(P18="","",IFERROR(MATCH(INDEX(tblVideos[Channel ID],P18),tblChannels[Channel ID],0),"")) | Y18: =IF(Q18="","",IFERROR(MATCH(INDEX(tblVideos[Channel ID],Q18),tblChannels[Channel ID],0),""))
B19: =IF(K19="","",IF(INDEX(tblVideos[Video ID],K19)="",IF(INDEX(tblVideos[Status],K19)="Watched","✓ ","▸ ")&INDEX(tblVideos[Title],K19),HYPERLINK("https://www.youtube.com/watch?v="&INDEX(tblVideos[Video ID],K19),IF(INDEX(tblVideos[Status],K19)="Watched","✓ ","▸ ")&INDEX(tblVideos[Title],K19)))) | C19: =IF(L19="","",IF(INDEX(tblVideos[Video ID],L19)="",IF(INDEX(tblVideos[Status],L19)="Watched","✓ ","▸ ")&INDEX(tblVideos[Title],L19),HYPERLINK("https://www.youtube.com/watch?v="&INDEX(tblVideos[Video ID],L19),IF(INDEX(tblVideos[Status],L19)="Watched","✓ ","▸ ")&INDEX(tblVideos[Title],L19)))) | D19: =IF(M19="","",IF(INDEX(tblVideos[Video ID],M19)="",IF(INDEX(tblVideos[Status],M19)="Watched","✓ ","▸ ")&INDEX(tblVideos[Title],M19),HYPERLINK("https://www.youtube.com/watch?v="&INDEX(tblVideos[Video ID],M19),IF(INDEX(tblVideos[Status],M19)="Watched","✓ ","▸ ")&INDEX(tblVideos[Title],M19)))) | E19: =IF(N19="","",IF(INDEX(tblVideos[Video ID],N19)="",IF(INDEX(tblVideos[Status],N19)="Watched","✓ ","▸ ")&INDEX(tblVideos[Title],N19),HYPERLINK("https://www.youtube.com/watch?v="&INDEX(tblVideos[Video ID],N19),IF(INDEX(tblVideos[Status],N19)="Watched","✓ ","▸ ")&INDEX(tblVideos[Title],N19)))) | F19: =IF(O19="","",IF(INDEX(tblVideos[Video ID],O19)="",IF(INDEX(tblVideos[Status],O19)="Watched","✓ ","▸ ")&INDEX(tblVideos[Title],O19),HYPERLINK("https://www.youtube.com/watch?v="&INDEX(tblVideos[Video ID],O19),IF(INDEX(tblVideos[Status],O19)="Watched","✓ ","▸ ")&INDEX(tblVideos[Title],O19)))) | G19: =IF(P19="","",IF(INDEX(tblVideos[Video ID],P19)="",IF(INDEX(tblVideos[Status],P19)="Watched","✓ ","▸ ")&INDEX(tblVideos[Title],P19),HYPERLINK("https://www.youtube.com/watch?v="&INDEX(tblVideos[Video ID],P19),IF(INDEX(tblVideos[Status],P19)="Watched","✓ ","▸ ")&INDEX(tblVideos[Title],P19)))) | H19: =IF(Q19="","",IF(INDEX(tblVideos[Video ID],Q19)="",IF(INDEX(tblVideos[Status],Q19)="Watched","✓ ","▸ ")&INDEX(tblVideos[Title],Q19),HYPERLINK("https://www.youtube.com/watch?v="&INDEX(tblVideos[Video ID],Q19),IF(INDEX(tblVideos[Status],Q19)="Watched","✓ ","▸ ")&INDEX(tblVideos[Title],Q19)))) | K19: =IF(S16>=3,MATCH(K16*100+3,tblVideos[Cal Key],0),"") | L19: =IF(T16>=3,MATCH(L16*100+3,tblVideos[Cal Key],0),"") | M19: =IF(U16>=3,MATCH(M16*100+3,tblVideos[Cal Key],0),"") | N19: =IF(V16>=3,MATCH(N16*100+3,tblVideos[Cal Key],0),"") | O19: =IF(W16>=3,MATCH(O16*100+3,tblVideos[Cal Key],0),"") | P19: =IF(X16>=3,MATCH(P16*100+3,tblVideos[Cal Key],0),"") | Q19: =IF(Y16>=3,MATCH(Q16*100+3,tblVideos[Cal Key],0),"") | S19: =IF(K19="","",IFERROR(MATCH(INDEX(tblVideos[Channel ID],K19),tblChannels[Channel ID],0),"")) | T19: =IF(L19="","",IFERROR(MATCH(INDEX(tblVideos[Channel ID],L19),tblChannels[Channel ID],0),"")) | U19: =IF(M19="","",IFERROR(MATCH(INDEX(tblVideos[Channel ID],M19),tblChannels[Channel ID],0),"")) | V19: =IF(N19="","",IFERROR(MATCH(INDEX(tblVideos[Channel ID],N19),tblChannels[Channel ID],0),"")) | W19: =IF(O19="","",IFERROR(MATCH(INDEX(tblVideos[Channel ID],O19),tblChannels[Channel ID],0),"")) | X19: =IF(P19="","",IFERROR(MATCH(INDEX(tblVideos[Channel ID],P19),tblChannels[Channel ID],0),"")) | Y19: =IF(Q19="","",IFERROR(MATCH(INDEX(tblVideos[Channel ID],Q19),tblChannels[Channel ID],0),""))
B20: =IF(K20="","",IF(INDEX(tblVideos[Video ID],K20)="",IF(INDEX(tblVideos[Status],K20)="Watched","✓ ","▸ ")&INDEX(tblVideos[Title],K20),HYPERLINK("https://www.youtube.com/watch?v="&INDEX(tblVideos[Video ID],K20),IF(INDEX(tblVideos[Status],K20)="Watched","✓ ","▸ ")&INDEX(tblVideos[Title],K20)))) | C20: =IF(L20="","",IF(INDEX(tblVideos[Video ID],L20)="",IF(INDEX(tblVideos[Status],L20)="Watched","✓ ","▸ ")&INDEX(tblVideos[Title],L20),HYPERLINK("https://www.youtube.com/watch?v="&INDEX(tblVideos[Video ID],L20),IF(INDEX(tblVideos[Status],L20)="Watched","✓ ","▸ ")&INDEX(tblVideos[Title],L20)))) | D20: =IF(M20="","",IF(INDEX(tblVideos[Video ID],M20)="",IF(INDEX(tblVideos[Status],M20)="Watched","✓ ","▸ ")&INDEX(tblVideos[Title],M20),HYPERLINK("https://www.youtube.com/watch?v="&INDEX(tblVideos[Video ID],M20),IF(INDEX(tblVideos[Status],M20)="Watched","✓ ","▸ ")&INDEX(tblVideos[Title],M20)))) | E20: =IF(N20="","",IF(INDEX(tblVideos[Video ID],N20)="",IF(INDEX(tblVideos[Status],N20)="Watched","✓ ","▸ ")&INDEX(tblVideos[Title],N20),HYPERLINK("https://www.youtube.com/watch?v="&INDEX(tblVideos[Video ID],N20),IF(INDEX(tblVideos[Status],N20)="Watched","✓ ","▸ ")&INDEX(tblVideos[Title],N20)))) | F20: =IF(O20="","",IF(INDEX(tblVideos[Video ID],O20)="",IF(INDEX(tblVideos[Status],O20)="Watched","✓ ","▸ ")&INDEX(tblVideos[Title],O20),HYPERLINK("https://www.youtube.com/watch?v="&INDEX(tblVideos[Video ID],O20),IF(INDEX(tblVideos[Status],O20)="Watched","✓ ","▸ ")&INDEX(tblVideos[Title],O20)))) | G20: =IF(P20="","",IF(INDEX(tblVideos[Video ID],P20)="",IF(INDEX(tblVideos[Status],P20)="Watched","✓ ","▸ ")&INDEX(tblVideos[Title],P20),HYPERLINK("https://www.youtube.com/watch?v="&INDEX(tblVideos[Video ID],P20),IF(INDEX(tblVideos[Status],P20)="Watched","✓ ","▸ ")&INDEX(tblVideos[Title],P20)))) | H20: =IF(Q20="","",IF(INDEX(tblVideos[Video ID],Q20)="",IF(INDEX(tblVideos[Status],Q20)="Watched","✓ ","▸ ")&INDEX(tblVideos[Title],Q20),HYPERLINK("https://www.youtube.com/watch?v="&INDEX(tblVideos[Video ID],Q20),IF(INDEX(tblVideos[Status],Q20)="Watched","✓ ","▸ ")&INDEX(tblVideos[Title],Q20)))) | K20: =IF(S16>=4,MATCH(K16*100+4,tblVideos[Cal Key],0),"") | L20: =IF(T16>=4,MATCH(L16*100+4,tblVideos[Cal Key],0),"") | M20: =IF(U16>=4,MATCH(M16*100+4,tblVideos[Cal Key],0),"") | N20: =IF(V16>=4,MATCH(N16*100+4,tblVideos[Cal Key],0),"") | O20: =IF(W16>=4,MATCH(O16*100+4,tblVideos[Cal Key],0),"") | P20: =IF(X16>=4,MATCH(P16*100+4,tblVideos[Cal Key],0),"") | Q20: =IF(Y16>=4,MATCH(Q16*100+4,tblVideos[Cal Key],0),"") | S20: =IF(K20="","",IFERROR(MATCH(INDEX(tblVideos[Channel ID],K20),tblChannels[Channel ID],0),"")) | T20: =IF(L20="","",IFERROR(MATCH(INDEX(tblVideos[Channel ID],L20),tblChannels[Channel ID],0),"")) | U20: =IF(M20="","",IFERROR(MATCH(INDEX(tblVideos[Channel ID],M20),tblChannels[Channel ID],0),"")) | V20: =IF(N20="","",IFERROR(MATCH(INDEX(tblVideos[Channel ID],N20),tblChannels[Channel ID],0),"")) | W20: =IF(O20="","",IFERROR(MATCH(INDEX(tblVideos[Channel ID],O20),tblChannels[Channel ID],0),"")) | X20: =IF(P20="","",IFERROR(MATCH(INDEX(tblVideos[Channel ID],P20),tblChannels[Channel ID],0),"")) | Y20: =IF(Q20="","",IFERROR(MATCH(INDEX(tblVideos[Channel ID],Q20),tblChannels[Channel ID],0),""))
B21: =IF(K21="","",IF(INDEX(tblVideos[Video ID],K21)="",IF(INDEX(tblVideos[Status],K21)="Watched","✓ ","▸ ")&INDEX(tblVideos[Title],K21),HYPERLINK("https://www.youtube.com/watch?v="&INDEX(tblVideos[Video ID],K21),IF(INDEX(tblVideos[Status],K21)="Watched","✓ ","▸ ")&INDEX(tblVideos[Title],K21)))) | C21: =IF(L21="","",IF(INDEX(tblVideos[Video ID],L21)="",IF(INDEX(tblVideos[Status],L21)="Watched","✓ ","▸ ")&INDEX(tblVideos[Title],L21),HYPERLINK("https://www.youtube.com/watch?v="&INDEX(tblVideos[Video ID],L21),IF(INDEX(tblVideos[Status],L21)="Watched","✓ ","▸ ")&INDEX(tblVideos[Title],L21)))) | D21: =IF(M21="","",IF(INDEX(tblVideos[Video ID],M21)="",IF(INDEX(tblVideos[Status],M21)="Watched","✓ ","▸ ")&INDEX(tblVideos[Title],M21),HYPERLINK("https://www.youtube.com/watch?v="&INDEX(tblVideos[Video ID],M21),IF(INDEX(tblVideos[Status],M21)="Watched","✓ ","▸ ")&INDEX(tblVideos[Title],M21)))) | E21: =IF(N21="","",IF(INDEX(tblVideos[Video ID],N21)="",IF(INDEX(tblVideos[Status],N21)="Watched","✓ ","▸ ")&INDEX(tblVideos[Title],N21),HYPERLINK("https://www.youtube.com/watch?v="&INDEX(tblVideos[Video ID],N21),IF(INDEX(tblVideos[Status],N21)="Watched","✓ ","▸ ")&INDEX(tblVideos[Title],N21)))) | F21: =IF(O21="","",IF(INDEX(tblVideos[Video ID],O21)="",IF(INDEX(tblVideos[Status],O21)="Watched","✓ ","▸ ")&INDEX(tblVideos[Title],O21),HYPERLINK("https://www.youtube.com/watch?v="&INDEX(tblVideos[Video ID],O21),IF(INDEX(tblVideos[Status],O21)="Watched","✓ ","▸ ")&INDEX(tblVideos[Title],O21)))) | G21: =IF(P21="","",IF(INDEX(tblVideos[Video ID],P21)="",IF(INDEX(tblVideos[Status],P21)="Watched","✓ ","▸ ")&INDEX(tblVideos[Title],P21),HYPERLINK("https://www.youtube.com/watch?v="&INDEX(tblVideos[Video ID],P21),IF(INDEX(tblVideos[Status],P21)="Watched","✓ ","▸ ")&INDEX(tblVideos[Title],P21)))) | H21: =IF(Q21="","",IF(INDEX(tblVideos[Video ID],Q21)="",IF(INDEX(tblVideos[Status],Q21)="Watched","✓ ","▸ ")&INDEX(tblVideos[Title],Q21),HYPERLINK("https://www.youtube.com/watch?v="&INDEX(tblVideos[Video ID],Q21),IF(INDEX(tblVideos[Status],Q21)="Watched","✓ ","▸ ")&INDEX(tblVideos[Title],Q21)))) | K21: =IF(S16>=5,MATCH(K16*100+5,tblVideos[Cal Key],0),"") | L21: =IF(T16>=5,MATCH(L16*100+5,tblVideos[Cal Key],0),"") | M21: =IF(U16>=5,MATCH(M16*100+5,tblVideos[Cal Key],0),"") | N21: =IF(V16>=5,MATCH(N16*100+5,tblVideos[Cal Key],0),"") | O21: =IF(W16>=5,MATCH(O16*100+5,tblVideos[Cal Key],0),"") | P21: =IF(X16>=5,MATCH(P16*100+5,tblVideos[Cal Key],0),"") | Q21: =IF(Y16>=5,MATCH(Q16*100+5,tblVideos[Cal Key],0),"") | S21: =IF(K21="","",IFERROR(MATCH(INDEX(tblVideos[Channel ID],K21),tblChannels[Channel ID],0),"")) | T21: =IF(L21="","",IFERROR(MATCH(INDEX(tblVideos[Channel ID],L21),tblChannels[Channel ID],0),"")) | U21: =IF(M21="","",IFERROR(MATCH(INDEX(tblVideos[Channel ID],M21),tblChannels[Channel ID],0),"")) | V21: =IF(N21="","",IFERROR(MATCH(INDEX(tblVideos[Channel ID],N21),tblChannels[Channel ID],0),"")) | W21: =IF(O21="","",IFERROR(MATCH(INDEX(tblVideos[Channel ID],O21),tblChannels[Channel ID],0),"")) | X21: =IF(P21="","",IFERROR(MATCH(INDEX(tblVideos[Channel ID],P21),tblChannels[Channel ID],0),"")) | Y21: =IF(Q21="","",IFERROR(MATCH(INDEX(tblVideos[Channel ID],Q21),tblChannels[Channel ID],0),""))
B22: =IF(MONTH(K22)=MONTH($K$2),DAY(K22)&IF(S22>0," · "&S22&IF(S22=1," video"," videos")&" · "&TEXT(AA22,"[h]:mm")&IF(S22>5," (+"&(S22-5)&" more)",""),""),"") | C22: =IF(MONTH(L22)=MONTH($K$2),DAY(L22)&IF(T22>0," · "&T22&IF(T22=1," video"," videos")&" · "&TEXT(AB22,"[h]:mm")&IF(T22>5," (+"&(T22-5)&" more)",""),""),"") | D22: =IF(MONTH(M22)=MONTH($K$2),DAY(M22)&IF(U22>0," · "&U22&IF(U22=1," video"," videos")&" · "&TEXT(AC22,"[h]:mm")&IF(U22>5," (+"&(U22-5)&" more)",""),""),"") | E22: =IF(MONTH(N22)=MONTH($K$2),DAY(N22)&IF(V22>0," · "&V22&IF(V22=1," video"," videos")&" · "&TEXT(AD22,"[h]:mm")&IF(V22>5," (+"&(V22-5)&" more)",""),""),"") | F22: =IF(MONTH(O22)=MONTH($K$2),DAY(O22)&IF(W22>0," · "&W22&IF(W22=1," video"," videos")&" · "&TEXT(AE22,"[h]:mm")&IF(W22>5," (+"&(W22-5)&" more)",""),""),"") | G22: =IF(MONTH(P22)=MONTH($K$2),DAY(P22)&IF(X22>0," · "&X22&IF(X22=1," video"," videos")&" · "&TEXT(AF22,"[h]:mm")&IF(X22>5," (+"&(X22-5)&" more)",""),""),"") | H22: =IF(MONTH(Q22)=MONTH($K$2),DAY(Q22)&IF(Y22>0," · "&Y22&IF(Y22=1," video"," videos")&" · "&TEXT(AG22,"[h]:mm")&IF(Y22>5," (+"&(Y22-5)&" more)",""),""),"") | K22: =$K$3+14 | L22: =$K$3+15 | M22: =$K$3+16 | N22: =$K$3+17 | O22: =$K$3+18 | P22: =$K$3+19 | Q22: =$K$3+20 | S22: =IF(MONTH(K22)=MONTH($K$2),COUNTIFS(tblVideos[Day],K22,tblVideos[Channel ID],$K$4),0) | T22: =IF(MONTH(L22)=MONTH($K$2),COUNTIFS(tblVideos[Day],L22,tblVideos[Channel ID],$K$4),0) | U22: =IF(MONTH(M22)=MONTH($K$2),COUNTIFS(tblVideos[Day],M22,tblVideos[Channel ID],$K$4),0) | V22: =IF(MONTH(N22)=MONTH($K$2),COUNTIFS(tblVideos[Day],N22,tblVideos[Channel ID],$K$4),0) | W22: =IF(MONTH(O22)=MONTH($K$2),COUNTIFS(tblVideos[Day],O22,tblVideos[Channel ID],$K$4),0) | X22: =IF(MONTH(P22)=MONTH($K$2),COUNTIFS(tblVideos[Day],P22,tblVideos[Channel ID],$K$4),0) | Y22: =IF(MONTH(Q22)=MONTH($K$2),COUNTIFS(tblVideos[Day],Q22,tblVideos[Channel ID],$K$4),0) | AA22: =IF(S22>0,SUMIFS(tblVideos[Length],tblVideos[Day],K22,tblVideos[Channel ID],$K$4),0) | AB22: =IF(T22>0,SUMIFS(tblVideos[Length],tblVideos[Day],L22,tblVideos[Channel ID],$K$4),0) | AC22: =IF(U22>0,SUMIFS(tblVideos[Length],tblVideos[Day],M22,tblVideos[Channel ID],$K$4),0) | AD22: =IF(V22>0,SUMIFS(tblVideos[Length],tblVideos[Day],N22,tblVideos[Channel ID],$K$4),0) | AE22: =IF(W22>0,SUMIFS(tblVideos[Length],tblVideos[Day],O22,tblVideos[Channel ID],$K$4),0) | AF22: =IF(X22>0,SUMIFS(tblVideos[Length],tblVideos[Day],P22,tblVideos[Channel ID],$K$4),0) | AG22: =IF(Y22>0,SUMIFS(tblVideos[Length],tblVideos[Day],Q22,tblVideos[Channel ID],$K$4),0)
B23: =IF(K23="","",IF(INDEX(tblVideos[Video ID],K23)="",IF(INDEX(tblVideos[Status],K23)="Watched","✓ ","▸ ")&INDEX(tblVideos[Title],K23),HYPERLINK("https://www.youtube.com/watch?v="&INDEX(tblVideos[Video ID],K23),IF(INDEX(tblVideos[Status],K23)="Watched","✓ ","▸ ")&INDEX(tblVideos[Title],K23)))) | C23: =IF(L23="","",IF(INDEX(tblVideos[Video ID],L23)="",IF(INDEX(tblVideos[Status],L23)="Watched","✓ ","▸ ")&INDEX(tblVideos[Title],L23),HYPERLINK("https://www.youtube.com/watch?v="&INDEX(tblVideos[Video ID],L23),IF(INDEX(tblVideos[Status],L23)="Watched","✓ ","▸ ")&INDEX(tblVideos[Title],L23)))) | D23: =IF(M23="","",IF(INDEX(tblVideos[Video ID],M23)="",IF(INDEX(tblVideos[Status],M23)="Watched","✓ ","▸ ")&INDEX(tblVideos[Title],M23),HYPERLINK("https://www.youtube.com/watch?v="&INDEX(tblVideos[Video ID],M23),IF(INDEX(tblVideos[Status],M23)="Watched","✓ ","▸ ")&INDEX(tblVideos[Title],M23)))) | E23: =IF(N23="","",IF(INDEX(tblVideos[Video ID],N23)="",IF(INDEX(tblVideos[Status],N23)="Watched","✓ ","▸ ")&INDEX(tblVideos[Title],N23),HYPERLINK("https://www.youtube.com/watch?v="&INDEX(tblVideos[Video ID],N23),IF(INDEX(tblVideos[Status],N23)="Watched","✓ ","▸ ")&INDEX(tblVideos[Title],N23)))) | F23: =IF(O23="","",IF(INDEX(tblVideos[Video ID],O23)="",IF(INDEX(tblVideos[Status],O23)="Watched","✓ ","▸ ")&INDEX(tblVideos[Title],O23),HYPERLINK("https://www.youtube.com/watch?v="&INDEX(tblVideos[Video ID],O23),IF(INDEX(tblVideos[Status],O23)="Watched","✓ ","▸ ")&INDEX(tblVideos[Title],O23)))) | G23: =IF(P23="","",IF(INDEX(tblVideos[Video ID],P23)="",IF(INDEX(tblVideos[Status],P23)="Watched","✓ ","▸ ")&INDEX(tblVideos[Title],P23),HYPERLINK("https://www.youtube.com/watch?v="&INDEX(tblVideos[Video ID],P23),IF(INDEX(tblVideos[Status],P23)="Watched","✓ ","▸ ")&INDEX(tblVideos[Title],P23)))) | H23: =IF(Q23="","",IF(INDEX(tblVideos[Video ID],Q23)="",IF(INDEX(tblVideos[Status],Q23)="Watched","✓ ","▸ ")&INDEX(tblVideos[Title],Q23),HYPERLINK("https://www.youtube.com/watch?v="&INDEX(tblVideos[Video ID],Q23),IF(INDEX(tblVideos[Status],Q23)="Watched","✓ ","▸ ")&INDEX(tblVideos[Title],Q23)))) | K23: =IF(S22>=1,MATCH(K22*100+1,tblVideos[Cal Key],0),"") | L23: =IF(T22>=1,MATCH(L22*100+1,tblVideos[Cal Key],0),"") | M23: =IF(U22>=1,MATCH(M22*100+1,tblVideos[Cal Key],0),"") | N23: =IF(V22>=1,MATCH(N22*100+1,tblVideos[Cal Key],0),"") | O23: =IF(W22>=1,MATCH(O22*100+1,tblVideos[Cal Key],0),"") | P23: =IF(X22>=1,MATCH(P22*100+1,tblVideos[Cal Key],0),"") | Q23: =IF(Y22>=1,MATCH(Q22*100+1,tblVideos[Cal Key],0),"") | S23: =IF(K23="","",IFERROR(MATCH(INDEX(tblVideos[Channel ID],K23),tblChannels[Channel ID],0),"")) | T23: =IF(L23="","",IFERROR(MATCH(INDEX(tblVideos[Channel ID],L23),tblChannels[Channel ID],0),"")) | U23: =IF(M23="","",IFERROR(MATCH(INDEX(tblVideos[Channel ID],M23),tblChannels[Channel ID],0),"")) | V23: =IF(N23="","",IFERROR(MATCH(INDEX(tblVideos[Channel ID],N23),tblChannels[Channel ID],0),"")) | W23: =IF(O23="","",IFERROR(MATCH(INDEX(tblVideos[Channel ID],O23),tblChannels[Channel ID],0),"")) | X23: =IF(P23="","",IFERROR(MATCH(INDEX(tblVideos[Channel ID],P23),tblChannels[Channel ID],0),"")) | Y23: =IF(Q23="","",IFERROR(MATCH(INDEX(tblVideos[Channel ID],Q23),tblChannels[Channel ID],0),""))
B24: =IF(K24="","",IF(INDEX(tblVideos[Video ID],K24)="",IF(INDEX(tblVideos[Status],K24)="Watched","✓ ","▸ ")&INDEX(tblVideos[Title],K24),HYPERLINK("https://www.youtube.com/watch?v="&INDEX(tblVideos[Video ID],K24),IF(INDEX(tblVideos[Status],K24)="Watched","✓ ","▸ ")&INDEX(tblVideos[Title],K24)))) | C24: =IF(L24="","",IF(INDEX(tblVideos[Video ID],L24)="",IF(INDEX(tblVideos[Status],L24)="Watched","✓ ","▸ ")&INDEX(tblVideos[Title],L24),HYPERLINK("https://www.youtube.com/watch?v="&INDEX(tblVideos[Video ID],L24),IF(INDEX(tblVideos[Status],L24)="Watched","✓ ","▸ ")&INDEX(tblVideos[Title],L24)))) | D24: =IF(M24="","",IF(INDEX(tblVideos[Video ID],M24)="",IF(INDEX(tblVideos[Status],M24)="Watched","✓ ","▸ ")&INDEX(tblVideos[Title],M24),HYPERLINK("https://www.youtube.com/watch?v="&INDEX(tblVideos[Video ID],M24),IF(INDEX(tblVideos[Status],M24)="Watched","✓ ","▸ ")&INDEX(tblVideos[Title],M24)))) | E24: =IF(N24="","",IF(INDEX(tblVideos[Video ID],N24)="",IF(INDEX(tblVideos[Status],N24)="Watched","✓ ","▸ ")&INDEX(tblVideos[Title],N24),HYPERLINK("https://www.youtube.com/watch?v="&INDEX(tblVideos[Video ID],N24),IF(INDEX(tblVideos[Status],N24)="Watched","✓ ","▸ ")&INDEX(tblVideos[Title],N24)))) | F24: =IF(O24="","",IF(INDEX(tblVideos[Video ID],O24)="",IF(INDEX(tblVideos[Status],O24)="Watched","✓ ","▸ ")&INDEX(tblVideos[Title],O24),HYPERLINK("https://www.youtube.com/watch?v="&INDEX(tblVideos[Video ID],O24),IF(INDEX(tblVideos[Status],O24)="Watched","✓ ","▸ ")&INDEX(tblVideos[Title],O24)))) | G24: =IF(P24="","",IF(INDEX(tblVideos[Video ID],P24)="",IF(INDEX(tblVideos[Status],P24)="Watched","✓ ","▸ ")&INDEX(tblVideos[Title],P24),HYPERLINK("https://www.youtube.com/watch?v="&INDEX(tblVideos[Video ID],P24),IF(INDEX(tblVideos[Status],P24)="Watched","✓ ","▸ ")&INDEX(tblVideos[Title],P24)))) | H24: =IF(Q24="","",IF(INDEX(tblVideos[Video ID],Q24)="",IF(INDEX(tblVideos[Status],Q24)="Watched","✓ ","▸ ")&INDEX(tblVideos[Title],Q24),HYPERLINK("https://www.youtube.com/watch?v="&INDEX(tblVideos[Video ID],Q24),IF(INDEX(tblVideos[Status],Q24)="Watched","✓ ","▸ ")&INDEX(tblVideos[Title],Q24)))) | K24: =IF(S22>=2,MATCH(K22*100+2,tblVideos[Cal Key],0),"") | L24: =IF(T22>=2,MATCH(L22*100+2,tblVideos[Cal Key],0),"") | M24: =IF(U22>=2,MATCH(M22*100+2,tblVideos[Cal Key],0),"") | N24: =IF(V22>=2,MATCH(N22*100+2,tblVideos[Cal Key],0),"") | O24: =IF(W22>=2,MATCH(O22*100+2,tblVideos[Cal Key],0),"") | P24: =IF(X22>=2,MATCH(P22*100+2,tblVideos[Cal Key],0),"") | Q24: =IF(Y22>=2,MATCH(Q22*100+2,tblVideos[Cal Key],0),"") | S24: =IF(K24="","",IFERROR(MATCH(INDEX(tblVideos[Channel ID],K24),tblChannels[Channel ID],0),"")) | T24: =IF(L24="","",IFERROR(MATCH(INDEX(tblVideos[Channel ID],L24),tblChannels[Channel ID],0),"")) | U24: =IF(M24="","",IFERROR(MATCH(INDEX(tblVideos[Channel ID],M24),tblChannels[Channel ID],0),"")) | V24: =IF(N24="","",IFERROR(MATCH(INDEX(tblVideos[Channel ID],N24),tblChannels[Channel ID],0),"")) | W24: =IF(O24="","",IFERROR(MATCH(INDEX(tblVideos[Channel ID],O24),tblChannels[Channel ID],0),"")) | X24: =IF(P24="","",IFERROR(MATCH(INDEX(tblVideos[Channel ID],P24),tblChannels[Channel ID],0),"")) | Y24: =IF(Q24="","",IFERROR(MATCH(INDEX(tblVideos[Channel ID],Q24),tblChannels[Channel ID],0),""))
B25: =IF(K25="","",IF(INDEX(tblVideos[Video ID],K25)="",IF(INDEX(tblVideos[Status],K25)="Watched","✓ ","▸ ")&INDEX(tblVideos[Title],K25),HYPERLINK("https://www.youtube.com/watch?v="&INDEX(tblVideos[Video ID],K25),IF(INDEX(tblVideos[Status],K25)="Watched","✓ ","▸ ")&INDEX(tblVideos[Title],K25)))) | C25: =IF(L25="","",IF(INDEX(tblVideos[Video ID],L25)="",IF(INDEX(tblVideos[Status],L25)="Watched","✓ ","▸ ")&INDEX(tblVideos[Title],L25),HYPERLINK("https://www.youtube.com/watch?v="&INDEX(tblVideos[Video ID],L25),IF(INDEX(tblVideos[Status],L25)="Watched","✓ ","▸ ")&INDEX(tblVideos[Title],L25)))) | D25: =IF(M25="","",IF(INDEX(tblVideos[Video ID],M25)="",IF(INDEX(tblVideos[Status],M25)="Watched","✓ ","▸ ")&INDEX(tblVideos[Title],M25),HYPERLINK("https://www.youtube.com/watch?v="&INDEX(tblVideos[Video ID],M25),IF(INDEX(tblVideos[Status],M25)="Watched","✓ ","▸ ")&INDEX(tblVideos[Title],M25)))) | E25: =IF(N25="","",IF(INDEX(tblVideos[Video ID],N25)="",IF(INDEX(tblVideos[Status],N25)="Watched","✓ ","▸ ")&INDEX(tblVideos[Title],N25),HYPERLINK("https://www.youtube.com/watch?v="&INDEX(tblVideos[Video ID],N25),IF(INDEX(tblVideos[Status],N25)="Watched","✓ ","▸ ")&INDEX(tblVideos[Title],N25)))) | F25: =IF(O25="","",IF(INDEX(tblVideos[Video ID],O25)="",IF(INDEX(tblVideos[Status],O25)="Watched","✓ ","▸ ")&INDEX(tblVideos[Title],O25),HYPERLINK("https://www.youtube.com/watch?v="&INDEX(tblVideos[Video ID],O25),IF(INDEX(tblVideos[Status],O25)="Watched","✓ ","▸ ")&INDEX(tblVideos[Title],O25)))) | G25: =IF(P25="","",IF(INDEX(tblVideos[Video ID],P25)="",IF(INDEX(tblVideos[Status],P25)="Watched","✓ ","▸ ")&INDEX(tblVideos[Title],P25),HYPERLINK("https://www.youtube.com/watch?v="&INDEX(tblVideos[Video ID],P25),IF(INDEX(tblVideos[Status],P25)="Watched","✓ ","▸ ")&INDEX(tblVideos[Title],P25)))) | H25: =IF(Q25="","",IF(INDEX(tblVideos[Video ID],Q25)="",IF(INDEX(tblVideos[Status],Q25)="Watched","✓ ","▸ ")&INDEX(tblVideos[Title],Q25),HYPERLINK("https://www.youtube.com/watch?v="&INDEX(tblVideos[Video ID],Q25),IF(INDEX(tblVideos[Status],Q25)="Watched","✓ ","▸ ")&INDEX(tblVideos[Title],Q25)))) | K25: =IF(S22>=3,MATCH(K22*100+3,tblVideos[Cal Key],0),"") | L25: =IF(T22>=3,MATCH(L22*100+3,tblVideos[Cal Key],0),"") | M25: =IF(U22>=3,MATCH(M22*100+3,tblVideos[Cal Key],0),"") | N25: =IF(V22>=3,MATCH(N22*100+3,tblVideos[Cal Key],0),"") | O25: =IF(W22>=3,MATCH(O22*100+3,tblVideos[Cal Key],0),"") | P25: =IF(X22>=3,MATCH(P22*100+3,tblVideos[Cal Key],0),"") | Q25: =IF(Y22>=3,MATCH(Q22*100+3,tblVideos[Cal Key],0),"") | S25: =IF(K25="","",IFERROR(MATCH(INDEX(tblVideos[Channel ID],K25),tblChannels[Channel ID],0),"")) | T25: =IF(L25="","",IFERROR(MATCH(INDEX(tblVideos[Channel ID],L25),tblChannels[Channel ID],0),"")) | U25: =IF(M25="","",IFERROR(MATCH(INDEX(tblVideos[Channel ID],M25),tblChannels[Channel ID],0),"")) | V25: =IF(N25="","",IFERROR(MATCH(INDEX(tblVideos[Channel ID],N25),tblChannels[Channel ID],0),"")) | W25: =IF(O25="","",IFERROR(MATCH(INDEX(tblVideos[Channel ID],O25),tblChannels[Channel ID],0),"")) | X25: =IF(P25="","",IFERROR(MATCH(INDEX(tblVideos[Channel ID],P25),tblChannels[Channel ID],0),"")) | Y25: =IF(Q25="","",IFERROR(MATCH(INDEX(tblVideos[Channel ID],Q25),tblChannels[Channel ID],0),""))
B26: =IF(K26="","",IF(INDEX(tblVideos[Video ID],K26)="",IF(INDEX(tblVideos[Status],K26)="Watched","✓ ","▸ ")&INDEX(tblVideos[Title],K26),HYPERLINK("https://www.youtube.com/watch?v="&INDEX(tblVideos[Video ID],K26),IF(INDEX(tblVideos[Status],K26)="Watched","✓ ","▸ ")&INDEX(tblVideos[Title],K26)))) | C26: =IF(L26="","",IF(INDEX(tblVideos[Video ID],L26)="",IF(INDEX(tblVideos[Status],L26)="Watched","✓ ","▸ ")&INDEX(tblVideos[Title],L26),HYPERLINK("https://www.youtube.com/watch?v="&INDEX(tblVideos[Video ID],L26),IF(INDEX(tblVideos[Status],L26)="Watched","✓ ","▸ ")&INDEX(tblVideos[Title],L26)))) | D26: =IF(M26="","",IF(INDEX(tblVideos[Video ID],M26)="",IF(INDEX(tblVideos[Status],M26)="Watched","✓ ","▸ ")&INDEX(tblVideos[Title],M26),HYPERLINK("https://www.youtube.com/watch?v="&INDEX(tblVideos[Video ID],M26),IF(INDEX(tblVideos[Status],M26)="Watched","✓ ","▸ ")&INDEX(tblVideos[Title],M26)))) | E26: =IF(N26="","",IF(INDEX(tblVideos[Video ID],N26)="",IF(INDEX(tblVideos[Status],N26)="Watched","✓ ","▸ ")&INDEX(tblVideos[Title],N26),HYPERLINK("https://www.youtube.com/watch?v="&INDEX(tblVideos[Video ID],N26),IF(INDEX(tblVideos[Status],N26)="Watched","✓ ","▸ ")&INDEX(tblVideos[Title],N26)))) | F26: =IF(O26="","",IF(INDEX(tblVideos[Video ID],O26)="",IF(INDEX(tblVideos[Status],O26)="Watched","✓ ","▸ ")&INDEX(tblVideos[Title],O26),HYPERLINK("https://www.youtube.com/watch?v="&INDEX(tblVideos[Video ID],O26),IF(INDEX(tblVideos[Status],O26)="Watched","✓ ","▸ ")&INDEX(tblVideos[Title],O26)))) | G26: =IF(P26="","",IF(INDEX(tblVideos[Video ID],P26)="",IF(INDEX(tblVideos[Status],P26)="Watched","✓ ","▸ ")&INDEX(tblVideos[Title],P26),HYPERLINK("https://www.youtube.com/watch?v="&INDEX(tblVideos[Video ID],P26),IF(INDEX(tblVideos[Status],P26)="Watched","✓ ","▸ ")&INDEX(tblVideos[Title],P26)))) | H26: =IF(Q26="","",IF(INDEX(tblVideos[Video ID],Q26)="",IF(INDEX(tblVideos[Status],Q26)="Watched","✓ ","▸ ")&INDEX(tblVideos[Title],Q26),HYPERLINK("https://www.youtube.com/watch?v="&INDEX(tblVideos[Video ID],Q26),IF(INDEX(tblVideos[Status],Q26)="Watched","✓ ","▸ ")&INDEX(tblVideos[Title],Q26)))) | K26: =IF(S22>=4,MATCH(K22*100+4,tblVideos[Cal Key],0),"") | L26: =IF(T22>=4,MATCH(L22*100+4,tblVideos[Cal Key],0),"") | M26: =IF(U22>=4,MATCH(M22*100+4,tblVideos[Cal Key],0),"") | N26: =IF(V22>=4,MATCH(N22*100+4,tblVideos[Cal Key],0),"") | O26: =IF(W22>=4,MATCH(O22*100+4,tblVideos[Cal Key],0),"") | P26: =IF(X22>=4,MATCH(P22*100+4,tblVideos[Cal Key],0),"") | Q26: =IF(Y22>=4,MATCH(Q22*100+4,tblVideos[Cal Key],0),"") | S26: =IF(K26="","",IFERROR(MATCH(INDEX(tblVideos[Channel ID],K26),tblChannels[Channel ID],0),"")) | T26: =IF(L26="","",IFERROR(MATCH(INDEX(tblVideos[Channel ID],L26),tblChannels[Channel ID],0),"")) | U26: =IF(M26="","",IFERROR(MATCH(INDEX(tblVideos[Channel ID],M26),tblChannels[Channel ID],0),"")) | V26: =IF(N26="","",IFERROR(MATCH(INDEX(tblVideos[Channel ID],N26),tblChannels[Channel ID],0),"")) | W26: =IF(O26="","",IFERROR(MATCH(INDEX(tblVideos[Channel ID],O26),tblChannels[Channel ID],0),"")) | X26: =IF(P26="","",IFERROR(MATCH(INDEX(tblVideos[Channel ID],P26),tblChannels[Channel ID],0),"")) | Y26: =IF(Q26="","",IFERROR(MATCH(INDEX(tblVideos[Channel ID],Q26),tblChannels[Channel ID],0),""))
B27: =IF(K27="","",IF(INDEX(tblVideos[Video ID],K27)="",IF(INDEX(tblVideos[Status],K27)="Watched","✓ ","▸ ")&INDEX(tblVideos[Title],K27),HYPERLINK("https://www.youtube.com/watch?v="&INDEX(tblVideos[Video ID],K27),IF(INDEX(tblVideos[Status],K27)="Watched","✓ ","▸ ")&INDEX(tblVideos[Title],K27)))) | C27: =IF(L27="","",IF(INDEX(tblVideos[Video ID],L27)="",IF(INDEX(tblVideos[Status],L27)="Watched","✓ ","▸ ")&INDEX(tblVideos[Title],L27),HYPERLINK("https://www.youtube.com/watch?v="&INDEX(tblVideos[Video ID],L27),IF(INDEX(tblVideos[Status],L27)="Watched","✓ ","▸ ")&INDEX(tblVideos[Title],L27)))) | D27: =IF(M27="","",IF(INDEX(tblVideos[Video ID],M27)="",IF(INDEX(tblVideos[Status],M27)="Watched","✓ ","▸ ")&INDEX(tblVideos[Title],M27),HYPERLINK("https://www.youtube.com/watch?v="&INDEX(tblVideos[Video ID],M27),IF(INDEX(tblVideos[Status],M27)="Watched","✓ ","▸ ")&INDEX(tblVideos[Title],M27)))) | E27: =IF(N27="","",IF(INDEX(tblVideos[Video ID],N27)="",IF(INDEX(tblVideos[Status],N27)="Watched","✓ ","▸ ")&INDEX(tblVideos[Title],N27),HYPERLINK("https://www.youtube.com/watch?v="&INDEX(tblVideos[Video ID],N27),IF(INDEX(tblVideos[Status],N27)="Watched","✓ ","▸ ")&INDEX(tblVideos[Title],N27)))) | F27: =IF(O27="","",IF(INDEX(tblVideos[Video ID],O27)="",IF(INDEX(tblVideos[Status],O27)="Watched","✓ ","▸ ")&INDEX(tblVideos[Title],O27),HYPERLINK("https://www.youtube.com/watch?v="&INDEX(tblVideos[Video ID],O27),IF(INDEX(tblVideos[Status],O27)="Watched","✓ ","▸ ")&INDEX(tblVideos[Title],O27)))) | G27: =IF(P27="","",IF(INDEX(tblVideos[Video ID],P27)="",IF(INDEX(tblVideos[Status],P27)="Watched","✓ ","▸ ")&INDEX(tblVideos[Title],P27),HYPERLINK("https://www.youtube.com/watch?v="&INDEX(tblVideos[Video ID],P27),IF(INDEX(tblVideos[Status],P27)="Watched","✓ ","▸ ")&INDEX(tblVideos[Title],P27)))) | H27: =IF(Q27="","",IF(INDEX(tblVideos[Video ID],Q27)="",IF(INDEX(tblVideos[Status],Q27)="Watched","✓ ","▸ ")&INDEX(tblVideos[Title],Q27),HYPERLINK("https://www.youtube.com/watch?v="&INDEX(tblVideos[Video ID],Q27),IF(INDEX(tblVideos[Status],Q27)="Watched","✓ ","▸ ")&INDEX(tblVideos[Title],Q27)))) | K27: =IF(S22>=5,MATCH(K22*100+5,tblVideos[Cal Key],0),"") | L27: =IF(T22>=5,MATCH(L22*100+5,tblVideos[Cal Key],0),"") | M27: =IF(U22>=5,MATCH(M22*100+5,tblVideos[Cal Key],0),"") | N27: =IF(V22>=5,MATCH(N22*100+5,tblVideos[Cal Key],0),"") | O27: =IF(W22>=5,MATCH(O22*100+5,tblVideos[Cal Key],0),"") | P27: =IF(X22>=5,MATCH(P22*100+5,tblVideos[Cal Key],0),"") | Q27: =IF(Y22>=5,MATCH(Q22*100+5,tblVideos[Cal Key],0),"") | S27: =IF(K27="","",IFERROR(MATCH(INDEX(tblVideos[Channel ID],K27),tblChannels[Channel ID],0),"")) | T27: =IF(L27="","",IFERROR(MATCH(INDEX(tblVideos[Channel ID],L27),tblChannels[Channel ID],0),"")) | U27: =IF(M27="","",IFERROR(MATCH(INDEX(tblVideos[Channel ID],M27),tblChannels[Channel ID],0),"")) | V27: =IF(N27="","",IFERROR(MATCH(INDEX(tblVideos[Channel ID],N27),tblChannels[Channel ID],0),"")) | W27: =IF(O27="","",IFERROR(MATCH(INDEX(tblVideos[Channel ID],O27),tblChannels[Channel ID],0),"")) | X27: =IF(P27="","",IFERROR(MATCH(INDEX(tblVideos[Channel ID],P27),tblChannels[Channel ID],0),"")) | Y27: =IF(Q27="","",IFERROR(MATCH(INDEX(tblVideos[Channel ID],Q27),tblChannels[Channel ID],0),""))
B28: =IF(MONTH(K28)=MONTH($K$2),DAY(K28)&IF(S28>0," · "&S28&IF(S28=1," video"," videos")&" · "&TEXT(AA28,"[h]:mm")&IF(S28>5," (+"&(S28-5)&" more)",""),""),"") | C28: =IF(MONTH(L28)=MONTH($K$2),DAY(L28)&IF(T28>0," · "&T28&IF(T28=1," video"," videos")&" · "&TEXT(AB28,"[h]:mm")&IF(T28>5," (+"&(T28-5)&" more)",""),""),"") | D28: =IF(MONTH(M28)=MONTH($K$2),DAY(M28)&IF(U28>0," · "&U28&IF(U28=1," video"," videos")&" · "&TEXT(AC28,"[h]:mm")&IF(U28>5," (+"&(U28-5)&" more)",""),""),"") | E28: =IF(MONTH(N28)=MONTH($K$2),DAY(N28)&IF(V28>0," · "&V28&IF(V28=1," video"," videos")&" · "&TEXT(AD28,"[h]:mm")&IF(V28>5," (+"&(V28-5)&" more)",""),""),"") | F28: =IF(MONTH(O28)=MONTH($K$2),DAY(O28)&IF(W28>0," · "&W28&IF(W28=1," video"," videos")&" · "&TEXT(AE28,"[h]:mm")&IF(W28>5," (+"&(W28-5)&" more)",""),""),"") | G28: =IF(MONTH(P28)=MONTH($K$2),DAY(P28)&IF(X28>0," · "&X28&IF(X28=1," video"," videos")&" · "&TEXT(AF28,"[h]:mm")&IF(X28>5," (+"&(X28-5)&" more)",""),""),"") | H28: =IF(MONTH(Q28)=MONTH($K$2),DAY(Q28)&IF(Y28>0," · "&Y28&IF(Y28=1," video"," videos")&" · "&TEXT(AG28,"[h]:mm")&IF(Y28>5," (+"&(Y28-5)&" more)",""),""),"") | K28: =$K$3+21 | L28: =$K$3+22 | M28: =$K$3+23 | N28: =$K$3+24 | O28: =$K$3+25 | P28: =$K$3+26 | Q28: =$K$3+27 | S28: =IF(MONTH(K28)=MONTH($K$2),COUNTIFS(tblVideos[Day],K28,tblVideos[Channel ID],$K$4),0) | T28: =IF(MONTH(L28)=MONTH($K$2),COUNTIFS(tblVideos[Day],L28,tblVideos[Channel ID],$K$4),0) | U28: =IF(MONTH(M28)=MONTH($K$2),COUNTIFS(tblVideos[Day],M28,tblVideos[Channel ID],$K$4),0) | V28: =IF(MONTH(N28)=MONTH($K$2),COUNTIFS(tblVideos[Day],N28,tblVideos[Channel ID],$K$4),0) | W28: =IF(MONTH(O28)=MONTH($K$2),COUNTIFS(tblVideos[Day],O28,tblVideos[Channel ID],$K$4),0) | X28: =IF(MONTH(P28)=MONTH($K$2),COUNTIFS(tblVideos[Day],P28,tblVideos[Channel ID],$K$4),0) | Y28: =IF(MONTH(Q28)=MONTH($K$2),COUNTIFS(tblVideos[Day],Q28,tblVideos[Channel ID],$K$4),0) | AA28: =IF(S28>0,SUMIFS(tblVideos[Length],tblVideos[Day],K28,tblVideos[Channel ID],$K$4),0) | AB28: =IF(T28>0,SUMIFS(tblVideos[Length],tblVideos[Day],L28,tblVideos[Channel ID],$K$4),0) | AC28: =IF(U28>0,SUMIFS(tblVideos[Length],tblVideos[Day],M28,tblVideos[Channel ID],$K$4),0) | AD28: =IF(V28>0,SUMIFS(tblVideos[Length],tblVideos[Day],N28,tblVideos[Channel ID],$K$4),0) | AE28: =IF(W28>0,SUMIFS(tblVideos[Length],tblVideos[Day],O28,tblVideos[Channel ID],$K$4),0) | AF28: =IF(X28>0,SUMIFS(tblVideos[Length],tblVideos[Day],P28,tblVideos[Channel ID],$K$4),0) | AG28: =IF(Y28>0,SUMIFS(tblVideos[Length],tblVideos[Day],Q28,tblVideos[Channel ID],$K$4),0)
B29: =IF(K29="","",IF(INDEX(tblVideos[Video ID],K29)="",IF(INDEX(tblVideos[Status],K29)="Watched","✓ ","▸ ")&INDEX(tblVideos[Title],K29),HYPERLINK("https://www.youtube.com/watch?v="&INDEX(tblVideos[Video ID],K29),IF(INDEX(tblVideos[Status],K29)="Watched","✓ ","▸ ")&INDEX(tblVideos[Title],K29)))) | C29: =IF(L29="","",IF(INDEX(tblVideos[Video ID],L29)="",IF(INDEX(tblVideos[Status],L29)="Watched","✓ ","▸ ")&INDEX(tblVideos[Title],L29),HYPERLINK("https://www.youtube.com/watch?v="&INDEX(tblVideos[Video ID],L29),IF(INDEX(tblVideos[Status],L29)="Watched","✓ ","▸ ")&INDEX(tblVideos[Title],L29)))) | D29: =IF(M29="","",IF(INDEX(tblVideos[Video ID],M29)="",IF(INDEX(tblVideos[Status],M29)="Watched","✓ ","▸ ")&INDEX(tblVideos[Title],M29),HYPERLINK("https://www.youtube.com/watch?v="&INDEX(tblVideos[Video ID],M29),IF(INDEX(tblVideos[Status],M29)="Watched","✓ ","▸ ")&INDEX(tblVideos[Title],M29)))) | E29: =IF(N29="","",IF(INDEX(tblVideos[Video ID],N29)="",IF(INDEX(tblVideos[Status],N29)="Watched","✓ ","▸ ")&INDEX(tblVideos[Title],N29),HYPERLINK("https://www.youtube.com/watch?v="&INDEX(tblVideos[Video ID],N29),IF(INDEX(tblVideos[Status],N29)="Watched","✓ ","▸ ")&INDEX(tblVideos[Title],N29)))) | F29: =IF(O29="","",IF(INDEX(tblVideos[Video ID],O29)="",IF(INDEX(tblVideos[Status],O29)="Watched","✓ ","▸ ")&INDEX(tblVideos[Title],O29),HYPERLINK("https://www.youtube.com/watch?v="&INDEX(tblVideos[Video ID],O29),IF(INDEX(tblVideos[Status],O29)="Watched","✓ ","▸ ")&INDEX(tblVideos[Title],O29)))) | G29: =IF(P29="","",IF(INDEX(tblVideos[Video ID],P29)="",IF(INDEX(tblVideos[Status],P29)="Watched","✓ ","▸ ")&INDEX(tblVideos[Title],P29),HYPERLINK("https://www.youtube.com/watch?v="&INDEX(tblVideos[Video ID],P29),IF(INDEX(tblVideos[Status],P29)="Watched","✓ ","▸ ")&INDEX(tblVideos[Title],P29)))) | H29: =IF(Q29="","",IF(INDEX(tblVideos[Video ID],Q29)="",IF(INDEX(tblVideos[Status],Q29)="Watched","✓ ","▸ ")&INDEX(tblVideos[Title],Q29),HYPERLINK("https://www.youtube.com/watch?v="&INDEX(tblVideos[Video ID],Q29),IF(INDEX(tblVideos[Status],Q29)="Watched","✓ ","▸ ")&INDEX(tblVideos[Title],Q29)))) | K29: =IF(S28>=1,MATCH(K28*100+1,tblVideos[Cal Key],0),"") | L29: =IF(T28>=1,MATCH(L28*100+1,tblVideos[Cal Key],0),"") | M29: =IF(U28>=1,MATCH(M28*100+1,tblVideos[Cal Key],0),"") | N29: =IF(V28>=1,MATCH(N28*100+1,tblVideos[Cal Key],0),"") | O29: =IF(W28>=1,MATCH(O28*100+1,tblVideos[Cal Key],0),"") | P29: =IF(X28>=1,MATCH(P28*100+1,tblVideos[Cal Key],0),"") | Q29: =IF(Y28>=1,MATCH(Q28*100+1,tblVideos[Cal Key],0),"") | S29: =IF(K29="","",IFERROR(MATCH(INDEX(tblVideos[Channel ID],K29),tblChannels[Channel ID],0),"")) | T29: =IF(L29="","",IFERROR(MATCH(INDEX(tblVideos[Channel ID],L29),tblChannels[Channel ID],0),"")) | U29: =IF(M29="","",IFERROR(MATCH(INDEX(tblVideos[Channel ID],M29),tblChannels[Channel ID],0),"")) | V29: =IF(N29="","",IFERROR(MATCH(INDEX(tblVideos[Channel ID],N29),tblChannels[Channel ID],0),"")) | W29: =IF(O29="","",IFERROR(MATCH(INDEX(tblVideos[Channel ID],O29),tblChannels[Channel ID],0),"")) | X29: =IF(P29="","",IFERROR(MATCH(INDEX(tblVideos[Channel ID],P29),tblChannels[Channel ID],0),"")) | Y29: =IF(Q29="","",IFERROR(MATCH(INDEX(tblVideos[Channel ID],Q29),tblChannels[Channel ID],0),""))
B30: =IF(K30="","",IF(INDEX(tblVideos[Video ID],K30)="",IF(INDEX(tblVideos[Status],K30)="Watched","✓ ","▸ ")&INDEX(tblVideos[Title],K30),HYPERLINK("https://www.youtube.com/watch?v="&INDEX(tblVideos[Video ID],K30),IF(INDEX(tblVideos[Status],K30)="Watched","✓ ","▸ ")&INDEX(tblVideos[Title],K30)))) | C30: =IF(L30="","",IF(INDEX(tblVideos[Video ID],L30)="",IF(INDEX(tblVideos[Status],L30)="Watched","✓ ","▸ ")&INDEX(tblVideos[Title],L30),HYPERLINK("https://www.youtube.com/watch?v="&INDEX(tblVideos[Video ID],L30),IF(INDEX(tblVideos[Status],L30)="Watched","✓ ","▸ ")&INDEX(tblVideos[Title],L30)))) | D30: =IF(M30="","",IF(INDEX(tblVideos[Video ID],M30)="",IF(INDEX(tblVideos[Status],M30)="Watched","✓ ","▸ ")&INDEX(tblVideos[Title],M30),HYPERLINK("https://www.youtube.com/watch?v="&INDEX(tblVideos[Video ID],M30),IF(INDEX(tblVideos[Status],M30)="Watched","✓ ","▸ ")&INDEX(tblVideos[Title],M30)))) | E30: =IF(N30="","",IF(INDEX(tblVideos[Video ID],N30)="",IF(INDEX(tblVideos[Status],N30)="Watched","✓ ","▸ ")&INDEX(tblVideos[Title],N30),HYPERLINK("https://www.youtube.com/watch?v="&INDEX(tblVideos[Video ID],N30),IF(INDEX(tblVideos[Status],N30)="Watched","✓ ","▸ ")&INDEX(tblVideos[Title],N30)))) | F30: =IF(O30="","",IF(INDEX(tblVideos[Video ID],O30)="",IF(INDEX(tblVideos[Status],O30)="Watched","✓ ","▸ ")&INDEX(tblVideos[Title],O30),HYPERLINK("https://www.youtube.com/watch?v="&INDEX(tblVideos[Video ID],O30),IF(INDEX(tblVideos[Status],O30)="Watched","✓ ","▸ ")&INDEX(tblVideos[Title],O30)))) | G30: =IF(P30="","",IF(INDEX(tblVideos[Video ID],P30)="",IF(INDEX(tblVideos[Status],P30)="Watched","✓ ","▸ ")&INDEX(tblVideos[Title],P30),HYPERLINK("https://www.youtube.com/watch?v="&INDEX(tblVideos[Video ID],P30),IF(INDEX(tblVideos[Status],P30)="Watched","✓ ","▸ ")&INDEX(tblVideos[Title],P30)))) | H30: =IF(Q30="","",IF(INDEX(tblVideos[Video ID],Q30)="",IF(INDEX(tblVideos[Status],Q30)="Watched","✓ ","▸ ")&INDEX(tblVideos[Title],Q30),HYPERLINK("https://www.youtube.com/watch?v="&INDEX(tblVideos[Video ID],Q30),IF(INDEX(tblVideos[Status],Q30)="Watched","✓ ","▸ ")&INDEX(tblVideos[Title],Q30)))) | K30: =IF(S28>=2,MATCH(K28*100+2,tblVideos[Cal Key],0),"") | L30: =IF(T28>=2,MATCH(L28*100+2,tblVideos[Cal Key],0),"") | M30: =IF(U28>=2,MATCH(M28*100+2,tblVideos[Cal Key],0),"") | N30: =IF(V28>=2,MATCH(N28*100+2,tblVideos[Cal Key],0),"") | O30: =IF(W28>=2,MATCH(O28*100+2,tblVideos[Cal Key],0),"") | P30: =IF(X28>=2,MATCH(P28*100+2,tblVideos[Cal Key],0),"") | Q30: =IF(Y28>=2,MATCH(Q28*100+2,tblVideos[Cal Key],0),"") | S30: =IF(K30="","",IFERROR(MATCH(INDEX(tblVideos[Channel ID],K30),tblChannels[Channel ID],0),"")) | T30: =IF(L30="","",IFERROR(MATCH(INDEX(tblVideos[Channel ID],L30),tblChannels[Channel ID],0),"")) | U30: =IF(M30="","",IFERROR(MATCH(INDEX(tblVideos[Channel ID],M30),tblChannels[Channel ID],0),"")) | V30: =IF(N30="","",IFERROR(MATCH(INDEX(tblVideos[Channel ID],N30),tblChannels[Channel ID],0),"")) | W30: =IF(O30="","",IFERROR(MATCH(INDEX(tblVideos[Channel ID],O30),tblChannels[Channel ID],0),"")) | X30: =IF(P30="","",IFERROR(MATCH(INDEX(tblVideos[Channel ID],P30),tblChannels[Channel ID],0),"")) | Y30: =IF(Q30="","",IFERROR(MATCH(INDEX(tblVideos[Channel ID],Q30),tblChannels[Channel ID],0),""))
B31: =IF(K31="","",IF(INDEX(tblVideos[Video ID],K31)="",IF(INDEX(tblVideos[Status],K31)="Watched","✓ ","▸ ")&INDEX(tblVideos[Title],K31),HYPERLINK("https://www.youtube.com/watch?v="&INDEX(tblVideos[Video ID],K31),IF(INDEX(tblVideos[Status],K31)="Watched","✓ ","▸ ")&INDEX(tblVideos[Title],K31)))) | C31: =IF(L31="","",IF(INDEX(tblVideos[Video ID],L31)="",IF(INDEX(tblVideos[Status],L31)="Watched","✓ ","▸ ")&INDEX(tblVideos[Title],L31),HYPERLINK("https://www.youtube.com/watch?v="&INDEX(tblVideos[Video ID],L31),IF(INDEX(tblVideos[Status],L31)="Watched","✓ ","▸ ")&INDEX(tblVideos[Title],L31)))) | D31: =IF(M31="","",IF(INDEX(tblVideos[Video ID],M31)="",IF(INDEX(tblVideos[Status],M31)="Watched","✓ ","▸ ")&INDEX(tblVideos[Title],M31),HYPERLINK("https://www.youtube.com/watch?v="&INDEX(tblVideos[Video ID],M31),IF(INDEX(tblVideos[Status],M31)="Watched","✓ ","▸ ")&INDEX(tblVideos[Title],M31)))) | E31: =IF(N31="","",IF(INDEX(tblVideos[Video ID],N31)="",IF(INDEX(tblVideos[Status],N31)="Watched","✓ ","▸ ")&INDEX(tblVideos[Title],N31),HYPERLINK("https://www.youtube.com/watch?v="&INDEX(tblVideos[Video ID],N31),IF(INDEX(tblVideos[Status],N31)="Watched","✓ ","▸ ")&INDEX(tblVideos[Title],N31)))) | F31: =IF(O31="","",IF(INDEX(tblVideos[Video ID],O31)="",IF(INDEX(tblVideos[Status],O31)="Watched","✓ ","▸ ")&INDEX(tblVideos[Title],O31),HYPERLINK("https://www.youtube.com/watch?v="&INDEX(tblVideos[Video ID],O31),IF(INDEX(tblVideos[Status],O31)="Watched","✓ ","▸ ")&INDEX(tblVideos[Title],O31)))) | G31: =IF(P31="","",IF(INDEX(tblVideos[Video ID],P31)="",IF(INDEX(tblVideos[Status],P31)="Watched","✓ ","▸ ")&INDEX(tblVideos[Title],P31),HYPERLINK("https://www.youtube.com/watch?v="&INDEX(tblVideos[Video ID],P31),IF(INDEX(tblVideos[Status],P31)="Watched","✓ ","▸ ")&INDEX(tblVideos[Title],P31)))) | H31: =IF(Q31="","",IF(INDEX(tblVideos[Video ID],Q31)="",IF(INDEX(tblVideos[Status],Q31)="Watched","✓ ","▸ ")&INDEX(tblVideos[Title],Q31),HYPERLINK("https://www.youtube.com/watch?v="&INDEX(tblVideos[Video ID],Q31),IF(INDEX(tblVideos[Status],Q31)="Watched","✓ ","▸ ")&INDEX(tblVideos[Title],Q31)))) | K31: =IF(S28>=3,MATCH(K28*100+3,tblVideos[Cal Key],0),"") | L31: =IF(T28>=3,MATCH(L28*100+3,tblVideos[Cal Key],0),"") | M31: =IF(U28>=3,MATCH(M28*100+3,tblVideos[Cal Key],0),"") | N31: =IF(V28>=3,MATCH(N28*100+3,tblVideos[Cal Key],0),"") | O31: =IF(W28>=3,MATCH(O28*100+3,tblVideos[Cal Key],0),"") | P31: =IF(X28>=3,MATCH(P28*100+3,tblVideos[Cal Key],0),"") | Q31: =IF(Y28>=3,MATCH(Q28*100+3,tblVideos[Cal Key],0),"") | S31: =IF(K31="","",IFERROR(MATCH(INDEX(tblVideos[Channel ID],K31),tblChannels[Channel ID],0),"")) | T31: =IF(L31="","",IFERROR(MATCH(INDEX(tblVideos[Channel ID],L31),tblChannels[Channel ID],0),"")) | U31: =IF(M31="","",IFERROR(MATCH(INDEX(tblVideos[Channel ID],M31),tblChannels[Channel ID],0),"")) | V31: =IF(N31="","",IFERROR(MATCH(INDEX(tblVideos[Channel ID],N31),tblChannels[Channel ID],0),"")) | W31: =IF(O31="","",IFERROR(MATCH(INDEX(tblVideos[Channel ID],O31),tblChannels[Channel ID],0),"")) | X31: =IF(P31="","",IFERROR(MATCH(INDEX(tblVideos[Channel ID],P31),tblChannels[Channel ID],0),"")) | Y31: =IF(Q31="","",IFERROR(MATCH(INDEX(tblVideos[Channel ID],Q31),tblChannels[Channel ID],0),""))
B32: =IF(K32="","",IF(INDEX(tblVideos[Video ID],K32)="",IF(INDEX(tblVideos[Status],K32)="Watched","✓ ","▸ ")&INDEX(tblVideos[Title],K32),HYPERLINK("https://www.youtube.com/watch?v="&INDEX(tblVideos[Video ID],K32),IF(INDEX(tblVideos[Status],K32)="Watched","✓ ","▸ ")&INDEX(tblVideos[Title],K32)))) | C32: =IF(L32="","",IF(INDEX(tblVideos[Video ID],L32)="",IF(INDEX(tblVideos[Status],L32)="Watched","✓ ","▸ ")&INDEX(tblVideos[Title],L32),HYPERLINK("https://www.youtube.com/watch?v="&INDEX(tblVideos[Video ID],L32),IF(INDEX(tblVideos[Status],L32)="Watched","✓ ","▸ ")&INDEX(tblVideos[Title],L32)))) | D32: =IF(M32="","",IF(INDEX(tblVideos[Video ID],M32)="",IF(INDEX(tblVideos[Status],M32)="Watched","✓ ","▸ ")&INDEX(tblVideos[Title],M32),HYPERLINK("https://www.youtube.com/watch?v="&INDEX(tblVideos[Video ID],M32),IF(INDEX(tblVideos[Status],M32)="Watched","✓ ","▸ ")&INDEX(tblVideos[Title],M32)))) | E32: =IF(N32="","",IF(INDEX(tblVideos[Video ID],N32)="",IF(INDEX(tblVideos[Status],N32)="Watched","✓ ","▸ ")&INDEX(tblVideos[Title],N32),HYPERLINK("https://www.youtube.com/watch?v="&INDEX(tblVideos[Video ID],N32),IF(INDEX(tblVideos[Status],N32)="Watched","✓ ","▸ ")&INDEX(tblVideos[Title],N32)))) | F32: =IF(O32="","",IF(INDEX(tblVideos[Video ID],O32)="",IF(INDEX(tblVideos[Status],O32)="Watched","✓ ","▸ ")&INDEX(tblVideos[Title],O32),HYPERLINK("https://www.youtube.com/watch?v="&INDEX(tblVideos[Video ID],O32),IF(INDEX(tblVideos[Status],O32)="Watched","✓ ","▸ ")&INDEX(tblVideos[Title],O32)))) | G32: =IF(P32="","",IF(INDEX(tblVideos[Video ID],P32)="",IF(INDEX(tblVideos[Status],P32)="Watched","✓ ","▸ ")&INDEX(tblVideos[Title],P32),HYPERLINK("https://www.youtube.com/watch?v="&INDEX(tblVideos[Video ID],P32),IF(INDEX(tblVideos[Status],P32)="Watched","✓ ","▸ ")&INDEX(tblVideos[Title],P32)))) | H32: =IF(Q32="","",IF(INDEX(tblVideos[Video ID],Q32)="",IF(INDEX(tblVideos[Status],Q32)="Watched","✓ ","▸ ")&INDEX(tblVideos[Title],Q32),HYPERLINK("https://www.youtube.com/watch?v="&INDEX(tblVideos[Video ID],Q32),IF(INDEX(tblVideos[Status],Q32)="Watched","✓ ","▸ ")&INDEX(tblVideos[Title],Q32)))) | K32: =IF(S28>=4,MATCH(K28*100+4,tblVideos[Cal Key],0),"") | L32: =IF(T28>=4,MATCH(L28*100+4,tblVideos[Cal Key],0),"") | M32: =IF(U28>=4,MATCH(M28*100+4,tblVideos[Cal Key],0),"") | N32: =IF(V28>=4,MATCH(N28*100+4,tblVideos[Cal Key],0),"") | O32: =IF(W28>=4,MATCH(O28*100+4,tblVideos[Cal Key],0),"") | P32: =IF(X28>=4,MATCH(P28*100+4,tblVideos[Cal Key],0),"") | Q32: =IF(Y28>=4,MATCH(Q28*100+4,tblVideos[Cal Key],0),"") | S32: =IF(K32="","",IFERROR(MATCH(INDEX(tblVideos[Channel ID],K32),tblChannels[Channel ID],0),"")) | T32: =IF(L32="","",IFERROR(MATCH(INDEX(tblVideos[Channel ID],L32),tblChannels[Channel ID],0),"")) | U32: =IF(M32="","",IFERROR(MATCH(INDEX(tblVideos[Channel ID],M32),tblChannels[Channel ID],0),"")) | V32: =IF(N32="","",IFERROR(MATCH(INDEX(tblVideos[Channel ID],N32),tblChannels[Channel ID],0),"")) | W32: =IF(O32="","",IFERROR(MATCH(INDEX(tblVideos[Channel ID],O32),tblChannels[Channel ID],0),"")) | X32: =IF(P32="","",IFERROR(MATCH(INDEX(tblVideos[Channel ID],P32),tblChannels[Channel ID],0),"")) | Y32: =IF(Q32="","",IFERROR(MATCH(INDEX(tblVideos[Channel ID],Q32),tblChannels[Channel ID],0),""))
B33: =IF(K33="","",IF(INDEX(tblVideos[Video ID],K33)="",IF(INDEX(tblVideos[Status],K33)="Watched","✓ ","▸ ")&INDEX(tblVideos[Title],K33),HYPERLINK("https://www.youtube.com/watch?v="&INDEX(tblVideos[Video ID],K33),IF(INDEX(tblVideos[Status],K33)="Watched","✓ ","▸ ")&INDEX(tblVideos[Title],K33)))) | C33: =IF(L33="","",IF(INDEX(tblVideos[Video ID],L33)="",IF(INDEX(tblVideos[Status],L33)="Watched","✓ ","▸ ")&INDEX(tblVideos[Title],L33),HYPERLINK("https://www.youtube.com/watch?v="&INDEX(tblVideos[Video ID],L33),IF(INDEX(tblVideos[Status],L33)="Watched","✓ ","▸ ")&INDEX(tblVideos[Title],L33)))) | D33: =IF(M33="","",IF(INDEX(tblVideos[Video ID],M33)="",IF(INDEX(tblVideos[Status],M33)="Watched","✓ ","▸ ")&INDEX(tblVideos[Title],M33),HYPERLINK("https://www.youtube.com/watch?v="&INDEX(tblVideos[Video ID],M33),IF(INDEX(tblVideos[Status],M33)="Watched","✓ ","▸ ")&INDEX(tblVideos[Title],M33)))) | E33: =IF(N33="","",IF(INDEX(tblVideos[Video ID],N33)="",IF(INDEX(tblVideos[Status],N33)="Watched","✓ ","▸ ")&INDEX(tblVideos[Title],N33),HYPERLINK("https://www.youtube.com/watch?v="&INDEX(tblVideos[Video ID],N33),IF(INDEX(tblVideos[Status],N33)="Watched","✓ ","▸ ")&INDEX(tblVideos[Title],N33)))) | F33: =IF(O33="","",IF(INDEX(tblVideos[Video ID],O33)="",IF(INDEX(tblVideos[Status],O33)="Watched","✓ ","▸ ")&INDEX(tblVideos[Title],O33),HYPERLINK("https://www.youtube.com/watch?v="&INDEX(tblVideos[Video ID],O33),IF(INDEX(tblVideos[Status],O33)="Watched","✓ ","▸ ")&INDEX(tblVideos[Title],O33)))) | G33: =IF(P33="","",IF(INDEX(tblVideos[Video ID],P33)="",IF(INDEX(tblVideos[Status],P33)="Watched","✓ ","▸ ")&INDEX(tblVideos[Title],P33),HYPERLINK("https://www.youtube.com/watch?v="&INDEX(tblVideos[Video ID],P33),IF(INDEX(tblVideos[Status],P33)="Watched","✓ ","▸ ")&INDEX(tblVideos[Title],P33)))) | H33: =IF(Q33="","",IF(INDEX(tblVideos[Video ID],Q33)="",IF(INDEX(tblVideos[Status],Q33)="Watched","✓ ","▸ ")&INDEX(tblVideos[Title],Q33),HYPERLINK("https://www.youtube.com/watch?v="&INDEX(tblVideos[Video ID],Q33),IF(INDEX(tblVideos[Status],Q33)="Watched","✓ ","▸ ")&INDEX(tblVideos[Title],Q33)))) | K33: =IF(S28>=5,MATCH(K28*100+5,tblVideos[Cal Key],0),"") | L33: =IF(T28>=5,MATCH(L28*100+5,tblVideos[Cal Key],0),"") | M33: =IF(U28>=5,MATCH(M28*100+5,tblVideos[Cal Key],0),"") | N33: =IF(V28>=5,MATCH(N28*100+5,tblVideos[Cal Key],0),"") | O33: =IF(W28>=5,MATCH(O28*100+5,tblVideos[Cal Key],0),"") | P33: =IF(X28>=5,MATCH(P28*100+5,tblVideos[Cal Key],0),"") | Q33: =IF(Y28>=5,MATCH(Q28*100+5,tblVideos[Cal Key],0),"") | S33: =IF(K33="","",IFERROR(MATCH(INDEX(tblVideos[Channel ID],K33),tblChannels[Channel ID],0),"")) | T33: =IF(L33="","",IFERROR(MATCH(INDEX(tblVideos[Channel ID],L33),tblChannels[Channel ID],0),"")) | U33: =IF(M33="","",IFERROR(MATCH(INDEX(tblVideos[Channel ID],M33),tblChannels[Channel ID],0),"")) | V33: =IF(N33="","",IFERROR(MATCH(INDEX(tblVideos[Channel ID],N33),tblChannels[Channel ID],0),"")) | W33: =IF(O33="","",IFERROR(MATCH(INDEX(tblVideos[Channel ID],O33),tblChannels[Channel ID],0),"")) | X33: =IF(P33="","",IFERROR(MATCH(INDEX(tblVideos[Channel ID],P33),tblChannels[Channel ID],0),"")) | Y33: =IF(Q33="","",IFERROR(MATCH(INDEX(tblVideos[Channel ID],Q33),tblChannels[Channel ID],0),""))
B34: =IF(MONTH(K34)=MONTH($K$2),DAY(K34)&IF(S34>0," · "&S34&IF(S34=1," video"," videos")&" · "&TEXT(AA34,"[h]:mm")&IF(S34>5," (+"&(S34-5)&" more)",""),""),"") | C34: =IF(MONTH(L34)=MONTH($K$2),DAY(L34)&IF(T34>0," · "&T34&IF(T34=1," video"," videos")&" · "&TEXT(AB34,"[h]:mm")&IF(T34>5," (+"&(T34-5)&" more)",""),""),"") | D34: =IF(MONTH(M34)=MONTH($K$2),DAY(M34)&IF(U34>0," · "&U34&IF(U34=1," video"," videos")&" · "&TEXT(AC34,"[h]:mm")&IF(U34>5," (+"&(U34-5)&" more)",""),""),"") | E34: =IF(MONTH(N34)=MONTH($K$2),DAY(N34)&IF(V34>0," · "&V34&IF(V34=1," video"," videos")&" · "&TEXT(AD34,"[h]:mm")&IF(V34>5," (+"&(V34-5)&" more)",""),""),"") | F34: =IF(MONTH(O34)=MONTH($K$2),DAY(O34)&IF(W34>0," · "&W34&IF(W34=1," video"," videos")&" · "&TEXT(AE34,"[h]:mm")&IF(W34>5," (+"&(W34-5)&" more)",""),""),"") | G34: =IF(MONTH(P34)=MONTH($K$2),DAY(P34)&IF(X34>0," · "&X34&IF(X34=1," video"," videos")&" · "&TEXT(AF34,"[h]:mm")&IF(X34>5," (+"&(X34-5)&" more)",""),""),"") | H34: =IF(MONTH(Q34)=MONTH($K$2),DAY(Q34)&IF(Y34>0," · "&Y34&IF(Y34=1," video"," videos")&" · "&TEXT(AG34,"[h]:mm")&IF(Y34>5," (+"&(Y34-5)&" more)",""),""),"") | K34: =$K$3+28 | L34: =$K$3+29 | M34: =$K$3+30 | N34: =$K$3+31 | O34: =$K$3+32 | P34: =$K$3+33 | Q34: =$K$3+34 | S34: =IF(MONTH(K34)=MONTH($K$2),COUNTIFS(tblVideos[Day],K34,tblVideos[Channel ID],$K$4),0) | T34: =IF(MONTH(L34)=MONTH($K$2),COUNTIFS(tblVideos[Day],L34,tblVideos[Channel ID],$K$4),0) | U34: =IF(MONTH(M34)=MONTH($K$2),COUNTIFS(tblVideos[Day],M34,tblVideos[Channel ID],$K$4),0) | V34: =IF(MONTH(N34)=MONTH($K$2),COUNTIFS(tblVideos[Day],N34,tblVideos[Channel ID],$K$4),0) | W34: =IF(MONTH(O34)=MONTH($K$2),COUNTIFS(tblVideos[Day],O34,tblVideos[Channel ID],$K$4),0) | X34: =IF(MONTH(P34)=MONTH($K$2),COUNTIFS(tblVideos[Day],P34,tblVideos[Channel ID],$K$4),0) | Y34: =IF(MONTH(Q34)=MONTH($K$2),COUNTIFS(tblVideos[Day],Q34,tblVideos[Channel ID],$K$4),0) | AA34: =IF(S34>0,SUMIFS(tblVideos[Length],tblVideos[Day],K34,tblVideos[Channel ID],$K$4),0) | AB34: =IF(T34>0,SUMIFS(tblVideos[Length],tblVideos[Day],L34,tblVideos[Channel ID],$K$4),0) | AC34: =IF(U34>0,SUMIFS(tblVideos[Length],tblVideos[Day],M34,tblVideos[Channel ID],$K$4),0) | AD34: =IF(V34>0,SUMIFS(tblVideos[Length],tblVideos[Day],N34,tblVideos[Channel ID],$K$4),0) | AE34: =IF(W34>0,SUMIFS(tblVideos[Length],tblVideos[Day],O34,tblVideos[Channel ID],$K$4),0) | AF34: =IF(X34>0,SUMIFS(tblVideos[Length],tblVideos[Day],P34,tblVideos[Channel ID],$K$4),0) | AG34: =IF(Y34>0,SUMIFS(tblVideos[Length],tblVideos[Day],Q34,tblVideos[Channel ID],$K$4),0)
B35: =IF(K35="","",IF(INDEX(tblVideos[Video ID],K35)="",IF(INDEX(tblVideos[Status],K35)="Watched","✓ ","▸ ")&INDEX(tblVideos[Title],K35),HYPERLINK("https://www.youtube.com/watch?v="&INDEX(tblVideos[Video ID],K35),IF(INDEX(tblVideos[Status],K35)="Watched","✓ ","▸ ")&INDEX(tblVideos[Title],K35)))) | C35: =IF(L35="","",IF(INDEX(tblVideos[Video ID],L35)="",IF(INDEX(tblVideos[Status],L35)="Watched","✓ ","▸ ")&INDEX(tblVideos[Title],L35),HYPERLINK("https://www.youtube.com/watch?v="&INDEX(tblVideos[Video ID],L35),IF(INDEX(tblVideos[Status],L35)="Watched","✓ ","▸ ")&INDEX(tblVideos[Title],L35)))) | D35: =IF(M35="","",IF(INDEX(tblVideos[Video ID],M35)="",IF(INDEX(tblVideos[Status],M35)="Watched","✓ ","▸ ")&INDEX(tblVideos[Title],M35),HYPERLINK("https://www.youtube.com/watch?v="&INDEX(tblVideos[Video ID],M35),IF(INDEX(tblVideos[Status],M35)="Watched","✓ ","▸ ")&INDEX(tblVideos[Title],M35)))) | E35: =IF(N35="","",IF(INDEX(tblVideos[Video ID],N35)="",IF(INDEX(tblVideos[Status],N35)="Watched","✓ ","▸ ")&INDEX(tblVideos[Title],N35),HYPERLINK("https://www.youtube.com/watch?v="&INDEX(tblVideos[Video ID],N35),IF(INDEX(tblVideos[Status],N35)="Watched","✓ ","▸ ")&INDEX(tblVideos[Title],N35)))) | F35: =IF(O35="","",IF(INDEX(tblVideos[Video ID],O35)="",IF(INDEX(tblVideos[Status],O35)="Watched","✓ ","▸ ")&INDEX(tblVideos[Title],O35),HYPERLINK("https://www.youtube.com/watch?v="&INDEX(tblVideos[Video ID],O35),IF(INDEX(tblVideos[Status],O35)="Watched","✓ ","▸ ")&INDEX(tblVideos[Title],O35)))) | G35: =IF(P35="","",IF(INDEX(tblVideos[Video ID],P35)="",IF(INDEX(tblVideos[Status],P35)="Watched","✓ ","▸ ")&INDEX(tblVideos[Title],P35),HYPERLINK("https://www.youtube.com/watch?v="&INDEX(tblVideos[Video ID],P35),IF(INDEX(tblVideos[Status],P35)="Watched","✓ ","▸ ")&INDEX(tblVideos[Title],P35)))) | H35: =IF(Q35="","",IF(INDEX(tblVideos[Video ID],Q35)="",IF(INDEX(tblVideos[Status],Q35)="Watched","✓ ","▸ ")&INDEX(tblVideos[Title],Q35),HYPERLINK("https://www.youtube.com/watch?v="&INDEX(tblVideos[Video ID],Q35),IF(INDEX(tblVideos[Status],Q35)="Watched","✓ ","▸ ")&INDEX(tblVideos[Title],Q35)))) | K35: =IF(S34>=1,MATCH(K34*100+1,tblVideos[Cal Key],0),"") | L35: =IF(T34>=1,MATCH(L34*100+1,tblVideos[Cal Key],0),"") | M35: =IF(U34>=1,MATCH(M34*100+1,tblVideos[Cal Key],0),"") | N35: =IF(V34>=1,MATCH(N34*100+1,tblVideos[Cal Key],0),"") | O35: =IF(W34>=1,MATCH(O34*100+1,tblVideos[Cal Key],0),"") | P35: =IF(X34>=1,MATCH(P34*100+1,tblVideos[Cal Key],0),"") | Q35: =IF(Y34>=1,MATCH(Q34*100+1,tblVideos[Cal Key],0),"") | S35: =IF(K35="","",IFERROR(MATCH(INDEX(tblVideos[Channel ID],K35),tblChannels[Channel ID],0),"")) | T35: =IF(L35="","",IFERROR(MATCH(INDEX(tblVideos[Channel ID],L35),tblChannels[Channel ID],0),"")) | U35: =IF(M35="","",IFERROR(MATCH(INDEX(tblVideos[Channel ID],M35),tblChannels[Channel ID],0),"")) | V35: =IF(N35="","",IFERROR(MATCH(INDEX(tblVideos[Channel ID],N35),tblChannels[Channel ID],0),"")) | W35: =IF(O35="","",IFERROR(MATCH(INDEX(tblVideos[Channel ID],O35),tblChannels[Channel ID],0),"")) | X35: =IF(P35="","",IFERROR(MATCH(INDEX(tblVideos[Channel ID],P35),tblChannels[Channel ID],0),"")) | Y35: =IF(Q35="","",IFERROR(MATCH(INDEX(tblVideos[Channel ID],Q35),tblChannels[Channel ID],0),""))
B36: =IF(K36="","",IF(INDEX(tblVideos[Video ID],K36)="",IF(INDEX(tblVideos[Status],K36)="Watched","✓ ","▸ ")&INDEX(tblVideos[Title],K36),HYPERLINK("https://www.youtube.com/watch?v="&INDEX(tblVideos[Video ID],K36),IF(INDEX(tblVideos[Status],K36)="Watched","✓ ","▸ ")&INDEX(tblVideos[Title],K36)))) | C36: =IF(L36="","",IF(INDEX(tblVideos[Video ID],L36)="",IF(INDEX(tblVideos[Status],L36)="Watched","✓ ","▸ ")&INDEX(tblVideos[Title],L36),HYPERLINK("https://www.youtube.com/watch?v="&INDEX(tblVideos[Video ID],L36),IF(INDEX(tblVideos[Status],L36)="Watched","✓ ","▸ ")&INDEX(tblVideos[Title],L36)))) | D36: =IF(M36="","",IF(INDEX(tblVideos[Video ID],M36)="",IF(INDEX(tblVideos[Status],M36)="Watched","✓ ","▸ ")&INDEX(tblVideos[Title],M36),HYPERLINK("https://www.youtube.com/watch?v="&INDEX(tblVideos[Video ID],M36),IF(INDEX(tblVideos[Status],M36)="Watched","✓ ","▸ ")&INDEX(tblVideos[Title],M36)))) | E36: =IF(N36="","",IF(INDEX(tblVideos[Video ID],N36)="",IF(INDEX(tblVideos[Status],N36)="Watched","✓ ","▸ ")&INDEX(tblVideos[Title],N36),HYPERLINK("https://www.youtube.com/watch?v="&INDEX(tblVideos[Video ID],N36),IF(INDEX(tblVideos[Status],N36)="Watched","✓ ","▸ ")&INDEX(tblVideos[Title],N36)))) | F36: =IF(O36="","",IF(INDEX(tblVideos[Video ID],O36)="",IF(INDEX(tblVideos[Status],O36)="Watched","✓ ","▸ ")&INDEX(tblVideos[Title],O36),HYPERLINK("https://www.youtube.com/watch?v="&INDEX(tblVideos[Video ID],O36),IF(INDEX(tblVideos[Status],O36)="Watched","✓ ","▸ ")&INDEX(tblVideos[Title],O36)))) | G36: =IF(P36="","",IF(INDEX(tblVideos[Video ID],P36)="",IF(INDEX(tblVideos[Status],P36)="Watched","✓ ","▸ ")&INDEX(tblVideos[Title],P36),HYPERLINK("https://www.youtube.com/watch?v="&INDEX(tblVideos[Video ID],P36),IF(INDEX(tblVideos[Status],P36)="Watched","✓ ","▸ ")&INDEX(tblVideos[Title],P36)))) | H36: =IF(Q36="","",IF(INDEX(tblVideos[Video ID],Q36)="",IF(INDEX(tblVideos[Status],Q36)="Watched","✓ ","▸ ")&INDEX(tblVideos[Title],Q36),HYPERLINK("https://www.youtube.com/watch?v="&INDEX(tblVideos[Video ID],Q36),IF(INDEX(tblVideos[Status],Q36)="Watched","✓ ","▸ ")&INDEX(tblVideos[Title],Q36)))) | K36: =IF(S34>=2,MATCH(K34*100+2,tblVideos[Cal Key],0),"") | L36: =IF(T34>=2,MATCH(L34*100+2,tblVideos[Cal Key],0),"") | M36: =IF(U34>=2,MATCH(M34*100+2,tblVideos[Cal Key],0),"") | N36: =IF(V34>=2,MATCH(N34*100+2,tblVideos[Cal Key],0),"") | O36: =IF(W34>=2,MATCH(O34*100+2,tblVideos[Cal Key],0),"") | P36: =IF(X34>=2,MATCH(P34*100+2,tblVideos[Cal Key],0),"") | Q36: =IF(Y34>=2,MATCH(Q34*100+2,tblVideos[Cal Key],0),"") | S36: =IF(K36="","",IFERROR(MATCH(INDEX(tblVideos[Channel ID],K36),tblChannels[Channel ID],0),"")) | T36: =IF(L36="","",IFERROR(MATCH(INDEX(tblVideos[Channel ID],L36),tblChannels[Channel ID],0),"")) | U36: =IF(M36="","",IFERROR(MATCH(INDEX(tblVideos[Channel ID],M36),tblChannels[Channel ID],0),"")) | V36: =IF(N36="","",IFERROR(MATCH(INDEX(tblVideos[Channel ID],N36),tblChannels[Channel ID],0),"")) | W36: =IF(O36="","",IFERROR(MATCH(INDEX(tblVideos[Channel ID],O36),tblChannels[Channel ID],0),"")) | X36: =IF(P36="","",IFERROR(MATCH(INDEX(tblVideos[Channel ID],P36),tblChannels[Channel ID],0),"")) | Y36: =IF(Q36="","",IFERROR(MATCH(INDEX(tblVideos[Channel ID],Q36),tblChannels[Channel ID],0),""))
B37: =IF(K37="","",IF(INDEX(tblVideos[Video ID],K37)="",IF(INDEX(tblVideos[Status],K37)="Watched","✓ ","▸ ")&INDEX(tblVideos[Title],K37),HYPERLINK("https://www.youtube.com/watch?v="&INDEX(tblVideos[Video ID],K37),IF(INDEX(tblVideos[Status],K37)="Watched","✓ ","▸ ")&INDEX(tblVideos[Title],K37)))) | C37: =IF(L37="","",IF(INDEX(tblVideos[Video ID],L37)="",IF(INDEX(tblVideos[Status],L37)="Watched","✓ ","▸ ")&INDEX(tblVideos[Title],L37),HYPERLINK("https://www.youtube.com/watch?v="&INDEX(tblVideos[Video ID],L37),IF(INDEX(tblVideos[Status],L37)="Watched","✓ ","▸ ")&INDEX(tblVideos[Title],L37)))) | D37: =IF(M37="","",IF(INDEX(tblVideos[Video ID],M37)="",IF(INDEX(tblVideos[Status],M37)="Watched","✓ ","▸ ")&INDEX(tblVideos[Title],M37),HYPERLINK("https://www.youtube.com/watch?v="&INDEX(tblVideos[Video ID],M37),IF(INDEX(tblVideos[Status],M37)="Watched","✓ ","▸ ")&INDEX(tblVideos[Title],M37)))) | E37: =IF(N37="","",IF(INDEX(tblVideos[Video ID],N37)="",IF(INDEX(tblVideos[Status],N37)="Watched","✓ ","▸ ")&INDEX(tblVideos[Title],N37),HYPERLINK("https://www.youtube.com/watch?v="&INDEX(tblVideos[Video ID],N37),IF(INDEX(tblVideos[Status],N37)="Watched","✓ ","▸ ")&INDEX(tblVideos[Title],N37)))) | F37: =IF(O37="","",IF(INDEX(tblVideos[Video ID],O37)="",IF(INDEX(tblVideos[Status],O37)="Watched","✓ ","▸ ")&INDEX(tblVideos[Title],O37),HYPERLINK("https://www.youtube.com/watch?v="&INDEX(tblVideos[Video ID],O37),IF(INDEX(tblVideos[Status],O37)="Watched","✓ ","▸ ")&INDEX(tblVideos[Title],O37)))) | G37: =IF(P37="","",IF(INDEX(tblVideos[Video ID],P37)="",IF(INDEX(tblVideos[Status],P37)="Watched","✓ ","▸ ")&INDEX(tblVideos[Title],P37),HYPERLINK("https://www.youtube.com/watch?v="&INDEX(tblVideos[Video ID],P37),IF(INDEX(tblVideos[Status],P37)="Watched","✓ ","▸ ")&INDEX(tblVideos[Title],P37)))) | H37: =IF(Q37="","",IF(INDEX(tblVideos[Video ID],Q37)="",IF(INDEX(tblVideos[Status],Q37)="Watched","✓ ","▸ ")&INDEX(tblVideos[Title],Q37),HYPERLINK("https://www.youtube.com/watch?v="&INDEX(tblVideos[Video ID],Q37),IF(INDEX(tblVideos[Status],Q37)="Watched","✓ ","▸ ")&INDEX(tblVideos[Title],Q37)))) | K37: =IF(S34>=3,MATCH(K34*100+3,tblVideos[Cal Key],0),"") | L37: =IF(T34>=3,MATCH(L34*100+3,tblVideos[Cal Key],0),"") | M37: =IF(U34>=3,MATCH(M34*100+3,tblVideos[Cal Key],0),"") | N37: =IF(V34>=3,MATCH(N34*100+3,tblVideos[Cal Key],0),"") | O37: =IF(W34>=3,MATCH(O34*100+3,tblVideos[Cal Key],0),"") | P37: =IF(X34>=3,MATCH(P34*100+3,tblVideos[Cal Key],0),"") | Q37: =IF(Y34>=3,MATCH(Q34*100+3,tblVideos[Cal Key],0),"") | S37: =IF(K37="","",IFERROR(MATCH(INDEX(tblVideos[Channel ID],K37),tblChannels[Channel ID],0),"")) | T37: =IF(L37="","",IFERROR(MATCH(INDEX(tblVideos[Channel ID],L37),tblChannels[Channel ID],0),"")) | U37: =IF(M37="","",IFERROR(MATCH(INDEX(tblVideos[Channel ID],M37),tblChannels[Channel ID],0),"")) | V37: =IF(N37="","",IFERROR(MATCH(INDEX(tblVideos[Channel ID],N37),tblChannels[Channel ID],0),"")) | W37: =IF(O37="","",IFERROR(MATCH(INDEX(tblVideos[Channel ID],O37),tblChannels[Channel ID],0),"")) | X37: =IF(P37="","",IFERROR(MATCH(INDEX(tblVideos[Channel ID],P37),tblChannels[Channel ID],0),"")) | Y37: =IF(Q37="","",IFERROR(MATCH(INDEX(tblVideos[Channel ID],Q37),tblChannels[Channel ID],0),""))
B38: =IF(K38="","",IF(INDEX(tblVideos[Video ID],K38)="",IF(INDEX(tblVideos[Status],K38)="Watched","✓ ","▸ ")&INDEX(tblVideos[Title],K38),HYPERLINK("https://www.youtube.com/watch?v="&INDEX(tblVideos[Video ID],K38),IF(INDEX(tblVideos[Status],K38)="Watched","✓ ","▸ ")&INDEX(tblVideos[Title],K38)))) | C38: =IF(L38="","",IF(INDEX(tblVideos[Video ID],L38)="",IF(INDEX(tblVideos[Status],L38)="Watched","✓ ","▸ ")&INDEX(tblVideos[Title],L38),HYPERLINK("https://www.youtube.com/watch?v="&INDEX(tblVideos[Video ID],L38),IF(INDEX(tblVideos[Status],L38)="Watched","✓ ","▸ ")&INDEX(tblVideos[Title],L38)))) | D38: =IF(M38="","",IF(INDEX(tblVideos[Video ID],M38)="",IF(INDEX(tblVideos[Status],M38)="Watched","✓ ","▸ ")&INDEX(tblVideos[Title],M38),HYPERLINK("https://www.youtube.com/watch?v="&INDEX(tblVideos[Video ID],M38),IF(INDEX(tblVideos[Status],M38)="Watched","✓ ","▸ ")&INDEX(tblVideos[Title],M38)))) | E38: =IF(N38="","",IF(INDEX(tblVideos[Video ID],N38)="",IF(INDEX(tblVideos[Status],N38)="Watched","✓ ","▸ ")&INDEX(tblVideos[Title],N38),HYPERLINK("https://www.youtube.com/watch?v="&INDEX(tblVideos[Video ID],N38),IF(INDEX(tblVideos[Status],N38)="Watched","✓ ","▸ ")&INDEX(tblVideos[Title],N38)))) | F38: =IF(O38="","",IF(INDEX(tblVideos[Video ID],O38)="",IF(INDEX(tblVideos[Status],O38)="Watched","✓ ","▸ ")&INDEX(tblVideos[Title],O38),HYPERLINK("https://www.youtube.com/watch?v="&INDEX(tblVideos[Video ID],O38),IF(INDEX(tblVideos[Status],O38)="Watched","✓ ","▸ ")&INDEX(tblVideos[Title],O38)))) | G38: =IF(P38="","",IF(INDEX(tblVideos[Video ID],P38)="",IF(INDEX(tblVideos[Status],P38)="Watched","✓ ","▸ ")&INDEX(tblVideos[Title],P38),HYPERLINK("https://www.youtube.com/watch?v="&INDEX(tblVideos[Video ID],P38),IF(INDEX(tblVideos[Status],P38)="Watched","✓ ","▸ ")&INDEX(tblVideos[Title],P38)))) | H38: =IF(Q38="","",IF(INDEX(tblVideos[Video ID],Q38)="",IF(INDEX(tblVideos[Status],Q38)="Watched","✓ ","▸ ")&INDEX(tblVideos[Title],Q38),HYPERLINK("https://www.youtube.com/watch?v="&INDEX(tblVideos[Video ID],Q38),IF(INDEX(tblVideos[Status],Q38)="Watched","✓ ","▸ ")&INDEX(tblVideos[Title],Q38)))) | K38: =IF(S34>=4,MATCH(K34*100+4,tblVideos[Cal Key],0),"") | L38: =IF(T34>=4,MATCH(L34*100+4,tblVideos[Cal Key],0),"") | M38: =IF(U34>=4,MATCH(M34*100+4,tblVideos[Cal Key],0),"") | N38: =IF(V34>=4,MATCH(N34*100+4,tblVideos[Cal Key],0),"") | O38: =IF(W34>=4,MATCH(O34*100+4,tblVideos[Cal Key],0),"") | P38: =IF(X34>=4,MATCH(P34*100+4,tblVideos[Cal Key],0),"") | Q38: =IF(Y34>=4,MATCH(Q34*100+4,tblVideos[Cal Key],0),"") | S38: =IF(K38="","",IFERROR(MATCH(INDEX(tblVideos[Channel ID],K38),tblChannels[Channel ID],0),"")) | T38: =IF(L38="","",IFERROR(MATCH(INDEX(tblVideos[Channel ID],L38),tblChannels[Channel ID],0),"")) | U38: =IF(M38="","",IFERROR(MATCH(INDEX(tblVideos[Channel ID],M38),tblChannels[Channel ID],0),"")) | V38: =IF(N38="","",IFERROR(MATCH(INDEX(tblVideos[Channel ID],N38),tblChannels[Channel ID],0),"")) | W38: =IF(O38="","",IFERROR(MATCH(INDEX(tblVideos[Channel ID],O38),tblChannels[Channel ID],0),"")) | X38: =IF(P38="","",IFERROR(MATCH(INDEX(tblVideos[Channel ID],P38),tblChannels[Channel ID],0),"")) | Y38: =IF(Q38="","",IFERROR(MATCH(INDEX(tblVideos[Channel ID],Q38),tblChannels[Channel ID],0),""))
B39: =IF(K39="","",IF(INDEX(tblVideos[Video ID],K39)="",IF(INDEX(tblVideos[Status],K39)="Watched","✓ ","▸ ")&INDEX(tblVideos[Title],K39),HYPERLINK("https://www.youtube.com/watch?v="&INDEX(tblVideos[Video ID],K39),IF(INDEX(tblVideos[Status],K39)="Watched","✓ ","▸ ")&INDEX(tblVideos[Title],K39)))) | C39: =IF(L39="","",IF(INDEX(tblVideos[Video ID],L39)="",IF(INDEX(tblVideos[Status],L39)="Watched","✓ ","▸ ")&INDEX(tblVideos[Title],L39),HYPERLINK("https://www.youtube.com/watch?v="&INDEX(tblVideos[Video ID],L39),IF(INDEX(tblVideos[Status],L39)="Watched","✓ ","▸ ")&INDEX(tblVideos[Title],L39)))) | D39: =IF(M39="","",IF(INDEX(tblVideos[Video ID],M39)="",IF(INDEX(tblVideos[Status],M39)="Watched","✓ ","▸ ")&INDEX(tblVideos[Title],M39),HYPERLINK("https://www.youtube.com/watch?v="&INDEX(tblVideos[Video ID],M39),IF(INDEX(tblVideos[Status],M39)="Watched","✓ ","▸ ")&INDEX(tblVideos[Title],M39)))) | E39: =IF(N39="","",IF(INDEX(tblVideos[Video ID],N39)="",IF(INDEX(tblVideos[Status],N39)="Watched","✓ ","▸ ")&INDEX(tblVideos[Title],N39),HYPERLINK("https://www.youtube.com/watch?v="&INDEX(tblVideos[Video ID],N39),IF(INDEX(tblVideos[Status],N39)="Watched","✓ ","▸ ")&INDEX(tblVideos[Title],N39)))) | F39: =IF(O39="","",IF(INDEX(tblVideos[Video ID],O39)="",IF(INDEX(tblVideos[Status],O39)="Watched","✓ ","▸ ")&INDEX(tblVideos[Title],O39),HYPERLINK("https://www.youtube.com/watch?v="&INDEX(tblVideos[Video ID],O39),IF(INDEX(tblVideos[Status],O39)="Watched","✓ ","▸ ")&INDEX(tblVideos[Title],O39)))) | G39: =IF(P39="","",IF(INDEX(tblVideos[Video ID],P39)="",IF(INDEX(tblVideos[Status],P39)="Watched","✓ ","▸ ")&INDEX(tblVideos[Title],P39),HYPERLINK("https://www.youtube.com/watch?v="&INDEX(tblVideos[Video ID],P39),IF(INDEX(tblVideos[Status],P39)="Watched","✓ ","▸ ")&INDEX(tblVideos[Title],P39)))) | H39: =IF(Q39="","",IF(INDEX(tblVideos[Video ID],Q39)="",IF(INDEX(tblVideos[Status],Q39)="Watched","✓ ","▸ ")&INDEX(tblVideos[Title],Q39),HYPERLINK("https://www.youtube.com/watch?v="&INDEX(tblVideos[Video ID],Q39),IF(INDEX(tblVideos[Status],Q39)="Watched","✓ ","▸ ")&INDEX(tblVideos[Title],Q39)))) | K39: =IF(S34>=5,MATCH(K34*100+5,tblVideos[Cal Key],0),"") | L39: =IF(T34>=5,MATCH(L34*100+5,tblVideos[Cal Key],0),"") | M39: =IF(U34>=5,MATCH(M34*100+5,tblVideos[Cal Key],0),"") | N39: =IF(V34>=5,MATCH(N34*100+5,tblVideos[Cal Key],0),"") | O39: =IF(W34>=5,MATCH(O34*100+5,tblVideos[Cal Key],0),"") | P39: =IF(X34>=5,MATCH(P34*100+5,tblVideos[Cal Key],0),"") | Q39: =IF(Y34>=5,MATCH(Q34*100+5,tblVideos[Cal Key],0),"") | S39: =IF(K39="","",IFERROR(MATCH(INDEX(tblVideos[Channel ID],K39),tblChannels[Channel ID],0),"")) | T39: =IF(L39="","",IFERROR(MATCH(INDEX(tblVideos[Channel ID],L39),tblChannels[Channel ID],0),"")) | U39: =IF(M39="","",IFERROR(MATCH(INDEX(tblVideos[Channel ID],M39),tblChannels[Channel ID],0),"")) | V39: =IF(N39="","",IFERROR(MATCH(INDEX(tblVideos[Channel ID],N39),tblChannels[Channel ID],0),"")) | W39: =IF(O39="","",IFERROR(MATCH(INDEX(tblVideos[Channel ID],O39),tblChannels[Channel ID],0),"")) | X39: =IF(P39="","",IFERROR(MATCH(INDEX(tblVideos[Channel ID],P39),tblChannels[Channel ID],0),"")) | Y39: =IF(Q39="","",IFERROR(MATCH(INDEX(tblVideos[Channel ID],Q39),tblChannels[Channel ID],0),""))
B40: =IF(MONTH(K40)=MONTH($K$2),DAY(K40)&IF(S40>0," · "&S40&IF(S40=1," video"," videos")&" · "&TEXT(AA40,"[h]:mm")&IF(S40>5," (+"&(S40-5)&" more)",""),""),"") | C40: =IF(MONTH(L40)=MONTH($K$2),DAY(L40)&IF(T40>0," · "&T40&IF(T40=1," video"," videos")&" · "&TEXT(AB40,"[h]:mm")&IF(T40>5," (+"&(T40-5)&" more)",""),""),"") | D40: =IF(MONTH(M40)=MONTH($K$2),DAY(M40)&IF(U40>0," · "&U40&IF(U40=1," video"," videos")&" · "&TEXT(AC40,"[h]:mm")&IF(U40>5," (+"&(U40-5)&" more)",""),""),"") | E40: =IF(MONTH(N40)=MONTH($K$2),DAY(N40)&IF(V40>0," · "&V40&IF(V40=1," video"," videos")&" · "&TEXT(AD40,"[h]:mm")&IF(V40>5," (+"&(V40-5)&" more)",""),""),"") | F40: =IF(MONTH(O40)=MONTH($K$2),DAY(O40)&IF(W40>0," · "&W40&IF(W40=1," video"," videos")&" · "&TEXT(AE40,"[h]:mm")&IF(W40>5," (+"&(W40-5)&" more)",""),""),"") | G40: =IF(MONTH(P40)=MONTH($K$2),DAY(P40)&IF(X40>0," · "&X40&IF(X40=1," video"," videos")&" · "&TEXT(AF40,"[h]:mm")&IF(X40>5," (+"&(X40-5)&" more)",""),""),"") | H40: =IF(MONTH(Q40)=MONTH($K$2),DAY(Q40)&IF(Y40>0," · "&Y40&IF(Y40=1," video"," videos")&" · "&TEXT(AG40,"[h]:mm")&IF(Y40>5," (+"&(Y40-5)&" more)",""),""),"") | K40: =$K$3+35 | L40: =$K$3+36 | M40: =$K$3+37 | N40: =$K$3+38 | O40: =$K$3+39 | P40: =$K$3+40 | Q40: =$K$3+41 | S40: =IF(MONTH(K40)=MONTH($K$2),COUNTIFS(tblVideos[Day],K40,tblVideos[Channel ID],$K$4),0) | T40: =IF(MONTH(L40)=MONTH($K$2),COUNTIFS(tblVideos[Day],L40,tblVideos[Channel ID],$K$4),0) | U40: =IF(MONTH(M40)=MONTH($K$2),COUNTIFS(tblVideos[Day],M40,tblVideos[Channel ID],$K$4),0) | V40: =IF(MONTH(N40)=MONTH($K$2),COUNTIFS(tblVideos[Day],N40,tblVideos[Channel ID],$K$4),0) | W40: =IF(MONTH(O40)=MONTH($K$2),COUNTIFS(tblVideos[Day],O40,tblVideos[Channel ID],$K$4),0) | X40: =IF(MONTH(P40)=MONTH($K$2),COUNTIFS(tblVideos[Day],P40,tblVideos[Channel ID],$K$4),0) | Y40: =IF(MONTH(Q40)=MONTH($K$2),COUNTIFS(tblVideos[Day],Q40,tblVideos[Channel ID],$K$4),0) | AA40: =IF(S40>0,SUMIFS(tblVideos[Length],tblVideos[Day],K40,tblVideos[Channel ID],$K$4),0) | AB40: =IF(T40>0,SUMIFS(tblVideos[Length],tblVideos[Day],L40,tblVideos[Channel ID],$K$4),0) | AC40: =IF(U40>0,SUMIFS(tblVideos[Length],tblVideos[Day],M40,tblVideos[Channel ID],$K$4),0) | AD40: =IF(V40>0,SUMIFS(tblVideos[Length],tblVideos[Day],N40,tblVideos[Channel ID],$K$4),0) | AE40: =IF(W40>0,SUMIFS(tblVideos[Length],tblVideos[Day],O40,tblVideos[Channel ID],$K$4),0) | AF40: =IF(X40>0,SUMIFS(tblVideos[Length],tblVideos[Day],P40,tblVideos[Channel ID],$K$4),0) | AG40: =IF(Y40>0,SUMIFS(tblVideos[Length],tblVideos[Day],Q40,tblVideos[Channel ID],$K$4),0)
B41: =IF(K41="","",IF(INDEX(tblVideos[Video ID],K41)="",IF(INDEX(tblVideos[Status],K41)="Watched","✓ ","▸ ")&INDEX(tblVideos[Title],K41),HYPERLINK("https://www.youtube.com/watch?v="&INDEX(tblVideos[Video ID],K41),IF(INDEX(tblVideos[Status],K41)="Watched","✓ ","▸ ")&INDEX(tblVideos[Title],K41)))) | C41: =IF(L41="","",IF(INDEX(tblVideos[Video ID],L41)="",IF(INDEX(tblVideos[Status],L41)="Watched","✓ ","▸ ")&INDEX(tblVideos[Title],L41),HYPERLINK("https://www.youtube.com/watch?v="&INDEX(tblVideos[Video ID],L41),IF(INDEX(tblVideos[Status],L41)="Watched","✓ ","▸ ")&INDEX(tblVideos[Title],L41)))) | D41: =IF(M41="","",IF(INDEX(tblVideos[Video ID],M41)="",IF(INDEX(tblVideos[Status],M41)="Watched","✓ ","▸ ")&INDEX(tblVideos[Title],M41),HYPERLINK("https://www.youtube.com/watch?v="&INDEX(tblVideos[Video ID],M41),IF(INDEX(tblVideos[Status],M41)="Watched","✓ ","▸ ")&INDEX(tblVideos[Title],M41)))) | E41: =IF(N41="","",IF(INDEX(tblVideos[Video ID],N41)="",IF(INDEX(tblVideos[Status],N41)="Watched","✓ ","▸ ")&INDEX(tblVideos[Title],N41),HYPERLINK("https://www.youtube.com/watch?v="&INDEX(tblVideos[Video ID],N41),IF(INDEX(tblVideos[Status],N41)="Watched","✓ ","▸ ")&INDEX(tblVideos[Title],N41)))) | F41: =IF(O41="","",IF(INDEX(tblVideos[Video ID],O41)="",IF(INDEX(tblVideos[Status],O41)="Watched","✓ ","▸ ")&INDEX(tblVideos[Title],O41),HYPERLINK("https://www.youtube.com/watch?v="&INDEX(tblVideos[Video ID],O41),IF(INDEX(tblVideos[Status],O41)="Watched","✓ ","▸ ")&INDEX(tblVideos[Title],O41)))) | G41: =IF(P41="","",IF(INDEX(tblVideos[Video ID],P41)="",IF(INDEX(tblVideos[Status],P41)="Watched","✓ ","▸ ")&INDEX(tblVideos[Title],P41),HYPERLINK("https://www.youtube.com/watch?v="&INDEX(tblVideos[Video ID],P41),IF(INDEX(tblVideos[Status],P41)="Watched","✓ ","▸ ")&INDEX(tblVideos[Title],P41)))) | H41: =IF(Q41="","",IF(INDEX(tblVideos[Video ID],Q41)="",IF(INDEX(tblVideos[Status],Q41)="Watched","✓ ","▸ ")&INDEX(tblVideos[Title],Q41),HYPERLINK("https://www.youtube.com/watch?v="&INDEX(tblVideos[Video ID],Q41),IF(INDEX(tblVideos[Status],Q41)="Watched","✓ ","▸ ")&INDEX(tblVideos[Title],Q41)))) | K41: =IF(S40>=1,MATCH(K40*100+1,tblVideos[Cal Key],0),"") | L41: =IF(T40>=1,MATCH(L40*100+1,tblVideos[Cal Key],0),"") | M41: =IF(U40>=1,MATCH(M40*100+1,tblVideos[Cal Key],0),"") | N41: =IF(V40>=1,MATCH(N40*100+1,tblVideos[Cal Key],0),"") | O41: =IF(W40>=1,MATCH(O40*100+1,tblVideos[Cal Key],0),"") | P41: =IF(X40>=1,MATCH(P40*100+1,tblVideos[Cal Key],0),"") | Q41: =IF(Y40>=1,MATCH(Q40*100+1,tblVideos[Cal Key],0),"") | S41: =IF(K41="","",IFERROR(MATCH(INDEX(tblVideos[Channel ID],K41),tblChannels[Channel ID],0),"")) | T41: =IF(L41="","",IFERROR(MATCH(INDEX(tblVideos[Channel ID],L41),tblChannels[Channel ID],0),"")) | U41: =IF(M41="","",IFERROR(MATCH(INDEX(tblVideos[Channel ID],M41),tblChannels[Channel ID],0),"")) | V41: =IF(N41="","",IFERROR(MATCH(INDEX(tblVideos[Channel ID],N41),tblChannels[Channel ID],0),"")) | W41: =IF(O41="","",IFERROR(MATCH(INDEX(tblVideos[Channel ID],O41),tblChannels[Channel ID],0),"")) | X41: =IF(P41="","",IFERROR(MATCH(INDEX(tblVideos[Channel ID],P41),tblChannels[Channel ID],0),"")) | Y41: =IF(Q41="","",IFERROR(MATCH(INDEX(tblVideos[Channel ID],Q41),tblChannels[Channel ID],0),""))
B42: =IF(K42="","",IF(INDEX(tblVideos[Video ID],K42)="",IF(INDEX(tblVideos[Status],K42)="Watched","✓ ","▸ ")&INDEX(tblVideos[Title],K42),HYPERLINK("https://www.youtube.com/watch?v="&INDEX(tblVideos[Video ID],K42),IF(INDEX(tblVideos[Status],K42)="Watched","✓ ","▸ ")&INDEX(tblVideos[Title],K42)))) | C42: =IF(L42="","",IF(INDEX(tblVideos[Video ID],L42)="",IF(INDEX(tblVideos[Status],L42)="Watched","✓ ","▸ ")&INDEX(tblVideos[Title],L42),HYPERLINK("https://www.youtube.com/watch?v="&INDEX(tblVideos[Video ID],L42),IF(INDEX(tblVideos[Status],L42)="Watched","✓ ","▸ ")&INDEX(tblVideos[Title],L42)))) | D42: =IF(M42="","",IF(INDEX(tblVideos[Video ID],M42)="",IF(INDEX(tblVideos[Status],M42)="Watched","✓ ","▸ ")&INDEX(tblVideos[Title],M42),HYPERLINK("https://www.youtube.com/watch?v="&INDEX(tblVideos[Video ID],M42),IF(INDEX(tblVideos[Status],M42)="Watched","✓ ","▸ ")&INDEX(tblVideos[Title],M42)))) | E42: =IF(N42="","",IF(INDEX(tblVideos[Video ID],N42)="",IF(INDEX(tblVideos[Status],N42)="Watched","✓ ","▸ ")&INDEX(tblVideos[Title],N42),HYPERLINK("https://www.youtube.com/watch?v="&INDEX(tblVideos[Video ID],N42),IF(INDEX(tblVideos[Status],N42)="Watched","✓ ","▸ ")&INDEX(tblVideos[Title],N42)))) | F42: =IF(O42="","",IF(INDEX(tblVideos[Video ID],O42)="",IF(INDEX(tblVideos[Status],O42)="Watched","✓ ","▸ ")&INDEX(tblVideos[Title],O42),HYPERLINK("https://www.youtube.com/watch?v="&INDEX(tblVideos[Video ID],O42),IF(INDEX(tblVideos[Status],O42)="Watched","✓ ","▸ ")&INDEX(tblVideos[Title],O42)))) | G42: =IF(P42="","",IF(INDEX(tblVideos[Video ID],P42)="",IF(INDEX(tblVideos[Status],P42)="Watched","✓ ","▸ ")&INDEX(tblVideos[Title],P42),HYPERLINK("https://www.youtube.com/watch?v="&INDEX(tblVideos[Video ID],P42),IF(INDEX(tblVideos[Status],P42)="Watched","✓ ","▸ ")&INDEX(tblVideos[Title],P42)))) | H42: =IF(Q42="","",IF(INDEX(tblVideos[Video ID],Q42)="",IF(INDEX(tblVideos[Status],Q42)="Watched","✓ ","▸ ")&INDEX(tblVideos[Title],Q42),HYPERLINK("https://www.youtube.com/watch?v="&INDEX(tblVideos[Video ID],Q42),IF(INDEX(tblVideos[Status],Q42)="Watched","✓ ","▸ ")&INDEX(tblVideos[Title],Q42)))) | K42: =IF(S40>=2,MATCH(K40*100+2,tblVideos[Cal Key],0),"") | L42: =IF(T40>=2,MATCH(L40*100+2,tblVideos[Cal Key],0),"") | M42: =IF(U40>=2,MATCH(M40*100+2,tblVideos[Cal Key],0),"") | N42: =IF(V40>=2,MATCH(N40*100+2,tblVideos[Cal Key],0),"") | O42: =IF(W40>=2,MATCH(O40*100+2,tblVideos[Cal Key],0),"") | P42: =IF(X40>=2,MATCH(P40*100+2,tblVideos[Cal Key],0),"") | Q42: =IF(Y40>=2,MATCH(Q40*100+2,tblVideos[Cal Key],0),"") | S42: =IF(K42="","",IFERROR(MATCH(INDEX(tblVideos[Channel ID],K42),tblChannels[Channel ID],0),"")) | T42: =IF(L42="","",IFERROR(MATCH(INDEX(tblVideos[Channel ID],L42),tblChannels[Channel ID],0),"")) | U42: =IF(M42="","",IFERROR(MATCH(INDEX(tblVideos[Channel ID],M42),tblChannels[Channel ID],0),"")) | V42: =IF(N42="","",IFERROR(MATCH(INDEX(tblVideos[Channel ID],N42),tblChannels[Channel ID],0),"")) | W42: =IF(O42="","",IFERROR(MATCH(INDEX(tblVideos[Channel ID],O42),tblChannels[Channel ID],0),"")) | X42: =IF(P42="","",IFERROR(MATCH(INDEX(tblVideos[Channel ID],P42),tblChannels[Channel ID],0),"")) | Y42: =IF(Q42="","",IFERROR(MATCH(INDEX(tblVideos[Channel ID],Q42),tblChannels[Channel ID],0),""))
B43: =IF(K43="","",IF(INDEX(tblVideos[Video ID],K43)="",IF(INDEX(tblVideos[Status],K43)="Watched","✓ ","▸ ")&INDEX(tblVideos[Title],K43),HYPERLINK("https://www.youtube.com/watch?v="&INDEX(tblVideos[Video ID],K43),IF(INDEX(tblVideos[Status],K43)="Watched","✓ ","▸ ")&INDEX(tblVideos[Title],K43)))) | C43: =IF(L43="","",IF(INDEX(tblVideos[Video ID],L43)="",IF(INDEX(tblVideos[Status],L43)="Watched","✓ ","▸ ")&INDEX(tblVideos[Title],L43),HYPERLINK("https://www.youtube.com/watch?v="&INDEX(tblVideos[Video ID],L43),IF(INDEX(tblVideos[Status],L43)="Watched","✓ ","▸ ")&INDEX(tblVideos[Title],L43)))) | D43: =IF(M43="","",IF(INDEX(tblVideos[Video ID],M43)="",IF(INDEX(tblVideos[Status],M43)="Watched","✓ ","▸ ")&INDEX(tblVideos[Title],M43),HYPERLINK("https://www.youtube.com/watch?v="&INDEX(tblVideos[Video ID],M43),IF(INDEX(tblVideos[Status],M43)="Watched","✓ ","▸ ")&INDEX(tblVideos[Title],M43)))) | E43: =IF(N43="","",IF(INDEX(tblVideos[Video ID],N43)="",IF(INDEX(tblVideos[Status],N43)="Watched","✓ ","▸ ")&INDEX(tblVideos[Title],N43),HYPERLINK("https://www.youtube.com/watch?v="&INDEX(tblVideos[Video ID],N43),IF(INDEX(tblVideos[Status],N43)="Watched","✓ ","▸ ")&INDEX(tblVideos[Title],N43)))) | F43: =IF(O43="","",IF(INDEX(tblVideos[Video ID],O43)="",IF(INDEX(tblVideos[Status],O43)="Watched","✓ ","▸ ")&INDEX(tblVideos[Title],O43),HYPERLINK("https://www.youtube.com/watch?v="&INDEX(tblVideos[Video ID],O43),IF(INDEX(tblVideos[Status],O43)="Watched","✓ ","▸ ")&INDEX(tblVideos[Title],O43)))) | G43: =IF(P43="","",IF(INDEX(tblVideos[Video ID],P43)="",IF(INDEX(tblVideos[Status],P43)="Watched","✓ ","▸ ")&INDEX(tblVideos[Title],P43),HYPERLINK("https://www.youtube.com/watch?v="&INDEX(tblVideos[Video ID],P43),IF(INDEX(tblVideos[Status],P43)="Watched","✓ ","▸ ")&INDEX(tblVideos[Title],P43)))) | H43: =IF(Q43="","",IF(INDEX(tblVideos[Video ID],Q43)="",IF(INDEX(tblVideos[Status],Q43)="Watched","✓ ","▸ ")&INDEX(tblVideos[Title],Q43),HYPERLINK("https://www.youtube.com/watch?v="&INDEX(tblVideos[Video ID],Q43),IF(INDEX(tblVideos[Status],Q43)="Watched","✓ ","▸ ")&INDEX(tblVideos[Title],Q43)))) | K43: =IF(S40>=3,MATCH(K40*100+3,tblVideos[Cal Key],0),"") | L43: =IF(T40>=3,MATCH(L40*100+3,tblVideos[Cal Key],0),"") | M43: =IF(U40>=3,MATCH(M40*100+3,tblVideos[Cal Key],0),"") | N43: =IF(V40>=3,MATCH(N40*100+3,tblVideos[Cal Key],0),"") | O43: =IF(W40>=3,MATCH(O40*100+3,tblVideos[Cal Key],0),"") | P43: =IF(X40>=3,MATCH(P40*100+3,tblVideos[Cal Key],0),"") | Q43: =IF(Y40>=3,MATCH(Q40*100+3,tblVideos[Cal Key],0),"") | S43: =IF(K43="","",IFERROR(MATCH(INDEX(tblVideos[Channel ID],K43),tblChannels[Channel ID],0),"")) | T43: =IF(L43="","",IFERROR(MATCH(INDEX(tblVideos[Channel ID],L43),tblChannels[Channel ID],0),"")) | U43: =IF(M43="","",IFERROR(MATCH(INDEX(tblVideos[Channel ID],M43),tblChannels[Channel ID],0),"")) | V43: =IF(N43="","",IFERROR(MATCH(INDEX(tblVideos[Channel ID],N43),tblChannels[Channel ID],0),"")) | W43: =IF(O43="","",IFERROR(MATCH(INDEX(tblVideos[Channel ID],O43),tblChannels[Channel ID],0),"")) | X43: =IF(P43="","",IFERROR(MATCH(INDEX(tblVideos[Channel ID],P43),tblChannels[Channel ID],0),"")) | Y43: =IF(Q43="","",IFERROR(MATCH(INDEX(tblVideos[Channel ID],Q43),tblChannels[Channel ID],0),""))
B44: =IF(K44="","",IF(INDEX(tblVideos[Video ID],K44)="",IF(INDEX(tblVideos[Status],K44)="Watched","✓ ","▸ ")&INDEX(tblVideos[Title],K44),HYPERLINK("https://www.youtube.com/watch?v="&INDEX(tblVideos[Video ID],K44),IF(INDEX(tblVideos[Status],K44)="Watched","✓ ","▸ ")&INDEX(tblVideos[Title],K44)))) | C44: =IF(L44="","",IF(INDEX(tblVideos[Video ID],L44)="",IF(INDEX(tblVideos[Status],L44)="Watched","✓ ","▸ ")&INDEX(tblVideos[Title],L44),HYPERLINK("https://www.youtube.com/watch?v="&INDEX(tblVideos[Video ID],L44),IF(INDEX(tblVideos[Status],L44)="Watched","✓ ","▸ ")&INDEX(tblVideos[Title],L44)))) | D44: =IF(M44="","",IF(INDEX(tblVideos[Video ID],M44)="",IF(INDEX(tblVideos[Status],M44)="Watched","✓ ","▸ ")&INDEX(tblVideos[Title],M44),HYPERLINK("https://www.youtube.com/watch?v="&INDEX(tblVideos[Video ID],M44),IF(INDEX(tblVideos[Status],M44)="Watched","✓ ","▸ ")&INDEX(tblVideos[Title],M44)))) | E44: =IF(N44="","",IF(INDEX(tblVideos[Video ID],N44)="",IF(INDEX(tblVideos[Status],N44)="Watched","✓ ","▸ ")&INDEX(tblVideos[Title],N44),HYPERLINK("https://www.youtube.com/watch?v="&INDEX(tblVideos[Video ID],N44),IF(INDEX(tblVideos[Status],N44)="Watched","✓ ","▸ ")&INDEX(tblVideos[Title],N44)))) | F44: =IF(O44="","",IF(INDEX(tblVideos[Video ID],O44)="",IF(INDEX(tblVideos[Status],O44)="Watched","✓ ","▸ ")&INDEX(tblVideos[Title],O44),HYPERLINK("https://www.youtube.com/watch?v="&INDEX(tblVideos[Video ID],O44),IF(INDEX(tblVideos[Status],O44)="Watched","✓ ","▸ ")&INDEX(tblVideos[Title],O44)))) | G44: =IF(P44="","",IF(INDEX(tblVideos[Video ID],P44)="",IF(INDEX(tblVideos[Status],P44)="Watched","✓ ","▸ ")&INDEX(tblVideos[Title],P44),HYPERLINK("https://www.youtube.com/watch?v="&INDEX(tblVideos[Video ID],P44),IF(INDEX(tblVideos[Status],P44)="Watched","✓ ","▸ ")&INDEX(tblVideos[Title],P44)))) | H44: =IF(Q44="","",IF(INDEX(tblVideos[Video ID],Q44)="",IF(INDEX(tblVideos[Status],Q44)="Watched","✓ ","▸ ")&INDEX(tblVideos[Title],Q44),HYPERLINK("https://www.youtube.com/watch?v="&INDEX(tblVideos[Video ID],Q44),IF(INDEX(tblVideos[Status],Q44)="Watched","✓ ","▸ ")&INDEX(tblVideos[Title],Q44)))) | K44: =IF(S40>=4,MATCH(K40*100+4,tblVideos[Cal Key],0),"") | L44: =IF(T40>=4,MATCH(L40*100+4,tblVideos[Cal Key],0),"") | M44: =IF(U40>=4,MATCH(M40*100+4,tblVideos[Cal Key],0),"") | N44: =IF(V40>=4,MATCH(N40*100+4,tblVideos[Cal Key],0),"") | O44: =IF(W40>=4,MATCH(O40*100+4,tblVideos[Cal Key],0),"") | P44: =IF(X40>=4,MATCH(P40*100+4,tblVideos[Cal Key],0),"") | Q44: =IF(Y40>=4,MATCH(Q40*100+4,tblVideos[Cal Key],0),"") | S44: =IF(K44="","",IFERROR(MATCH(INDEX(tblVideos[Channel ID],K44),tblChannels[Channel ID],0),"")) | T44: =IF(L44="","",IFERROR(MATCH(INDEX(tblVideos[Channel ID],L44),tblChannels[Channel ID],0),"")) | U44: =IF(M44="","",IFERROR(MATCH(INDEX(tblVideos[Channel ID],M44),tblChannels[Channel ID],0),"")) | V44: =IF(N44="","",IFERROR(MATCH(INDEX(tblVideos[Channel ID],N44),tblChannels[Channel ID],0),"")) | W44: =IF(O44="","",IFERROR(MATCH(INDEX(tblVideos[Channel ID],O44),tblChannels[Channel ID],0),"")) | X44: =IF(P44="","",IFERROR(MATCH(INDEX(tblVideos[Channel ID],P44),tblChannels[Channel ID],0),"")) | Y44: =IF(Q44="","",IFERROR(MATCH(INDEX(tblVideos[Channel ID],Q44),tblChannels[Channel ID],0),""))
B45: =IF(K45="","",IF(INDEX(tblVideos[Video ID],K45)="",IF(INDEX(tblVideos[Status],K45)="Watched","✓ ","▸ ")&INDEX(tblVideos[Title],K45),HYPERLINK("https://www.youtube.com/watch?v="&INDEX(tblVideos[Video ID],K45),IF(INDEX(tblVideos[Status],K45)="Watched","✓ ","▸ ")&INDEX(tblVideos[Title],K45)))) | C45: =IF(L45="","",IF(INDEX(tblVideos[Video ID],L45)="",IF(INDEX(tblVideos[Status],L45)="Watched","✓ ","▸ ")&INDEX(tblVideos[Title],L45),HYPERLINK("https://www.youtube.com/watch?v="&INDEX(tblVideos[Video ID],L45),IF(INDEX(tblVideos[Status],L45)="Watched","✓ ","▸ ")&INDEX(tblVideos[Title],L45)))) | D45: =IF(M45="","",IF(INDEX(tblVideos[Video ID],M45)="",IF(INDEX(tblVideos[Status],M45)="Watched","✓ ","▸ ")&INDEX(tblVideos[Title],M45),HYPERLINK("https://www.youtube.com/watch?v="&INDEX(tblVideos[Video ID],M45),IF(INDEX(tblVideos[Status],M45)="Watched","✓ ","▸ ")&INDEX(tblVideos[Title],M45)))) | E45: =IF(N45="","",IF(INDEX(tblVideos[Video ID],N45)="",IF(INDEX(tblVideos[Status],N45)="Watched","✓ ","▸ ")&INDEX(tblVideos[Title],N45),HYPERLINK("https://www.youtube.com/watch?v="&INDEX(tblVideos[Video ID],N45),IF(INDEX(tblVideos[Status],N45)="Watched","✓ ","▸ ")&INDEX(tblVideos[Title],N45)))) | F45: =IF(O45="","",IF(INDEX(tblVideos[Video ID],O45)="",IF(INDEX(tblVideos[Status],O45)="Watched","✓ ","▸ ")&INDEX(tblVideos[Title],O45),HYPERLINK("https://www.youtube.com/watch?v="&INDEX(tblVideos[Video ID],O45),IF(INDEX(tblVideos[Status],O45)="Watched","✓ ","▸ ")&INDEX(tblVideos[Title],O45)))) | G45: =IF(P45="","",IF(INDEX(tblVideos[Video ID],P45)="",IF(INDEX(tblVideos[Status],P45)="Watched","✓ ","▸ ")&INDEX(tblVideos[Title],P45),HYPERLINK("https://www.youtube.com/watch?v="&INDEX(tblVideos[Video ID],P45),IF(INDEX(tblVideos[Status],P45)="Watched","✓ ","▸ ")&INDEX(tblVideos[Title],P45)))) | H45: =IF(Q45="","",IF(INDEX(tblVideos[Video ID],Q45)="",IF(INDEX(tblVideos[Status],Q45)="Watched","✓ ","▸ ")&INDEX(tblVideos[Title],Q45),HYPERLINK("https://www.youtube.com/watch?v="&INDEX(tblVideos[Video ID],Q45),IF(INDEX(tblVideos[Status],Q45)="Watched","✓ ","▸ ")&INDEX(tblVideos[Title],Q45)))) | K45: =IF(S40>=5,MATCH(K40*100+5,tblVideos[Cal Key],0),"") | L45: =IF(T40>=5,MATCH(L40*100+5,tblVideos[Cal Key],0),"") | M45: =IF(U40>=5,MATCH(M40*100+5,tblVideos[Cal Key],0),"") | N45: =IF(V40>=5,MATCH(N40*100+5,tblVideos[Cal Key],0),"") | O45: =IF(W40>=5,MATCH(O40*100+5,tblVideos[Cal Key],0),"") | P45: =IF(X40>=5,MATCH(P40*100+5,tblVideos[Cal Key],0),"") | Q45: =IF(Y40>=5,MATCH(Q40*100+5,tblVideos[Cal Key],0),"") | S45: =IF(K45="","",IFERROR(MATCH(INDEX(tblVideos[Channel ID],K45),tblChannels[Channel ID],0),"")) | T45: =IF(L45="","",IFERROR(MATCH(INDEX(tblVideos[Channel ID],L45),tblChannels[Channel ID],0),"")) | U45: =IF(M45="","",IFERROR(MATCH(INDEX(tblVideos[Channel ID],M45),tblChannels[Channel ID],0),"")) | V45: =IF(N45="","",IFERROR(MATCH(INDEX(tblVideos[Channel ID],N45),tblChannels[Channel ID],0),"")) | W45: =IF(O45="","",IFERROR(MATCH(INDEX(tblVideos[Channel ID],O45),tblChannels[Channel ID],0),"")) | X45: =IF(P45="","",IFERROR(MATCH(INDEX(tblVideos[Channel ID],P45),tblChannels[Channel ID],0),"")) | Y45: =IF(Q45="","",IFERROR(MATCH(INDEX(tblVideos[Channel ID],Q45),tblChannels[Channel ID],0),""))

Sheet History
B2: History
C3: Channel | G3: Heatmap shows | K3: Year view
B4: =HYPERLINK("#Dashboard!A1","◄ Dashboard") | C4: All channels | G4: Videos | K4: 2026 | T4: =IF($C$4="All channels","*",IFERROR(INDEX(tblChannels[Channel ID],MATCH($C$4,tblChannels[Display Name],0)),"none"))
B5: How the channels uploaded over the years - and how much of it you've watched.
B6: Upload heatmap - darker = more (hours are rounded)
B7: Year | C7: Jan | D7: Feb | E7: Mar | F7: Apr | G7: May | H7: Jun | I7: Jul | J7: Aug | K7: Sep | L7: Oct | M7: Nov | N7: Dec | O7: Total
B8: 2012 | C8: =IF($G$4="Hours",ROUND(SUMIFS(tblVideos[Length],tblVideos[Day],">="&DATE($B8,1,1),tblVideos[Day],"<"&DATE($B8,2,1),tblVideos[Channel ID],$T$4)*24,0),COUNTIFS(tblVideos[Day],">="&DATE($B8,1,1),tblVideos[Day],"<"&DATE($B8,2,1),tblVideos[Channel ID],$T$4)) | D8: =IF($G$4="Hours",ROUND(SUMIFS(tblVideos[Length],tblVideos[Day],">="&DATE($B8,2,1),tblVideos[Day],"<"&DATE($B8,3,1),tblVideos[Channel ID],$T$4)*24,0),COUNTIFS(tblVideos[Day],">="&DATE($B8,2,1),tblVideos[Day],"<"&DATE($B8,3,1),tblVideos[Channel ID],$T$4)) | E8: =IF($G$4="Hours",ROUND(SUMIFS(tblVideos[Length],tblVideos[Day],">="&DATE($B8,3,1),tblVideos[Day],"<"&DATE($B8,4,1),tblVideos[Channel ID],$T$4)*24,0),COUNTIFS(tblVideos[Day],">="&DATE($B8,3,1),tblVideos[Day],"<"&DATE($B8,4,1),tblVideos[Channel ID],$T$4)) | F8: =IF($G$4="Hours",ROUND(SUMIFS(tblVideos[Length],tblVideos[Day],">="&DATE($B8,4,1),tblVideos[Day],"<"&DATE($B8,5,1),tblVideos[Channel ID],$T$4)*24,0),COUNTIFS(tblVideos[Day],">="&DATE($B8,4,1),tblVideos[Day],"<"&DATE($B8,5,1),tblVideos[Channel ID],$T$4)) | G8: =IF($G$4="Hours",ROUND(SUMIFS(tblVideos[Length],tblVideos[Day],">="&DATE($B8,5,1),tblVideos[Day],"<"&DATE($B8,6,1),tblVideos[Channel ID],$T$4)*24,0),COUNTIFS(tblVideos[Day],">="&DATE($B8,5,1),tblVideos[Day],"<"&DATE($B8,6,1),tblVideos[Channel ID],$T$4)) | H8: =IF($G$4="Hours",ROUND(SUMIFS(tblVideos[Length],tblVideos[Day],">="&DATE($B8,6,1),tblVideos[Day],"<"&DATE($B8,7,1),tblVideos[Channel ID],$T$4)*24,0),COUNTIFS(tblVideos[Day],">="&DATE($B8,6,1),tblVideos[Day],"<"&DATE($B8,7,1),tblVideos[Channel ID],$T$4)) | I8: =IF($G$4="Hours",ROUND(SUMIFS(tblVideos[Length],tblVideos[Day],">="&DATE($B8,7,1),tblVideos[Day],"<"&DATE($B8,8,1),tblVideos[Channel ID],$T$4)*24,0),COUNTIFS(tblVideos[Day],">="&DATE($B8,7,1),tblVideos[Day],"<"&DATE($B8,8,1),tblVideos[Channel ID],$T$4)) | J8: =IF($G$4="Hours",ROUND(SUMIFS(tblVideos[Length],tblVideos[Day],">="&DATE($B8,8,1),tblVideos[Day],"<"&DATE($B8,9,1),tblVideos[Channel ID],$T$4)*24,0),COUNTIFS(tblVideos[Day],">="&DATE($B8,8,1),tblVideos[Day],"<"&DATE($B8,9,1),tblVideos[Channel ID],$T$4)) | K8: =IF($G$4="Hours",ROUND(SUMIFS(tblVideos[Length],tblVideos[Day],">="&DATE($B8,9,1),tblVideos[Day],"<"&DATE($B8,10,1),tblVideos[Channel ID],$T$4)*24,0),COUNTIFS(tblVideos[Day],">="&DATE($B8,9,1),tblVideos[Day],"<"&DATE($B8,10,1),tblVideos[Channel ID],$T$4)) | L8: =IF($G$4="Hours",ROUND(SUMIFS(tblVideos[Length],tblVideos[Day],">="&DATE($B8,10,1),tblVideos[Day],"<"&DATE($B8,11,1),tblVideos[Channel ID],$T$4)*24,0),COUNTIFS(tblVideos[Day],">="&DATE($B8,10,1),tblVideos[Day],"<"&DATE($B8,11,1),tblVideos[Channel ID],$T$4)) | M8: =IF($G$4="Hours",ROUND(SUMIFS(tblVideos[Length],tblVideos[Day],">="&DATE($B8,11,1),tblVideos[Day],"<"&DATE($B8,12,1),tblVideos[Channel ID],$T$4)*24,0),COUNTIFS(tblVideos[Day],">="&DATE($B8,11,1),tblVideos[Day],"<"&DATE($B8,12,1),tblVideos[Channel ID],$T$4)) | N8: =IF($G$4="Hours",ROUND(SUMIFS(tblVideos[Length],tblVideos[Day],">="&DATE($B8,12,1),tblVideos[Day],"<"&DATE($B8,13,1),tblVideos[Channel ID],$T$4)*24,0),COUNTIFS(tblVideos[Day],">="&DATE($B8,12,1),tblVideos[Day],"<"&DATE($B8,13,1),tblVideos[Channel ID],$T$4)) | O8: =SUM(C8:N8)
B9: 2013 | C9: =IF($G$4="Hours",ROUND(SUMIFS(tblVideos[Length],tblVideos[Day],">="&DATE($B9,1,1),tblVideos[Day],"<"&DATE($B9,2,1),tblVideos[Channel ID],$T$4)*24,0),COUNTIFS(tblVideos[Day],">="&DATE($B9,1,1),tblVideos[Day],"<"&DATE($B9,2,1),tblVideos[Channel ID],$T$4)) | D9: =IF($G$4="Hours",ROUND(SUMIFS(tblVideos[Length],tblVideos[Day],">="&DATE($B9,2,1),tblVideos[Day],"<"&DATE($B9,3,1),tblVideos[Channel ID],$T$4)*24,0),COUNTIFS(tblVideos[Day],">="&DATE($B9,2,1),tblVideos[Day],"<"&DATE($B9,3,1),tblVideos[Channel ID],$T$4)) | E9: =IF($G$4="Hours",ROUND(SUMIFS(tblVideos[Length],tblVideos[Day],">="&DATE($B9,3,1),tblVideos[Day],"<"&DATE($B9,4,1),tblVideos[Channel ID],$T$4)*24,0),COUNTIFS(tblVideos[Day],">="&DATE($B9,3,1),tblVideos[Day],"<"&DATE($B9,4,1),tblVideos[Channel ID],$T$4)) | F9: =IF($G$4="Hours",ROUND(SUMIFS(tblVideos[Length],tblVideos[Day],">="&DATE($B9,4,1),tblVideos[Day],"<"&DATE($B9,5,1),tblVideos[Channel ID],$T$4)*24,0),COUNTIFS(tblVideos[Day],">="&DATE($B9,4,1),tblVideos[Day],"<"&DATE($B9,5,1),tblVideos[Channel ID],$T$4)) | G9: =IF($G$4="Hours",ROUND(SUMIFS(tblVideos[Length],tblVideos[Day],">="&DATE($B9,5,1),tblVideos[Day],"<"&DATE($B9,6,1),tblVideos[Channel ID],$T$4)*24,0),COUNTIFS(tblVideos[Day],">="&DATE($B9,5,1),tblVideos[Day],"<"&DATE($B9,6,1),tblVideos[Channel ID],$T$4)) | H9: =IF($G$4="Hours",ROUND(SUMIFS(tblVideos[Length],tblVideos[Day],">="&DATE($B9,6,1),tblVideos[Day],"<"&DATE($B9,7,1),tblVideos[Channel ID],$T$4)*24,0),COUNTIFS(tblVideos[Day],">="&DATE($B9,6,1),tblVideos[Day],"<"&DATE($B9,7,1),tblVideos[Channel ID],$T$4)) | I9: =IF($G$4="Hours",ROUND(SUMIFS(tblVideos[Length],tblVideos[Day],">="&DATE($B9,7,1),tblVideos[Day],"<"&DATE($B9,8,1),tblVideos[Channel ID],$T$4)*24,0),COUNTIFS(tblVideos[Day],">="&DATE($B9,7,1),tblVideos[Day],"<"&DATE($B9,8,1),tblVideos[Channel ID],$T$4)) | J9: =IF($G$4="Hours",ROUND(SUMIFS(tblVideos[Length],tblVideos[Day],">="&DATE($B9,8,1),tblVideos[Day],"<"&DATE($B9,9,1),tblVideos[Channel ID],$T$4)*24,0),COUNTIFS(tblVideos[Day],">="&DATE($B9,8,1),tblVideos[Day],"<"&DATE($B9,9,1),tblVideos[Channel ID],$T$4)) | K9: =IF($G$4="Hours",ROUND(SUMIFS(tblVideos[Length],tblVideos[Day],">="&DATE($B9,9,1),tblVideos[Day],"<"&DATE($B9,10,1),tblVideos[Channel ID],$T$4)*24,0),COUNTIFS(tblVideos[Day],">="&DATE($B9,9,1),tblVideos[Day],"<"&DATE($B9,10,1),tblVideos[Channel ID],$T$4)) | L9: =IF($G$4="Hours",ROUND(SUMIFS(tblVideos[Length],tblVideos[Day],">="&DATE($B9,10,1),tblVideos[Day],"<"&DATE($B9,11,1),tblVideos[Channel ID],$T$4)*24,0),COUNTIFS(tblVideos[Day],">="&DATE($B9,10,1),tblVideos[Day],"<"&DATE($B9,11,1),tblVideos[Channel ID],$T$4)) | M9: =IF($G$4="Hours",ROUND(SUMIFS(tblVideos[Length],tblVideos[Day],">="&DATE($B9,11,1),tblVideos[Day],"<"&DATE($B9,12,1),tblVideos[Channel ID],$T$4)*24,0),COUNTIFS(tblVideos[Day],">="&DATE($B9,11,1),tblVideos[Day],"<"&DATE($B9,12,1),tblVideos[Channel ID],$T$4)) | N9: =IF($G$4="Hours",ROUND(SUMIFS(tblVideos[Length],tblVideos[Day],">="&DATE($B9,12,1),tblVideos[Day],"<"&DATE($B9,13,1),tblVideos[Channel ID],$T$4)*24,0),COUNTIFS(tblVideos[Day],">="&DATE($B9,12,1),tblVideos[Day],"<"&DATE($B9,13,1),tblVideos[Channel ID],$T$4)) | O9: =SUM(C9:N9)
B10: 2014 | C10: =IF($G$4="Hours",ROUND(SUMIFS(tblVideos[Length],tblVideos[Day],">="&DATE($B10,1,1),tblVideos[Day],"<"&DATE($B10,2,1),tblVideos[Channel ID],$T$4)*24,0),COUNTIFS(tblVideos[Day],">="&DATE($B10,1,1),tblVideos[Day],"<"&DATE($B10,2,1),tblVideos[Channel ID],$T$4)) | D10: =IF($G$4="Hours",ROUND(SUMIFS(tblVideos[Length],tblVideos[Day],">="&DATE($B10,2,1),tblVideos[Day],"<"&DATE($B10,3,1),tblVideos[Channel ID],$T$4)*24,0),COUNTIFS(tblVideos[Day],">="&DATE($B10,2,1),tblVideos[Day],"<"&DATE($B10,3,1),tblVideos[Channel ID],$T$4)) | E10: =IF($G$4="Hours",ROUND(SUMIFS(tblVideos[Length],tblVideos[Day],">="&DATE($B10,3,1),tblVideos[Day],"<"&DATE($B10,4,1),tblVideos[Channel ID],$T$4)*24,0),COUNTIFS(tblVideos[Day],">="&DATE($B10,3,1),tblVideos[Day],"<"&DATE($B10,4,1),tblVideos[Channel ID],$T$4)) | F10: =IF($G$4="Hours",ROUND(SUMIFS(tblVideos[Length],tblVideos[Day],">="&DATE($B10,4,1),tblVideos[Day],"<"&DATE($B10,5,1),tblVideos[Channel ID],$T$4)*24,0),COUNTIFS(tblVideos[Day],">="&DATE($B10,4,1),tblVideos[Day],"<"&DATE($B10,5,1),tblVideos[Channel ID],$T$4)) | G10: =IF($G$4="Hours",ROUND(SUMIFS(tblVideos[Length],tblVideos[Day],">="&DATE($B10,5,1),tblVideos[Day],"<"&DATE($B10,6,1),tblVideos[Channel ID],$T$4)*24,0),COUNTIFS(tblVideos[Day],">="&DATE($B10,5,1),tblVideos[Day],"<"&DATE($B10,6,1),tblVideos[Channel ID],$T$4)) | H10: =IF($G$4="Hours",ROUND(SUMIFS(tblVideos[Length],tblVideos[Day],">="&DATE($B10,6,1),tblVideos[Day],"<"&DATE($B10,7,1),tblVideos[Channel ID],$T$4)*24,0),COUNTIFS(tblVideos[Day],">="&DATE($B10,6,1),tblVideos[Day],"<"&DATE($B10,7,1),tblVideos[Channel ID],$T$4)) | I10: =IF($G$4="Hours",ROUND(SUMIFS(tblVideos[Length],tblVideos[Day],">="&DATE($B10,7,1),tblVideos[Day],"<"&DATE($B10,8,1),tblVideos[Channel ID],$T$4)*24,0),COUNTIFS(tblVideos[Day],">="&DATE($B10,7,1),tblVideos[Day],"<"&DATE($B10,8,1),tblVideos[Channel ID],$T$4)) | J10: =IF($G$4="Hours",ROUND(SUMIFS(tblVideos[Length],tblVideos[Day],">="&DATE($B10,8,1),tblVideos[Day],"<"&DATE($B10,9,1),tblVideos[Channel ID],$T$4)*24,0),COUNTIFS(tblVideos[Day],">="&DATE($B10,8,1),tblVideos[Day],"<"&DATE($B10,9,1),tblVideos[Channel ID],$T$4)) | K10: =IF($G$4="Hours",ROUND(SUMIFS(tblVideos[Length],tblVideos[Day],">="&DATE($B10,9,1),tblVideos[Day],"<"&DATE($B10,10,1),tblVideos[Channel ID],$T$4)*24,0),COUNTIFS(tblVideos[Day],">="&DATE($B10,9,1),tblVideos[Day],"<"&DATE($B10,10,1),tblVideos[Channel ID],$T$4)) | L10: =IF($G$4="Hours",ROUND(SUMIFS(tblVideos[Length],tblVideos[Day],">="&DATE($B10,10,1),tblVideos[Day],"<"&DATE($B10,11,1),tblVideos[Channel ID],$T$4)*24,0),COUNTIFS(tblVideos[Day],">="&DATE($B10,10,1),tblVideos[Day],"<"&DATE($B10,11,1),tblVideos[Channel ID],$T$4)) | M10: =IF($G$4="Hours",ROUND(SUMIFS(tblVideos[Length],tblVideos[Day],">="&DATE($B10,11,1),tblVideos[Day],"<"&DATE($B10,12,1),tblVideos[Channel ID],$T$4)*24,0),COUNTIFS(tblVideos[Day],">="&DATE($B10,11,1),tblVideos[Day],"<"&DATE($B10,12,1),tblVideos[Channel ID],$T$4)) | N10: =IF($G$4="Hours",ROUND(SUMIFS(tblVideos[Length],tblVideos[Day],">="&DATE($B10,12,1),tblVideos[Day],"<"&DATE($B10,13,1),tblVideos[Channel ID],$T$4)*24,0),COUNTIFS(tblVideos[Day],">="&DATE($B10,12,1),tblVideos[Day],"<"&DATE($B10,13,1),tblVideos[Channel ID],$T$4)) | O10: =SUM(C10:N10)
B11: 2015 | C11: =IF($G$4="Hours",ROUND(SUMIFS(tblVideos[Length],tblVideos[Day],">="&DATE($B11,1,1),tblVideos[Day],"<"&DATE($B11,2,1),tblVideos[Channel ID],$T$4)*24,0),COUNTIFS(tblVideos[Day],">="&DATE($B11,1,1),tblVideos[Day],"<"&DATE($B11,2,1),tblVideos[Channel ID],$T$4)) | D11: =IF($G$4="Hours",ROUND(SUMIFS(tblVideos[Length],tblVideos[Day],">="&DATE($B11,2,1),tblVideos[Day],"<"&DATE($B11,3,1),tblVideos[Channel ID],$T$4)*24,0),COUNTIFS(tblVideos[Day],">="&DATE($B11,2,1),tblVideos[Day],"<"&DATE($B11,3,1),tblVideos[Channel ID],$T$4)) | E11: =IF($G$4="Hours",ROUND(SUMIFS(tblVideos[Length],tblVideos[Day],">="&DATE($B11,3,1),tblVideos[Day],"<"&DATE($B11,4,1),tblVideos[Channel ID],$T$4)*24,0),COUNTIFS(tblVideos[Day],">="&DATE($B11,3,1),tblVideos[Day],"<"&DATE($B11,4,1),tblVideos[Channel ID],$T$4)) | F11: =IF($G$4="Hours",ROUND(SUMIFS(tblVideos[Length],tblVideos[Day],">="&DATE($B11,4,1),tblVideos[Day],"<"&DATE($B11,5,1),tblVideos[Channel ID],$T$4)*24,0),COUNTIFS(tblVideos[Day],">="&DATE($B11,4,1),tblVideos[Day],"<"&DATE($B11,5,1),tblVideos[Channel ID],$T$4)) | G11: =IF($G$4="Hours",ROUND(SUMIFS(tblVideos[Length],tblVideos[Day],">="&DATE($B11,5,1),tblVideos[Day],"<"&DATE($B11,6,1),tblVideos[Channel ID],$T$4)*24,0),COUNTIFS(tblVideos[Day],">="&DATE($B11,5,1),tblVideos[Day],"<"&DATE($B11,6,1),tblVideos[Channel ID],$T$4)) | H11: =IF($G$4="Hours",ROUND(SUMIFS(tblVideos[Length],tblVideos[Day],">="&DATE($B11,6,1),tblVideos[Day],"<"&DATE($B11,7,1),tblVideos[Channel ID],$T$4)*24,0),COUNTIFS(tblVideos[Day],">="&DATE($B11,6,1),tblVideos[Day],"<"&DATE($B11,7,1),tblVideos[Channel ID],$T$4)) | I11: =IF($G$4="Hours",ROUND(SUMIFS(tblVideos[Length],tblVideos[Day],">="&DATE($B11,7,1),tblVideos[Day],"<"&DATE($B11,8,1),tblVideos[Channel ID],$T$4)*24,0),COUNTIFS(tblVideos[Day],">="&DATE($B11,7,1),tblVideos[Day],"<"&DATE($B11,8,1),tblVideos[Channel ID],$T$4)) | J11: =IF($G$4="Hours",ROUND(SUMIFS(tblVideos[Length],tblVideos[Day],">="&DATE($B11,8,1),tblVideos[Day],"<"&DATE($B11,9,1),tblVideos[Channel ID],$T$4)*24,0),COUNTIFS(tblVideos[Day],">="&DATE($B11,8,1),tblVideos[Day],"<"&DATE($B11,9,1),tblVideos[Channel ID],$T$4)) | K11: =IF($G$4="Hours",ROUND(SUMIFS(tblVideos[Length],tblVideos[Day],">="&DATE($B11,9,1),tblVideos[Day],"<"&DATE($B11,10,1),tblVideos[Channel ID],$T$4)*24,0),COUNTIFS(tblVideos[Day],">="&DATE($B11,9,1),tblVideos[Day],"<"&DATE($B11,10,1),tblVideos[Channel ID],$T$4)) | L11: =IF($G$4="Hours",ROUND(SUMIFS(tblVideos[Length],tblVideos[Day],">="&DATE($B11,10,1),tblVideos[Day],"<"&DATE($B11,11,1),tblVideos[Channel ID],$T$4)*24,0),COUNTIFS(tblVideos[Day],">="&DATE($B11,10,1),tblVideos[Day],"<"&DATE($B11,11,1),tblVideos[Channel ID],$T$4)) | M11: =IF($G$4="Hours",ROUND(SUMIFS(tblVideos[Length],tblVideos[Day],">="&DATE($B11,11,1),tblVideos[Day],"<"&DATE($B11,12,1),tblVideos[Channel ID],$T$4)*24,0),COUNTIFS(tblVideos[Day],">="&DATE($B11,11,1),tblVideos[Day],"<"&DATE($B11,12,1),tblVideos[Channel ID],$T$4)) | N11: =IF($G$4="Hours",ROUND(SUMIFS(tblVideos[Length],tblVideos[Day],">="&DATE($B11,12,1),tblVideos[Day],"<"&DATE($B11,13,1),tblVideos[Channel ID],$T$4)*24,0),COUNTIFS(tblVideos[Day],">="&DATE($B11,12,1),tblVideos[Day],"<"&DATE($B11,13,1),tblVideos[Channel ID],$T$4)) | O11: =SUM(C11:N11)
B12: 2016 | C12: =IF($G$4="Hours",ROUND(SUMIFS(tblVideos[Length],tblVideos[Day],">="&DATE($B12,1,1),tblVideos[Day],"<"&DATE($B12,2,1),tblVideos[Channel ID],$T$4)*24,0),COUNTIFS(tblVideos[Day],">="&DATE($B12,1,1),tblVideos[Day],"<"&DATE($B12,2,1),tblVideos[Channel ID],$T$4)) | D12: =IF($G$4="Hours",ROUND(SUMIFS(tblVideos[Length],tblVideos[Day],">="&DATE($B12,2,1),tblVideos[Day],"<"&DATE($B12,3,1),tblVideos[Channel ID],$T$4)*24,0),COUNTIFS(tblVideos[Day],">="&DATE($B12,2,1),tblVideos[Day],"<"&DATE($B12,3,1),tblVideos[Channel ID],$T$4)) | E12: =IF($G$4="Hours",ROUND(SUMIFS(tblVideos[Length],tblVideos[Day],">="&DATE($B12,3,1),tblVideos[Day],"<"&DATE($B12,4,1),tblVideos[Channel ID],$T$4)*24,0),COUNTIFS(tblVideos[Day],">="&DATE($B12,3,1),tblVideos[Day],"<"&DATE($B12,4,1),tblVideos[Channel ID],$T$4)) | F12: =IF($G$4="Hours",ROUND(SUMIFS(tblVideos[Length],tblVideos[Day],">="&DATE($B12,4,1),tblVideos[Day],"<"&DATE($B12,5,1),tblVideos[Channel ID],$T$4)*24,0),COUNTIFS(tblVideos[Day],">="&DATE($B12,4,1),tblVideos[Day],"<"&DATE($B12,5,1),tblVideos[Channel ID],$T$4)) | G12: =IF($G$4="Hours",ROUND(SUMIFS(tblVideos[Length],tblVideos[Day],">="&DATE($B12,5,1),tblVideos[Day],"<"&DATE($B12,6,1),tblVideos[Channel ID],$T$4)*24,0),COUNTIFS(tblVideos[Day],">="&DATE($B12,5,1),tblVideos[Day],"<"&DATE($B12,6,1),tblVideos[Channel ID],$T$4)) | H12: =IF($G$4="Hours",ROUND(SUMIFS(tblVideos[Length],tblVideos[Day],">="&DATE($B12,6,1),tblVideos[Day],"<"&DATE($B12,7,1),tblVideos[Channel ID],$T$4)*24,0),COUNTIFS(tblVideos[Day],">="&DATE($B12,6,1),tblVideos[Day],"<"&DATE($B12,7,1),tblVideos[Channel ID],$T$4)) | I12: =IF($G$4="Hours",ROUND(SUMIFS(tblVideos[Length],tblVideos[Day],">="&DATE($B12,7,1),tblVideos[Day],"<"&DATE($B12,8,1),tblVideos[Channel ID],$T$4)*24,0),COUNTIFS(tblVideos[Day],">="&DATE($B12,7,1),tblVideos[Day],"<"&DATE($B12,8,1),tblVideos[Channel ID],$T$4)) | J12: =IF($G$4="Hours",ROUND(SUMIFS(tblVideos[Length],tblVideos[Day],">="&DATE($B12,8,1),tblVideos[Day],"<"&DATE($B12,9,1),tblVideos[Channel ID],$T$4)*24,0),COUNTIFS(tblVideos[Day],">="&DATE($B12,8,1),tblVideos[Day],"<"&DATE($B12,9,1),tblVideos[Channel ID],$T$4)) | K12: =IF($G$4="Hours",ROUND(SUMIFS(tblVideos[Length],tblVideos[Day],">="&DATE($B12,9,1),tblVideos[Day],"<"&DATE($B12,10,1),tblVideos[Channel ID],$T$4)*24,0),COUNTIFS(tblVideos[Day],">="&DATE($B12,9,1),tblVideos[Day],"<"&DATE($B12,10,1),tblVideos[Channel ID],$T$4)) | L12: =IF($G$4="Hours",ROUND(SUMIFS(tblVideos[Length],tblVideos[Day],">="&DATE($B12,10,1),tblVideos[Day],"<"&DATE($B12,11,1),tblVideos[Channel ID],$T$4)*24,0),COUNTIFS(tblVideos[Day],">="&DATE($B12,10,1),tblVideos[Day],"<"&DATE($B12,11,1),tblVideos[Channel ID],$T$4)) | M12: =IF($G$4="Hours",ROUND(SUMIFS(tblVideos[Length],tblVideos[Day],">="&DATE($B12,11,1),tblVideos[Day],"<"&DATE($B12,12,1),tblVideos[Channel ID],$T$4)*24,0),COUNTIFS(tblVideos[Day],">="&DATE($B12,11,1),tblVideos[Day],"<"&DATE($B12,12,1),tblVideos[Channel ID],$T$4)) | N12: =IF($G$4="Hours",ROUND(SUMIFS(tblVideos[Length],tblVideos[Day],">="&DATE($B12,12,1),tblVideos[Day],"<"&DATE($B12,13,1),tblVideos[Channel ID],$T$4)*24,0),COUNTIFS(tblVideos[Day],">="&DATE($B12,12,1),tblVideos[Day],"<"&DATE($B12,13,1),tblVideos[Channel ID],$T$4)) | O12: =SUM(C12:N12)
B13: 2017 | C13: =IF($G$4="Hours",ROUND(SUMIFS(tblVideos[Length],tblVideos[Day],">="&DATE($B13,1,1),tblVideos[Day],"<"&DATE($B13,2,1),tblVideos[Channel ID],$T$4)*24,0),COUNTIFS(tblVideos[Day],">="&DATE($B13,1,1),tblVideos[Day],"<"&DATE($B13,2,1),tblVideos[Channel ID],$T$4)) | D13: =IF($G$4="Hours",ROUND(SUMIFS(tblVideos[Length],tblVideos[Day],">="&DATE($B13,2,1),tblVideos[Day],"<"&DATE($B13,3,1),tblVideos[Channel ID],$T$4)*24,0),COUNTIFS(tblVideos[Day],">="&DATE($B13,2,1),tblVideos[Day],"<"&DATE($B13,3,1),tblVideos[Channel ID],$T$4)) | E13: =IF($G$4="Hours",ROUND(SUMIFS(tblVideos[Length],tblVideos[Day],">="&DATE($B13,3,1),tblVideos[Day],"<"&DATE($B13,4,1),tblVideos[Channel ID],$T$4)*24,0),COUNTIFS(tblVideos[Day],">="&DATE($B13,3,1),tblVideos[Day],"<"&DATE($B13,4,1),tblVideos[Channel ID],$T$4)) | F13: =IF($G$4="Hours",ROUND(SUMIFS(tblVideos[Length],tblVideos[Day],">="&DATE($B13,4,1),tblVideos[Day],"<"&DATE($B13,5,1),tblVideos[Channel ID],$T$4)*24,0),COUNTIFS(tblVideos[Day],">="&DATE($B13,4,1),tblVideos[Day],"<"&DATE($B13,5,1),tblVideos[Channel ID],$T$4)) | G13: =IF($G$4="Hours",ROUND(SUMIFS(tblVideos[Length],tblVideos[Day],">="&DATE($B13,5,1),tblVideos[Day],"<"&DATE($B13,6,1),tblVideos[Channel ID],$T$4)*24,0),COUNTIFS(tblVideos[Day],">="&DATE($B13,5,1),tblVideos[Day],"<"&DATE($B13,6,1),tblVideos[Channel ID],$T$4)) | H13: =IF($G$4="Hours",ROUND(SUMIFS(tblVideos[Length],tblVideos[Day],">="&DATE($B13,6,1),tblVideos[Day],"<"&DATE($B13,7,1),tblVideos[Channel ID],$T$4)*24,0),COUNTIFS(tblVideos[Day],">="&DATE($B13,6,1),tblVideos[Day],"<"&DATE($B13,7,1),tblVideos[Channel ID],$T$4)) | I13: =IF($G$4="Hours",ROUND(SUMIFS(tblVideos[Length],tblVideos[Day],">="&DATE($B13,7,1),tblVideos[Day],"<"&DATE($B13,8,1),tblVideos[Channel ID],$T$4)*24,0),COUNTIFS(tblVideos[Day],">="&DATE($B13,7,1),tblVideos[Day],"<"&DATE($B13,8,1),tblVideos[Channel ID],$T$4)) | J13: =IF($G$4="Hours",ROUND(SUMIFS(tblVideos[Length],tblVideos[Day],">="&DATE($B13,8,1),tblVideos[Day],"<"&DATE($B13,9,1),tblVideos[Channel ID],$T$4)*24,0),COUNTIFS(tblVideos[Day],">="&DATE($B13,8,1),tblVideos[Day],"<"&DATE($B13,9,1),tblVideos[Channel ID],$T$4)) | K13: =IF($G$4="Hours",ROUND(SUMIFS(tblVideos[Length],tblVideos[Day],">="&DATE($B13,9,1),tblVideos[Day],"<"&DATE($B13,10,1),tblVideos[Channel ID],$T$4)*24,0),COUNTIFS(tblVideos[Day],">="&DATE($B13,9,1),tblVideos[Day],"<"&DATE($B13,10,1),tblVideos[Channel ID],$T$4)) | L13: =IF($G$4="Hours",ROUND(SUMIFS(tblVideos[Length],tblVideos[Day],">="&DATE($B13,10,1),tblVideos[Day],"<"&DATE($B13,11,1),tblVideos[Channel ID],$T$4)*24,0),COUNTIFS(tblVideos[Day],">="&DATE($B13,10,1),tblVideos[Day],"<"&DATE($B13,11,1),tblVideos[Channel ID],$T$4)) | M13: =IF($G$4="Hours",ROUND(SUMIFS(tblVideos[Length],tblVideos[Day],">="&DATE($B13,11,1),tblVideos[Day],"<"&DATE($B13,12,1),tblVideos[Channel ID],$T$4)*24,0),COUNTIFS(tblVideos[Day],">="&DATE($B13,11,1),tblVideos[Day],"<"&DATE($B13,12,1),tblVideos[Channel ID],$T$4)) | N13: =IF($G$4="Hours",ROUND(SUMIFS(tblVideos[Length],tblVideos[Day],">="&DATE($B13,12,1),tblVideos[Day],"<"&DATE($B13,13,1),tblVideos[Channel ID],$T$4)*24,0),COUNTIFS(tblVideos[Day],">="&DATE($B13,12,1),tblVideos[Day],"<"&DATE($B13,13,1),tblVideos[Channel ID],$T$4)) | O13: =SUM(C13:N13)
B14: 2018 | C14: =IF($G$4="Hours",ROUND(SUMIFS(tblVideos[Length],tblVideos[Day],">="&DATE($B14,1,1),tblVideos[Day],"<"&DATE($B14,2,1),tblVideos[Channel ID],$T$4)*24,0),COUNTIFS(tblVideos[Day],">="&DATE($B14,1,1),tblVideos[Day],"<"&DATE($B14,2,1),tblVideos[Channel ID],$T$4)) | D14: =IF($G$4="Hours",ROUND(SUMIFS(tblVideos[Length],tblVideos[Day],">="&DATE($B14,2,1),tblVideos[Day],"<"&DATE($B14,3,1),tblVideos[Channel ID],$T$4)*24,0),COUNTIFS(tblVideos[Day],">="&DATE($B14,2,1),tblVideos[Day],"<"&DATE($B14,3,1),tblVideos[Channel ID],$T$4)) | E14: =IF($G$4="Hours",ROUND(SUMIFS(tblVideos[Length],tblVideos[Day],">="&DATE($B14,3,1),tblVideos[Day],"<"&DATE($B14,4,1),tblVideos[Channel ID],$T$4)*24,0),COUNTIFS(tblVideos[Day],">="&DATE($B14,3,1),tblVideos[Day],"<"&DATE($B14,4,1),tblVideos[Channel ID],$T$4)) | F14: =IF($G$4="Hours",ROUND(SUMIFS(tblVideos[Length],tblVideos[Day],">="&DATE($B14,4,1),tblVideos[Day],"<"&DATE($B14,5,1),tblVideos[Channel ID],$T$4)*24,0),COUNTIFS(tblVideos[Day],">="&DATE($B14,4,1),tblVideos[Day],"<"&DATE($B14,5,1),tblVideos[Channel ID],$T$4)) | G14: =IF($G$4="Hours",ROUND(SUMIFS(tblVideos[Length],tblVideos[Day],">="&DATE($B14,5,1),tblVideos[Day],"<"&DATE($B14,6,1),tblVideos[Channel ID],$T$4)*24,0),COUNTIFS(tblVideos[Day],">="&DATE($B14,5,1),tblVideos[Day],"<"&DATE($B14,6,1),tblVideos[Channel ID],$T$4)) | H14: =IF($G$4="Hours",ROUND(SUMIFS(tblVideos[Length],tblVideos[Day],">="&DATE($B14,6,1),tblVideos[Day],"<"&DATE($B14,7,1),tblVideos[Channel ID],$T$4)*24,0),COUNTIFS(tblVideos[Day],">="&DATE($B14,6,1),tblVideos[Day],"<"&DATE($B14,7,1),tblVideos[Channel ID],$T$4)) | I14: =IF($G$4="Hours",ROUND(SUMIFS(tblVideos[Length],tblVideos[Day],">="&DATE($B14,7,1),tblVideos[Day],"<"&DATE($B14,8,1),tblVideos[Channel ID],$T$4)*24,0),COUNTIFS(tblVideos[Day],">="&DATE($B14,7,1),tblVideos[Day],"<"&DATE($B14,8,1),tblVideos[Channel ID],$T$4)) | J14: =IF($G$4="Hours",ROUND(SUMIFS(tblVideos[Length],tblVideos[Day],">="&DATE($B14,8,1),tblVideos[Day],"<"&DATE($B14,9,1),tblVideos[Channel ID],$T$4)*24,0),COUNTIFS(tblVideos[Day],">="&DATE($B14,8,1),tblVideos[Day],"<"&DATE($B14,9,1),tblVideos[Channel ID],$T$4)) | K14: =IF($G$4="Hours",ROUND(SUMIFS(tblVideos[Length],tblVideos[Day],">="&DATE($B14,9,1),tblVideos[Day],"<"&DATE($B14,10,1),tblVideos[Channel ID],$T$4)*24,0),COUNTIFS(tblVideos[Day],">="&DATE($B14,9,1),tblVideos[Day],"<"&DATE($B14,10,1),tblVideos[Channel ID],$T$4)) | L14: =IF($G$4="Hours",ROUND(SUMIFS(tblVideos[Length],tblVideos[Day],">="&DATE($B14,10,1),tblVideos[Day],"<"&DATE($B14,11,1),tblVideos[Channel ID],$T$4)*24,0),COUNTIFS(tblVideos[Day],">="&DATE($B14,10,1),tblVideos[Day],"<"&DATE($B14,11,1),tblVideos[Channel ID],$T$4)) | M14: =IF($G$4="Hours",ROUND(SUMIFS(tblVideos[Length],tblVideos[Day],">="&DATE($B14,11,1),tblVideos[Day],"<"&DATE($B14,12,1),tblVideos[Channel ID],$T$4)*24,0),COUNTIFS(tblVideos[Day],">="&DATE($B14,11,1),tblVideos[Day],"<"&DATE($B14,12,1),tblVideos[Channel ID],$T$4)) | N14: =IF($G$4="Hours",ROUND(SUMIFS(tblVideos[Length],tblVideos[Day],">="&DATE($B14,12,1),tblVideos[Day],"<"&DATE($B14,13,1),tblVideos[Channel ID],$T$4)*24,0),COUNTIFS(tblVideos[Day],">="&DATE($B14,12,1),tblVideos[Day],"<"&DATE($B14,13,1),tblVideos[Channel ID],$T$4)) | O14: =SUM(C14:N14)
B15: 2019 | C15: =IF($G$4="Hours",ROUND(SUMIFS(tblVideos[Length],tblVideos[Day],">="&DATE($B15,1,1),tblVideos[Day],"<"&DATE($B15,2,1),tblVideos[Channel ID],$T$4)*24,0),COUNTIFS(tblVideos[Day],">="&DATE($B15,1,1),tblVideos[Day],"<"&DATE($B15,2,1),tblVideos[Channel ID],$T$4)) | D15: =IF($G$4="Hours",ROUND(SUMIFS(tblVideos[Length],tblVideos[Day],">="&DATE($B15,2,1),tblVideos[Day],"<"&DATE($B15,3,1),tblVideos[Channel ID],$T$4)*24,0),COUNTIFS(tblVideos[Day],">="&DATE($B15,2,1),tblVideos[Day],"<"&DATE($B15,3,1),tblVideos[Channel ID],$T$4)) | E15: =IF($G$4="Hours",ROUND(SUMIFS(tblVideos[Length],tblVideos[Day],">="&DATE($B15,3,1),tblVideos[Day],"<"&DATE($B15,4,1),tblVideos[Channel ID],$T$4)*24,0),COUNTIFS(tblVideos[Day],">="&DATE($B15,3,1),tblVideos[Day],"<"&DATE($B15,4,1),tblVideos[Channel ID],$T$4)) | F15: =IF($G$4="Hours",ROUND(SUMIFS(tblVideos[Length],tblVideos[Day],">="&DATE($B15,4,1),tblVideos[Day],"<"&DATE($B15,5,1),tblVideos[Channel ID],$T$4)*24,0),COUNTIFS(tblVideos[Day],">="&DATE($B15,4,1),tblVideos[Day],"<"&DATE($B15,5,1),tblVideos[Channel ID],$T$4)) | G15: =IF($G$4="Hours",ROUND(SUMIFS(tblVideos[Length],tblVideos[Day],">="&DATE($B15,5,1),tblVideos[Day],"<"&DATE($B15,6,1),tblVideos[Channel ID],$T$4)*24,0),COUNTIFS(tblVideos[Day],">="&DATE($B15,5,1),tblVideos[Day],"<"&DATE($B15,6,1),tblVideos[Channel ID],$T$4)) | H15: =IF($G$4="Hours",ROUND(SUMIFS(tblVideos[Length],tblVideos[Day],">="&DATE($B15,6,1),tblVideos[Day],"<"&DATE($B15,7,1),tblVideos[Channel ID],$T$4)*24,0),COUNTIFS(tblVideos[Day],">="&DATE($B15,6,1),tblVideos[Day],"<"&DATE($B15,7,1),tblVideos[Channel ID],$T$4)) | I15: =IF($G$4="Hours",ROUND(SUMIFS(tblVideos[Length],tblVideos[Day],">="&DATE($B15,7,1),tblVideos[Day],"<"&DATE($B15,8,1),tblVideos[Channel ID],$T$4)*24,0),COUNTIFS(tblVideos[Day],">="&DATE($B15,7,1),tblVideos[Day],"<"&DATE($B15,8,1),tblVideos[Channel ID],$T$4)) | J15: =IF($G$4="Hours",ROUND(SUMIFS(tblVideos[Length],tblVideos[Day],">="&DATE($B15,8,1),tblVideos[Day],"<"&DATE($B15,9,1),tblVideos[Channel ID],$T$4)*24,0),COUNTIFS(tblVideos[Day],">="&DATE($B15,8,1),tblVideos[Day],"<"&DATE($B15,9,1),tblVideos[Channel ID],$T$4)) | K15: =IF($G$4="Hours",ROUND(SUMIFS(tblVideos[Length],tblVideos[Day],">="&DATE($B15,9,1),tblVideos[Day],"<"&DATE($B15,10,1),tblVideos[Channel ID],$T$4)*24,0),COUNTIFS(tblVideos[Day],">="&DATE($B15,9,1),tblVideos[Day],"<"&DATE($B15,10,1),tblVideos[Channel ID],$T$4)) | L15: =IF($G$4="Hours",ROUND(SUMIFS(tblVideos[Length],tblVideos[Day],">="&DATE($B15,10,1),tblVideos[Day],"<"&DATE($B15,11,1),tblVideos[Channel ID],$T$4)*24,0),COUNTIFS(tblVideos[Day],">="&DATE($B15,10,1),tblVideos[Day],"<"&DATE($B15,11,1),tblVideos[Channel ID],$T$4)) | M15: =IF($G$4="Hours",ROUND(SUMIFS(tblVideos[Length],tblVideos[Day],">="&DATE($B15,11,1),tblVideos[Day],"<"&DATE($B15,12,1),tblVideos[Channel ID],$T$4)*24,0),COUNTIFS(tblVideos[Day],">="&DATE($B15,11,1),tblVideos[Day],"<"&DATE($B15,12,1),tblVideos[Channel ID],$T$4)) | N15: =IF($G$4="Hours",ROUND(SUMIFS(tblVideos[Length],tblVideos[Day],">="&DATE($B15,12,1),tblVideos[Day],"<"&DATE($B15,13,1),tblVideos[Channel ID],$T$4)*24,0),COUNTIFS(tblVideos[Day],">="&DATE($B15,12,1),tblVideos[Day],"<"&DATE($B15,13,1),tblVideos[Channel ID],$T$4)) | O15: =SUM(C15:N15)
B16: 2020 | C16: =IF($G$4="Hours",ROUND(SUMIFS(tblVideos[Length],tblVideos[Day],">="&DATE($B16,1,1),tblVideos[Day],"<"&DATE($B16,2,1),tblVideos[Channel ID],$T$4)*24,0),COUNTIFS(tblVideos[Day],">="&DATE($B16,1,1),tblVideos[Day],"<"&DATE($B16,2,1),tblVideos[Channel ID],$T$4)) | D16: =IF($G$4="Hours",ROUND(SUMIFS(tblVideos[Length],tblVideos[Day],">="&DATE($B16,2,1),tblVideos[Day],"<"&DATE($B16,3,1),tblVideos[Channel ID],$T$4)*24,0),COUNTIFS(tblVideos[Day],">="&DATE($B16,2,1),tblVideos[Day],"<"&DATE($B16,3,1),tblVideos[Channel ID],$T$4)) | E16: =IF($G$4="Hours",ROUND(SUMIFS(tblVideos[Length],tblVideos[Day],">="&DATE($B16,3,1),tblVideos[Day],"<"&DATE($B16,4,1),tblVideos[Channel ID],$T$4)*24,0),COUNTIFS(tblVideos[Day],">="&DATE($B16,3,1),tblVideos[Day],"<"&DATE($B16,4,1),tblVideos[Channel ID],$T$4)) | F16: =IF($G$4="Hours",ROUND(SUMIFS(tblVideos[Length],tblVideos[Day],">="&DATE($B16,4,1),tblVideos[Day],"<"&DATE($B16,5,1),tblVideos[Channel ID],$T$4)*24,0),COUNTIFS(tblVideos[Day],">="&DATE($B16,4,1),tblVideos[Day],"<"&DATE($B16,5,1),tblVideos[Channel ID],$T$4)) | G16: =IF($G$4="Hours",ROUND(SUMIFS(tblVideos[Length],tblVideos[Day],">="&DATE($B16,5,1),tblVideos[Day],"<"&DATE($B16,6,1),tblVideos[Channel ID],$T$4)*24,0),COUNTIFS(tblVideos[Day],">="&DATE($B16,5,1),tblVideos[Day],"<"&DATE($B16,6,1),tblVideos[Channel ID],$T$4)) | H16: =IF($G$4="Hours",ROUND(SUMIFS(tblVideos[Length],tblVideos[Day],">="&DATE($B16,6,1),tblVideos[Day],"<"&DATE($B16,7,1),tblVideos[Channel ID],$T$4)*24,0),COUNTIFS(tblVideos[Day],">="&DATE($B16,6,1),tblVideos[Day],"<"&DATE($B16,7,1),tblVideos[Channel ID],$T$4)) | I16: =IF($G$4="Hours",ROUND(SUMIFS(tblVideos[Length],tblVideos[Day],">="&DATE($B16,7,1),tblVideos[Day],"<"&DATE($B16,8,1),tblVideos[Channel ID],$T$4)*24,0),COUNTIFS(tblVideos[Day],">="&DATE($B16,7,1),tblVideos[Day],"<"&DATE($B16,8,1),tblVideos[Channel ID],$T$4)) | J16: =IF($G$4="Hours",ROUND(SUMIFS(tblVideos[Length],tblVideos[Day],">="&DATE($B16,8,1),tblVideos[Day],"<"&DATE($B16,9,1),tblVideos[Channel ID],$T$4)*24,0),COUNTIFS(tblVideos[Day],">="&DATE($B16,8,1),tblVideos[Day],"<"&DATE($B16,9,1),tblVideos[Channel ID],$T$4)) | K16: =IF($G$4="Hours",ROUND(SUMIFS(tblVideos[Length],tblVideos[Day],">="&DATE($B16,9,1),tblVideos[Day],"<"&DATE($B16,10,1),tblVideos[Channel ID],$T$4)*24,0),COUNTIFS(tblVideos[Day],">="&DATE($B16,9,1),tblVideos[Day],"<"&DATE($B16,10,1),tblVideos[Channel ID],$T$4)) | L16: =IF($G$4="Hours",ROUND(SUMIFS(tblVideos[Length],tblVideos[Day],">="&DATE($B16,10,1),tblVideos[Day],"<"&DATE($B16,11,1),tblVideos[Channel ID],$T$4)*24,0),COUNTIFS(tblVideos[Day],">="&DATE($B16,10,1),tblVideos[Day],"<"&DATE($B16,11,1),tblVideos[Channel ID],$T$4)) | M16: =IF($G$4="Hours",ROUND(SUMIFS(tblVideos[Length],tblVideos[Day],">="&DATE($B16,11,1),tblVideos[Day],"<"&DATE($B16,12,1),tblVideos[Channel ID],$T$4)*24,0),COUNTIFS(tblVideos[Day],">="&DATE($B16,11,1),tblVideos[Day],"<"&DATE($B16,12,1),tblVideos[Channel ID],$T$4)) | N16: =IF($G$4="Hours",ROUND(SUMIFS(tblVideos[Length],tblVideos[Day],">="&DATE($B16,12,1),tblVideos[Day],"<"&DATE($B16,13,1),tblVideos[Channel ID],$T$4)*24,0),COUNTIFS(tblVideos[Day],">="&DATE($B16,12,1),tblVideos[Day],"<"&DATE($B16,13,1),tblVideos[Channel ID],$T$4)) | O16: =SUM(C16:N16)
B17: 2021 | C17: =IF($G$4="Hours",ROUND(SUMIFS(tblVideos[Length],tblVideos[Day],">="&DATE($B17,1,1),tblVideos[Day],"<"&DATE($B17,2,1),tblVideos[Channel ID],$T$4)*24,0),COUNTIFS(tblVideos[Day],">="&DATE($B17,1,1),tblVideos[Day],"<"&DATE($B17,2,1),tblVideos[Channel ID],$T$4)) | D17: =IF($G$4="Hours",ROUND(SUMIFS(tblVideos[Length],tblVideos[Day],">="&DATE($B17,2,1),tblVideos[Day],"<"&DATE($B17,3,1),tblVideos[Channel ID],$T$4)*24,0),COUNTIFS(tblVideos[Day],">="&DATE($B17,2,1),tblVideos[Day],"<"&DATE($B17,3,1),tblVideos[Channel ID],$T$4)) | E17: =IF($G$4="Hours",ROUND(SUMIFS(tblVideos[Length],tblVideos[Day],">="&DATE($B17,3,1),tblVideos[Day],"<"&DATE($B17,4,1),tblVideos[Channel ID],$T$4)*24,0),COUNTIFS(tblVideos[Day],">="&DATE($B17,3,1),tblVideos[Day],"<"&DATE($B17,4,1),tblVideos[Channel ID],$T$4)) | F17: =IF($G$4="Hours",ROUND(SUMIFS(tblVideos[Length],tblVideos[Day],">="&DATE($B17,4,1),tblVideos[Day],"<"&DATE($B17,5,1),tblVideos[Channel ID],$T$4)*24,0),COUNTIFS(tblVideos[Day],">="&DATE($B17,4,1),tblVideos[Day],"<"&DATE($B17,5,1),tblVideos[Channel ID],$T$4)) | G17: =IF($G$4="Hours",ROUND(SUMIFS(tblVideos[Length],tblVideos[Day],">="&DATE($B17,5,1),tblVideos[Day],"<"&DATE($B17,6,1),tblVideos[Channel ID],$T$4)*24,0),COUNTIFS(tblVideos[Day],">="&DATE($B17,5,1),tblVideos[Day],"<"&DATE($B17,6,1),tblVideos[Channel ID],$T$4)) | H17: =IF($G$4="Hours",ROUND(SUMIFS(tblVideos[Length],tblVideos[Day],">="&DATE($B17,6,1),tblVideos[Day],"<"&DATE($B17,7,1),tblVideos[Channel ID],$T$4)*24,0),COUNTIFS(tblVideos[Day],">="&DATE($B17,6,1),tblVideos[Day],"<"&DATE($B17,7,1),tblVideos[Channel ID],$T$4)) | I17: =IF($G$4="Hours",ROUND(SUMIFS(tblVideos[Length],tblVideos[Day],">="&DATE($B17,7,1),tblVideos[Day],"<"&DATE($B17,8,1),tblVideos[Channel ID],$T$4)*24,0),COUNTIFS(tblVideos[Day],">="&DATE($B17,7,1),tblVideos[Day],"<"&DATE($B17,8,1),tblVideos[Channel ID],$T$4)) | J17: =IF($G$4="Hours",ROUND(SUMIFS(tblVideos[Length],tblVideos[Day],">="&DATE($B17,8,1),tblVideos[Day],"<"&DATE($B17,9,1),tblVideos[Channel ID],$T$4)*24,0),COUNTIFS(tblVideos[Day],">="&DATE($B17,8,1),tblVideos[Day],"<"&DATE($B17,9,1),tblVideos[Channel ID],$T$4)) | K17: =IF($G$4="Hours",ROUND(SUMIFS(tblVideos[Length],tblVideos[Day],">="&DATE($B17,9,1),tblVideos[Day],"<"&DATE($B17,10,1),tblVideos[Channel ID],$T$4)*24,0),COUNTIFS(tblVideos[Day],">="&DATE($B17,9,1),tblVideos[Day],"<"&DATE($B17,10,1),tblVideos[Channel ID],$T$4)) | L17: =IF($G$4="Hours",ROUND(SUMIFS(tblVideos[Length],tblVideos[Day],">="&DATE($B17,10,1),tblVideos[Day],"<"&DATE($B17,11,1),tblVideos[Channel ID],$T$4)*24,0),COUNTIFS(tblVideos[Day],">="&DATE($B17,10,1),tblVideos[Day],"<"&DATE($B17,11,1),tblVideos[Channel ID],$T$4)) | M17: =IF($G$4="Hours",ROUND(SUMIFS(tblVideos[Length],tblVideos[Day],">="&DATE($B17,11,1),tblVideos[Day],"<"&DATE($B17,12,1),tblVideos[Channel ID],$T$4)*24,0),COUNTIFS(tblVideos[Day],">="&DATE($B17,11,1),tblVideos[Day],"<"&DATE($B17,12,1),tblVideos[Channel ID],$T$4)) | N17: =IF($G$4="Hours",ROUND(SUMIFS(tblVideos[Length],tblVideos[Day],">="&DATE($B17,12,1),tblVideos[Day],"<"&DATE($B17,13,1),tblVideos[Channel ID],$T$4)*24,0),COUNTIFS(tblVideos[Day],">="&DATE($B17,12,1),tblVideos[Day],"<"&DATE($B17,13,1),tblVideos[Channel ID],$T$4)) | O17: =SUM(C17:N17)
B18: 2022 | C18: =IF($G$4="Hours",ROUND(SUMIFS(tblVideos[Length],tblVideos[Day],">="&DATE($B18,1,1),tblVideos[Day],"<"&DATE($B18,2,1),tblVideos[Channel ID],$T$4)*24,0),COUNTIFS(tblVideos[Day],">="&DATE($B18,1,1),tblVideos[Day],"<"&DATE($B18,2,1),tblVideos[Channel ID],$T$4)) | D18: =IF($G$4="Hours",ROUND(SUMIFS(tblVideos[Length],tblVideos[Day],">="&DATE($B18,2,1),tblVideos[Day],"<"&DATE($B18,3,1),tblVideos[Channel ID],$T$4)*24,0),COUNTIFS(tblVideos[Day],">="&DATE($B18,2,1),tblVideos[Day],"<"&DATE($B18,3,1),tblVideos[Channel ID],$T$4)) | E18: =IF($G$4="Hours",ROUND(SUMIFS(tblVideos[Length],tblVideos[Day],">="&DATE($B18,3,1),tblVideos[Day],"<"&DATE($B18,4,1),tblVideos[Channel ID],$T$4)*24,0),COUNTIFS(tblVideos[Day],">="&DATE($B18,3,1),tblVideos[Day],"<"&DATE($B18,4,1),tblVideos[Channel ID],$T$4)) | F18: =IF($G$4="Hours",ROUND(SUMIFS(tblVideos[Length],tblVideos[Day],">="&DATE($B18,4,1),tblVideos[Day],"<"&DATE($B18,5,1),tblVideos[Channel ID],$T$4)*24,0),COUNTIFS(tblVideos[Day],">="&DATE($B18,4,1),tblVideos[Day],"<"&DATE($B18,5,1),tblVideos[Channel ID],$T$4)) | G18: =IF($G$4="Hours",ROUND(SUMIFS(tblVideos[Length],tblVideos[Day],">="&DATE($B18,5,1),tblVideos[Day],"<"&DATE($B18,6,1),tblVideos[Channel ID],$T$4)*24,0),COUNTIFS(tblVideos[Day],">="&DATE($B18,5,1),tblVideos[Day],"<"&DATE($B18,6,1),tblVideos[Channel ID],$T$4)) | H18: =IF($G$4="Hours",ROUND(SUMIFS(tblVideos[Length],tblVideos[Day],">="&DATE($B18,6,1),tblVideos[Day],"<"&DATE($B18,7,1),tblVideos[Channel ID],$T$4)*24,0),COUNTIFS(tblVideos[Day],">="&DATE($B18,6,1),tblVideos[Day],"<"&DATE($B18,7,1),tblVideos[Channel ID],$T$4)) | I18: =IF($G$4="Hours",ROUND(SUMIFS(tblVideos[Length],tblVideos[Day],">="&DATE($B18,7,1),tblVideos[Day],"<"&DATE($B18,8,1),tblVideos[Channel ID],$T$4)*24,0),COUNTIFS(tblVideos[Day],">="&DATE($B18,7,1),tblVideos[Day],"<"&DATE($B18,8,1),tblVideos[Channel ID],$T$4)) | J18: =IF($G$4="Hours",ROUND(SUMIFS(tblVideos[Length],tblVideos[Day],">="&DATE($B18,8,1),tblVideos[Day],"<"&DATE($B18,9,1),tblVideos[Channel ID],$T$4)*24,0),COUNTIFS(tblVideos[Day],">="&DATE($B18,8,1),tblVideos[Day],"<"&DATE($B18,9,1),tblVideos[Channel ID],$T$4)) | K18: =IF($G$4="Hours",ROUND(SUMIFS(tblVideos[Length],tblVideos[Day],">="&DATE($B18,9,1),tblVideos[Day],"<"&DATE($B18,10,1),tblVideos[Channel ID],$T$4)*24,0),COUNTIFS(tblVideos[Day],">="&DATE($B18,9,1),tblVideos[Day],"<"&DATE($B18,10,1),tblVideos[Channel ID],$T$4)) | L18: =IF($G$4="Hours",ROUND(SUMIFS(tblVideos[Length],tblVideos[Day],">="&DATE($B18,10,1),tblVideos[Day],"<"&DATE($B18,11,1),tblVideos[Channel ID],$T$4)*24,0),COUNTIFS(tblVideos[Day],">="&DATE($B18,10,1),tblVideos[Day],"<"&DATE($B18,11,1),tblVideos[Channel ID],$T$4)) | M18: =IF($G$4="Hours",ROUND(SUMIFS(tblVideos[Length],tblVideos[Day],">="&DATE($B18,11,1),tblVideos[Day],"<"&DATE($B18,12,1),tblVideos[Channel ID],$T$4)*24,0),COUNTIFS(tblVideos[Day],">="&DATE($B18,11,1),tblVideos[Day],"<"&DATE($B18,12,1),tblVideos[Channel ID],$T$4)) | N18: =IF($G$4="Hours",ROUND(SUMIFS(tblVideos[Length],tblVideos[Day],">="&DATE($B18,12,1),tblVideos[Day],"<"&DATE($B18,13,1),tblVideos[Channel ID],$T$4)*24,0),COUNTIFS(tblVideos[Day],">="&DATE($B18,12,1),tblVideos[Day],"<"&DATE($B18,13,1),tblVideos[Channel ID],$T$4)) | O18: =SUM(C18:N18)
B19: 2023 | C19: =IF($G$4="Hours",ROUND(SUMIFS(tblVideos[Length],tblVideos[Day],">="&DATE($B19,1,1),tblVideos[Day],"<"&DATE($B19,2,1),tblVideos[Channel ID],$T$4)*24,0),COUNTIFS(tblVideos[Day],">="&DATE($B19,1,1),tblVideos[Day],"<"&DATE($B19,2,1),tblVideos[Channel ID],$T$4)) | D19: =IF($G$4="Hours",ROUND(SUMIFS(tblVideos[Length],tblVideos[Day],">="&DATE($B19,2,1),tblVideos[Day],"<"&DATE($B19,3,1),tblVideos[Channel ID],$T$4)*24,0),COUNTIFS(tblVideos[Day],">="&DATE($B19,2,1),tblVideos[Day],"<"&DATE($B19,3,1),tblVideos[Channel ID],$T$4)) | E19: =IF($G$4="Hours",ROUND(SUMIFS(tblVideos[Length],tblVideos[Day],">="&DATE($B19,3,1),tblVideos[Day],"<"&DATE($B19,4,1),tblVideos[Channel ID],$T$4)*24,0),COUNTIFS(tblVideos[Day],">="&DATE($B19,3,1),tblVideos[Day],"<"&DATE($B19,4,1),tblVideos[Channel ID],$T$4)) | F19: =IF($G$4="Hours",ROUND(SUMIFS(tblVideos[Length],tblVideos[Day],">="&DATE($B19,4,1),tblVideos[Day],"<"&DATE($B19,5,1),tblVideos[Channel ID],$T$4)*24,0),COUNTIFS(tblVideos[Day],">="&DATE($B19,4,1),tblVideos[Day],"<"&DATE($B19,5,1),tblVideos[Channel ID],$T$4)) | G19: =IF($G$4="Hours",ROUND(SUMIFS(tblVideos[Length],tblVideos[Day],">="&DATE($B19,5,1),tblVideos[Day],"<"&DATE($B19,6,1),tblVideos[Channel ID],$T$4)*24,0),COUNTIFS(tblVideos[Day],">="&DATE($B19,5,1),tblVideos[Day],"<"&DATE($B19,6,1),tblVideos[Channel ID],$T$4)) | H19: =IF($G$4="Hours",ROUND(SUMIFS(tblVideos[Length],tblVideos[Day],">="&DATE($B19,6,1),tblVideos[Day],"<"&DATE($B19,7,1),tblVideos[Channel ID],$T$4)*24,0),COUNTIFS(tblVideos[Day],">="&DATE($B19,6,1),tblVideos[Day],"<"&DATE($B19,7,1),tblVideos[Channel ID],$T$4)) | I19: =IF($G$4="Hours",ROUND(SUMIFS(tblVideos[Length],tblVideos[Day],">="&DATE($B19,7,1),tblVideos[Day],"<"&DATE($B19,8,1),tblVideos[Channel ID],$T$4)*24,0),COUNTIFS(tblVideos[Day],">="&DATE($B19,7,1),tblVideos[Day],"<"&DATE($B19,8,1),tblVideos[Channel ID],$T$4)) | J19: =IF($G$4="Hours",ROUND(SUMIFS(tblVideos[Length],tblVideos[Day],">="&DATE($B19,8,1),tblVideos[Day],"<"&DATE($B19,9,1),tblVideos[Channel ID],$T$4)*24,0),COUNTIFS(tblVideos[Day],">="&DATE($B19,8,1),tblVideos[Day],"<"&DATE($B19,9,1),tblVideos[Channel ID],$T$4)) | K19: =IF($G$4="Hours",ROUND(SUMIFS(tblVideos[Length],tblVideos[Day],">="&DATE($B19,9,1),tblVideos[Day],"<"&DATE($B19,10,1),tblVideos[Channel ID],$T$4)*24,0),COUNTIFS(tblVideos[Day],">="&DATE($B19,9,1),tblVideos[Day],"<"&DATE($B19,10,1),tblVideos[Channel ID],$T$4)) | L19: =IF($G$4="Hours",ROUND(SUMIFS(tblVideos[Length],tblVideos[Day],">="&DATE($B19,10,1),tblVideos[Day],"<"&DATE($B19,11,1),tblVideos[Channel ID],$T$4)*24,0),COUNTIFS(tblVideos[Day],">="&DATE($B19,10,1),tblVideos[Day],"<"&DATE($B19,11,1),tblVideos[Channel ID],$T$4)) | M19: =IF($G$4="Hours",ROUND(SUMIFS(tblVideos[Length],tblVideos[Day],">="&DATE($B19,11,1),tblVideos[Day],"<"&DATE($B19,12,1),tblVideos[Channel ID],$T$4)*24,0),COUNTIFS(tblVideos[Day],">="&DATE($B19,11,1),tblVideos[Day],"<"&DATE($B19,12,1),tblVideos[Channel ID],$T$4)) | N19: =IF($G$4="Hours",ROUND(SUMIFS(tblVideos[Length],tblVideos[Day],">="&DATE($B19,12,1),tblVideos[Day],"<"&DATE($B19,13,1),tblVideos[Channel ID],$T$4)*24,0),COUNTIFS(tblVideos[Day],">="&DATE($B19,12,1),tblVideos[Day],"<"&DATE($B19,13,1),tblVideos[Channel ID],$T$4)) | O19: =SUM(C19:N19)
... B22: 2026 | C22: =IF($G$4="Hours",ROUND(SUMIFS(tblVideos[Length],tblVideos[Day],">="&DATE($B22,1,1),tblVideos[Day],"<"&DATE($B22,2,1),tblVideos[Channel ID],$T$4)*24,0),COUNTIFS(tblVideos[Day],">="&DATE($B22,1,1),tblVideos[Day],"<"&DATE($B22,2,1),tblVideos[Channel ID],$T$4)) | D22: =IF($G$4="Hours",ROUND(SUMIFS(tblVideos[Length],tblVideos[Day],">="&DATE($B22,2,1),tblVideos[Day],"<"&DATE($B22,3,1),tblVideos[Channel ID],$T$4)*24,0),COUNTIFS(tblVideos[Day],">="&DATE($B22,2,1),tblVideos[Day],"<"&DATE($B22,3,1),tblVideos[Channel ID],$T$4)) | E22: =IF($G$4="Hours",ROUND(SUMIFS(tblVideos[Length],tblVideos[Day],">="&DATE($B22,3,1),tblVideos[Day],"<"&DATE($B22,4,1),tblVideos[Channel ID],$T$4)*24,0),COUNTIFS(tblVideos[Day],">="&DATE($B22,3,1),tblVideos[Day],"<"&DATE($B22,4,1),tblVideos[Channel ID],$T$4)) | F22: =IF($G$4="Hours",ROUND(SUMIFS(tblVideos[Length],tblVideos[Day],">="&DATE($B22,4,1),tblVideos[Day],"<"&DATE($B22,5,1),tblVideos[Channel ID],$T$4)*24,0),COUNTIFS(tblVideos[Day],">="&DATE($B22,4,1),tblVideos[Day],"<"&DATE($B22,5,1),tblVideos[Channel ID],$T$4)) | G22: =IF($G$4="Hours",ROUND(SUMIFS(tblVideos[Length],tblVideos[Day],">="&DATE($B22,5,1),tblVideos[Day],"<"&DATE($B22,6,1),tblVideos[Channel ID],$T$4)*24,0),COUNTIFS(tblVideos[Day],">="&DATE($B22,5,1),tblVideos[Day],"<"&DATE($B22,6,1),tblVideos[Channel ID],$T$4)) | H22: =IF($G$4="Hours",ROUND(SUMIFS(tblVideos[Length],tblVideos[Day],">="&DATE($B22,6,1),tblVideos[Day],"<"&DATE($B22,7,1),tblVideos[Channel ID],$T$4)*24,0),COUNTIFS(tblVideos[Day],">="&DATE($B22,6,1),tblVideos[Day],"<"&DATE($B22,7,1),tblVideos[Channel ID],$T$4)) | I22: =IF($G$4="Hours",ROUND(SUMIFS(tblVideos[Length],tblVideos[Day],">="&DATE($B22,7,1),tblVideos[Day],"<"&DATE($B22,8,1),tblVideos[Channel ID],$T$4)*24,0),COUNTIFS(tblVideos[Day],">="&DATE($B22,7,1),tblVideos[Day],"<"&DATE($B22,8,1),tblVideos[Channel ID],$T$4)) | J22: =IF($G$4="Hours",ROUND(SUMIFS(tblVideos[Length],tblVideos[Day],">="&DATE($B22,8,1),tblVideos[Day],"<"&DATE($B22,9,1),tblVideos[Channel ID],$T$4)*24,0),COUNTIFS(tblVideos[Day],">="&DATE($B22,8,1),tblVideos[Day],"<"&DATE($B22,9,1),tblVideos[Channel ID],$T$4)) | K22: =IF($G$4="Hours",ROUND(SUMIFS(tblVideos[Length],tblVideos[Day],">="&DATE($B22,9,1),tblVideos[Day],"<"&DATE($B22,10,1),tblVideos[Channel ID],$T$4)*24,0),COUNTIFS(tblVideos[Day],">="&DATE($B22,9,1),tblVideos[Day],"<"&DATE($B22,10,1),tblVideos[Channel ID],$T$4)) | L22: =IF($G$4="Hours",ROUND(SUMIFS(tblVideos[Length],tblVideos[Day],">="&DATE($B22,10,1),tblVideos[Day],"<"&DATE($B22,11,1),tblVideos[Channel ID],$T$4)*24,0),COUNTIFS(tblVideos[Day],">="&DATE($B22,10,1),tblVideos[Day],"<"&DATE($B22,11,1),tblVideos[Channel ID],$T$4)) | M22: =IF($G$4="Hours",ROUND(SUMIFS(tblVideos[Length],tblVideos[Day],">="&DATE($B22,11,1),tblVideos[Day],"<"&DATE($B22,12,1),tblVideos[Channel ID],$T$4)*24,0),COUNTIFS(tblVideos[Day],">="&DATE($B22,11,1),tblVideos[Day],"<"&DATE($B22,12,1),tblVideos[Channel ID],$T$4)) | N22: =IF($G$4="Hours",ROUND(SUMIFS(tblVideos[Length],tblVideos[Day],">="&DATE($B22,12,1),tblVideos[Day],"<"&DATE($B22,13,1),tblVideos[Channel ID],$T$4)*24,0),COUNTIFS(tblVideos[Day],">="&DATE($B22,12,1),tblVideos[Day],"<"&DATE($B22,13,1),tblVideos[Channel ID],$T$4)) | O22: =SUM(C22:N22)
B23: All years | C23: =SUM(C8:C22) | D23: =SUM(D8:D22) | E23: =SUM(E8:E22) | F23: =SUM(F8:F22) | G23: =SUM(G8:G22) | H23: =SUM(H8:H22) | I23: =SUM(I8:I22) | J23: =SUM(J8:J22) | ... O23: =SUM(O8:O22)
B26: ="Year view - "&$K$4
B27: Month | C27: =Channels!$C$6 | D27: =Channels!$C$7 | E27: =Channels!$C$8 | F27: =Channels!$C$9 | G27: =Channels!$C$10 | H27: =Channels!$C$11 | I27: Total | J27: Hours
B28: January | C28: =COUNTIFS(tblVideos[Day],">="&DATE($K$4,1,1),tblVideos[Day],"<"&DATE($K$4,2,1),tblVideos[Channel ID],Channels!$E$6) | D28: =COUNTIFS(tblVideos[Day],">="&DATE($K$4,1,1),tblVideos[Day],"<"&DATE($K$4,2,1),tblVideos[Channel ID],Channels!$E$7) | E28: =COUNTIFS(tblVideos[Day],">="&DATE($K$4,1,1),tblVideos[Day],"<"&DATE($K$4,2,1),tblVideos[Channel ID],Channels!$E$8) | F28: =COUNTIFS(tblVideos[Day],">="&DATE($K$4,1,1),tblVideos[Day],"<"&DATE($K$4,2,1),tblVideos[Channel ID],Channels!$E$9) | G28: =COUNTIFS(tblVideos[Day],">="&DATE($K$4,1,1),tblVideos[Day],"<"&DATE($K$4,2,1),tblVideos[Channel ID],Channels!$E$10) | H28: =COUNTIFS(tblVideos[Day],">="&DATE($K$4,1,1),tblVideos[Day],"<"&DATE($K$4,2,1),tblVideos[Channel ID],Channels!$E$11) | I28: =SUM(C28:H28) | J28: =SUMIFS(tblVideos[Length],tblVideos[Day],">="&DATE($K$4,1,1),tblVideos[Day],"<"&DATE($K$4,2,1))*24
B29: February | C29: =COUNTIFS(tblVideos[Day],">="&DATE($K$4,2,1),tblVideos[Day],"<"&DATE($K$4,3,1),tblVideos[Channel ID],Channels!$E$6) | D29: =COUNTIFS(tblVideos[Day],">="&DATE($K$4,2,1),tblVideos[Day],"<"&DATE($K$4,3,1),tblVideos[Channel ID],Channels!$E$7) | E29: =COUNTIFS(tblVideos[Day],">="&DATE($K$4,2,1),tblVideos[Day],"<"&DATE($K$4,3,1),tblVideos[Channel ID],Channels!$E$8) | F29: =COUNTIFS(tblVideos[Day],">="&DATE($K$4,2,1),tblVideos[Day],"<"&DATE($K$4,3,1),tblVideos[Channel ID],Channels!$E$9) | G29: =COUNTIFS(tblVideos[Day],">="&DATE($K$4,2,1),tblVideos[Day],"<"&DATE($K$4,3,1),tblVideos[Channel ID],Channels!$E$10) | H29: =COUNTIFS(tblVideos[Day],">="&DATE($K$4,2,1),tblVideos[Day],"<"&DATE($K$4,3,1),tblVideos[Channel ID],Channels!$E$11) | I29: =SUM(C29:H29) | J29: =SUMIFS(tblVideos[Length],tblVideos[Day],">="&DATE($K$4,2,1),tblVideos[Day],"<"&DATE($K$4,3,1))*24
B30: March | C30: =COUNTIFS(tblVideos[Day],">="&DATE($K$4,3,1),tblVideos[Day],"<"&DATE($K$4,4,1),tblVideos[Channel ID],Channels!$E$6) | D30: =COUNTIFS(tblVideos[Day],">="&DATE($K$4,3,1),tblVideos[Day],"<"&DATE($K$4,4,1),tblVideos[Channel ID],Channels!$E$7) | E30: =COUNTIFS(tblVideos[Day],">="&DATE($K$4,3,1),tblVideos[Day],"<"&DATE($K$4,4,1),tblVideos[Channel ID],Channels!$E$8) | F30: =COUNTIFS(tblVideos[Day],">="&DATE($K$4,3,1),tblVideos[Day],"<"&DATE($K$4,4,1),tblVideos[Channel ID],Channels!$E$9) | G30: =COUNTIFS(tblVideos[Day],">="&DATE($K$4,3,1),tblVideos[Day],"<"&DATE($K$4,4,1),tblVideos[Channel ID],Channels!$E$10) | H30: =COUNTIFS(tblVideos[Day],">="&DATE($K$4,3,1),tblVideos[Day],"<"&DATE($K$4,4,1),tblVideos[Channel ID],Channels!$E$11) | I30: =SUM(C30:H30) | J30: =SUMIFS(tblVideos[Length],tblVideos[Day],">="&DATE($K$4,3,1),tblVideos[Day],"<"&DATE($K$4,4,1))*24
B31: April | C31: =COUNTIFS(tblVideos[Day],">="&DATE($K$4,4,1),tblVideos[Day],"<"&DATE($K$4,5,1),tblVideos[Channel ID],Channels!$E$6) | D31: =COUNTIFS(tblVideos[Day],">="&DATE($K$4,4,1),tblVideos[Day],"<"&DATE($K$4,5,1),tblVideos[Channel ID],Channels!$E$7) | E31: =COUNTIFS(tblVideos[Day],">="&DATE($K$4,4,1),tblVideos[Day],"<"&DATE($K$4,5,1),tblVideos[Channel ID],Channels!$E$8) | F31: =COUNTIFS(tblVideos[Day],">="&DATE($K$4,4,1),tblVideos[Day],"<"&DATE($K$4,5,1),tblVideos[Channel ID],Channels!$E$9) | G31: =COUNTIFS(tblVideos[Day],">="&DATE($K$4,4,1),tblVideos[Day],"<"&DATE($K$4,5,1),tblVideos[Channel ID],Channels!$E$10) | H31: =COUNTIFS(tblVideos[Day],">="&DATE($K$4,4,1),tblVideos[Day],"<"&DATE($K$4,5,1),tblVideos[Channel ID],Channels!$E$11) | I31: =SUM(C31:H31) | J31: =SUMIFS(tblVideos[Length],tblVideos[Day],">="&DATE($K$4,4,1),tblVideos[Day],"<"&DATE($K$4,5,1))*24
B32: May | C32: =COUNTIFS(tblVideos[Day],">="&DATE($K$4,5,1),tblVideos[Day],"<"&DATE($K$4,6,1),tblVideos[Channel ID],Channels!$E$6) | D32: =COUNTIFS(tblVideos[Day],">="&DATE($K$4,5,1),tblVideos[Day],"<"&DATE($K$4,6,1),tblVideos[Channel ID],Channels!$E$7) | E32: =COUNTIFS(tblVideos[Day],">="&DATE($K$4,5,1),tblVideos[Day],"<"&DATE($K$4,6,1),tblVideos[Channel ID],Channels!$E$8) | F32: =COUNTIFS(tblVideos[Day],">="&DATE($K$4,5,1),tblVideos[Day],"<"&DATE($K$4,6,1),tblVideos[Channel ID],Channels!$E$9) | G32: =COUNTIFS(tblVideos[Day],">="&DATE($K$4,5,1),tblVideos[Day],"<"&DATE($K$4,6,1),tblVideos[Channel ID],Channels!$E$10) | H32: =COUNTIFS(tblVideos[Day],">="&DATE($K$4,5,1),tblVideos[Day],"<"&DATE($K$4,6,1),tblVideos[Channel ID],Channels!$E$11) | I32: =SUM(C32:H32) | J32: =SUMIFS(tblVideos[Length],tblVideos[Day],">="&DATE($K$4,5,1),tblVideos[Day],"<"&DATE($K$4,6,1))*24
B33: June | C33: =COUNTIFS(tblVideos[Day],">="&DATE($K$4,6,1),tblVideos[Day],"<"&DATE($K$4,7,1),tblVideos[Channel ID],Channels!$E$6) | D33: =COUNTIFS(tblVideos[Day],">="&DATE($K$4,6,1),tblVideos[Day],"<"&DATE($K$4,7,1),tblVideos[Channel ID],Channels!$E$7) | E33: =COUNTIFS(tblVideos[Day],">="&DATE($K$4,6,1),tblVideos[Day],"<"&DATE($K$4,7,1),tblVideos[Channel ID],Channels!$E$8) | F33: =COUNTIFS(tblVideos[Day],">="&DATE($K$4,6,1),tblVideos[Day],"<"&DATE($K$4,7,1),tblVideos[Channel ID],Channels!$E$9) | G33: =COUNTIFS(tblVideos[Day],">="&DATE($K$4,6,1),tblVideos[Day],"<"&DATE($K$4,7,1),tblVideos[Channel ID],Channels!$E$10) | H33: =COUNTIFS(tblVideos[Day],">="&DATE($K$4,6,1),tblVideos[Day],"<"&DATE($K$4,7,1),tblVideos[Channel ID],Channels!$E$11) | I33: =SUM(C33:H33) | J33: =SUMIFS(tblVideos[Length],tblVideos[Day],">="&DATE($K$4,6,1),tblVideos[Day],"<"&DATE($K$4,7,1))*24
