Workbook
Name YearList: Lists!$A$1:$A$15
Name MonthList: Lists!$C$1:$C$12
Name ChannelList: OFFSET(Lists!$E$1,0,0,COUNTIF(Lists!$E$1:$E$40,"?*"),1)

Sheet Dashboard
B2: SCB Video Library
B3: =IF(Settings!$C$5="","","Last updated "&TEXT(Settings!$C$5,"d mmm yyyy h:mm AM/PM")&" · "&TODAY()-INT(Settings!$C$5)&" day(s) ago")
B4: =HYPERLINK("#Library!A1","Library") | C4: =HYPERLINK("#Queue!A1","Queue") | D4: =HYPERLINK("#Calendar!A1","Calendar") | E4: =HYPERLINK("#History!A1","History") | F4: =HYPERLINK("#Stats!A1","Stats") | G4: =HYPERLINK("#Channels!A1","Channels") | H4: =HYPERLINK("#Settings!A1","Settings")
B6: TOTAL VIDEOS | D6: WATCHED | F6: BACKLOG | H6: % WATCHED | J6: HOURS WATCHED | L6: HOURS REMAINING
B7: =Stats!C14 | D7: =Stats!D14 | F7: =Stats!E14+Stats!F14 | H7: =Stats!H14 | J7: =Stats!J14*24 | L7: =Stats!K14*24
B8: ="across "&6&" channels" | D8: ="of "&TEXT(Stats!C14-Stats!G14,"#,##0")&" tracked" | F8: =TEXT(Stats!E14,"#,##0")&" watch-later" | H8: =TEXT(Stats!L14,"0.0%")&" of runtime" | J8: ="of "&TEXT(Stats!I14*24,"#,##0")&" h total" | L8: ="≈ "&TEXT(Stats!K14,"#,##0")&" days of video"
B10: By channel
B11: Channel | E11: Videos | F11: Watched | G11: Backlog | H11: % Watched | I11: Time left | J11: Latest upload | L11: Days since
B12: =Stats!B8 | E12: =Stats!C8 | F12: =Stats!D8 | G12: =Stats!E8+Stats!F8 | H12: =Stats!H8 | I12: =Stats!K8 | J12: =Stats!D20 | L12: =IF(J12="","",TODAY()-J12)
B13: =Stats!B9 | E13: =Stats!C9 | F13: =Stats!D9 | G13: =Stats!E9+Stats!F9 | H13: =Stats!H9 | I13: =Stats!K9 | J13: =Stats!D21 | L13: =IF(J13="","",TODAY()-J13)
B14: =Stats!B10 | E14: =Stats!C10 | F14: =Stats!D10 | G14: =Stats!E10+Stats!F10 | H14: =Stats!H10 | I14: =Stats!K10 | J14: =Stats!D22 | L14: =IF(J14="","",TODAY()-J14)
B15: =Stats!B11 | E15: =Stats!C11 | F15: =Stats!D11 | G15: =Stats!E11+Stats!F11 | H15: =Stats!H11 | I15: =Stats!K11 | J15: =Stats!D23 | L15: =IF(J15="","",TODAY()-J15)
B16: =Stats!B12 | E16: =Stats!C12 | F16: =Stats!D12 | G16: =Stats!E12+Stats!F12 | H16: =Stats!H12 | I16: =Stats!K12 | J16: =Stats!D24 | L16: =IF(J16="","",TODAY()-J16)
B17: =Stats!B13 | E17: =Stats!C13 | F17: =Stats!D13 | G17: =Stats!E13+Stats!F13 | H17: =Stats!H13 | I17: =Stats!K13 | J17: =Stats!D25 | L17: =IF(J17="","",TODAY()-J17)
B18: All channels | E18: =Stats!C14 | F18: =Stats!D14 | G18: =Stats!E14+Stats!F14 | H18: =Stats!H14 | I18: =Stats!K14
B39: Up next - oldest unwatched video in each channel
B40: Channel | E40: Video | L40: Length | M40: Published
B41: =Channels!$C$6 | E41: =IF($O41="","All caught up ✓",IF(INDEX(tblVideos[Video ID],$O41)="",INDEX(tblVideos[Title],$O41),HYPERLINK("https://www.youtube.com/watch?v="&INDEX(tblVideos[Video ID],$O41),INDEX(tblVideos[Title],$O41)))) | L41: =IF($O41="","",INDEX(tblVideos[Length],$O41)) | M41: =IF($O41="","",INDEX(tblVideos[Day],$O41)) | O41: =IF(_xlfn.MINIFS(tblVideos[Seq],tblVideos[Channel ID],Channels!$E$6,tblVideos[Status],"Unwatched")=0,"",MATCH(_xlfn.MINIFS(tblVideos[Seq],tblVideos[Channel ID],Channels!$E$6,tblVideos[Status],"Unwatched"),tblVideos[Seq],0))
B42: =Channels!$C$7 | E42: =IF($O42="","All caught up ✓",IF(INDEX(tblVideos[Video ID],$O42)="",INDEX(tblVideos[Title],$O42),HYPERLINK("https://www.youtube.com/watch?v="&INDEX(tblVideos[Video ID],$O42),INDEX(tblVideos[Title],$O42)))) | L42: =IF($O42="","",INDEX(tblVideos[Length],$O42)) | M42: =IF($O42="","",INDEX(tblVideos[Day],$O42)) | O42: =IF(_xlfn.MINIFS(tblVideos[Seq],tblVideos[Channel ID],Channels!$E$7,tblVideos[Status],"Unwatched")=0,"",MATCH(_xlfn.MINIFS(tblVideos[Seq],tblVideos[Channel ID],Channels!$E$7,tblVideos[Status],"Unwatched"),tblVideos[Seq],0))
B43: =Channels!$C$8 | E43: =IF($O43="","All caught up ✓",IF(INDEX(tblVideos[Video ID],$O43)="",INDEX(tblVideos[Title],$O43),HYPERLINK("https://www.youtube.com/watch?v="&INDEX(tblVideos[Video ID],$O43),INDEX(tblVideos[Title],$O43)))) | L43: =IF($O43="","",INDEX(tblVideos[Length],$O43)) | M43: =IF($O43="","",INDEX(tblVideos[Day],$O43)) | O43: =IF(_xlfn.MINIFS(tblVideos[Seq],tblVideos[Channel ID],Channels!$E$8,tblVideos[Status],"Unwatched")=0,"",MATCH(_xlfn.MINIFS(tblVideos[Seq],tblVideos[Channel ID],Channels!$E$8,tblVideos[Status],"Unwatched"),tblVideos[Seq],0))
B44: =Channels!$C$9 | E44: =IF($O44="","All caught up ✓",IF(INDEX(tblVideos[Video ID],$O44)="",INDEX(tblVideos[Title],$O44),HYPERLINK("https://www.youtube.com/watch?v="&INDEX(tblVideos[Video ID],$O44),INDEX(tblVideos[Title],$O44)))) | L44: =IF($O44="","",INDEX(tblVideos[Length],$O44)) | M44: =IF($O44="","",INDEX(tblVideos[Day],$O44)) | O44: =IF(_xlfn.MINIFS(tblVideos[Seq],tblVideos[Channel ID],Channels!$E$9,tblVideos[Status],"Unwatched")=0,"",MATCH(_xlfn.MINIFS(tblVideos[Seq],tblVideos[Channel ID],Channels!$E$9,tblVideos[Status],"Unwatched"),tblVideos[Seq],0))
B45: =Channels!$C$10 | E45: =IF($O45="","All caught up ✓",IF(INDEX(tblVideos[Video ID],$O45)="",INDEX(tblVideos[Title],$O45),HYPERLINK("https://www.youtube.com/watch?v="&INDEX(tblVideos[Video ID],$O45),INDEX(tblVideos[Title],$O45)))) | L45: =IF($O45="","",INDEX(tblVideos[Length],$O45)) | M45: =IF($O45="","",INDEX(tblVideos[Day],$O45)) | O45: =IF(_xlfn.MINIFS(tblVideos[Seq],tblVideos[Channel ID],Channels!$E$10,tblVideos[Status],"Unwatched")=0,"",MATCH(_xlfn.MINIFS(tblVideos[Seq],tblVideos[Channel ID],Channels!$E$10,tblVideos[Status],"Unwatched"),tblVideos[Seq],0))
B46: =Channels!$C$11 | E46: =IF($O46="","All caught up ✓",IF(INDEX(tblVideos[Video ID],$O46)="",INDEX(tblVideos[Title],$O46),HYPERLINK("https://www.youtube.com/watch?v="&INDEX(tblVideos[Video ID],$O46),INDEX(tblVideos[Title],$O46)))) | L46: =IF($O46="","",INDEX(tblVideos[Length],$O46)) | M46: =IF($O46="","",INDEX(tblVideos[Day],$O46)) | O46: =IF(_xlfn.MINIFS(tblVideos[Seq],tblVideos[Channel ID],Channels!$E$11,tblVideos[Status],"Unwatched")=0,"",MATCH(_xlfn.MINIFS(tblVideos[Seq],tblVideos[Channel ID],Channels!$E$11,tblVideos[Status],"Unwatched"),tblVideos[Seq],0))
B49: Newest uploads
B50: Published | D50: Channel | F50: Title | L50: Length | M50: Status
B51: =IF($O51="","",INDEX(tblVideos[Day],$O51)) | D51: =IF($O51="","",INDEX(tblVideos[Channel],$O51)) | F51: =IF($O51="","",IF(INDEX(tblVideos[Video ID],$O51)="",INDEX(tblVideos[Title],$O51),HYPERLINK("https://www.youtube.com/watch?v="&INDEX(tblVideos[Video ID],$O51),INDEX(tblVideos[Title],$O51)))) | L51: =IF($O51="","",INDEX(tblVideos[Length],$O51)) | M51: =IF($O51="","",INDEX(tblVideos[Status],$O51)) | O51: =IFERROR(MATCH(MAX(tblVideos[Seq])-0,tblVideos[Seq],0),"")
B52: =IF($O52="","",INDEX(tblVideos[Day],$O52)) | D52: =IF($O52="","",INDEX(tblVideos[Channel],$O52)) | F52: =IF($O52="","",IF(INDEX(tblVideos[Video ID],$O52)="",INDEX(tblVideos[Title],$O52),HYPERLINK("https://www.youtube.com/watch?v="&INDEX(tblVideos[Video ID],$O52),INDEX(tblVideos[Title],$O52)))) | L52: =IF($O52="","",INDEX(tblVideos[Length],$O52)) | M52: =IF($O52="","",INDEX(tblVideos[Status],$O52)) | O52: =IFERROR(MATCH(MAX(tblVideos[Seq])-1,tblVideos[Seq],0),"")
B53: =IF($O53="","",INDEX(tblVideos[Day],$O53)) | D53: =IF($O53="","",INDEX(tblVideos[Channel],$O53)) | F53: =IF($O53="","",IF(INDEX(tblVideos[Video ID],$O53)="",INDEX(tblVideos[Title],$O53),HYPERLINK("https://www.youtube.com/watch?v="&INDEX(tblVideos[Video ID],$O53),INDEX(tblVideos[Title],$O53)))) | L53: =IF($O53="","",INDEX(tblVideos[Length],$O53)) | M53: =IF($O53="","",INDEX(tblVideos[Status],$O53)) | O53: =IFERROR(MATCH(MAX(tblVideos[Seq])-2,tblVideos[Seq],0),"")
B54: =IF($O54="","",INDEX(tblVideos[Day],$O54)) | D54: =IF($O54="","",INDEX(tblVideos[Channel],$O54)) | F54: =IF($O54="","",IF(INDEX(tblVideos[Video ID],$O54)="",INDEX(tblVideos[Title],$O54),HYPERLINK("https://www.youtube.com/watch?v="&INDEX(tblVideos[Video ID],$O54),INDEX(tblVideos[Title],$O54)))) | L54: =IF($O54="","",INDEX(tblVideos[Length],$O54)) | M54: =IF($O54="","",INDEX(tblVideos[Status],$O54)) | O54: =IFERROR(MATCH(MAX(tblVideos[Seq])-3,tblVideos[Seq],0),"")
B55: =IF($O55="","",INDEX(tblVideos[Day],$O55)) | D55: =IF($O55="","",INDEX(tblVideos[Channel],$O55)) | F55: =IF($O55="","",IF(INDEX(tblVideos[Video ID],$O55)="",INDEX(tblVideos[Title],$O55),HYPERLINK("https://www.youtube.com/watch?v="&INDEX(tblVideos[Video ID],$O55),INDEX(tblVideos[Title],$O55)))) | L55: =IF($O55="","",INDEX(tblVideos[Length],$O55)) | M55: =IF($O55="","",INDEX(tblVideos[Status],$O55)) | O55: =IFERROR(MATCH(MAX(tblVideos[Seq])-4,tblVideos[Seq],0),"")
B56: =IF($O56="","",INDEX(tblVideos[Day],$O56)) | D56: =IF($O56="","",INDEX(tblVideos[Channel],$O56)) | F56: =IF($O56="","",IF(INDEX(tblVideos[Video ID],$O56)="",INDEX(tblVideos[Title],$O56),HYPERLINK("https://www.youtube.com/watch?v="&INDEX(tblVideos[Video ID],$O56),INDEX(tblVideos[Title],$O56)))) | L56: =IF($O56="","",INDEX(tblVideos[Length],$O56)) | M56: =IF($O56="","",INDEX(tblVideos[Status],$O56)) | O56: =IFERROR(MATCH(MAX(tblVideos[Seq])-5,tblVideos[Seq],0),"")
B57: =IF($O57="","",INDEX(tblVideos[Day],$O57)) | D57: =IF($O57="","",INDEX(tblVideos[Channel],$O57)) | F57: =IF($O57="","",IF(INDEX(tblVideos[Video ID],$O57)="",INDEX(tblVideos[Title],$O57),HYPERLINK("https://www.youtube.com/watch?v="&INDEX(tblVideos[Video ID],$O57),INDEX(tblVideos[Title],$O57)))) | L57: =IF($O57="","",INDEX(tblVideos[Length],$O57)) | M57: =IF($O57="","",INDEX(tblVideos[Status],$O57)) | O57: =IFERROR(MATCH(MAX(tblVideos[Seq])-6,tblVideos[Seq],0),"")
B58: =IF($O58="","",INDEX(tblVideos[Day],$O58)) | D58: =IF($O58="","",INDEX(tblVideos[Channel],$O58)) | F58: =IF($O58="","",IF(INDEX(tblVideos[Video ID],$O58)="",INDEX(tblVideos[Title],$O58),HYPERLINK("https://www.youtube.com/watch?v="&INDEX(tblVideos[Video ID],$O58),INDEX(tblVideos[Title],$O58)))) | L58: =IF($O58="","",INDEX(tblVideos[Length],$O58)) | M58: =IF($O58="","",INDEX(tblVideos[Status],$O58)) | O58: =IFERROR(MATCH(MAX(tblVideos[Seq])-7,tblVideos[Seq],0),"")
B59: =IF($O59="","",INDEX(tblVideos[Day],$O59)) | D59: =IF($O59="","",INDEX(tblVideos[Channel],$O59)) | F59: =IF($O59="","",IF(INDEX(tblVideos[Video ID],$O59)="",INDEX(tblVideos[Title],$O59),HYPERLINK("https://www.youtube.com/watch?v="&INDEX(tblVideos[Video ID],$O59),INDEX(tblVideos[Title],$O59)))) | L59: =IF($O59="","",INDEX(tblVideos[Length],$O59)) | M59: =IF($O59="","",INDEX(tblVideos[Status],$O59)) | O59: =IFERROR(MATCH(MAX(tblVideos[Seq])-8,tblVideos[Seq],0),"")
B60: =IF($O60="","",INDEX(tblVideos[Day],$O60)) | D60: =IF($O60="","",INDEX(tblVideos[Channel],$O60)) | F60: =IF($O60="","",IF(INDEX(tblVideos[Video ID],$O60)="",INDEX(tblVideos[Title],$O60),HYPERLINK("https://www.youtube.com/watch?v="&INDEX(tblVideos[Video ID],$O60),INDEX(tblVideos[Title],$O60)))) | L60: =IF($O60="","",INDEX(tblVideos[Length],$O60)) | M60: =IF($O60="","",INDEX(tblVideos[Status],$O60)) | O60: =IFERROR(MATCH(MAX(tblVideos[Seq])-9,tblVideos[Seq],0),"")

Sheet Library
A1: Video Library
A2: Slate columns come from YouTube and are refreshed by the updater. Teal columns are calculated. Gold columns (Mark, Watched On, Notes) are YOURS and are never overwritten.
A3: =HYPERLINK("#Dashboard!A1","◄ Dashboard")
A5: Open | B5: Status | C5: Mark | D5: Watched On | E5: Published | F5: Channel | G5: Title | H5: Length | I5: Views | J5: Likes | K5: Comments | L5: Notes | M5: Video ID | N5: Channel ID | O5: Published UTC | P5: Day | Q5: Seq | R5: Availability | S5: First Seen | T5: Last Seen | U5: Description | V5: Cal Key | W5: Queue Key
A6: =IF(M6="","",HYPERLINK("https://www.youtube.com/watch?v="&M6,"▶")) | B6: =IF(C6<>"",C6,IF(P6<=IFERROR(INDEX(tblChannels[Watched Through],MATCH(N6,tblChannels[Channel ID],0)),0),"Watched","Unwatched")) | E6: 46297.417 | F6: Popcorn Culture | G6: Top 100 TV Shows! | Popcorn Culture | H6: 0.077893519 | I6: 209 | J6: 16 | K6: 7 | N6: UCHfIbq9thHPC8yrKjAdJgDA | O6: 46297.583 | P6: 46297 | Q6: 3262 | R6: No Video ID yet | U6: In the 356th episode of the Pop, Ben and J discuss victorious sports, nervous tics, evolution of technology, and the NYT 100 Best TV Shows of the 21st Century. NYT 100 Top Shows List - | V6: =IF(AND(P6>=Calendar!$K$2,P6<EDATE(Calendar!$K$2,1),OR(Calendar!$K$4="*",N6=Calendar!$K$4)),P6*100+COUNTIFS($P$6:$P$3267,P6,$Q$6:$Q$3267,"<="&Q6,$N$6:$N$3267,Calendar!$K$4),"") | W6: =IF(AND(B6=Queue!$C$4,OR(Queue!$K$4="*",N6=Queue!$K$4)),Q6,"")
A7: =IF(M7="","",HYPERLINK("https://www.youtube.com/watch?v="&M7,"▶")) | B7: =IF(C7<>"",C7,IF(P7<=IFERROR(INDEX(tblChannels[Watched Through],MATCH(N7,tblChannels[Channel ID],0)),0),"Watched","Unwatched")) | E7: 46295.649 | F7: Super Carlin Brothers | G7: Slughorn’s SECRET Son Revealed | H7: 0.011087963 | I7: 62777 | J7: 1573 | K7: 250 | N7: UCKZo4N0lVPccBkSiuyVh4yg | O7: 46295.815 | P7: 46295 | Q7: 3261 | R7: No Video ID yet | U7: This episode is sponsored by Factor – Head to and use code super50off to get 50% off and 1 free breakfast item per box for 1 year. This episode is sponsored by Raycon – Go to to get 20% off. Today J dives into Horace Slughorn’s memory to find out if he had a secret son hiding in plain sight this whole time. Who was the obsessive love he warns about in potions class? What does it have to do with the Crouch family and was Barty Crouch screaming the truth at us this whole time?! #HarryPotter #supercarlinbrothers | V7: =IF(AND(P7>=Calendar!$K$2,P7<EDATE(Calendar!$K$2,1),OR(Calendar!$K$4="*",N7=Calendar!$K$4)),P7*100+COUNTIFS($P$6:$P$3267,P7,$Q$6:$Q$3267,"<="&Q7,$N$6:$N$3267,Calendar!$K$4),"") | W7: =IF(AND(B7=Queue!$C$4,OR(Queue!$K$4="*",N7=Queue!$K$4)),Q7,"")
A8: =IF(M8="","",HYPERLINK("https://www.youtube.com/watch?v="&M8,"▶")) | B8: =IF(C8<>"",C8,IF(P8<=IFERROR(INDEX(tblChannels[Watched Through],MATCH(N8,tblChannels[Channel ID],0)),0),"Watched","Unwatched")) | E8: 46292.417 | F8: Through The Griffin Door | G8: Chapter 15: The Unbreakable Vow | Half-Blood Prince | H8: 0.076793981 | I8: 41173 | J8: 692 | K8: 303 | N8: UCEscP6ETYXWSSvsNrDHekMQ | O8: 46292.583 | P8: 46292 | Q8: 3260 | R8: No Video ID yet | U8: This episode is sponsored by Shopify – Go to shopify.com/griffin to start your free trial! Taking care of your health just got easier – start here with Zocdoc: Join J and Ben as they dive into Chapter 15 of the Half Blood Prince and discuss mistletoe and snogging, finding the name of Charms, everlasting elixirs, a ridiculous Madame Pince moment, cute Harmione moments, Harry going to the party with Luna, Draco getting caught, strawfangs, and Snape and Malfoy’s secret discussion. 05:45 - Chapter Breakdown 59:48 - Ad Break (Shopify & ZocDoc) 1:02:57 - More Chapter Breakdown 1:43:16 - Closing Thoughts and Review | V8: =IF(AND(P8>=Calendar!$K$2,P8<EDATE(Calendar!$K$2,1),OR(Calendar!$K$4="*",N8=Calendar!$K$4)),P8*100+COUNTIFS($P$6:$P$3267,P8,$Q$6:$Q$3267,"<="&Q8,$N$6:$N$3267,Calendar!$K$4),"") | W8: =IF(AND(B8=Queue!$C$4,OR(Queue!$K$4="*",N8=Queue!$K$4)),Q8,"")
A9: =IF(M9="","",HYPERLINK("https://www.youtube.com/watch?v="&M9,"▶")) | B9: =IF(C9<>"",C9,IF(P9<=IFERROR(INDEX(tblChannels[Watched Through],MATCH(N9,tblChannels[Channel ID],0)),0),"Watched","Unwatched")) | E9: 46290.682 | F9: Super Carlin Brothers | G9: J vs Ben: How Well Do We Know The Boy Who Lived (MAX DIFFICULTY) | H9: 0.034791667 | I9: 102063 | J9: 1791 | K9: 297 | N9: UCKZo4N0lVPccBkSiuyVh4yg | O9: 46290.849 | P9: 46290 | Q9: 3259 | R9: No Video ID yet | U9: This video is sponsored by Proton VPN – go to to get 70% off a two year plan. This video is also sponsored by Faire – Sign up today and get 50% off your first wholesale order, up to $100 at Today J and Ben face off once more to find out who knows more about The Boy Who Lived, The Chosen One: Harry Potter. As the main character, questions about Harry could come from ANYWHERE and span all 7 books - Have our Quiz Masters managed to stump the guys? Special Thanks to these Quiz Masters: Fate3841, Firemon6000, Hermione Baggins, Mercedes, MrTeacher, Kellbell, Peyton Taylor, Elizabeth Potter, Tina's Hotdog Sophie, TrexDog, Julie Sherwood, LifeIsLavely, Crafty Lizard, Teghan Denlinger, Denise, Bradferd, Elfish Princess Hosted by: Kat Stine | V9: =IF(AND(P9>=Calendar!$K$2,P9<EDATE(Calendar!$K$2,1),OR(Calendar!$K$4="*",N9=Calendar!$K$4)),P9*100+COUNTIFS($P$6:$P$3267,P9,$Q$6:$Q$3267,"<="&Q9,$N$6:$N$3267,Calendar!$K$4),"") | W9: =IF(AND(B9=Queue!$C$4,OR(Queue!$K$4="*",N9=Queue!$K$4)),Q9,"")
A10: =IF(M10="","",HYPERLINK("https://www.youtube.com/watch?v="&M10,"▶")) | B10: =IF(C10<>"",C10,IF(P10<=IFERROR(INDEX(tblChannels[Watched Through],MATCH(N10,tblChannels[Channel ID],0)),0),"Watched","Unwatched")) | E10: 46290.417 | F10: Popcorn Culture | G10: Tour in a Podshell | Popcorn Culture | H10: 0.047337963 | I10: 3615 | J10: 90 | K10: 18 | N10: UCHfIbq9thHPC8yrKjAdJgDA | O10: 46290.583 | P10: 46290 | Q10: 3258 | R10: No Video ID yet | U10: In the 355th episode of the Pod, Ben and J discuss all things TOUR: getting locked out of the van, an amazing Boston show, Hartford being AN place, the magic of New York, the race to the finish line and many special moments in between. Lolita - | V10: =IF(AND(P10>=Calendar!$K$2,P10<EDATE(Calendar!$K$2,1),OR(Calendar!$K$4="*",N10=Calendar!$K$4)),P10*100+COUNTIFS($P$6:$P$3267,P10,$Q$6:$Q$3267,"<="&Q10,$N$6:$N$3267,Calendar!$K$4),"") | W10: =IF(AND(B10=Queue!$C$4,OR(Queue!$K$4="*",N10=Queue!$K$4)),Q10,"")
A11: =IF(M11="","",HYPERLINK("https://www.youtube.com/watch?v="&M11,"▶")) | B11: =IF(C11<>"",C11,IF(P11<=IFERROR(INDEX(tblChannels[Watched Through],MATCH(N11,tblChannels[Channel ID],0)),0),"Watched","Unwatched")) | E11: 46289.653 | F11: Popcorn Culture | G11: Mr. Ben's Worst Day Ever | Popcorn Culture | H11: 0.0026273148 | I11: 2235 | J11: 118 | K11: 27 | N11: UCHfIbq9thHPC8yrKjAdJgDA | O11: 46289.82 | P11: 46289 | Q11: 3257 | R11: No Video ID yet | U11: You know that feeling when the universe is determined to make your own life hard for you? Yeah! That. Watch the full episode: Animated by: Isybelle Christley | V11: =IF(AND(P11>=Calendar!$K$2,P11<EDATE(Calendar!$K$2,1),OR(Calendar!$K$4="*",N11=Calendar!$K$4)),P11*100+COUNTIFS($P$6:$P$3267,P11,$Q$6:$Q$3267,"<="&Q11,$N$6:$N$3267,Calendar!$K$4),"") | W11: =IF(AND(B11=Queue!$C$4,OR(Queue!$K$4="*",N11=Queue!$K$4)),Q11,"")
A12: =IF(M12="","",HYPERLINK("https://www.youtube.com/watch?v="&M12,"▶")) | B12: =IF(C12<>"",C12,IF(P12<=IFERROR(INDEX(tblChannels[Watched Through],MATCH(N12,tblChannels[Channel ID],0)),0),"Watched","Unwatched")) | E12: 46288.674 | F12: Super Carlin Brothers | G12: Slughorn’s SECRET Role In Creating Voldemort | H12: 0.011018519 | I12: 188618 | J12: 3039 | K12: 280 | N12: UCKZo4N0lVPccBkSiuyVh4yg | O12: 46288.841 | P12: 46288 | Q12: 3256 | R12: No Video ID yet | U12: This show is sponsored by BetterHelp. Go to to get 10% off your first month. Head to and use code super50off to get 50% off and 1 free breakfast item per box for 1 year. What if Slughorn’s role in Voldemort’s story began long before he explained Horcruxes to Tom Riddle? Today Ben dives into the Wizarding World of Harry Potter and Voldemort’s past. From Merope Gaunt and the Slug Club to Tom’s first connections at Hogwarts, we’re tracing a theory that puts Horace Slughorn at nearly every turning point in Voldemort’s rise. Then there’s a strange run of luck involving Harry, the Half-Blood Prince’s potion book, and Felix Felicis that may have helped bring Voldemort down. Did Slughorn accidentally help create the Dark Lord and give Harry the means to defeat him? Let’s dive on in! | V12: =IF(AND(P12>=Calendar!$K$2,P12<EDATE(Calendar!$K$2,1),OR(Calendar!$K$4="*",N12=Calendar!$K$4)),P12*100+COUNTIFS($P$6:$P$3267,P12,$Q$6:$Q$3267,"<="&Q12,$N$6:$N$3267,Calendar!$K$4),"") | W12: =IF(AND(B12=Queue!$C$4,OR(Queue!$K$4="*",N12=Queue!$K$4)),Q12,"")
A13: =IF(M13="","",HYPERLINK("https://www.youtube.com/watch?v="&M13,"▶")) | B13: =IF(C13<>"",C13,IF(P13<=IFERROR(INDEX(tblChannels[Watched Through],MATCH(N13,tblChannels[Channel ID],0)),0),"Watched","Unwatched")) | E13: 46285.417 | F13: Through The Griffin Door | G13: The Owlery Special Part 5! | H13: 0.054189815 | I13: 25554 | J13: 452 | K13: 122 | N13: UCEscP6ETYXWSSvsNrDHekMQ | O13: 46285.583 | P13: 46285 | Q13: 3255 | R13: No Video ID yet | U13: Join J and Ben as they dive into YOUR QUESTIONS and answer the questions: How EXACTLY does the Unbreakable Vow work? What would have changed if Sirius just picked up Voldy's wand in the Godric's Hollow wreckage? Is Peter Pettigrew actually INCREDIBLY powerful? Do you want to have your questions answered on a future episode of The Owlery? Support us on Patreon: 02:12 - Question 1 27:08 - Question 2 53:40 - Question 3 Edited by :: Ethan Edghill and Isybelle Christley | V13: =IF(AND(P13>=Calendar!$K$2,P13<EDATE(Calendar!$K$2,1),OR(Calendar!$K$4="*",N13=Calendar!$K$4)),P13*100+COUNTIFS($P$6:$P$3267,P13,$Q$6:$Q$3267,"<="&Q13,$N$6:$N$3267,Calendar!$K$4),"") | W13: =IF(AND(B13=Queue!$C$4,OR(Queue!$K$4="*",N13=Queue!$K$4)),Q13,"")
A14: =IF(M14="","",HYPERLINK("https://www.youtube.com/watch?v="&M14,"▶")) | B14: =IF(C14<>"",C14,IF(P14<=IFERROR(INDEX(tblChannels[Watched Through],MATCH(N14,tblChannels[Channel ID],0)),0),"Watched","Unwatched")) | E14: 46283.625 | F14: Super Carlin Brothers | G14: J & Ben VS AI - Harry Potter Trivia | H14: 0.031261574 | I14: 115261 | J14: 2389 | K14: 450 | N14: UCKZo4N0lVPccBkSiuyVh4yg | O14: 46283.792 | P14: 46283 | Q14: 3254 | R14: No Video ID yet | U14: Today J and Ben join forces to take down Artificial Intelligence as they compete with ChatGPT in Harry Potter Trivia. AI might be able to read all 7 books in 3 seconds… but can it remember which kids Voldemort brought to the cave? Which Weasley went through platform 9 ¾ first? Play Along With Us :: | V14: =IF(AND(P14>=Calendar!$K$2,P14<EDATE(Calendar!$K$2,1),OR(Calendar!$K$4="*",N14=Calendar!$K$4)),P14*100+COUNTIFS($P$6:$P$3267,P14,$Q$6:$Q$3267,"<="&Q14,$N$6:$N$3267,Calendar!$K$4),"") | W14: =IF(AND(B14=Queue!$C$4,OR(Queue!$K$4="*",N14=Queue!$K$4)),Q14,"")
A15: =IF(M15="","",HYPERLINK("https://www.youtube.com/watch?v="&M15,"▶")) | B15: =IF(C15<>"",C15,IF(P15<=IFERROR(INDEX(tblChannels[Watched Through],MATCH(N15,tblChannels[Channel ID],0)),0),"Watched","Unwatched")) | E15: 46283.417 | F15: Popcorn Culture | G15: The Roanoke Bracket | Popcorn Culture | H15: 0.050405093 | I15: 3167 | J15: 96 | K15: 22 | N15: UCHfIbq9thHPC8yrKjAdJgDA | O15: 46283.583 | P15: 46283 | Q15: 3253 | R15: No Video ID yet | U15: In the 354th episode of the PopBen and J discuss tour prep, a Roanoke this or that, camaraderie of sports, buying a movie theater, classic Hollywood stories, and CGI Bluey. CGI Bluey Trailer - 2D vs CGI 00:00 - Intro, Tour Prep 01:37 - Improving Roanoke 46:57 - Bringing Back the Oldies 56:40 - CGI Bluey | V15: =IF(AND(P15>=Calendar!$K$2,P15<EDATE(Calendar!$K$2,1),OR(Calendar!$K$4="*",N15=Calendar!$K$4)),P15*100+COUNTIFS($P$6:$P$3267,P15,$Q$6:$Q$3267,"<="&Q15,$N$6:$N$3267,Calendar!$K$4),"") | W15: =IF(AND(B15=Queue!$C$4,OR(Queue!$K$4="*",N15=Queue!$K$4)),Q15,"")
A16: =IF(M16="","",HYPERLINK("https://www.youtube.com/watch?v="&M16,"▶")) | B16: =IF(C16<>"",C16,IF(P16<=IFERROR(INDEX(tblChannels[Watched Through],MATCH(N16,tblChannels[Channel ID],0)),0),"Watched","Unwatched")) | E16: 46281.625 | F16: Super Carlin Brothers | G16: Theories From A Hat: Defending MORE Wild Harry Potter Theories | H16: 0.0271875 | I16: 104475 | J16: 1972 | K16: 409 | N16: UCKZo4N0lVPccBkSiuyVh4yg | O16: 46281.792 | P16: 46281 | Q16: 3252 | R16: No Video ID yet | U16: This show is sponsored by BetterHelp – Go to Today J and Ben are diving into the magical Theory Hat once more to draw and defend your craziest, worst and funniest Harry Potter theories on the fly! Was Snape ACTUALLY in love with James? Did Moody create a Horcrux? Is Felix Felicis just bourbon? Was Hermione secretly in love with Harry?? #HarryPotter #supercarlinbrothers | V16: =IF(AND(P16>=Calendar!$K$2,P16<EDATE(Calendar!$K$2,1),OR(Calendar!$K$4="*",N16=Calendar!$K$4)),P16*100+COUNTIFS($P$6:$P$3267,P16,$Q$6:$Q$3267,"<="&Q16,$N$6:$N$3267,Calendar!$K$4),"") | W16: =IF(AND(B16=Queue!$C$4,OR(Queue!$K$4="*",N16=Queue!$K$4)),Q16,"")
A17: =IF(M17="","",HYPERLINK("https://www.youtube.com/watch?v="&M17,"▶")) | B17: =IF(C17<>"",C17,IF(P17<=IFERROR(INDEX(tblChannels[Watched Through],MATCH(N17,tblChannels[Channel ID],0)),0),"Watched","Unwatched")) | E17: 46278.476 | F17: Through The Griffin Door | G17: Chapter 14: Felix Felicis | Half-Blood Prince | H17: 0.079710648 | I17: 38643 | J17: 813 | K17: 243 | N17: UCEscP6ETYXWSSvsNrDHekMQ | O17: 46278.642 | P17: 46278 | Q17: 3251 | R17: No Video ID yet | U17: This episode is sponsored by Shopify – Go to shopify.com/griffin to start your free trial! Join J and Ben as they dive into Chapter 14 of the Half Blood Prince and discuss “weird mist”, new Voldemort “lore”, Neville crushing herbology, gross plants, the snogging conflict with Ginny, Harry’s placebo plan, Hermione’s fumble, and the beginning of WonWon and LavLav. 5:53- Chapter Breakdown 52:52 - Ad Break (Shopify) 54:33 - More Chapter Breakdown 1:41:11- Closing Thoughts and Review | V17: =IF(AND(P17>=Calendar!$K$2,P17<EDATE(Calendar!$K$2,1),OR(Calendar!$K$4="*",N17=Calendar!$K$4)),P17*100+COUNTIFS($P$6:$P$3267,P17,$Q$6:$Q$3267,"<="&Q17,$N$6:$N$3267,Calendar!$K$4),"") | W17: =IF(AND(B17=Queue!$C$4,OR(Queue!$K$4="*",N17=Queue!$K$4)),Q17,"")
... A202: =IF(M202="","",HYPERLINK("https://www.youtube.com/watch?v="&M202,"▶")) | B202: =IF(C202<>"",C202,IF(P202<=IFERROR(INDEX(tblChannels[Watched Through],MATCH(N202,tblChannels[Channel ID],0)),0),"Watched","Unwatched")) | E202: 45988.542 | F202: Super Carlin Brothers | G202: J vs Ben: Goblet of Fire QUIZ Returns! (THERMAGEDDON 🔥 2.6 Million Scovilles!) | H202: 0.044456019 | I202: 103849 | J202: 3904 | K202: 513 | N202: UCKZo4N0lVPccBkSiuyVh4yg | O202: 45988.75 | P202: 45988 | Q202: 3066 | R202: No Video ID yet | U202: Exclusive $45-off Carver Mat at Promo Code SCB Happy Thanksgiving, everyone! It’s time again for the annual Super Carlin Brothers Goblet of Fire Quiz — but this year we’ve turned the heat ALL the way up. Every wrong answer? Eat a wing covered in over 2.6 million Scovilles of molten thermageddon. Think you know Harry Potter and the Goblet of Fire? Play along and see if YOU can answer these questions before J & Ben melt into puddles of spicy regret.. #HarryPotter #SuperCarlinBrothers #JvsBen Written by: The Quizmasters! Hosted by: Kat Stine, Isybelle Christley and Ethan Edghill 🎟️ Through the Griffin Door LIVE Tour— Southwest 2025 | V202: =IF(AND(P202>=Calendar!$K$2,P202<EDATE(Calendar!$K$2,1),OR(Calendar!$K$4="*",N202=Calendar!$K$4)),P202*100+COUNTIFS($P$6:$P$3267,P202,$Q$6:$Q$3267,"<="&Q202,$N$6:$N$3267,Calendar!$K$4),"") | W202: =IF(AND(B202=Queue!$C$4,OR(Queue!$K$4="*",N202=Queue!$K$4)),Q202,"")
A203: =IF(M203="","",HYPERLINK("https://www.youtube.com/watch?v="&M203,"▶")) | B203: =IF(C203<>"",C203,IF(P203<=IFERROR(INDEX(tblChannels[Watched Through],MATCH(N203,tblChannels[Channel ID],0)),0),"Watched","Unwatched")) | E203: 45987.631 | F203: Super Carlin Brothers | G203: The VEIL Created the Deathly Hallows?! | Harry Potter Theory | H203: 0.011956019 | I203: 91853 | J203: 4079 | K203: 438 | N203: UCKZo4N0lVPccBkSiuyVh4yg | O203: 45987.84 | P203: 45987 | Q203: 3065 | R203: No Video ID yet | V203: =IF(AND(P203>=Calendar!$K$2,P203<EDATE(Calendar!$K$2,1),OR(Calendar!$K$4="*",N203=Calendar!$K$4)),P203*100+COUNTIFS($P$6:$P$3267,P203,$Q$6:$Q$3267,"<="&Q203,$N$6:$N$3267,Calendar!$K$4),"") | W203: =IF(AND(B203=Queue!$C$4,OR(Queue!$K$4="*",N203=Queue!$K$4)),Q203,"")
A204: =IF(M204="","",HYPERLINK("https://www.youtube.com/watch?v="&M204,"▶")) | B204: =IF(C204<>"",C204,IF(P204<=IFERROR(INDEX(tblChannels[Watched Through],MATCH(N204,tblChannels[Channel ID],0)),0),"Watched","Unwatched")) | E204: 45987.625 | F204: Through The Griffin Door | G204: Live in Cleveland - Chapter 13: Detention with Dolores | Order of the Phoenix | H204: 0.05125 | I204: 6440 | J204: 254 | K204: 79 | N204: UCEscP6ETYXWSSvsNrDHekMQ | O204: 45987.833 | P204: 45987 | Q204: 3064 | R204: No Video ID yet | U204: Join J and Ben as they dive BACK into Chapter 13 of Order of the Phoenix LIVE IN CLEVELAND! Harry jumping down EVERYONE'S throats (again), the RIDICULOUS amount of information Draco has compared to Harry, and the literal torture session Umbridge puts him through. | V204: =IF(AND(P204>=Calendar!$K$2,P204<EDATE(Calendar!$K$2,1),OR(Calendar!$K$4="*",N204=Calendar!$K$4)),P204*100+COUNTIFS($P$6:$P$3267,P204,$Q$6:$Q$3267,"<="&Q204,$N$6:$N$3267,Calendar!$K$4),"") | W204: =IF(AND(B204=Queue!$C$4,OR(Queue!$K$4="*",N204=Queue!$K$4)),Q204,"")
A205: =IF(M205="","",HYPERLINK("https://www.youtube.com/watch?v="&M205,"▶")) | B205: =IF(C205<>"",C205,IF(P205<=IFERROR(INDEX(tblChannels[Watched Through],MATCH(N205,tblChannels[Channel ID],0)),0),"Watched","Unwatched")) | E205: 45984.417 | F205: Through The Griffin Door | G205: Chapter 13: Detention with Dolores | Order of the Phoenix | H205: 0.091747685 | I205: 53370 | J205: 1250 | K205: 475 | N205: UCEscP6ETYXWSSvsNrDHekMQ | O205: 45984.626 | P205: 45984 | Q205: 3063 | R205: No Video ID yet | U205: This episode is sponsored by MasterClass – Our listeners get an additional 15% off any annual membership at Join J and Ben as they dive into Chapter 13 of the Order of the Phoenix and discuss Hermione’s perspective, the twins testing on first years, Ronmione moments, better teachers, bowtruckles, Draco knowing about Hagrid, Angelina freaking out about tryouts, the detention from hell and Harry finally finding out about Ron wanting to play Quidditch. Why Neville is ACTUALLY a Samurai - Last Year’s Goblet of FIRE - 09:08 - Chapter Breakdown 1:04:41 - Ad Break (Masterclass) 1:06:16 - More Chapter Breakdown 2:01:01 - Closing Thoughts and Review | V205: =IF(AND(P205>=Calendar!$K$2,P205<EDATE(Calendar!$K$2,1),OR(Calendar!$K$4="*",N205=Calendar!$K$4)),P205*100+COUNTIFS($P$6:$P$3267,P205,$Q$6:$Q$3267,"<="&Q205,$N$6:$N$3267,Calendar!$K$4),"") | W205: =IF(AND(B205=Queue!$C$4,OR(Queue!$K$4="*",N205=Queue!$K$4)),Q205,"")
A206: =IF(M206="","",HYPERLINK("https://www.youtube.com/watch?v="&M206,"▶")) | B206: =IF(C206<>"",C206,IF(P206<=IFERROR(INDEX(tblChannels[Watched Through],MATCH(N206,tblChannels[Channel ID],0)),0),"Watched","Unwatched")) | E206: 45982.685 | F206: Super Carlin Brothers | G206: The Defense Against the Dark Arts Curse EXPLAINED | Harry Potter | H206: 0.010925926 | I206: 85056 | J206: 3669 | K206: 448 | N206: UCKZo4N0lVPccBkSiuyVh4yg | O206: 45982.894 | P206: 45982 | Q206: 3062 | R206: No Video ID yet | U206: This episode is sponsored by BetterHelp – Go to to get 10% off your first month. Today Ben dives into the Wizarding World of Harry Potter to break down one of the most quietly devastating moves Tom Riddle ever made: the infamous Defense Against the Dark Arts Curse. From the snowy night he returned to Hogwarts to hide the diadem, to the ripple effects that shaped entire generations of undertrained witches and wizards, this “petty revenge curse” may actually be Voldemort’s most effective long-term strategy in the entire series. #HarryPotter #SuperCarlinBrothers #JvsBen | V206: =IF(AND(P206>=Calendar!$K$2,P206<EDATE(Calendar!$K$2,1),OR(Calendar!$K$4="*",N206=Calendar!$K$4)),P206*100+COUNTIFS($P$6:$P$3267,P206,$Q$6:$Q$3267,"<="&Q206,$N$6:$N$3267,Calendar!$K$4),"") | W206: =IF(AND(B206=Queue!$C$4,OR(Queue!$K$4="*",N206=Queue!$K$4)),Q206,"")
A207: =IF(M207="","",HYPERLINK("https://www.youtube.com/watch?v="&M207,"▶")) | B207: =IF(C207<>"",C207,IF(P207<=IFERROR(INDEX(tblChannels[Watched Through],MATCH(N207,tblChannels[Channel ID],0)),0),"Watched","Unwatched")) | E207: 45982.417 | F207: Popcorn Culture | G207: Casually Castle Shopping | Popcorn Culture | H207: 0.057604167 | I207: 3375 | J207: 145 | K207: 19 | N207: UCHfIbq9thHPC8yrKjAdJgDA | O207: 45982.625 | P207: 45982 | Q207: 3061 | R207: No Video ID yet | U207: In the 311th episode of the Pop, Ben and J discuss Ben’s new ink, the CRAZY economy of scale in California, iron ore hunting, techno-babble, and rental car woes. The Social Network - | V207: =IF(AND(P207>=Calendar!$K$2,P207<EDATE(Calendar!$K$2,1),OR(Calendar!$K$4="*",N207=Calendar!$K$4)),P207*100+COUNTIFS($P$6:$P$3267,P207,$Q$6:$Q$3267,"<="&Q207,$N$6:$N$3267,Calendar!$K$4),"") | W207: =IF(AND(B207=Queue!$C$4,OR(Queue!$K$4="*",N207=Queue!$K$4)),Q207,"")
A208: =IF(M208="","",HYPERLINK("https://www.youtube.com/watch?v="&M208,"▶")) | B208: =IF(C208<>"",C208,IF(P208<=IFERROR(INDEX(tblChannels[Watched Through],MATCH(N208,tblChannels[Channel ID],0)),0),"Watched","Unwatched")) | E208: 45980.702 | F208: Super Carlin Brothers | G208: J vs Ben: MAX DIFFICULTY Order of the Phoenix Open Book Harry Potter Trivia | H208: 0.035844907 | I208: 82201 | J208: 2839 | K208: 345 | N208: UCKZo4N0lVPccBkSiuyVh4yg | O208: 45980.91 | P208: 45980 | Q208: 3060 | R208: No Video ID yet | U208: Go to now to Get 10 Free Meals + a Free Item for Life! Today J and Ben go head-to-head in a MAX DIFFICULTY Order of the Phoenix Open Book Harry Potter Quiz — and this one is BRUTAL. From Tonks’ broomstick to the Black Family motto, giants, Sturgis Podmore, and MORE… this quiz goes deeper into OOTP than ever before. Think YOU can beat us? Grab your copy of Order of the Phoenix and play along — and don’t forget to submit YOUR questions for next week’s quiz! Special Thanks to our Quiz Masters: Ryan Silveira, Sam Shunpike, magicalmisfires, GooeyChewie, GenKenobi, tinas_hotdog_sophie, Big D aka the Songwriter, Bracelet Liz, Oryan’s Wizard Parts, CJ, MaddstheHatter, Teghan - Denlinger, Bunny, Mia Likes Nougat, Jessica Theirault, Bradferd, Captain Hawk, Drawing Xaos, and Tara Walker. #HarryPotter #SuperCarlinBrothers #JvsBen | V208: =IF(AND(P208>=Calendar!$K$2,P208<EDATE(Calendar!$K$2,1),OR(Calendar!$K$4="*",N208=Calendar!$K$4)),P208*100+COUNTIFS($P$6:$P$3267,P208,$Q$6:$Q$3267,"<="&Q208,$N$6:$N$3267,Calendar!$K$4),"") | W208: =IF(AND(B208=Queue!$C$4,OR(Queue!$K$4="*",N208=Queue!$K$4)),Q208,"")
A209: =IF(M209="","",HYPERLINK("https://www.youtube.com/watch?v="&M209,"▶")) | B209: =IF(C209<>"",C209,IF(P209<=IFERROR(INDEX(tblChannels[Watched Through],MATCH(N209,tblChannels[Channel ID],0)),0),"Watched","Unwatched")) | E209: 45977.417 | F209: Through The Griffin Door | G209: Live in Detroit - Chapter 12: Professor Umbridge | Order Of The Phoenix | H209: 0.054988426 | I209: 10837 | J209: 442 | K209: 117 | N209: UCEscP6ETYXWSSvsNrDHekMQ | O209: 45977.626 | P209: 45977 | Q209: 3059 | R209: No Video ID yet | U209: Join J and Ben as they dive BACK into Chapter 12 of Order of the Phoenix LIVE IN DETROIT! You’re getting the live on Sunday this week cause Ben is ILL. But in this episode J and Ben discuss why Harry is being a real pr… I mean Mimbulus Mimbletonia, Ron’s poor attempts to drop hints about wanting to play quidditch, and how Harry gets just SO much detention… that we don’t even get to read about until next week!! | V209: =IF(AND(P209>=Calendar!$K$2,P209<EDATE(Calendar!$K$2,1),OR(Calendar!$K$4="*",N209=Calendar!$K$4)),P209*100+COUNTIFS($P$6:$P$3267,P209,$Q$6:$Q$3267,"<="&Q209,$N$6:$N$3267,Calendar!$K$4),"") | W209: =IF(AND(B209=Queue!$C$4,OR(Queue!$K$4="*",N209=Queue!$K$4)),Q209,"")
A210: =IF(M210="","",HYPERLINK("https://www.youtube.com/watch?v="&M210,"▶")) | B210: =IF(C210<>"",C210,IF(P210<=IFERROR(INDEX(tblChannels[Watched Through],MATCH(N210,tblChannels[Channel ID],0)),0),"Watched","Unwatched")) | E210: 45976.417 | F210: Super Carlin Brothers | G210: Through the Griffin Door Supercut: Order of the Phoenix Chapters 10-12 | H210: 0.22894676 | I210: 10206 | J210: 206 | K210: 24 | N210: UCKZo4N0lVPccBkSiuyVh4yg | O210: 45976.625 | P210: 45976 | Q210: 3058 | R210: No Video ID yet | U210: 00:00:00 - Chapter 10: Luna Lovegood 1:46:34 - Chapter 11: The Sorting Hat's New Song 3:41:18 - Chapter 12: Professor Umbridge | V210: =IF(AND(P210>=Calendar!$K$2,P210<EDATE(Calendar!$K$2,1),OR(Calendar!$K$4="*",N210=Calendar!$K$4)),P210*100+COUNTIFS($P$6:$P$3267,P210,$Q$6:$Q$3267,"<="&Q210,$N$6:$N$3267,Calendar!$K$4),"") | W210: =IF(AND(B210=Queue!$C$4,OR(Queue!$K$4="*",N210=Queue!$K$4)),Q210,"")
A211: =IF(M211="","",HYPERLINK("https://www.youtube.com/watch?v="&M211,"▶")) | B211: =IF(C211<>"",C211,IF(P211<=IFERROR(INDEX(tblChannels[Watched Through],MATCH(N211,tblChannels[Channel ID],0)),0),"Watched","Unwatched")) | E211: 45975.692 | F211: Super Carlin Brothers | G211: A SCATHING Review of The Order of the Phoenix | Harry Potter | H211: 0.014328704 | I211: 186695 | J211: 6080 | K211: 766 | N211: UCKZo4N0lVPccBkSiuyVh4yg | O211: 45975.9 | P211: 45975 | Q211: 3057 | R211: No Video ID yet | U211: Head on over to to get 15% off! Today J dives into the Wizarding World of Harry Potter to give a SCATHING review of the Order of the Phoenix From losing both Wizarding Wars, to missing obvious clues, to wasting their greatest assets (TONKS!!), to forcing a teenage boy to run an illegal, underground Defense club—this organization fumbles the bag spectacularly at every turn. Let’s dive into the most savage performance review Hogwarts has ever seen. | V211: =IF(AND(P211>=Calendar!$K$2,P211<EDATE(Calendar!$K$2,1),OR(Calendar!$K$4="*",N211=Calendar!$K$4)),P211*100+COUNTIFS($P$6:$P$3267,P211,$Q$6:$Q$3267,"<="&Q211,$N$6:$N$3267,Calendar!$K$4),"") | W211: =IF(AND(B211=Queue!$C$4,OR(Queue!$K$4="*",N211=Queue!$K$4)),Q211,"")
A212: =IF(M212="","",HYPERLINK("https://www.youtube.com/watch?v="&M212,"▶")) | B212: =IF(C212<>"",C212,IF(P212<=IFERROR(INDEX(tblChannels[Watched Through],MATCH(N212,tblChannels[Channel ID],0)),0),"Watched","Unwatched")) | E212: 45975.417 | F212: Popcorn Culture | G212: "Yes, And..." | Popcorn Culture | H212: 0.046064815 | I212: 2939 | J212: 138 | K212: 15 | N212: UCHfIbq9thHPC8yrKjAdJgDA | O212: 45975.625 | P212: 45975 | Q212: 3056 | R212: No Video ID yet | U212: In the 310th episode of the Pop, Ben and J discuss “yes, and” improv, a new coined phrase, “A-Pop”, 67, music trivia, wall art, and tattoo complexities. Fool Me Once… - Bluey - KPop Demon Hunters - Spider-Man: Into the Spider-Verse - Klaus - Talladega Nights: The Ballad of Ricky Bobby - Will Gay - 00:00 - Intro, Hostmanship 06:32 - Yes, And-ing 11:51 - A-Pop 44:42 - Wall Art | V212: =IF(AND(P212>=Calendar!$K$2,P212<EDATE(Calendar!$K$2,1),OR(Calendar!$K$4="*",N212=Calendar!$K$4)),P212*100+COUNTIFS($P$6:$P$3267,P212,$Q$6:$Q$3267,"<="&Q212,$N$6:$N$3267,Calendar!$K$4),"") | W212: =IF(AND(B212=Queue!$C$4,OR(Queue!$K$4="*",N212=Queue!$K$4)),Q212,"")
A213: =IF(M213="","",HYPERLINK("https://www.youtube.com/watch?v="&M213,"▶")) | B213: =IF(C213<>"",C213,IF(P213<=IFERROR(INDEX(tblChannels[Watched Through],MATCH(N213,tblChannels[Channel ID],0)),0),"Watched","Unwatched")) | E213: 45973.719 | F213: Super Carlin Brothers | G213: The Invisibility Cloak’s SECRET Power | Harry Potter Theory | H213: 0.012974537 | I213: 132393 | J213: 5518 | K213: 612 | N213: UCKZo4N0lVPccBkSiuyVh4yg | O213: 45973.928 | P213: 45973 | Q213: 3055 | R213: No Video ID yet | U213: This episode is sponsored by BetterHelp. Go to to get 10% off your first month. Go to to sign up for your $1-per-month trial period. What makes Harry Potter’s Invisibility Cloak truly special? Sure, it’s one of the legendary Deathly Hallows — indestructible, eternal, and able to render its wearer perfectly invisible. But Dumbledore tells Harry that it only ever worked fully for him, its rightful master. So what’s the secret power hidden inside the Cloak? In this video, J dives deep into the theory that the Cloak’s magic isn’t about invisibility at all — it’s about protection. From Moody’s enchanted eye to the Marauder’s Map and even Nagini at Godric’s Hollow, every moment the Cloak “fails” actually proves it’s doing something more powerful… 😉 Because sometimes, to stay hidden… you have to be seen. | V213: =IF(AND(P213>=Calendar!$K$2,P213<EDATE(Calendar!$K$2,1),OR(Calendar!$K$4="*",N213=Calendar!$K$4)),P213*100+COUNTIFS($P$6:$P$3267,P213,$Q$6:$Q$3267,"<="&Q213,$N$6:$N$3267,Calendar!$K$4),"") | W213: =IF(AND(B213=Queue!$C$4,OR(Queue!$K$4="*",N213=Queue!$K$4)),Q213,"")
A214: =IF(M214="","",HYPERLINK("https://www.youtube.com/watch?v="&M214,"▶")) | B214: =IF(C214<>"",C214,IF(P214<=IFERROR(INDEX(tblChannels[Watched Through],MATCH(N214,tblChannels[Channel ID],0)),0),"Watched","Unwatched")) | E214: 45973.213 | F214: Super Carlin Gaming | G214: BEN PLAYS DIABLO 2 FOR NO REASON ON A TUESDAY DIABLO 2SDAY ANYONE? | H214: 0.058576389 | I214: 1344 | J214: 73 | K214: 13 | N214: UCor_9jRnNNZVzTuQ92PKsaQ | O214: 45973.421 | P214: 45973 | Q214: 3054 | R214: No Video ID yet | U214: Hey. The gaming channel is getting a reboot. We have a new computer and stuff and we're working out the kinks. So come say hello. ask questions. be feisty. but not too feisty. look you're already overthinking it. just be yourself. wow. | V214: =IF(AND(P214>=Calendar!$K$2,P214<EDATE(Calendar!$K$2,1),OR(Calendar!$K$4="*",N214=Calendar!$K$4)),P214*100+COUNTIFS($P$6:$P$3267,P214,$Q$6:$Q$3267,"<="&Q214,$N$6:$N$3267,Calendar!$K$4),"") | W214: =IF(AND(B214=Queue!$C$4,OR(Queue!$K$4="*",N214=Queue!$K$4)),Q214,"")
A215: =IF(M215="","",HYPERLINK("https://www.youtube.com/watch?v="&M215,"▶")) | B215: =IF(C215<>"",C215,IF(P215<=IFERROR(INDEX(tblChannels[Watched Through],MATCH(N215,tblChannels[Channel ID],0)),0),"Watched","Unwatched")) | E215: 45970.417 | F215: Through The Griffin Door | G215: Chapter 12: Professor Umbridge | Order of the Phoenix | H215: 0.075266204 | I215: 49505 | J215: 1243 | K215: 462 | N215: UCEscP6ETYXWSSvsNrDHekMQ | O215: 45970.625 | P215: 45970 | Q215: 3053 | R215: No Video ID yet | U215: Join J and Ben as they dive into Chapter 12 of the Order of the Phoenix and discuss Dean being Switzerland, Fred and George’s flyer, Ron’s subtle Quidditch hints, OWLs, Snape still being a bad Potions teacher, Divination class, and every infuriating moment of Umbridge’s class. 06:14 - Chapter Breakdown 1:39:46 - Closing Thoughts and Review | V215: =IF(AND(P215>=Calendar!$K$2,P215<EDATE(Calendar!$K$2,1),OR(Calendar!$K$4="*",N215=Calendar!$K$4)),P215*100+COUNTIFS($P$6:$P$3267,P215,$Q$6:$Q$3267,"<="&Q215,$N$6:$N$3267,Calendar!$K$4),"") | W215: =IF(AND(B215=Queue!$C$4,OR(Queue!$K$4="*",N215=Queue!$K$4)),Q215,"")
... A217: =IF(M217="","",HYPERLINK("https://www.youtube.com/watch?v="&M217,"▶")) | B217: =IF(C217<>"",C217,IF(P217<=IFERROR(INDEX(tblChannels[Watched Through],MATCH(N217,tblChannels[Channel ID],0)),0),"Watched","Unwatched")) | E217: 45968.66 | F217: Through The Griffin Door | G217: Live In Chicago - Chapter 11: The Sorting Hat's New Song | Order of the Phoenix | H217: 0.052638889 | I217: 7417 | J217: 320 | K217: 58 | N217: UCEscP6ETYXWSSvsNrDHekMQ | O217: 45968.868 | P217: 45968 | Q217: 3051 | R217: No Video ID yet | U217: Join J and Ben as they dive BACK into Chapter 11 of Order of the Phoenix LIVE IN CHICAGO! and honestly you just have to watch this one because J sings THE ENTIRE SONG and it is worth the price of admission | V217: =IF(AND(P217>=Calendar!$K$2,P217<EDATE(Calendar!$K$2,1),OR(Calendar!$K$4="*",N217=Calendar!$K$4)),P217*100+COUNTIFS($P$6:$P$3267,P217,$Q$6:$Q$3267,"<="&Q217,$N$6:$N$3267,Calendar!$K$4),"") | W217: =IF(AND(B217=Queue!$C$4,OR(Queue!$K$4="*",N217=Queue!$K$4)),Q217,"")
A218: =IF(M218="","",HYPERLINK("https://www.youtube.com/watch?v="&M218,"▶")) | B218: =IF(C218<>"",C218,IF(P218<=IFERROR(INDEX(tblChannels[Watched Through],MATCH(N218,tblChannels[Channel ID],0)),0),"Watched","Unwatched")) | E218: 45968.541 | F218: Popcorn Culture | G218: ARE WE LIVE?! | Popcorn Culture | H218: 0.046238426 | I218: 2453 | J218: 120 | K218: 16 | N218: UCHfIbq9thHPC8yrKjAdJgDA | O218: 45968.749 | P218: 45968 | Q218: 3050 | R218: No Video ID yet | V218: =IF(AND(P218>=Calendar!$K$2,P218<EDATE(Calendar!$K$2,1),OR(Calendar!$K$4="*",N218=Calendar!$K$4)),P218*100+COUNTIFS($P$6:$P$3267,P218,$Q$6:$Q$3267,"<="&Q218,$N$6:$N$3267,Calendar!$K$4),"") | W218: =IF(AND(B218=Queue!$C$4,OR(Queue!$K$4="*",N218=Queue!$K$4)),Q218,"")
A219: =IF(M219="","",HYPERLINK("https://www.youtube.com/watch?v="&M219,"▶")) | B219: =IF(C219<>"",C219,IF(P219<=IFERROR(INDEX(tblChannels[Watched Through],MATCH(N219,tblChannels[Channel ID],0)),0),"Watched","Unwatched")) | E219: 45968.484 | F219: Popcorn Culture | G219: POP Question and A with Benjamin and J - 11/07/2025 - GETCHER TAQUITOS | H219: 0.0011921296 | I219: 452 | J219: 22 | K219: 3 | N219: UCHfIbq9thHPC8yrKjAdJgDA | O219: 45968.692 | P219: 45968 | Q219: 3049 | R219: No Video ID yet | U219: Hello Patrons! As ever thank you for your support! Excited to chat with everyone and answer all the questions! | V219: =IF(AND(P219>=Calendar!$K$2,P219<EDATE(Calendar!$K$2,1),OR(Calendar!$K$4="*",N219=Calendar!$K$4)),P219*100+COUNTIFS($P$6:$P$3267,P219,$Q$6:$Q$3267,"<="&Q219,$N$6:$N$3267,Calendar!$K$4),"") | W219: =IF(AND(B219=Queue!$C$4,OR(Queue!$K$4="*",N219=Queue!$K$4)),Q219,"")
A220: =IF(M220="","",HYPERLINK("https://www.youtube.com/watch?v="&M220,"▶")) | B220: =IF(C220<>"",C220,IF(P220<=IFERROR(INDEX(tblChannels[Watched Through],MATCH(N220,tblChannels[Channel ID],0)),0),"Watched","Unwatched")) | E220: 45968.417 | F220: Popcorn Culture | G220: The BIGGEST NYC Marathon! | Popcorn Culture | H220: 0.043969907 | I220: 2537 | J220: 125 | K220: 12 | N220: UCHfIbq9thHPC8yrKjAdJgDA | O220: 45968.625 | P220: 45968 | Q220: 3048 | R220: No Video ID yet | U220: In the 309th episode of the Pop, Ben and J discuss more travel woes, carboloading, The Great Gatsby, THE Marathon, cheering sprints, and future triathlons. Without Limits - Go Pin Pro HQ - The Great Gatsby - | V220: =IF(AND(P220>=Calendar!$K$2,P220<EDATE(Calendar!$K$2,1),OR(Calendar!$K$4="*",N220=Calendar!$K$4)),P220*100+COUNTIFS($P$6:$P$3267,P220,$Q$6:$Q$3267,"<="&Q220,$N$6:$N$3267,Calendar!$K$4),"") | W220: =IF(AND(B220=Queue!$C$4,OR(Queue!$K$4="*",N220=Queue!$K$4)),Q220,"")
A221: =IF(M221="","",HYPERLINK("https://www.youtube.com/watch?v="&M221,"▶")) | B221: =IF(C221<>"",C221,IF(P221<=IFERROR(INDEX(tblChannels[Watched Through],MATCH(N221,tblChannels[Channel ID],0)),0),"Watched","Unwatched")) | E221: 45966.683 | F221: Super Carlin Brothers | G221: Was Voldemort Planning to Eradicate ALL Wizards? | Harry Potter Theory | H221: 0.010601852 | I221: 101211 | J221: 4529 | K221: 558 | N221: UCKZo4N0lVPccBkSiuyVh4yg | O221: 45966.891 | P221: 45966 | Q221: 3047 | R221: No Video ID yet | U221: This episode is sponsored by BetterHelp – Go to to get 10% off your first month. Was Voldemort’s obsession with “purebloods” and immortality a front for something even darker? From the Gaunt family’s collapse to the twisted irony of his own half-blood heritage, this theory explores how Voldemort’s perfect world may have ended in the extinction of wizardkind itself. Join us as we explore what might’ve happened if the Boy Who Lived… hadn’t. | V221: =IF(AND(P221>=Calendar!$K$2,P221<EDATE(Calendar!$K$2,1),OR(Calendar!$K$4="*",N221=Calendar!$K$4)),P221*100+COUNTIFS($P$6:$P$3267,P221,$Q$6:$Q$3267,"<="&Q221,$N$6:$N$3267,Calendar!$K$4),"") | W221: =IF(AND(B221=Queue!$C$4,OR(Queue!$K$4="*",N221=Queue!$K$4)),Q221,"")
A222: =IF(M222="","",HYPERLINK("https://www.youtube.com/watch?v="&M222,"▶")) | B222: =IF(C222<>"",C222,IF(P222<=IFERROR(INDEX(tblChannels[Watched Through],MATCH(N222,tblChannels[Channel ID],0)),0),"Watched","Unwatched")) | E222: 45966.458 | F222: Through The Griffin Door | G222: THROUGH THE GRIFFIN TOUR - SOUTHWEST | H222: 0.0017476852 | I222: 2476 | J222: 158 | K222: 38 | N222: UCEscP6ETYXWSSvsNrDHekMQ | O222: 45966.667 | P222: 45966 | Q222: 3046 | R222: No Video ID yet | U222: Calling All Griffin Doorks! We are so excited to announce that we will be continuing the Through the Griffin TOUR in the Southwest this March! Tickets go on sale THIS FRIDAY, November 7th at 10:00am LOCAL TIME. You can find the links to each location here on our website! Denver, CO - 03/07 Salt Lake City, UT - 03/09 Las Vegas, NV - 03/11 Phoenix, AZ - 03/12 Houston, TX - 03/14 Dallas, TX - 03/15 VIP tickets will be available yet again for this tour as well for an additional $50! These will include a VIP meet and greet with J and Ben, a signed tour poster and early/premium seating. Each of the websites does their VIP ticket add ons differently so be sure to pay attention to how to add that before you check out! Again, you can get your tickets here: on Friday, November 7th at 10:00am LOCAL TIME. We can’t wait to see you in real life, brother! Denver, CO - 03/07/2026: Salt Lake City, UT - 03/09/2026: Las Vegas, NV - 03/11/2026: Phoenix, AZ - 03/12/2026: Houston, TX - 03/14/2026: Dallas, TX - 03/15/2026: | V222: =IF(AND(P222>=Calendar!$K$2,P222<EDATE(Calendar!$K$2,1),OR(Calendar!$K$4="*",N222=Calendar!$K$4)),P222*100+COUNTIFS($P$6:$P$3267,P222,$Q$6:$Q$3267,"<="&Q222,$N$6:$N$3267,Calendar!$K$4),"") | W222: =IF(AND(B222=Queue!$C$4,OR(Queue!$K$4="*",N222=Queue!$K$4)),Q222,"")
A223: =IF(M223="","",HYPERLINK("https://www.youtube.com/watch?v="&M223,"▶")) | B223: =IF(C223<>"",C223,IF(P223<=IFERROR(INDEX(tblChannels[Watched Through],MATCH(N223,tblChannels[Channel ID],0)),0),"Watched","Unwatched")) | E223: 45966.458 | F223: Super Carlin Brothers | G223: THROUGH THE GRIFFIN TOUR - SOUTHWEST | H223: 0.00085648148 | I223: 3913 | J223: 204 | K223: 70 | N223: UCKZo4N0lVPccBkSiuyVh4yg | O223: 45966.667 | P223: 45966 | Q223: 3045 | R223: No Video ID yet | U223: Calling All Griffin Doorks! We are so excited to announce that we will be continuing the Through the Griffin TOUR in the Southwest this March! Tickets go on sale THIS FRIDAY, November 7th at 10:00am LOCAL TIME. You can find the links to each location here on our website! Denver, CO - 03/07 Salt Lake City, UT - 03/09 Las Vegas, NV - 03/11 Phoenix, AZ - 03/12 Houston, TX - 03/14 Dallas, TX - 03/15 VIP tickets will be available yet again for this tour as well for an additional $50! These will include a VIP meet and greet with J and Ben, a signed tour poster and early/premium seating. Each of the websites does their VIP ticket add ons differently so be sure to pay attention to how to add that before you check out! Again, you can get your tickets here: on Friday, November 7th at 10:00am LOCAL TIME. We can’t wait to see you in real life, brother! Denver, CO - 03/07/2026: Salt Lake City, UT - 03/09/2026: Las Vegas, NV - 03/11/2026: Phoenix, AZ - 03/12/2026: Houston, TX - 03/14/2026: Dallas, TX - 03/15/2026: | V223: =IF(AND(P223>=Calendar!$K$2,P223<EDATE(Calendar!$K$2,1),OR(Calendar!$K$4="*",N223=Calendar!$K$4)),P223*100+COUNTIFS($P$6:$P$3267,P223,$Q$6:$Q$3267,"<="&Q223,$N$6:$N$3267,Calendar!$K$4),"") | W223: =IF(AND(B223=Queue!$C$4,OR(Queue!$K$4="*",N223=Queue!$K$4)),Q223,"")
A224: =IF(M224="","",HYPERLINK("https://www.youtube.com/watch?v="&M224,"▶")) | B224: =IF(C224<>"",C224,IF(P224<=IFERROR(INDEX(tblChannels[Watched Through],MATCH(N224,tblChannels[Channel ID],0)),0),"Watched","Unwatched")) | E224: 45963.417 | F224: Through The Griffin Door | G224: Chapter 11: The Sorting Hat’s New Song | Order of the Phoenix | H224: 0.080462963 | I224: 49858 | J224: 1232 | K224: 384 | N224: UCEscP6ETYXWSSvsNrDHekMQ | O224: 45963.626 | P224: 45963 | Q224: 3044 | R224: No Video ID yet | U224: Join J and Ben as they dive into Chapter 11 of the Order of the Phoenix and discuss Luna’s thoughts on Hagrid, students whispering about Harry, Hagrid’s vegetarianism, the Hat’s song, the Founders, Umbridge’s speech and the ramifications of it. 07:25 - Chapter Breakdown 1:09:58 - Ad Break (Shopify) 1:11:23 - More Chapter Breakdown 1:41:47 - Closing Thoughts and Review | V224: =IF(AND(P224>=Calendar!$K$2,P224<EDATE(Calendar!$K$2,1),OR(Calendar!$K$4="*",N224=Calendar!$K$4)),P224*100+COUNTIFS($P$6:$P$3267,P224,$Q$6:$Q$3267,"<="&Q224,$N$6:$N$3267,Calendar!$K$4),"") | W224: =IF(AND(B224=Queue!$C$4,OR(Queue!$K$4="*",N224=Queue!$K$4)),Q224,"")
A225: =IF(M225="","",HYPERLINK("https://www.youtube.com/watch?v="&M225,"▶")) | B225: =IF(C225<>"",C225,IF(P225<=IFERROR(INDEX(tblChannels[Watched Through],MATCH(N225,tblChannels[Channel ID],0)),0),"Watched","Unwatched")) | E225: 45961.674 | F225: Super Carlin Brothers | G225: Why Dumbledore REALLY Says He See Socks In The Mirror | Harry Potter Theory | H225: 0.011087963 | I225: 125461 | J225: 5312 | K225: 568 | N225: UCKZo4N0lVPccBkSiuyVh4yg | O225: 45961.84 | P225: 45961 | Q225: 3043 | R225: No Video ID yet | U225: Today J dives into the Wizarding World of Harry Potter to reveal WHY Dumbledore claims to see himself holding socks in the Mirror of Erised. Go to and use code super50off to get 50% off your first box, plus Free Breakfast for 1 Year. It goes way deeper than you think. Today we break down the symbolism of socks across the entire Harry Potter series — from Dobby’s freedom to Hermione’s knitted S.P.E.W. gifts — and reveal how Dumbledore’s “joke” about socks actually hides his most profound regret: the family he lost and the freedom he never found. Go Check out Katy for more fun HP thoughts! | V225: =IF(AND(P225>=Calendar!$K$2,P225<EDATE(Calendar!$K$2,1),OR(Calendar!$K$4="*",N225=Calendar!$K$4)),P225*100+COUNTIFS($P$6:$P$3267,P225,$Q$6:$Q$3267,"<="&Q225,$N$6:$N$3267,Calendar!$K$4),"") | W225: =IF(AND(B225=Queue!$C$4,OR(Queue!$K$4="*",N225=Queue!$K$4)),Q225,"")
A226: =IF(M226="","",HYPERLINK("https://www.youtube.com/watch?v="&M226,"▶")) | B226: =IF(C226<>"",C226,IF(P226<=IFERROR(INDEX(tblChannels[Watched Through],MATCH(N226,tblChannels[Channel ID],0)),0),"Watched","Unwatched")) | E226: 45961.417 | F226: Popcorn Culture | G226: Luke’s Toy Empathy | Popcorn Culture | H226: 0.044583333 | I226: 2770 | J226: 153 | K226: 23 | N226: UCHfIbq9thHPC8yrKjAdJgDA | O226: 45961.583 | P226: 45961 | Q226: 3042 | R226: No Video ID yet | U226: In the 308th episode of the Pop, Ben and J discuss swimming in cold weather, BIG CHAP, KPop, Luke’s empathy, the Reverse Golden Rule, and analogies. KPop Demon Hunters - BLACKPINK - Elemental - Max Verstappen Song - Green Day - Nobody Wants This - BIG CHAP Chapless Benjamin 00:00 - Intro, Swimming 16:24 - An Embarrassing Story 28:33 - Luke’s Empathy | V226: =IF(AND(P226>=Calendar!$K$2,P226<EDATE(Calendar!$K$2,1),OR(Calendar!$K$4="*",N226=Calendar!$K$4)),P226*100+COUNTIFS($P$6:$P$3267,P226,$Q$6:$Q$3267,"<="&Q226,$N$6:$N$3267,Calendar!$K$4),"") | W226: =IF(AND(B226=Queue!$C$4,OR(Queue!$K$4="*",N226=Queue!$K$4)),Q226,"")
A227: =IF(M227="","",HYPERLINK("https://www.youtube.com/watch?v="&M227,"▶")) | B227: =IF(C227<>"",C227,IF(P227<=IFERROR(INDEX(tblChannels[Watched Through],MATCH(N227,tblChannels[Channel ID],0)),0),"Watched","Unwatched")) | E227: 45960.708 | F227: Through The Griffin Door | G227: Live In Milwaukee - Chapter 10: Luna Lovegood | Order of the Phoenix | H227: 0.049733796 | I227: 7555 | J227: 319 | K227: 39 | N227: UCEscP6ETYXWSSvsNrDHekMQ | O227: 45960.875 | P227: 45960 | Q227: 3041 | R227: No Video ID yet | U227: Join J and Ben as they dive BACK into Chapter 10 of Order of the Phoenix LIVE IN MILWAUKEE! and discuss the merits of various highlighter colors, why Molly and Sirius are always bickering, and who the heck the extra Gryffindor girl is! | V227: =IF(AND(P227>=Calendar!$K$2,P227<EDATE(Calendar!$K$2,1),OR(Calendar!$K$4="*",N227=Calendar!$K$4)),P227*100+COUNTIFS($P$6:$P$3267,P227,$Q$6:$Q$3267,"<="&Q227,$N$6:$N$3267,Calendar!$K$4),"") | W227: =IF(AND(B227=Queue!$C$4,OR(Queue!$K$4="*",N227=Queue!$K$4)),Q227,"")
A228: =IF(M228="","",HYPERLINK("https://www.youtube.com/watch?v="&M228,"▶")) | B228: =IF(C228<>"",C228,IF(P228<=IFERROR(INDEX(tblChannels[Watched Through],MATCH(N228,tblChannels[Channel ID],0)),0),"Watched","Unwatched")) | E228: 45959.713 | F228: Super Carlin Brothers | G228: Could Draco Malfoy Have Become Master of Death?! | Harry Potter Theory | H228: 0.014467593 | I228: 99118 | J228: 3371 | K228: 368 | N228: UCKZo4N0lVPccBkSiuyVh4yg | O228: 45959.879 | P228: 45959 | Q228: 3040 | R228: No Video ID yet | U228: Today J dives into the Wizarding World of Harry Potter to ask What If Draco kept the invisibility cloak when he takes it from Harry on the Train? This episode is sponsored by BetterHelp – Go to to get 10% off your first month. This episode is sponsored by Uncommon Goods – Go to for 15% off your next gift. Could Draco have used it to unwittingly become master of Death? What does it take to Master the Cloak? Could Draco have defeated Voldemort if he had united the Deathly Hallows? | V228: =IF(AND(P228>=Calendar!$K$2,P228<EDATE(Calendar!$K$2,1),OR(Calendar!$K$4="*",N228=Calendar!$K$4)),P228*100+COUNTIFS($P$6:$P$3267,P228,$Q$6:$Q$3267,"<="&Q228,$N$6:$N$3267,Calendar!$K$4),"") | W228: =IF(AND(B228=Queue!$C$4,OR(Queue!$K$4="*",N228=Queue!$K$4)),Q228,"")
A229: =IF(M229="","",HYPERLINK("https://www.youtube.com/watch?v="&M229,"▶")) | B229: =IF(C229<>"",C229,IF(P229<=IFERROR(INDEX(tblChannels[Watched Through],MATCH(N229,tblChannels[Channel ID],0)),0),"Watched","Unwatched")) | E229: 45956.417 | F229: Through The Griffin Door | G229: Chapter 10: Luna Lovegood | Order of the Phoenix | H229: 0.07400463 | I229: 49702 | J229: 1305 | K229: 457 | N229: UCEscP6ETYXWSSvsNrDHekMQ | O229: 45956.584 | P229: 45956 | Q229: 3039 | R229: No Video ID yet | U229: Join J and Ben as they dive into Chapter 10 of the Order of the Phoenix and discuss Harry’s Dream, hurriedly leaving Grimmauld Place, the different Hogwarts Express ride, the Mimbulus Mimbletonia, RedMoon, and Hagrid missing and the Thestrals. The Jumper - 07:09 - Chapter Breakdown 1:35:02 - Closing Thoughts and Review | V229: =IF(AND(P229>=Calendar!$K$2,P229<EDATE(Calendar!$K$2,1),OR(Calendar!$K$4="*",N229=Calendar!$K$4)),P229*100+COUNTIFS($P$6:$P$3267,P229,$Q$6:$Q$3267,"<="&Q229,$N$6:$N$3267,Calendar!$K$4),"") | W229: =IF(AND(B229=Queue!$C$4,OR(Queue!$K$4="*",N229=Queue!$K$4)),Q229,"")
A230: =IF(M230="","",HYPERLINK("https://www.youtube.com/watch?v="&M230,"▶")) | B230: =IF(C230<>"",C230,IF(P230<=IFERROR(INDEX(tblChannels[Watched Through],MATCH(N230,tblChannels[Channel ID],0)),0),"Watched","Unwatched")) | E230: 45955.417 | F230: Super Carlin Brothers | G230: Through the Griffin Door Supercut: Order of the Phoenix Chapters 7-9 | H230: 0.21555556 | I230: 9813 | J230: 202 | K230: 38 | N230: UCKZo4N0lVPccBkSiuyVh4yg | O230: 45955.583 | P230: 45955 | Q230: 3038 | R230: No Video ID yet | U230: 00:00:00 - Chapter 7: The Ministry of Magic 1:32:40 - Chapter 8: The Hearing 3:15:38 - Chapter 9: The Woes of Mrs. Weasley | V230: =IF(AND(P230>=Calendar!$K$2,P230<EDATE(Calendar!$K$2,1),OR(Calendar!$K$4="*",N230=Calendar!$K$4)),P230*100+COUNTIFS($P$6:$P$3267,P230,$Q$6:$Q$3267,"<="&Q230,$N$6:$N$3267,Calendar!$K$4),"") | W230: =IF(AND(B230=Queue!$C$4,OR(Queue!$K$4="*",N230=Queue!$K$4)),Q230,"")
... A274: =IF(M274="","",HYPERLINK("https://www.youtube.com/watch?v="&M274,"▶")) | B274: =IF(C274<>"",C274,IF(P274<=IFERROR(INDEX(tblChannels[Watched Through],MATCH(N274,tblChannels[Channel ID],0)),0),"Watched","Unwatched")) | E274: 45898.417 | F274: Popcorn Culture | G274: J WON WORLDS! | Popcorn Culture | H274: 0.048206019 | I274: 2868 | J274: 154 | K274: 12 | N274: UCHfIbq9thHPC8yrKjAdJgDA | O274: 45898.583 | P274: 45898 | Q274: 2994 | R274: No Video ID yet | U274: In the 299th episode of the Pop, Ben and J discuss farmers' tans, and all the wonderful things at Pokemon Worlds. Check out Through the Griffin Door Patreon to hear those Owlery Episodes - patreon.com/ThroughtheGriffinDoor Get your tickets for Through the Griffin Tour MIDWEST here: St. Louis, MO - 9/17 (low ticket warning) Detroit, MI - 9/24 (sold out) 00:00 - Intro, Tanning 05:29 - Pokemon Worlds | V274: =IF(AND(P274>=Calendar!$K$2,P274<EDATE(Calendar!$K$2,1),OR(Calendar!$K$4="*",N274=Calendar!$K$4)),P274*100+COUNTIFS($P$6:$P$3267,P274,$Q$6:$Q$3267,"<="&Q274,$N$6:$N$3267,Calendar!$K$4),"") | W274: =IF(AND(B274=Queue!$C$4,OR(Queue!$K$4="*",N274=Queue!$K$4)),Q274,"")
A275: =IF(M275="","",HYPERLINK("https://www.youtube.com/watch?v="&M275,"▶")) | B275: =IF(C275<>"",C275,IF(P275<=IFERROR(INDEX(tblChannels[Watched Through],MATCH(N275,tblChannels[Channel ID],0)),0),"Watched","Unwatched")) | E275: 45898.201 | F275: Super Carlin Gaming | G275: PRISMATIC EVOLUTIONS - Pokemon Box Breakers SEASON 16 - Episode 1 - 08/28/2025 | H275: 0.11099537 | I275: 799 | J275: 34 | K275: 5 | N275: UCor_9jRnNNZVzTuQ92PKsaQ | O275: 45898.368 | P275: 45898 | Q275: 2993 | R275: No Video ID yet | V275: =IF(AND(P275>=Calendar!$K$2,P275<EDATE(Calendar!$K$2,1),OR(Calendar!$K$4="*",N275=Calendar!$K$4)),P275*100+COUNTIFS($P$6:$P$3267,P275,$Q$6:$Q$3267,"<="&Q275,$N$6:$N$3267,Calendar!$K$4),"") | W275: =IF(AND(B275=Queue!$C$4,OR(Queue!$K$4="*",N275=Queue!$K$4)),Q275,"")
A276: =IF(M276="","",HYPERLINK("https://www.youtube.com/watch?v="&M276,"▶")) | B276: =IF(C276<>"",C276,IF(P276<=IFERROR(INDEX(tblChannels[Watched Through],MATCH(N276,tblChannels[Channel ID],0)),0),"Watched","Unwatched")) | E276: 45896.693 | F276: Super Carlin Brothers | G276: J vs Ben: Can We Remember MORE Of Our Harry Potter Theories?? | H276: 0.033240741 | I276: 124166 | J276: 3792 | K276: 369 | N276: UCKZo4N0lVPccBkSiuyVh4yg | O276: 45896.86 | P276: 45896 | Q276: 2992 | R276: No Video ID yet | U276: Go to and use code jvsb50off to get 50% off your first box, plus Free Breakfast for 1 Year Snag a Carlin Brothers Coffee Subscription at It’s time for another J vs Ben Quiz — but this time, it’s all about our own Harry Potter theories! After years of making wild predictions, fan theories, and “What If” scenarios, can we actually remember what we said? Or will we get stumped by our own videos? Play along and see if you can beat us! Special thanks to our Patrons who submitted today’s questions: Dorian R., Essential Escapism, Michaela Henry, Bradferd, Amanda B., Teghan Denlinger, Katrina A., Complete Crimson, Tara Walker, Fis, LawNinja, Dola, GooeyChewie, Reddrick, The Hufflepuff Pancake Chef, and Sarah Makiyama! Des Moines, IA - 9/19 (SOLD OUT) St. Paul, MN - 9/20 (SOLD OUT) Detroit, MI - 9/24 (SOLD OUT) Cleveland, OH - 9/25 (SOLD OUT) #harrypotter #SuperCarlinBrothers Written by :: Our Quiz Masters! Hosted by :: Kat Stine | V276: =IF(AND(P276>=Calendar!$K$2,P276<EDATE(Calendar!$K$2,1),OR(Calendar!$K$4="*",N276=Calendar!$K$4)),P276*100+COUNTIFS($P$6:$P$3267,P276,$Q$6:$Q$3267,"<="&Q276,$N$6:$N$3267,Calendar!$K$4),"") | W276: =IF(AND(B276=Queue!$C$4,OR(Queue!$K$4="*",N276=Queue!$K$4)),Q276,"")
A277: =IF(M277="","",HYPERLINK("https://www.youtube.com/watch?v="&M277,"▶")) | B277: =IF(C277<>"",C277,IF(P277<=IFERROR(INDEX(tblChannels[Watched Through],MATCH(N277,tblChannels[Channel ID],0)),0),"Watched","Unwatched")) | E277: 45895.469 | F277: Super Carlin Brothers | G277: I Built a Pokémon Skateboard! (ASMR) | H277: 0.0016666667 | I277: 14859 | J277: 589 | K277: 30 | N277: UCKZo4N0lVPccBkSiuyVh4yg | O277: 45895.636 | P277: 45895 | Q277: 2991 | R277: No Video ID yet | U277: I built the exclusive Bear Walker Pikachu Skateboard from Pokémon Worlds 2025! ⚡ (with just absolutely zero mishaps at all, not even ONE!) #Pokemon #PokemonWorlds2025 #Pikachu #PokemonShorts #BearWalker #PokemonSkateboard #skate #skateboard #asmrsounds #asmrvideo | V277: =IF(AND(P277>=Calendar!$K$2,P277<EDATE(Calendar!$K$2,1),OR(Calendar!$K$4="*",N277=Calendar!$K$4)),P277*100+COUNTIFS($P$6:$P$3267,P277,$Q$6:$Q$3267,"<="&Q277,$N$6:$N$3267,Calendar!$K$4),"") | W277: =IF(AND(B277=Queue!$C$4,OR(Queue!$K$4="*",N277=Queue!$K$4)),Q277,"")
A278: =IF(M278="","",HYPERLINK("https://www.youtube.com/watch?v="&M278,"▶")) | B278: =IF(C278<>"",C278,IF(P278<=IFERROR(INDEX(tblChannels[Watched Through],MATCH(N278,tblChannels[Channel ID],0)),0),"Watched","Unwatched")) | E278: 45893.417 | F278: Through The Griffin Door | G278: Chapter 1: Dudley Demented | Order of the Phoenix | H278: 0.061805556 | I278: 58297 | J278: 1607 | K278: 491 | N278: UCEscP6ETYXWSSvsNrDHekMQ | O278: 45893.583 | P278: 45893 | Q278: 2990 | R278: No Video ID yet | U278: Join J and Ben as they dive into Chapter 1 of the Order of the Phoenix and discuss the muggle news, Vernon grabbing Harry, Mundungus apparating, Harry/Voldemort’s dreams, picking a fight with Dudley and the dementor attack. In Defense of Dudley Dursley - THROUGH THE GRIFFIN TOUR MIDWEST TICKETS ARE ON SALE RIGHT NOW St. Louis, MO - 9/17 (low ticket warning) Detroit, MI - 9/24 (sold out) 08:39 - Chapter Breakdown 1:19:12 - Closing Thoughts and Review | V278: =IF(AND(P278>=Calendar!$K$2,P278<EDATE(Calendar!$K$2,1),OR(Calendar!$K$4="*",N278=Calendar!$K$4)),P278*100+COUNTIFS($P$6:$P$3267,P278,$Q$6:$Q$3267,"<="&Q278,$N$6:$N$3267,Calendar!$K$4),"") | W278: =IF(AND(B278=Queue!$C$4,OR(Queue!$K$4="*",N278=Queue!$K$4)),Q278,"")
A279: =IF(M279="","",HYPERLINK("https://www.youtube.com/watch?v="&M279,"▶")) | B279: =IF(C279<>"",C279,IF(P279<=IFERROR(INDEX(tblChannels[Watched Through],MATCH(N279,tblChannels[Channel ID],0)),0),"Watched","Unwatched")) | E279: 45891.617 | F279: Super Carlin Brothers | G279: What If Merope Never Released Tom Riddle? | Harry Potter Theory | H279: 0.013032407 | I279: 182226 | J279: 5538 | K279: 622 | N279: UCKZo4N0lVPccBkSiuyVh4yg | O279: 45891.783 | P279: 45891 | Q279: 2989 | R279: No Video ID yet | U279: This episode is sponsored by BetterHelp. Get 10% off your first month at In Half-Blood Prince, we learn that Merope Gaunt used a love potion to force Tom Riddle Sr. into a relationship — but once she released him, he abandoned her, and she eventually died giving birth to Voldemort. But what if she never released him? Would Voldemort have had a “normal” childhood? Could love — even fake love — have changed the outcome? Or was Voldemort always destined for darkness? Today we explore how this alternate timeline could have unfolded, from Merope’s choices to Voldemort’s obsession with power, the Deathly Hallows, and even how it might erase Harry Potter from existence entirely. Would the Dark Lord have still risen… or might all have been saved? 🔔 Don’t forget to subscribe for more Harry Potter theories every week! Des Moines, IA - 9/19 (SOLD OUT) St. Paul, MN - 9/20 (SOLD OUT) Detroit, MI - 9/24 (SOLD OUT) Cleveland, OH - 9/25 (SOLD OUT) Written by :: J Carlin | V279: =IF(AND(P279>=Calendar!$K$2,P279<EDATE(Calendar!$K$2,1),OR(Calendar!$K$4="*",N279=Calendar!$K$4)),P279*100+COUNTIFS($P$6:$P$3267,P279,$Q$6:$Q$3267,"<="&Q279,$N$6:$N$3267,Calendar!$K$4),"") | W279: =IF(AND(B279=Queue!$C$4,OR(Queue!$K$4="*",N279=Queue!$K$4)),Q279,"")
A280: =IF(M280="","",HYPERLINK("https://www.youtube.com/watch?v="&M280,"▶")) | B280: =IF(C280<>"",C280,IF(P280<=IFERROR(INDEX(tblChannels[Watched Through],MATCH(N280,tblChannels[Channel ID],0)),0),"Watched","Unwatched")) | E280: 45891.417 | F280: Popcorn Culture | G280: Ben's SPECIALEST Guest| Popcorn Culture | H280: 0.049768519 | I280: 4425 | J280: 262 | K280: 40 | N280: UCHfIbq9thHPC8yrKjAdJgDA | O280: 45891.583 | P280: 45891 | Q280: 2988 | R280: No Video ID yet | U280: In the 298th episode of the Pop, Ben and ALYCE(!!!) discuss daily routines, Addy’s new negotiation techniques, their dogs, pageants, Alyce’s ex, star signs, and F1. The Gilded Age - Carlos Sainz - New’d - Ben and Alyce’s Wedding - Get your tickets for Through the Griffin Tour MIDWEST here: St. Louis, MO - 9/17 (low ticket warning) Detroit, MI - 9/24 (sold out) Do We Talk Too Much? Pageant Queen The Third Place 00:00 - Intro, Talking Too Much 12:24 - Negotiating and the Dogs 19:04 - Pageanting 43:13 - David 54:01 - Astrology | V280: =IF(AND(P280>=Calendar!$K$2,P280<EDATE(Calendar!$K$2,1),OR(Calendar!$K$4="*",N280=Calendar!$K$4)),P280*100+COUNTIFS($P$6:$P$3267,P280,$Q$6:$Q$3267,"<="&Q280,$N$6:$N$3267,Calendar!$K$4),"") | W280: =IF(AND(B280=Queue!$C$4,OR(Queue!$K$4="*",N280=Queue!$K$4)),Q280,"")
A281: =IF(M281="","",HYPERLINK("https://www.youtube.com/watch?v="&M281,"▶")) | B281: =IF(C281<>"",C281,IF(P281<=IFERROR(INDEX(tblChannels[Watched Through],MATCH(N281,tblChannels[Channel ID],0)),0),"Watched","Unwatched")) | E281: 45889.68 | F281: Super Carlin Brothers | G281: Pokémon Fossils Never Went Extinct… They EVOLVED | Pokemon Theory | H281: 0.0115625 | I281: 143862 | J281: 5588 | K281: 927 | N281: UCKZo4N0lVPccBkSiuyVh4yg | O281: 45889.847 | P281: 45889 | Q281: 2987 | R281: No Video ID yet | U281: Go to to get 20% off the fan favorite Everyday Earbuds Classic! Today J dives into the Wide World of Pokemon to uncover the SECRET Pokémon Fossil Theory Game Freaks has been hiding from us! For decades we’ve been told Aerodactyl, Kabutops, and Omastar disappeared millions of years ago — but the Pokédex, habitats, and even predator-prey relationships tell a different story. Today we uncover the hidden fossil family tree that connects these prehistoric Pokémon to some of the most iconic species we know today: Scyther, Octillery, and more! From the Isle of Armor to the Safari Zone, from Kanto to Galar, from Psyduck’s evolutionary arms race to Aerodactyl’s fiery “rebirth,” the evidence is all there — and it might just change the way you see Fossil Pokémon forever! Des Moines, IA - 9/19 (SOLD OUT) St. Paul, MN - 9/20 (SOLD OUT) Detroit, MI - 9/24 (SOLD OUT) Cleveland, OH - 9/25 (SOLD OUT) Written by :: J Carlin | V281: =IF(AND(P281>=Calendar!$K$2,P281<EDATE(Calendar!$K$2,1),OR(Calendar!$K$4="*",N281=Calendar!$K$4)),P281*100+COUNTIFS($P$6:$P$3267,P281,$Q$6:$Q$3267,"<="&Q281,$N$6:$N$3267,Calendar!$K$4),"") | W281: =IF(AND(B281=Queue!$C$4,OR(Queue!$K$4="*",N281=Queue!$K$4)),Q281,"")
A282: =IF(M282="","",HYPERLINK("https://www.youtube.com/watch?v="&M282,"▶")) | B282: =IF(C282<>"",C282,IF(P282<=IFERROR(INDEX(tblChannels[Watched Through],MATCH(N282,tblChannels[Channel ID],0)),0),"Watched","Unwatched")) | E282: 45886.417 | F282: Through The Griffin Door | G282: Dumbledore's Big Plan: Goblet of Fire Edition | H282: 0.038356481 | I282: 44224 | J282: 1179 | K282: 318 | N282: UCEscP6ETYXWSSvsNrDHekMQ | O282: 45886.584 | P282: 45886 | Q282: 2986 | R282: No Video ID yet | U282: Join J and Ben as they dive into how Dumbledore’s Big Plan fits into the Goblet of Fire! THROUGH THE GRIFFIN TOUR MIDWEST TICKETS ARE ON SALE RIGHT NOW St. Louis, MO - 9/17 (low ticket warning) Detroit, MI - 9/24 (low ticket warning) 05:16 - DBP Breakdown 29:23- Ad Break (Pair Eyewear) 30:38 - More DBP Breakdown | V282: =IF(AND(P282>=Calendar!$K$2,P282<EDATE(Calendar!$K$2,1),OR(Calendar!$K$4="*",N282=Calendar!$K$4)),P282*100+COUNTIFS($P$6:$P$3267,P282,$Q$6:$Q$3267,"<="&Q282,$N$6:$N$3267,Calendar!$K$4),"") | W282: =IF(AND(B282=Queue!$C$4,OR(Queue!$K$4="*",N282=Queue!$K$4)),Q282,"")
A283: =IF(M283="","",HYPERLINK("https://www.youtube.com/watch?v="&M283,"▶")) | B283: =IF(C283<>"",C283,IF(P283<=IFERROR(INDEX(tblChannels[Watched Through],MATCH(N283,tblChannels[Channel ID],0)),0),"Watched","Unwatched")) | E283: 45885.417 | F283: Super Carlin Brothers | G283: Through the Griffin Door Supercut: Goblet of Fire Chapters 34-37 | H283: 0.27604167 | I283: 11281 | J283: 223 | K283: 47 | N283: UCKZo4N0lVPccBkSiuyVh4yg | O283: 45885.584 | P283: 45885 | Q283: 2985 | R283: No Video ID yet | U283: 0:00:00 - Chapter 34: Priori Incantatem 1:26:26 - Chapter 35: Veritaserum 3:08:52 - Chapter 36: The Parting of the Ways 4:51:43 - Chapter 37: The Beginning | V283: =IF(AND(P283>=Calendar!$K$2,P283<EDATE(Calendar!$K$2,1),OR(Calendar!$K$4="*",N283=Calendar!$K$4)),P283*100+COUNTIFS($P$6:$P$3267,P283,$Q$6:$Q$3267,"<="&Q283,$N$6:$N$3267,Calendar!$K$4),"") | W283: =IF(AND(B283=Queue!$C$4,OR(Queue!$K$4="*",N283=Queue!$K$4)),Q283,"")
A284: =IF(M284="","",HYPERLINK("https://www.youtube.com/watch?v="&M284,"▶")) | B284: =IF(C284<>"",C284,IF(P284<=IFERROR(INDEX(tblChannels[Watched Through],MATCH(N284,tblChannels[Channel ID],0)),0),"Watched","Unwatched")) | E284: 45884.667 | F284: Super Carlin Brothers | G284: The BIZARRE Reason Vernon Couldn’t Harm Harry | Harry Potter Theory | H284: 0.0091898148 | I284: 139273 | J284: 5990 | K284: 701 | N284: UCKZo4N0lVPccBkSiuyVh4yg | O284: 45884.834 | P284: 45884 | Q284: 2984 | R284: No Video ID yet | U284: This episode is sponsored by BetterHelp - go to to get 10% off your first month. In today’s episode Ben explores a potential NEW power of the “Bond of Blood” charm that we had never previously considered. How far does its power extend? Just Voldemort? His agents? What about the Dursley’s themselves? A recent discovery may just change how we interpret this novel and obscure brand of magic. Des Moines, IA - 9/19 (SOLD OUT) St. Paul, MN - 9/20 (SOLD OUT) Detroit, MI - 9/24 (SOLD OUT) Cleveland, OH - 9/25 (SOLD OUT) Written by :: Ben Carlin | V284: =IF(AND(P284>=Calendar!$K$2,P284<EDATE(Calendar!$K$2,1),OR(Calendar!$K$4="*",N284=Calendar!$K$4)),P284*100+COUNTIFS($P$6:$P$3267,P284,$Q$6:$Q$3267,"<="&Q284,$N$6:$N$3267,Calendar!$K$4),"") | W284: =IF(AND(B284=Queue!$C$4,OR(Queue!$K$4="*",N284=Queue!$K$4)),Q284,"")
A285: =IF(M285="","",HYPERLINK("https://www.youtube.com/watch?v="&M285,"▶")) | B285: =IF(C285<>"",C285,IF(P285<=IFERROR(INDEX(tblChannels[Watched Through],MATCH(N285,tblChannels[Channel ID],0)),0),"Watched","Unwatched")) | E285: 45884.417 | F285: Popcorn Culture | G285: How to... Charisma? | Popcorn Culture | H285: 0.058032407 | I285: 3171 | J285: 150 | K285: 14 | N285: UCHfIbq9thHPC8yrKjAdJgDA | O285: 45884.583 | P285: 45884 | Q285: 2983 | R285: No Video ID yet | U285: In the 297th episode of the Pop, Ben and J discuss being charismatic, similarities between The Bear and Encanto, whether or not pressure is helpful or harmful, and taking your kids to the mall. Stitch Fix - The Bear - Encanto - Will Poulter - Get your tickets for Through the Griffin Tour MIDWEST here: St. Louis, MO - 9/17 (low ticket warning) Detroit, MI - 9/24 (sold out) 00:00 - Intro, Charisma 09:22 - Pressure 48:40 - Family Life | V285: =IF(AND(P285>=Calendar!$K$2,P285<EDATE(Calendar!$K$2,1),OR(Calendar!$K$4="*",N285=Calendar!$K$4)),P285*100+COUNTIFS($P$6:$P$3267,P285,$Q$6:$Q$3267,"<="&Q285,$N$6:$N$3267,Calendar!$K$4),"") | W285: =IF(AND(B285=Queue!$C$4,OR(Queue!$K$4="*",N285=Queue!$K$4)),Q285,"")
A286: =IF(M286="","",HYPERLINK("https://www.youtube.com/watch?v="&M286,"▶")) | B286: =IF(C286<>"",C286,IF(P286<=IFERROR(INDEX(tblChannels[Watched Through],MATCH(N286,tblChannels[Channel ID],0)),0),"Watched","Unwatched")) | E286: 45882.708 | F286: Super Carlin Brothers | G286: J vs. Ben: EXPERT Level Goblet of Fire Quiz | Harry Potter TRIVIA | H286: 0.031273148 | I286: 115153 | J286: 3711 | K286: 389 | N286: UCKZo4N0lVPccBkSiuyVh4yg | O286: 45882.875 | P286: 45882 | Q286: 2982 | R286: No Video ID yet | U286: This episode is sponsored by Upside - Download the FREE Upside App and use promo code JVSB to get an extra 25 cents back for every gallon on your first tank of gas! This episode is sponsored by Hello Fresh - Go to now to Get 10 Free Meals + a Free Item for Life! J and Ben just wrapped the final chapter of their most thorough read-through yet of Goblet of Fire over on their podcast: Through the Griffin Door - But can they recall the book's most obscure trivia questions? Today we put them to the test with some of the most challenging book four trivia questions thanks to our Quizmasters on Patreon! Des Moines, IA - 9/19 (SOLD OUT) St. Paul, MN - 9/20 (SOLD OUT) Detroit, MI - 9/24 (SOLD OUT) Cleveland, OH - 9/25 (SOLD OUT) Written by :: QUIZMASTERS! | V286: =IF(AND(P286>=Calendar!$K$2,P286<EDATE(Calendar!$K$2,1),OR(Calendar!$K$4="*",N286=Calendar!$K$4)),P286*100+COUNTIFS($P$6:$P$3267,P286,$Q$6:$Q$3267,"<="&Q286,$N$6:$N$3267,Calendar!$K$4),"") | W286: =IF(AND(B286=Queue!$C$4,OR(Queue!$K$4="*",N286=Queue!$K$4)),Q286,"")
A287: =IF(M287="","",HYPERLINK("https://www.youtube.com/watch?v="&M287,"▶")) | B287: =IF(C287<>"",C287,IF(P287<=IFERROR(INDEX(tblChannels[Watched Through],MATCH(N287,tblChannels[Channel ID],0)),0),"Watched","Unwatched")) | E287: 45879.417 | F287: Through The Griffin Door | G287: Chapter 37: The Beginning | Goblet of Fire | H287: 0.074351852 | I287: 56282 | J287: 1487 | K287: 376 | N287: UCEscP6ETYXWSSvsNrDHekMQ | O287: 45879.583 | P287: 45879 | Q287: 2981 | R287: No Video ID yet | U287: This episode is sponsored by Pair Eyewear – Go to paireyewear.com and use code 'GRIFFIN' for 15% off your first pair. Join J and Ben as they dive into Chapter 37 (the last chapter!) of the Goblet of Fire and discuss the in-between week, visiting Hagrid, Snape’s position, Dumbledore’s speech, saying goodbye to the other schools, hexings on the train and giving the twins his prize money. THROUGH THE GRIFFIN TOUR MIDWEST TICKETS ARE ON SALE RIGHT NOW St. Louis, MO - 9/17 (low ticket warning) Detroit, MI - 9/24 (low ticket warning) 05:13 - Chapter Breakdown 32:21- Ad Break (Pair Eyewear) 33:39 - More Chapter Breakdown 1:33:41 - Closing Thoughts and Review | V287: =IF(AND(P287>=Calendar!$K$2,P287<EDATE(Calendar!$K$2,1),OR(Calendar!$K$4="*",N287=Calendar!$K$4)),P287*100+COUNTIFS($P$6:$P$3267,P287,$Q$6:$Q$3267,"<="&Q287,$N$6:$N$3267,Calendar!$K$4),"") | W287: =IF(AND(B287=Queue!$C$4,OR(Queue!$K$4="*",N287=Queue!$K$4)),Q287,"")
... A303: =IF(M303="","",HYPERLINK("https://www.youtube.com/watch?v="&M303,"▶")) | B303: =IF(C303<>"",C303,IF(P303<=IFERROR(INDEX(tblChannels[Watched Through],MATCH(N303,tblChannels[Channel ID],0)),0),"Watched","Unwatched")) | E303: 45857.417 | F303: Super Carlin Brothers | G303: Through the Griffin Door Supercut: Goblet of Fire Chapters 31-33 | H303: 0.19008102 | I303: 13533 | J303: 260 | K303: 71 | N303: UCKZo4N0lVPccBkSiuyVh4yg | O303: 45857.583 | P303: 45857 | Q303: 2965 | R303: No Video ID yet | U303: 0:00:00 - Chapter 31: The Third Task 1:57:24 - Chapter 32 - Flesh, Blood and Bone 2:24:50 - Chapter 33: The Death Eaters | V303: =IF(AND(P303>=Calendar!$K$2,P303<EDATE(Calendar!$K$2,1),OR(Calendar!$K$4="*",N303=Calendar!$K$4)),P303*100+COUNTIFS($P$6:$P$3267,P303,$Q$6:$Q$3267,"<="&Q303,$N$6:$N$3267,Calendar!$K$4),"") | W303: =IF(AND(B303=Queue!$C$4,OR(Queue!$K$4="*",N303=Queue!$K$4)),Q303,"")
A304: =IF(M304="","",HYPERLINK("https://www.youtube.com/watch?v="&M304,"▶")) | B304: =IF(C304<>"",C304,IF(P304<=IFERROR(INDEX(tblChannels[Watched Through],MATCH(N304,tblChannels[Channel ID],0)),0),"Watched","Unwatched")) | E304: 45857.209 | F304: Super Carlin Gaming | G304: JOURNEY TOGETHER - Pokemon Box Breakers SEASON 15 - Episode 3 - 07/18/2025 | H304: 0.11209491 | I304: 811 | J304: 35 | K304: 1 | N304: UCor_9jRnNNZVzTuQ92PKsaQ | O304: 45857.376 | P304: 45857 | Q304: 2964 | R304: No Video ID yet | V304: =IF(AND(P304>=Calendar!$K$2,P304<EDATE(Calendar!$K$2,1),OR(Calendar!$K$4="*",N304=Calendar!$K$4)),P304*100+COUNTIFS($P$6:$P$3267,P304,$Q$6:$Q$3267,"<="&Q304,$N$6:$N$3267,Calendar!$K$4),"") | W304: =IF(AND(B304=Queue!$C$4,OR(Queue!$K$4="*",N304=Queue!$K$4)),Q304,"")
A305: =IF(M305="","",HYPERLINK("https://www.youtube.com/watch?v="&M305,"▶")) | B305: =IF(C305<>"",C305,IF(P305<=IFERROR(INDEX(tblChannels[Watched Through],MATCH(N305,tblChannels[Channel ID],0)),0),"Watched","Unwatched")) | E305: 45856.705 | F305: Super Carlin Brothers | G305: Regulus Black was the FIRST Chosen One | Harry Potter Film Theory | H305: 0.013206019 | I305: 145699 | J305: 6272 | K305: 743 | N305: UCKZo4N0lVPccBkSiuyVh4yg | O305: 45856.872 | P305: 45856 | Q305: 2963 | R305: No Video ID yet | U305: Long before Harry Potter, another wizard may have fit the prophecy—and it changes everything.. This episode is sponsored by BetterHelp - go to to get 10% off your first month. Was Harry Potter really the first Chosen One? Or was someone else chosen before him… and failed? Today J dives deep into the forgotten legacy of Regulus Arcturus Black—Slytherin’s golden boy, secret Horcrux hunter, and perhaps… the original Chosen One. We’ll explore how his death may have triggered the prophecy, how his values mirror Harry’s, and why his sacrifice in the cave holds more power than we ever realized. Could the Boy Who Lived be walking in the footsteps of the Boy Who Died? 👉 Let us know in the comments: Was Regulus the First Chosen One? Des Moines, IA - 9/19 (SOLD OUT) St. Paul, MN - 9/20 (SOLD OUT) Cleveland, OH - 9/25 (SOLD OUT) | V305: =IF(AND(P305>=Calendar!$K$2,P305<EDATE(Calendar!$K$2,1),OR(Calendar!$K$4="*",N305=Calendar!$K$4)),P305*100+COUNTIFS($P$6:$P$3267,P305,$Q$6:$Q$3267,"<="&Q305,$N$6:$N$3267,Calendar!$K$4),"") | W305: =IF(AND(B305=Queue!$C$4,OR(Queue!$K$4="*",N305=Queue!$K$4)),Q305,"")
A306: =IF(M306="","",HYPERLINK("https://www.youtube.com/watch?v="&M306,"▶")) | B306: =IF(C306<>"",C306,IF(P306<=IFERROR(INDEX(tblChannels[Watched Through],MATCH(N306,tblChannels[Channel ID],0)),0),"Watched","Unwatched")) | E306: 45856.561 | F306: Super Carlin Brothers | G306: The Mirror of Erised’s SECRET Origin.. | H306: 0.0017592593 | I306: 60444 | J306: 3101 | K306: 62 | N306: UCKZo4N0lVPccBkSiuyVh4yg | O306: 45856.728 | P306: 45856 | Q306: 2962 | R306: No Video ID yet | U306: The Mirror of Erised is one of the most iconic magical artifacts in the Wizarding World—but what if it’s more dangerous than we ever realized? In this short theory, we explore a shocking connection between the mirror, the Resurrection Stone, and the tale of the Three Brothers. #HarryPotter #WizardingWorld #MirrorOfErised #PeverellBrothers #HarryPotterTheory #Shorts | V306: =IF(AND(P306>=Calendar!$K$2,P306<EDATE(Calendar!$K$2,1),OR(Calendar!$K$4="*",N306=Calendar!$K$4)),P306*100+COUNTIFS($P$6:$P$3267,P306,$Q$6:$Q$3267,"<="&Q306,$N$6:$N$3267,Calendar!$K$4),"") | W306: =IF(AND(B306=Queue!$C$4,OR(Queue!$K$4="*",N306=Queue!$K$4)),Q306,"")
A307: =IF(M307="","",HYPERLINK("https://www.youtube.com/watch?v="&M307,"▶")) | B307: =IF(C307<>"",C307,IF(P307<=IFERROR(INDEX(tblChannels[Watched Through],MATCH(N307,tblChannels[Channel ID],0)),0),"Watched","Unwatched")) | E307: 45856.417 | F307: Popcorn Culture | G307: Summer Break (Ben’s Version) [From The Vault] | Popcorn Culture | H307: 0.046041667 | I307: 2900 | J307: 142 | K307: 22 | N307: UCHfIbq9thHPC8yrKjAdJgDA | O307: 45856.583 | P307: 45856 | Q307: 2961 | R307: No Video ID yet | U307: In the 293rd episode of the Pop, Ben and J discuss Ben’s lake trip, natural scents, 9 Lives, accents, roller hockey, longevity and Spearmint. Mr. Frumble’s Worst Day Ever - Dr Bronner’s soap - The Truman Show - Get your tickets for Through the Griffin Tour MIDWEST here: St. Louis, MO - 9/17 (low ticket warning) Detroit, MI - 9/24 (low ticket warning) 00:00 - Intro, Corporate PTO 04:55 - Ben’s Week Off | V307: =IF(AND(P307>=Calendar!$K$2,P307<EDATE(Calendar!$K$2,1),OR(Calendar!$K$4="*",N307=Calendar!$K$4)),P307*100+COUNTIFS($P$6:$P$3267,P307,$Q$6:$Q$3267,"<="&Q307,$N$6:$N$3267,Calendar!$K$4),"") | W307: =IF(AND(B307=Queue!$C$4,OR(Queue!$K$4="*",N307=Queue!$K$4)),Q307,"")
A308: =IF(M308="","",HYPERLINK("https://www.youtube.com/watch?v="&M308,"▶")) | B308: =IF(C308<>"",C308,IF(P308<=IFERROR(INDEX(tblChannels[Watched Through],MATCH(N308,tblChannels[Channel ID],0)),0),"Watched","Unwatched")) | E308: 45854.625 | F308: Super Carlin Brothers | G308: J vs Ben: Can We Remember Our OWN Harry Potter Theories?? | H308: 0.034988426 | I308: 216035 | J308: 5985 | K308: 497 | N308: UCKZo4N0lVPccBkSiuyVh4yg | O308: 45854.792 | P308: 45854 | Q308: 2960 | R308: No Video ID yet | U308: Download the FREE Upside App and use promo code JVSB to get an extra 25 cents back for every gallon on your first tank of gas. Go to and get TEN FREE MEALS with a FREE ITEM FOR LIFE. We’ve made hundreds of Harry Potter theory videos over the years... but how well do we remember what we actually said in them? Today, it’s J vs Ben in a trivia showdown featuring questions from our own backlog of theories, submitted by YOU, the viewers! How well do we know our own lore? Will we crumble under pressure? Will Ben remember which dragon built Hogwarts? Will J finally forget a pun?! Special thanks to our amazing Patrons who submitted questions for this episode! Essential Escapism, Fis, Dola, LawNinja, GooeyChewie, Amanda B., Gooie Cow (aka MaGoo), Teghan Denlinger, Bradferd, Oryan, Jessica Theriault, Michaela Henry, Tara Walker, and Rowena R. EVERY THEORY MENTIONED IN THIS VIDEO :: Des Moines, IA - 9/19 (SOLD OUT) St. Paul, MN - 9/20 (SOLD OUT) Cleveland, OH - 9/25 (SOLD OUT) #HarryPotter #JvsBen Written by :: THE QUIZ MASTERS | V308: =IF(AND(P308>=Calendar!$K$2,P308<EDATE(Calendar!$K$2,1),OR(Calendar!$K$4="*",N308=Calendar!$K$4)),P308*100+COUNTIFS($P$6:$P$3267,P308,$Q$6:$Q$3267,"<="&Q308,$N$6:$N$3267,Calendar!$K$4),"") | W308: =IF(AND(B308=Queue!$C$4,OR(Queue!$K$4="*",N308=Queue!$K$4)),Q308,"")
A309: =IF(M309="","",HYPERLINK("https://www.youtube.com/watch?v="&M309,"▶")) | B309: =IF(C309<>"",C309,IF(P309<=IFERROR(INDEX(tblChannels[Watched Through],MATCH(N309,tblChannels[Channel ID],0)),0),"Watched","Unwatched")) | E309: 45851.417 | F309: Through The Griffin Door | G309: Chapter 33: The Death Eaters | Goblet of Fire | H309: 0.069872685 | I309: 60349 | J309: 1460 | K309: 432 | N309: UCEscP6ETYXWSSvsNrDHekMQ | O309: 45851.584 | P309: 45851 | Q309: 2959 | R309: No Video ID yet | U309: This episode is sponsored by Pair Eyewear – Go to paireyewear.com and use code 'GRIFFIN' for 15% off your first pair. Join J and Ben as they dive into Chapter 33 of the Goblet of Fire and discuss yin and yang symbolism, impersonator Nagini, Voldemort’s wand, the Dark Mark, Voldemort monologuing, each of the Death Eaters, and constant contradictions. How Voldemort Got His ORIGINAL Wand Back - The Incredibles - Most Important Line in Harry Potter - THROUGH THE GRIFFIN TOUR MIDWEST TICKETS ARE ON SALE RIGHT NOW St. Louis, MO - 9/17 (low ticket warning) Detroit, MI - 9/24 (low ticket warning) Support us on Patreon AND GET YOUR GUMPSTER FIRE PIN: 3:56 - Chapter Breakdown 51:23 - Ad Break (Pair Eyewear) 53:07 - More Chapter Breakdown 1:37:43 - Closing Thoughts and Review | V309: =IF(AND(P309>=Calendar!$K$2,P309<EDATE(Calendar!$K$2,1),OR(Calendar!$K$4="*",N309=Calendar!$K$4)),P309*100+COUNTIFS($P$6:$P$3267,P309,$Q$6:$Q$3267,"<="&Q309,$N$6:$N$3267,Calendar!$K$4),"") | W309: =IF(AND(B309=Queue!$C$4,OR(Queue!$K$4="*",N309=Queue!$K$4)),Q309,"")
A310: =IF(M310="","",HYPERLINK("https://www.youtube.com/watch?v="&M310,"▶")) | B310: =IF(C310<>"",C310,IF(P310<=IFERROR(INDEX(tblChannels[Watched Through],MATCH(N310,tblChannels[Channel ID],0)),0),"Watched","Unwatched")) | E310: 45849.676 | F310: Super Carlin Brothers | G310: How Voldemort FOUND Nagini | Harry Potter Film Theory | H310: 0.011006944 | I310: 155582 | J310: 5801 | K310: 463 | N310: UCKZo4N0lVPccBkSiuyVh4yg | O310: 45849.843 | P310: 45849 | Q310: 2958 | R310: No Video ID yet | U310: This episode is sponsored by BetterHelp - go to to get 10% off your first month. What really happened to Nagini? Today, Ben dives deep into one of the darkest and most overlooked mysteries in the Wizarding World: Why did Nagini obey Voldemort so completely? From her origins as a cursed Maledictus in Fantastic Beasts to her final moments as Voldemort’s closest ally, we’re exploring a chilling theory that could explain everything about Voldemort’s favorite companion. Des Moines, IA - 9/19 (SOLD OUT) St. Paul, MN - 9/20 (SOLD OUT) Cleveland, OH - 9/25 (SOLD OUT) #HarryPotter #SuperCarlinBrothers #wizardingworld | V310: =IF(AND(P310>=Calendar!$K$2,P310<EDATE(Calendar!$K$2,1),OR(Calendar!$K$4="*",N310=Calendar!$K$4)),P310*100+COUNTIFS($P$6:$P$3267,P310,$Q$6:$Q$3267,"<="&Q310,$N$6:$N$3267,Calendar!$K$4),"") | W310: =IF(AND(B310=Queue!$C$4,OR(Queue!$K$4="*",N310=Queue!$K$4)),Q310,"")
A311: =IF(M311="","",HYPERLINK("https://www.youtube.com/watch?v="&M311,"▶")) | B311: =IF(C311<>"",C311,IF(P311<=IFERROR(INDEX(tblChannels[Watched Through],MATCH(N311,tblChannels[Channel ID],0)),0),"Watched","Unwatched")) | E311: 45849.417 | F311: Popcorn Culture | G311: J on 30A | Popcorn Culture | H311: 0.045659722 | I311: 3025 | J311: 148 | K311: 14 | N311: UCHfIbq9thHPC8yrKjAdJgDA | O311: 45849.583 | P311: 45849 | Q311: 2957 | R311: No Video ID yet | U311: In the 292nd episode of the Pop, Ben and J discuss Luke going to camp, J’s anniversary vacation, travel stress and Birkenstocks. F1 movie - Richard Scarry - Birkenstocks - Get your tickets for Through the Griffin Tour MIDWEST here: St. Louis, MO - 9/17 (low ticket warning) Detroit, MI - 9/24 (low ticket warning) Alternative Titles The Coolest Kid in 7th Grade 00:00 - Intro, Sunday Scaries 06:44 - J and Beth’s Anniversary | V311: =IF(AND(P311>=Calendar!$K$2,P311<EDATE(Calendar!$K$2,1),OR(Calendar!$K$4="*",N311=Calendar!$K$4)),P311*100+COUNTIFS($P$6:$P$3267,P311,$Q$6:$Q$3267,"<="&Q311,$N$6:$N$3267,Calendar!$K$4),"") | W311: =IF(AND(B311=Queue!$C$4,OR(Queue!$K$4="*",N311=Queue!$K$4)),Q311,"")
A312: =IF(M312="","",HYPERLINK("https://www.youtube.com/watch?v="&M312,"▶")) | B312: =IF(C312<>"",C312,IF(P312<=IFERROR(INDEX(tblChannels[Watched Through],MATCH(N312,tblChannels[Channel ID],0)),0),"Watched","Unwatched")) | E312: 45847.617 | F312: Super Carlin Brothers | G312: How ELIO Fits Into The Pixar Theory | H312: 0.01318287 | I312: 43184 | J312: 2186 | K312: 276 | N312: UCKZo4N0lVPccBkSiuyVh4yg | O312: 45847.784 | P312: 45847 | Q312: 2956 | R312: No Video ID yet | U312: Get started with AG1 Next Gen for less than $3 a day when you subscribe! Elio is finally here—and with it, a ton of new Pixar Theory questions! How do aliens fit into the timeline? Why didn’t they help Earth during the WALL-E era? And did we just uncover the true origin of the Cars universe?? Join J as he breaks down every clue, connection, and Easter egg Elio gives us and how it fits perfectly into the grand Pixar timeline. From space junk to golden records to a Giulia cameo from Luca, Elio might be the missing link between WALL-E, Onward, and… Car Clones?! Buckle up, it’s about to get galactic. 👕 Show your fandom with our 2025 Pride Shirt! 👉 🎟 THROUGH THE GRIFFIN TOUR – Midwest Dates ON SALE NOW! 👉 • Indianapolis, IN - 9/16 • St. Louis, MO - 9/17 • Des Moines, IA - 9/19 • St. Paul, MN - 9/20 • Milwaukee, WI - 9/21 • Chicago, IL - 9/23 • Detroit, MI - 9/24 • Cleveland, OH - 9/25 #PixarTheory #Elio #SuperCarlinBrothers | V312: =IF(AND(P312>=Calendar!$K$2,P312<EDATE(Calendar!$K$2,1),OR(Calendar!$K$4="*",N312=Calendar!$K$4)),P312*100+COUNTIFS($P$6:$P$3267,P312,$Q$6:$Q$3267,"<="&Q312,$N$6:$N$3267,Calendar!$K$4),"") | W312: =IF(AND(B312=Queue!$C$4,OR(Queue!$K$4="*",N312=Queue!$K$4)),Q312,"")
A313: =IF(M313="","",HYPERLINK("https://www.youtube.com/watch?v="&M313,"▶")) | B313: =IF(C313<>"",C313,IF(P313<=IFERROR(INDEX(tblChannels[Watched Through],MATCH(N313,tblChannels[Channel ID],0)),0),"Watched","Unwatched")) | E313: 45844.417 | F313: Through The Griffin Door | G313: The Owlery Special Part 2! | H313: 0.051539352 | I313: 28383 | J313: 880 | K313: 382 | N313: UCEscP6ETYXWSSvsNrDHekMQ | O313: 45844.583 | P313: 45844 | Q313: 2955 | R313: No Video ID yet | U313: Please enjoy this preview into The Owlery over on Patreon! We get a lot of interesting questions over there and love answering them so we wanted to share a few of them with you over on the main channel! Support us on Patreon to listen to MORE Owlery questions AND get your GUMPSTER FIRE pin: THROUGH THE GRIFFIN TOUR MIDWEST TICKETS ARE ON SALE RIGHT NOW St. Louis, MO - 9/17 (low ticket warning) Detroit, MI - 9/24 (low ticket warning) Get your Sorting Candle HERE: \ 05:03 - What If Harry Killed Bellatrix? 31:52 - All About Metamorphmagi 55:46 - When Did Petunia Tell Vernon About Magic? | V313: =IF(AND(P313>=Calendar!$K$2,P313<EDATE(Calendar!$K$2,1),OR(Calendar!$K$4="*",N313=Calendar!$K$4)),P313*100+COUNTIFS($P$6:$P$3267,P313,$Q$6:$Q$3267,"<="&Q313,$N$6:$N$3267,Calendar!$K$4),"") | W313: =IF(AND(B313=Queue!$C$4,OR(Queue!$K$4="*",N313=Queue!$K$4)),Q313,"")
A314: =IF(M314="","",HYPERLINK("https://www.youtube.com/watch?v="&M314,"▶")) | B314: =IF(C314<>"",C314,IF(P314<=IFERROR(INDEX(tblChannels[Watched Through],MATCH(N314,tblChannels[Channel ID],0)),0),"Watched","Unwatched")) | E314: 45842.625 | F314: Super Carlin Brothers | G314: J vs Ben: Impossible FRED & GEORGE Harry Potter Trivia Quiz | H314: 0.023657407 | I314: 81860 | J314: 3396 | K314: 264 | N314: UCKZo4N0lVPccBkSiuyVh4yg | O314: 45842.792 | P314: 45842 | Q314: 2954 | R314: No Video ID yet | U314: Get started at and use code jvsb50off to get 50% off plus FREE shipping on your first box. Check out our new SUPER Shirt at Think you can tell Fred and George apart? Today J and Ben face off once again to celebrate the chaotic brilliance of the Weasley twins with a Fred & George "Who Said What" Quiz! Can you spot the difference between Gred and Forge? Because we definitely struggled… This quiz is packed with iconic quotes submitted by Super Carlin Brothers Patrons aka THE QUIZ MASTERS—so huge thanks to everyone who helped make this possible! Play along and see if you can beat J or Ben's scores Quotes submitted by: Teghan Denlinger, Focus Pending, Jennifer Froh, Bradferd, Keeli Rae and Oryan, Looncall, Julie Sherwood and Tara Walker, Captain Hawk, Elli Collins, Sarah Makiyama, Oryan, Dola, LawNinja, Peyton Taylor, Wesley Walker Play Along With Us 👉 Show your colors AND your fandom! Grab the SCB Pride Month shirt now! 👉 Des Moines, IA - 9/19 (SOLD OUT) St. Paul, MN - 9/20 (SOLD OUT) Cleveland, OH - 9/25 (SOLD OUT) Written by :: QUIZMASTERS! Hosted by :: Isybelle Christley | V314: =IF(AND(P314>=Calendar!$K$2,P314<EDATE(Calendar!$K$2,1),OR(Calendar!$K$4="*",N314=Calendar!$K$4)),P314*100+COUNTIFS($P$6:$P$3267,P314,$Q$6:$Q$3267,"<="&Q314,$N$6:$N$3267,Calendar!$K$4),"") | W314: =IF(AND(B314=Queue!$C$4,OR(Queue!$K$4="*",N314=Queue!$K$4)),Q314,"")
A315: =IF(M315="","",HYPERLINK("https://www.youtube.com/watch?v="&M315,"▶")) | B315: =IF(C315<>"",C315,IF(P315<=IFERROR(INDEX(tblChannels[Watched Through],MATCH(N315,tblChannels[Channel ID],0)),0),"Watched","Unwatched")) | E315: 45842.417 | F315: Popcorn Culture | G315: Popcorn Never Goes Bad | Popcorn Culture | H315: 0.056226852 | I315: 3197 | J315: 152 | K315: 29 | N315: UCHfIbq9thHPC8yrKjAdJgDA | O315: 45842.583 | P315: 45842 | Q315: 2953 | R315: No Video ID yet | U315: In previous After the Final Pop Episodes, Ben and J discussed what letters of the alphabet are best, their Pringle eating competition and how to resolve conflict from your distant past. If you would like to get in on more of this ATFP action you can do so here: Get your tickets for Through the Griffin Tour MIDWEST here: St. Louis, MO - 9/17 (low ticket warning) Detroit, MI - 9/24 (low ticket warning) 03:03 - ATFP 286: Alphabet Rankings 31:09 - ATFP 211: Pringles 48:22 - ATFP 198: Conflict Resolution Edited by: Isybelle Christley and Ethan Edghill | V315: =IF(AND(P315>=Calendar!$K$2,P315<EDATE(Calendar!$K$2,1),OR(Calendar!$K$4="*",N315=Calendar!$K$4)),P315*100+COUNTIFS($P$6:$P$3267,P315,$Q$6:$Q$3267,"<="&Q315,$N$6:$N$3267,Calendar!$K$4),"") | W315: =IF(AND(B315=Queue!$C$4,OR(Queue!$K$4="*",N315=Queue!$K$4)),Q315,"")
A316: =IF(M316="","",HYPERLINK("https://www.youtube.com/watch?v="&M316,"▶")) | B316: =IF(C316<>"",C316,IF(P316<=IFERROR(INDEX(tblChannels[Watched Through],MATCH(N316,tblChannels[Channel ID],0)),0),"Watched","Unwatched")) | E316: 45840.667 | F316: Super Carlin Brothers | G316: The Pensieve’s Dark Twin REVEALED | Harry Potter Film Theory | H316: 0.013275463 | I316: 153963 | J316: 6496 | K316: 804 | N316: UCKZo4N0lVPccBkSiuyVh4yg | O316: 45840.833 | P316: 45840 | Q316: 2952 | R316: No Video ID yet | U316: This episode is sponsored by BetterHelp - go to to get 10% off your first month. Today, J dives into the Wizarding World of Harry Potter to reveal the Pensieve’s Dark twin and how it operates in the exact opposite way of the Pensieve. PLUS how this shows yet another of Voldemort’s shortcomings! Show your colors AND your fandom! Grab the SCB Pride Month shirt now! 👉 Des Moines, IA - 9/19 (SOLD OUT) St. Paul, MN - 9/20 (SOLD OUT) Cleveland, OH - 9/25 (SOLD OUT) | V316: =IF(AND(P316>=Calendar!$K$2,P316<EDATE(Calendar!$K$2,1),OR(Calendar!$K$4="*",N316=Calendar!$K$4)),P316*100+COUNTIFS($P$6:$P$3267,P316,$Q$6:$Q$3267,"<="&Q316,$N$6:$N$3267,Calendar!$K$4),"") | W316: =IF(AND(B316=Queue!$C$4,OR(Queue!$K$4="*",N316=Queue!$K$4)),Q316,"")
... A328: =IF(M328="","",HYPERLINK("https://www.youtube.com/watch?v="&M328,"▶")) | B328: =IF(C328<>"",C328,IF(P328<=IFERROR(INDEX(tblChannels[Watched Through],MATCH(N328,tblChannels[Channel ID],0)),0),"Watched","Unwatched")) | E328: 45823.417 | F328: Through The Griffin Door | G328: Chapter 30: The Pensive | Goblet of Fire | H328: 0.086053241 | I328: 65676 | J328: 1517 | K328: 506 | N328: UCEscP6ETYXWSSvsNrDHekMQ | O328: 45823.584 | P328: 45823 | Q328: 2940 | R328: No Video ID yet | U328: This episode is sponsored by Pair Eyewear – Go to paireyewear.com and use code 'GRIFFIN' for 15% off your first pair. Join J and Ben as they dive into Chapter 30 of the Goblet of Fire and discuss Dumbledore’s office, Fawkes, mechanics of the magic, Karkaroff’s trial, meeting the real Moody, Ludo Bagman’s trial, Barty Crouch Jr.’s trial, and telling Dumbledore about the dream. Barty Crouch Jr’s HORCRUX - THROUGH THE GRIFFIN TOUR MIDWEST TICKETS ARE ON SALE RIGHT NOW St. Louis, MO - 9/17a Support us on Patreon AND GET YOUR GUMPSTER FIRE PIN: 08:26 - Chapter Breakdown 43:08 - Ad Break (Pair Eyewear) 45:17 - More Chapter Breakdown 1:56:23 - Closing Thoughts and Review | V328: =IF(AND(P328>=Calendar!$K$2,P328<EDATE(Calendar!$K$2,1),OR(Calendar!$K$4="*",N328=Calendar!$K$4)),P328*100+COUNTIFS($P$6:$P$3267,P328,$Q$6:$Q$3267,"<="&Q328,$N$6:$N$3267,Calendar!$K$4),"") | W328: =IF(AND(B328=Queue!$C$4,OR(Queue!$K$4="*",N328=Queue!$K$4)),Q328,"")
A329: =IF(M329="","",HYPERLINK("https://www.youtube.com/watch?v="&M329,"▶")) | B329: =IF(C329<>"",C329,IF(P329<=IFERROR(INDEX(tblChannels[Watched Through],MATCH(N329,tblChannels[Channel ID],0)),0),"Watched","Unwatched")) | E329: 45822.216 | F329: Super Carlin Gaming | G329: JOURNEY TOGETHER - Pokemon Box Breakers SEASON 15 - Episode 2 - 06/13/2025 | H329: 0.11417824 | I329: 842 | J329: 30 | K329: 3 | N329: UCor_9jRnNNZVzTuQ92PKsaQ | O329: 45822.383 | P329: 45822 | Q329: 2939 | R329: No Video ID yet | V329: =IF(AND(P329>=Calendar!$K$2,P329<EDATE(Calendar!$K$2,1),OR(Calendar!$K$4="*",N329=Calendar!$K$4)),P329*100+COUNTIFS($P$6:$P$3267,P329,$Q$6:$Q$3267,"<="&Q329,$N$6:$N$3267,Calendar!$K$4),"") | W329: =IF(AND(B329=Queue!$C$4,OR(Queue!$K$4="*",N329=Queue!$K$4)),Q329,"")
A330: =IF(M330="","",HYPERLINK("https://www.youtube.com/watch?v="&M330,"▶")) | B330: =IF(C330<>"",C330,IF(P330<=IFERROR(INDEX(tblChannels[Watched Through],MATCH(N330,tblChannels[Channel ID],0)),0),"Watched","Unwatched")) | E330: 45821.705 | F330: Super Carlin Brothers | G330: Are Snape and Krum… BROTHERS?! | Harry Potter Film Theory | H330: 0.0092361111 | I330: 71393 | J330: 3494 | K330: 594 | N330: UCKZo4N0lVPccBkSiuyVh4yg | O330: 45821.872 | P330: 45821 | Q330: 2938 | R330: No Video ID yet | U330: Go to to sign up for your $1-per-month trial period. This episode is sponsored by BetterHelp. Go to to get 10% off your first month. Today Ben dives into the Wizarding World of Harry Potter to try and answer an unsuspecting question. Are Severus Snape and Viktor Krum secretly brothers? At first glance, it sounds completely bonkers… until you look at the shockingly similar physical descriptions, sketchy parental backstories, and eerily shared behaviors. In this deep-dive Harry Potter theory, we explore whether Snape’s muggle father, Tobias Snape, could have abandoned Eileen Prince… only to start a second family in Bulgaria. That’s right—could Krum and Snape actually share a parent without ever knowing it? From hooked noses to brilliant muggle-born crushes, the signs are everywhere if you know where to look.. #supercarlinbrothers #HarryPotter #Snape Written by :: J and Ben Carlin | V330: =IF(AND(P330>=Calendar!$K$2,P330<EDATE(Calendar!$K$2,1),OR(Calendar!$K$4="*",N330=Calendar!$K$4)),P330*100+COUNTIFS($P$6:$P$3267,P330,$Q$6:$Q$3267,"<="&Q330,$N$6:$N$3267,Calendar!$K$4),"") | W330: =IF(AND(B330=Queue!$C$4,OR(Queue!$K$4="*",N330=Queue!$K$4)),Q330,"")
A331: =IF(M331="","",HYPERLINK("https://www.youtube.com/watch?v="&M331,"▶")) | B331: =IF(C331<>"",C331,IF(P331<=IFERROR(INDEX(tblChannels[Watched Through],MATCH(N331,tblChannels[Channel ID],0)),0),"Watched","Unwatched")) | E331: 45821.417 | F331: Popcorn Culture | G331: A Funny Snake Story | Popcorn Culture | H331: 0.047476852 | I331: 3276 | J331: 159 | K331: 26 | N331: UCHfIbq9thHPC8yrKjAdJgDA | O331: 45821.583 | P331: 45821 | Q331: 2937 | R331: No Video ID yet | U331: In the 288th episode of the pop, Ben and J discuss alligator and snake stories, the Nate Bargatze Show, Mario Kart DESPAIR, garden updates, dopamine hits, and remote control cars. Nate Bargatze - Will Forte - Get your tickets for Through the Griffin Tour MIDWEST here: GATORS 00:00 - Intro, Gators and Snakes 13:14 - Nate Bargatze’s Special Guest 21:29 - Mario Kart World 37:52 - Garden Update | V331: =IF(AND(P331>=Calendar!$K$2,P331<EDATE(Calendar!$K$2,1),OR(Calendar!$K$4="*",N331=Calendar!$K$4)),P331*100+COUNTIFS($P$6:$P$3267,P331,$Q$6:$Q$3267,"<="&Q331,$N$6:$N$3267,Calendar!$K$4),"") | W331: =IF(AND(B331=Queue!$C$4,OR(Queue!$K$4="*",N331=Queue!$K$4)),Q331,"")
A332: =IF(M332="","",HYPERLINK("https://www.youtube.com/watch?v="&M332,"▶")) | B332: =IF(C332<>"",C332,IF(P332<=IFERROR(INDEX(tblChannels[Watched Through],MATCH(N332,tblChannels[Channel ID],0)),0),"Watched","Unwatched")) | E332: 45819.729 | F332: Super Carlin Brothers | G332: Reacting to EVERY Harry Potter HBO Casting So Far | Harry Potter Film Theory | H332: 0.013449074 | I332: 162980 | J332: 7478 | K332: 3052 | N332: UCKZo4N0lVPccBkSiuyVh4yg | O332: 45819.896 | P332: 45819 | Q332: 2936 | R332: No Video ID yet | U332: Today J dives into the Wizarding World of Harry Potter to give his honest thoughts about the casting of every character we know about so far including Paapa Essiedu as Severus Snape, John Lithgow as Albus Dumbledore, Janet McTeer as McGonagall, Nick Frost as Hagrid, and Katherine Parkinson as Molly and everyone else!! Written by :: J and Ben Carlin | V332: =IF(AND(P332>=Calendar!$K$2,P332<EDATE(Calendar!$K$2,1),OR(Calendar!$K$4="*",N332=Calendar!$K$4)),P332*100+COUNTIFS($P$6:$P$3267,P332,$Q$6:$Q$3267,"<="&Q332,$N$6:$N$3267,Calendar!$K$4),"") | W332: =IF(AND(B332=Queue!$C$4,OR(Queue!$K$4="*",N332=Queue!$K$4)),Q332,"")
A333: =IF(M333="","",HYPERLINK("https://www.youtube.com/watch?v="&M333,"▶")) | B333: =IF(C333<>"",C333,IF(P333<=IFERROR(INDEX(tblChannels[Watched Through],MATCH(N333,tblChannels[Channel ID],0)),0),"Watched","Unwatched")) | E333: 45819.62 | F333: Super Carlin Brothers | G333: Moana wasn't the first Chosen One.. #Disney | H333: 0.0020833333 | I333: 890031 | J333: 73573 | K333: 259 | N333: UCKZo4N0lVPccBkSiuyVh4yg | O333: 45819.787 | P333: 45819 | Q333: 2935 | R333: No Video ID yet | U333: Moana wasn't the first Chosen One by the ocean... just the first to finally pass the test. | V333: =IF(AND(P333>=Calendar!$K$2,P333<EDATE(Calendar!$K$2,1),OR(Calendar!$K$4="*",N333=Calendar!$K$4)),P333*100+COUNTIFS($P$6:$P$3267,P333,$Q$6:$Q$3267,"<="&Q333,$N$6:$N$3267,Calendar!$K$4),"") | W333: =IF(AND(B333=Queue!$C$4,OR(Queue!$K$4="*",N333=Queue!$K$4)),Q333,"")
A334: =IF(M334="","",HYPERLINK("https://www.youtube.com/watch?v="&M334,"▶")) | B334: =IF(C334<>"",C334,IF(P334<=IFERROR(INDEX(tblChannels[Watched Through],MATCH(N334,tblChannels[Channel ID],0)),0),"Watched","Unwatched")) | E334: 45817.84 | F334: Super Carlin Brothers | G334: What Happened To Kristoff’s Parents? #disney | H334: 0.0020949074 | I334: 182563 | J334: 17227 | K334: 89 | N334: UCKZo4N0lVPccBkSiuyVh4yg | O334: 45818.007 | P334: 45817 | Q334: 2934 | R334: No Video ID yet | U334: What ever happened to Kristoff's Parents in Frozen?? | V334: =IF(AND(P334>=Calendar!$K$2,P334<EDATE(Calendar!$K$2,1),OR(Calendar!$K$4="*",N334=Calendar!$K$4)),P334*100+COUNTIFS($P$6:$P$3267,P334,$Q$6:$Q$3267,"<="&Q334,$N$6:$N$3267,Calendar!$K$4),"") | W334: =IF(AND(B334=Queue!$C$4,OR(Queue!$K$4="*",N334=Queue!$K$4)),Q334,"")
A335: =IF(M335="","",HYPERLINK("https://www.youtube.com/watch?v="&M335,"▶")) | B335: =IF(C335<>"",C335,IF(P335<=IFERROR(INDEX(tblChannels[Watched Through],MATCH(N335,tblChannels[Channel ID],0)),0),"Watched","Unwatched")) | E335: 45816.417 | F335: Through The Griffin Door | G335: Chapter 29: The Dream | Goblet of Fire | H335: 0.063622685 | I335: 53144 | J335: 1380 | K335: 404 | N335: UCEscP6ETYXWSSvsNrDHekMQ | O335: 45816.583 | P335: 45816 | Q335: 2933 | R335: No Video ID yet | U335: This episode is sponsored by Pair Eyewear – Go to paireyewear.com and use code 'GRIFFIN' for 15% off your first pair. Join J and Ben as they dive into Chapter 29 of the Goblet of Fire and discuss the golden trio theororizing, running into the twins, BCJ having a horcrux, practicing for the third task, the actual dream and Harry overhearing convenient plot points Hogwarts is Alive - THROUGH THE GRIFFIN TOUR MIDWEST TICKETS ARE ON SALE RIGHT NOW St. Louis, MO - 9/17a Support us on Patreon AND GET YOUR GUMPSTER FIRE PIN: 10:32 - Chapter Breakdown 30:12 - Ad Break (Pair Eyewear) 31:58 - More Chapter Breakdown 1:23:11 - Closing Thoughts and Review | V335: =IF(AND(P335>=Calendar!$K$2,P335<EDATE(Calendar!$K$2,1),OR(Calendar!$K$4="*",N335=Calendar!$K$4)),P335*100+COUNTIFS($P$6:$P$3267,P335,$Q$6:$Q$3267,"<="&Q335,$N$6:$N$3267,Calendar!$K$4),"") | W335: =IF(AND(B335=Queue!$C$4,OR(Queue!$K$4="*",N335=Queue!$K$4)),Q335,"")
A336: =IF(M336="","",HYPERLINK("https://www.youtube.com/watch?v="&M336,"▶")) | B336: =IF(C336<>"",C336,IF(P336<=IFERROR(INDEX(tblChannels[Watched Through],MATCH(N336,tblChannels[Channel ID],0)),0),"Watched","Unwatched")) | E336: 45814.678 | F336: Super Carlin Brothers | G336: Barty Crouch Jr’s HORCRUX | Harry Potter Film Theory | H336: 0.010185185 | I336: 179627 | J336: 7938 | K336: 956 | N336: UCKZo4N0lVPccBkSiuyVh4yg | O336: 45814.844 | P336: 45814 | Q336: 2932 | R336: No Video ID yet | U336: Today Ben dives into the Wizarding World of Harry Potter to find out if one of it’s most notorious villains, Barty Crouch Jr., is still waiting in the wings to come back and wreak havoc once again! Did he make a Horcrux? What was it? Where is it? And what actually became of Barty Crouch Jr.? | V336: =IF(AND(P336>=Calendar!$K$2,P336<EDATE(Calendar!$K$2,1),OR(Calendar!$K$4="*",N336=Calendar!$K$4)),P336*100+COUNTIFS($P$6:$P$3267,P336,$Q$6:$Q$3267,"<="&Q336,$N$6:$N$3267,Calendar!$K$4),"") | W336: =IF(AND(B336=Queue!$C$4,OR(Queue!$K$4="*",N336=Queue!$K$4)),Q336,"")
A337: =IF(M337="","",HYPERLINK("https://www.youtube.com/watch?v="&M337,"▶")) | B337: =IF(C337<>"",C337,IF(P337<=IFERROR(INDEX(tblChannels[Watched Through],MATCH(N337,tblChannels[Channel ID],0)),0),"Watched","Unwatched")) | E337: 45814.674 | F337: Super Carlin Brothers | G337: How Dumbledore SPIES On People! #harrypotter | H337: 0.0017476852 | I337: 76902 | J337: 4849 | K337: 108 | N337: UCKZo4N0lVPccBkSiuyVh4yg | O337: 45814.84 | P337: 45814 | Q337: 2931 | R337: No Video ID yet | U337: Dumbledore's deluminator is a SUPER useful magical tool for putting out lights and finding your friends.. but has Dumbledore been using it to spy on everyone too!? | V337: =IF(AND(P337>=Calendar!$K$2,P337<EDATE(Calendar!$K$2,1),OR(Calendar!$K$4="*",N337=Calendar!$K$4)),P337*100+COUNTIFS($P$6:$P$3267,P337,$Q$6:$Q$3267,"<="&Q337,$N$6:$N$3267,Calendar!$K$4),"") | W337: =IF(AND(B337=Queue!$C$4,OR(Queue!$K$4="*",N337=Queue!$K$4)),Q337,"")
A338: =IF(M338="","",HYPERLINK("https://www.youtube.com/watch?v="&M338,"▶")) | B338: =IF(C338<>"",C338,IF(P338<=IFERROR(INDEX(tblChannels[Watched Through],MATCH(N338,tblChannels[Channel ID],0)),0),"Watched","Unwatched")) | E338: 45814.555 | F338: Popcorn Culture | G338: LETS MAKE CORNDOGS OUTSIDE | Popcorn Culture | H338: 0.00083333333 | I338: 6773 | J338: 526 | K338: 17 | N338: UCHfIbq9thHPC8yrKjAdJgDA | O338: 45814.722 | P338: 45814 | Q338: 2930 | R338: No Video ID yet | U338: Watch as Ben fulfills his lifelong dream of making a SUPER FUN family camping trip, complete with fresh corndogs. | V338: =IF(AND(P338>=Calendar!$K$2,P338<EDATE(Calendar!$K$2,1),OR(Calendar!$K$4="*",N338=Calendar!$K$4)),P338*100+COUNTIFS($P$6:$P$3267,P338,$Q$6:$Q$3267,"<="&Q338,$N$6:$N$3267,Calendar!$K$4),"") | W338: =IF(AND(B338=Queue!$C$4,OR(Queue!$K$4="*",N338=Queue!$K$4)),Q338,"")
A339: =IF(M339="","",HYPERLINK("https://www.youtube.com/watch?v="&M339,"▶")) | B339: =IF(C339<>"",C339,IF(P339<=IFERROR(INDEX(tblChannels[Watched Through],MATCH(N339,tblChannels[Channel ID],0)),0),"Watched","Unwatched")) | E339: 45814.417 | F339: Popcorn Culture | G339: Campfire Corndogs | Popcorn Culture | H339: 0.04349537 | I339: 3197 | J339: 158 | K339: 14 | N339: UCHfIbq9thHPC8yrKjAdJgDA | O339: 45814.583 | P339: 45814 | Q339: 2929 | R339: No Video ID yet | U339: In the 287th episode of the Pop, Ben and J discuss losing sleep, Outdoor Boys stopping YouTube, and their latest family camping trip. The Outdoor Boys Goodbye - Get your tickets for Through the Griffin Tour MIDWEST here: Ben’s Bag of Tricks Shovel Bread! 00:00 - Intro, Losing Sleep 15:12 - The Family Camping Trip 18:52 - (better audio) | V339: =IF(AND(P339>=Calendar!$K$2,P339<EDATE(Calendar!$K$2,1),OR(Calendar!$K$4="*",N339=Calendar!$K$4)),P339*100+COUNTIFS($P$6:$P$3267,P339,$Q$6:$Q$3267,"<="&Q339,$N$6:$N$3267,Calendar!$K$4),"") | W339: =IF(AND(B339=Queue!$C$4,OR(Queue!$K$4="*",N339=Queue!$K$4)),Q339,"")
A340: =IF(M340="","",HYPERLINK("https://www.youtube.com/watch?v="&M340,"▶")) | B340: =IF(C340<>"",C340,IF(P340<=IFERROR(INDEX(tblChannels[Watched Through],MATCH(N340,tblChannels[Channel ID],0)),0),"Watched","Unwatched")) | E340: 45812.703 | F340: Super Carlin Brothers | G340: J vs Ben: Who Said What? Harry Potter TRIVIA Quiz | H340: 0.032407407 | I340: 136700 | J340: 4376 | K340: 435 | N340: UCKZo4N0lVPccBkSiuyVh4yg | O340: 45812.87 | P340: 45812 | Q340: 2928 | R340: No Video ID yet | U340: Go to and use code jvsb50off to get 50% off and free shipping on your first box. Today J and Ben face off once more to find out who knows more about who said what in Harry Potter! Given just an out of context quote we have to name the character and book the quote is from! Written by :: QUIZMASTERS! Read by :: Kat Stine | V340: =IF(AND(P340>=Calendar!$K$2,P340<EDATE(Calendar!$K$2,1),OR(Calendar!$K$4="*",N340=Calendar!$K$4)),P340*100+COUNTIFS($P$6:$P$3267,P340,$Q$6:$Q$3267,"<="&Q340,$N$6:$N$3267,Calendar!$K$4),"") | W340: =IF(AND(B340=Queue!$C$4,OR(Queue!$K$4="*",N340=Queue!$K$4)),Q340,"")
A341: =IF(M341="","",HYPERLINK("https://www.youtube.com/watch?v="&M341,"▶")) | B341: =IF(C341<>"",C341,IF(P341<=IFERROR(INDEX(tblChannels[Watched Through],MATCH(N341,tblChannels[Channel ID],0)),0),"Watched","Unwatched")) | E341: 45812.649 | F341: Super Carlin Brothers | G341: Hunger Games MASTER Plan #HungerGames | H341: 0.0020833333 | I341: 107972 | J341: 5341 | K341: 104 | N341: UCKZo4N0lVPccBkSiuyVh4yg | O341: 45812.815 | P341: 45812 | Q341: 2927 | R341: No Video ID yet | U341: President Coin manipulated every aspect of Katniss' life from the moment Prim's name came out of the Reaping. | V341: =IF(AND(P341>=Calendar!$K$2,P341<EDATE(Calendar!$K$2,1),OR(Calendar!$K$4="*",N341=Calendar!$K$4)),P341*100+COUNTIFS($P$6:$P$3267,P341,$Q$6:$Q$3267,"<="&Q341,$N$6:$N$3267,Calendar!$K$4),"") | W341: =IF(AND(B341=Queue!$C$4,OR(Queue!$K$4="*",N341=Queue!$K$4)),Q341,"")
... A358: =IF(M358="","",HYPERLINK("https://www.youtube.com/watch?v="&M358,"▶")) | B358: =IF(C358<>"",C358,IF(P358<=IFERROR(INDEX(tblChannels[Watched Through],MATCH(N358,tblChannels[Channel ID],0)),0),"Watched","Unwatched")) | E358: 45787.417 | F358: Super Carlin Brothers | G358: Through the Griffin Door Supercut: Goblet of Fire Chapters 21-24 | H358: 0.2337037 | I358: 16147 | J358: 250 | K358: 59 | N358: UCKZo4N0lVPccBkSiuyVh4yg | O358: 45787.584 | P358: 45787 | Q358: 2910 | R358: No Video ID yet | U358: 0:00:00 - Chapter 22: The Unexpected Task 1:36:07 - Chapter 23: The Yule Ball 3:46:16 - Chapter 24: Rita Skeeter's Scoop | V358: =IF(AND(P358>=Calendar!$K$2,P358<EDATE(Calendar!$K$2,1),OR(Calendar!$K$4="*",N358=Calendar!$K$4)),P358*100+COUNTIFS($P$6:$P$3267,P358,$Q$6:$Q$3267,"<="&Q358,$N$6:$N$3267,Calendar!$K$4),"") | W358: =IF(AND(B358=Queue!$C$4,OR(Queue!$K$4="*",N358=Queue!$K$4)),Q358,"")
A359: =IF(M359="","",HYPERLINK("https://www.youtube.com/watch?v="&M359,"▶")) | B359: =IF(C359<>"",C359,IF(P359<=IFERROR(INDEX(tblChannels[Watched Through],MATCH(N359,tblChannels[Channel ID],0)),0),"Watched","Unwatched")) | E359: 45787.211 | F359: Super Carlin Gaming | G359: JOURNEY TOGETHER - Pokemon Box Breakers SEASON 15 - Episode 1 - 05/09/2025 | H359: 0.11145833 | I359: 1536 | J359: 48 | K359: 1 | N359: UCor_9jRnNNZVzTuQ92PKsaQ | O359: 45787.378 | P359: 45787 | Q359: 2909 | R359: No Video ID yet | V359: =IF(AND(P359>=Calendar!$K$2,P359<EDATE(Calendar!$K$2,1),OR(Calendar!$K$4="*",N359=Calendar!$K$4)),P359*100+COUNTIFS($P$6:$P$3267,P359,$Q$6:$Q$3267,"<="&Q359,$N$6:$N$3267,Calendar!$K$4),"") | W359: =IF(AND(B359=Queue!$C$4,OR(Queue!$K$4="*",N359=Queue!$K$4)),Q359,"")
A360: =IF(M360="","",HYPERLINK("https://www.youtube.com/watch?v="&M360,"▶")) | B360: =IF(C360<>"",C360,IF(P360<=IFERROR(INDEX(tblChannels[Watched Through],MATCH(N360,tblChannels[Channel ID],0)),0),"Watched","Unwatched")) | E360: 45786.71 | F360: Super Carlin Brothers | G360: What If Moody Defeated Barty Crouch Jr? | Harry Potter Film Theory | H360: 0.012372685 | I360: 153960 | J360: 6087 | K360: 794 | N360: UCKZo4N0lVPccBkSiuyVh4yg | O360: 45786.877 | P360: 45786 | Q360: 2908 | R360: No Video ID yet | U360: This episode is sponsored by BetterHelp - go to to get 10% off your first month. Today J dives into the Wizarding World of Harry Potter to find out: What If Moody had never been captured and just defeated Wormtail and Barty Crouch Jr.? Does Voldemort ever come back? Does Harry live a normal life? Does CEDRIC Live??? | V360: =IF(AND(P360>=Calendar!$K$2,P360<EDATE(Calendar!$K$2,1),OR(Calendar!$K$4="*",N360=Calendar!$K$4)),P360*100+COUNTIFS($P$6:$P$3267,P360,$Q$6:$Q$3267,"<="&Q360,$N$6:$N$3267,Calendar!$K$4),"") | W360: =IF(AND(B360=Queue!$C$4,OR(Queue!$K$4="*",N360=Queue!$K$4)),Q360,"")
A361: =IF(M361="","",HYPERLINK("https://www.youtube.com/watch?v="&M361,"▶")) | B361: =IF(C361<>"",C361,IF(P361<=IFERROR(INDEX(tblChannels[Watched Through],MATCH(N361,tblChannels[Channel ID],0)),0),"Watched","Unwatched")) | E361: 45786.5 | F361: Super Carlin Brothers | G361: Harry IS The Sorcerer’s Stone #harrypotter | H361: 0.0020833333 | I361: 192775 | J361: 12253 | K361: 161 | N361: UCKZo4N0lVPccBkSiuyVh4yg | O361: 45786.667 | P361: 45786 | Q361: 2907 | R361: No Video ID yet | U361: Harry Potter may not use the Sorcerer's Stone but he doesn't need to because he is a living, walking, talking version of the stone himself! | V361: =IF(AND(P361>=Calendar!$K$2,P361<EDATE(Calendar!$K$2,1),OR(Calendar!$K$4="*",N361=Calendar!$K$4)),P361*100+COUNTIFS($P$6:$P$3267,P361,$Q$6:$Q$3267,"<="&Q361,$N$6:$N$3267,Calendar!$K$4),"") | W361: =IF(AND(B361=Queue!$C$4,OR(Queue!$K$4="*",N361=Queue!$K$4)),Q361,"")
A362: =IF(M362="","",HYPERLINK("https://www.youtube.com/watch?v="&M362,"▶")) | B362: =IF(C362<>"",C362,IF(P362<=IFERROR(INDEX(tblChannels[Watched Through],MATCH(N362,tblChannels[Channel ID],0)),0),"Watched","Unwatched")) | E362: 45786.417 | F362: Popcorn Culture | G362: J DID A TRIATHLON!! | Popcorn Culture | H362: 0.046157407 | I362: 3254 | J362: 158 | K362: 16 | N362: UCHfIbq9thHPC8yrKjAdJgDA | O362: 45786.583 | P362: 45786 | Q362: 2906 | R362: No Video ID yet | U362: IN the 283rd episode of the Pop, Ben and J discuss J’s triathlon experience, chasing the novelty of change, tricking out Ben’s car and J’s garage. Get your tickets for Through the Griffin Tour MIDWEST here: The Novelty of Change 00:00 - Intro, J’s Triathlon! 37:47 - Ben’s Truck and Change | V362: =IF(AND(P362>=Calendar!$K$2,P362<EDATE(Calendar!$K$2,1),OR(Calendar!$K$4="*",N362=Calendar!$K$4)),P362*100+COUNTIFS($P$6:$P$3267,P362,$Q$6:$Q$3267,"<="&Q362,$N$6:$N$3267,Calendar!$K$4),"") | W362: =IF(AND(B362=Queue!$C$4,OR(Queue!$K$4="*",N362=Queue!$K$4)),Q362,"")
A363: =IF(M363="","",HYPERLINK("https://www.youtube.com/watch?v="&M363,"▶")) | B363: =IF(C363<>"",C363,IF(P363<=IFERROR(INDEX(tblChannels[Watched Through],MATCH(N363,tblChannels[Channel ID],0)),0),"Watched","Unwatched")) | E363: 45784.585 | F363: Super Carlin Brothers | G363: Pedro IS Casita! 🕯️ #disney | H363: 0.0020833333 | I363: 75558 | J363: 6699 | K363: 85 | N363: UCKZo4N0lVPccBkSiuyVh4yg | O363: 45784.751 | P363: 45784 | Q363: 2905 | R363: No Video ID yet | U363: Did Pedro become Casita in Encanto after he sacrificed himself to give his family a miracle? | V363: =IF(AND(P363>=Calendar!$K$2,P363<EDATE(Calendar!$K$2,1),OR(Calendar!$K$4="*",N363=Calendar!$K$4)),P363*100+COUNTIFS($P$6:$P$3267,P363,$Q$6:$Q$3267,"<="&Q363,$N$6:$N$3267,Calendar!$K$4),"") | W363: =IF(AND(B363=Queue!$C$4,OR(Queue!$K$4="*",N363=Queue!$K$4)),Q363,"")
A364: =IF(M364="","",HYPERLINK("https://www.youtube.com/watch?v="&M364,"▶")) | B364: =IF(C364<>"",C364,IF(P364<=IFERROR(INDEX(tblChannels[Watched Through],MATCH(N364,tblChannels[Channel ID],0)),0),"Watched","Unwatched")) | E364: 45784.581 | F364: Super Carlin Brothers | G364: J vs Ben: HARDEST Harry Potter First Chapters TRIVIA Quiz | H364: 0.029502315 | I364: 114994 | J364: 3715 | K364: 470 | N364: UCKZo4N0lVPccBkSiuyVh4yg | O364: 45784.748 | P364: 45784 | Q364: 2904 | R364: No Video ID yet | U364: Go to and use code jvsb50off to get 50% off and free shipping on your first box. Today J and Ben face off to find out who knows more about what happens in the First Chapter of each Harry Potter book! From The Boy Who Lived to Dark Lord Ascending we cover them all! Play Along With Us :: Become a Quiz Master :: | V364: =IF(AND(P364>=Calendar!$K$2,P364<EDATE(Calendar!$K$2,1),OR(Calendar!$K$4="*",N364=Calendar!$K$4)),P364*100+COUNTIFS($P$6:$P$3267,P364,$Q$6:$Q$3267,"<="&Q364,$N$6:$N$3267,Calendar!$K$4),"") | W364: =IF(AND(B364=Queue!$C$4,OR(Queue!$K$4="*",N364=Queue!$K$4)),Q364,"")
A365: =IF(M365="","",HYPERLINK("https://www.youtube.com/watch?v="&M365,"▶")) | B365: =IF(C365<>"",C365,IF(P365<=IFERROR(INDEX(tblChannels[Watched Through],MATCH(N365,tblChannels[Channel ID],0)),0),"Watched","Unwatched")) | E365: 45782.687 | F365: Super Carlin Brothers | G365: Hans Is A Personality Mirror #disney | H365: 0.0016087963 | I365: 1236816 | J365: 129881 | K365: 823 | N365: UCKZo4N0lVPccBkSiuyVh4yg | O365: 45782.853 | P365: 45782 | Q365: 2903 | R365: No Video ID yet | U365: Hans from Frozen is a Mirror that reflects whatever personality he is currently facing. You're happy? He's Happy! You're Mad? He's Mad! But what happens when he sees his own reflection...? | V365: =IF(AND(P365>=Calendar!$K$2,P365<EDATE(Calendar!$K$2,1),OR(Calendar!$K$4="*",N365=Calendar!$K$4)),P365*100+COUNTIFS($P$6:$P$3267,P365,$Q$6:$Q$3267,"<="&Q365,$N$6:$N$3267,Calendar!$K$4),"") | W365: =IF(AND(B365=Queue!$C$4,OR(Queue!$K$4="*",N365=Queue!$K$4)),Q365,"")
A366: =IF(M366="","",HYPERLINK("https://www.youtube.com/watch?v="&M366,"▶")) | B366: =IF(C366<>"",C366,IF(P366<=IFERROR(INDEX(tblChannels[Watched Through],MATCH(N366,tblChannels[Channel ID],0)),0),"Watched","Unwatched")) | E366: 45781.417 | F366: Through The Griffin Door | G366: Chapter 24: Rita Skeeter’s Scoop | Goblet of Fire | H366: 0.0765625 | I366: 58593 | J366: 1493 | K366: 354 | N366: UCEscP6ETYXWSSvsNrDHekMQ | O366: 45781.583 | P366: 45781 | Q366: 2902 | R366: No Video ID yet | U366: Join J and Ben as they dive into Chapter 24 of the Goblet of Fire and discuss post-ball debriefs, hand saw sounds, Prof. Grubbly-Plank, Rita’s article about Hagrid, cold water, running into Ludo Bagman, and Dumbeldore being unhinged. THROUGH THE GRIFFIN TOUR MIDWEST TICKETS ARE ON SALE RIGHT NOW St. Louis, MO - 9/17a Watch on Youtube: Want more Harry Potter Content? Harry Potter Theories: Dumbledore’s Big Plan: What If Harry Was in Slytherin: 06:14- Chapter Breakdown 1:42:30 - Closing Thoughts and Review | V366: =IF(AND(P366>=Calendar!$K$2,P366<EDATE(Calendar!$K$2,1),OR(Calendar!$K$4="*",N366=Calendar!$K$4)),P366*100+COUNTIFS($P$6:$P$3267,P366,$Q$6:$Q$3267,"<="&Q366,$N$6:$N$3267,Calendar!$K$4),"") | W366: =IF(AND(B366=Queue!$C$4,OR(Queue!$K$4="*",N366=Queue!$K$4)),Q366,"")
A367: =IF(M367="","",HYPERLINK("https://www.youtube.com/watch?v="&M367,"▶")) | B367: =IF(C367<>"",C367,IF(P367<=IFERROR(INDEX(tblChannels[Watched Through],MATCH(N367,tblChannels[Channel ID],0)),0),"Watched","Unwatched")) | E367: 45779.765 | F367: Super Carlin Brothers | G367: Mother Gothel COACHES The Other Disney Villains | Disney Film Theory | H367: 0.013738426 | I367: 53151 | J367: 2746 | K367: 364 | N367: UCKZo4N0lVPccBkSiuyVh4yg | O367: 45779.931 | P367: 45779 | Q367: 2901 | R367: No Video ID yet | U367: This episode is sponsored by BetterHelp – Go to to get 10% off your first month. This episode is sponsored by Aura Frames – Go to and use code SCB to get $35-off plus free shipping on their best-selling Carver Mat frame. Today Ben dives into the World of Disney to reveal Mother Gothel’s BIG PLAN to build herself an army and train the other Disney Villains like Jafar, The Evil Queen, Claude Frollo, The Beast and Maleficent! #supercarlinbrothers #Disney | V367: =IF(AND(P367>=Calendar!$K$2,P367<EDATE(Calendar!$K$2,1),OR(Calendar!$K$4="*",N367=Calendar!$K$4)),P367*100+COUNTIFS($P$6:$P$3267,P367,$Q$6:$Q$3267,"<="&Q367,$N$6:$N$3267,Calendar!$K$4),"") | W367: =IF(AND(B367=Queue!$C$4,OR(Queue!$K$4="*",N367=Queue!$K$4)),Q367,"")
A368: =IF(M368="","",HYPERLINK("https://www.youtube.com/watch?v="&M368,"▶")) | B368: =IF(C368<>"",C368,IF(P368<=IFERROR(INDEX(tblChannels[Watched Through],MATCH(N368,tblChannels[Channel ID],0)),0),"Watched","Unwatched")) | E368: 45779.699 | F368: Super Carlin Brothers | G368: Ty Lee Is An Air Nomad! #avatarthelastairbender | H368: 0.0020833333 | I368: 635991 | J368: 45085 | K368: 380 | N368: UCKZo4N0lVPccBkSiuyVh4yg | O368: 45779.866 | P368: 45779 | Q368: 2900 | R368: No Video ID yet | U368: Ty Lee may live in and fight for the Fire Nation, but she is almost certainly a descendant of the Air Nomads. #avatarthelastairbender | V368: =IF(AND(P368>=Calendar!$K$2,P368<EDATE(Calendar!$K$2,1),OR(Calendar!$K$4="*",N368=Calendar!$K$4)),P368*100+COUNTIFS($P$6:$P$3267,P368,$Q$6:$Q$3267,"<="&Q368,$N$6:$N$3267,Calendar!$K$4),"") | W368: =IF(AND(B368=Queue!$C$4,OR(Queue!$K$4="*",N368=Queue!$K$4)),Q368,"")
A369: =IF(M369="","",HYPERLINK("https://www.youtube.com/watch?v="&M369,"▶")) | B369: =IF(C369<>"",C369,IF(P369<=IFERROR(INDEX(tblChannels[Watched Through],MATCH(N369,tblChannels[Channel ID],0)),0),"Watched","Unwatched")) | E369: 45779.417 | F369: Popcorn Culture | G369: Ben’s Second Tattoo?? | Popcorn Culture | H369: 0.046493056 | I369: 3621 | J369: 170 | K369: 28 | N369: UCHfIbq9thHPC8yrKjAdJgDA | O369: 45779.583 | P369: 45779 | Q369: 2899 | R369: No Video ID yet | U369: In the 282nd episode of the Pop, Ben and J discuss a typical garden update, camping, cool knives, banana beer, and Ben’s newest tattoo! Most Recent Goblet of FIRE Quiz - Get your tickets for Through the Griffin Tour MIDWEST here: Catching Capitillers 00:00 - Intro, Garden Update 20:39 - Camping 59:00 - Ben’s New Tattoo | V369: =IF(AND(P369>=Calendar!$K$2,P369<EDATE(Calendar!$K$2,1),OR(Calendar!$K$4="*",N369=Calendar!$K$4)),P369*100+COUNTIFS($P$6:$P$3267,P369,$Q$6:$Q$3267,"<="&Q369,$N$6:$N$3267,Calendar!$K$4),"") | W369: =IF(AND(B369=Queue!$C$4,OR(Queue!$K$4="*",N369=Queue!$K$4)),Q369,"")
A370: =IF(M370="","",HYPERLINK("https://www.youtube.com/watch?v="&M370,"▶")) | B370: =IF(C370<>"",C370,IF(P370<=IFERROR(INDEX(tblChannels[Watched Through],MATCH(N370,tblChannels[Channel ID],0)),0),"Watched","Unwatched")) | E370: 45777.71 | F370: Super Carlin Brothers | G370: How To Get A Perfect Score On Space Ranger Spin #disney | H370: 0.0014236111 | I370: 653363 | J370: 40382 | K370: 143 | N370: UCKZo4N0lVPccBkSiuyVh4yg | O370: 45777.876 | P370: 45777 | Q370: 2898 | R370: No Video ID yet | U370: This ride is about to get an overhaul so NOW is your LAST CHANCE to get a perfect score on Buzz Lightyear: Space Ranger Spin! | V370: =IF(AND(P370>=Calendar!$K$2,P370<EDATE(Calendar!$K$2,1),OR(Calendar!$K$4="*",N370=Calendar!$K$4)),P370*100+COUNTIFS($P$6:$P$3267,P370,$Q$6:$Q$3267,"<="&Q370,$N$6:$N$3267,Calendar!$K$4),"") | W370: =IF(AND(B370=Queue!$C$4,OR(Queue!$K$4="*",N370=Queue!$K$4)),Q370,"")
A371: =IF(M371="","",HYPERLINK("https://www.youtube.com/watch?v="&M371,"▶")) | B371: =IF(C371<>"",C371,IF(P371<=IFERROR(INDEX(tblChannels[Watched Through],MATCH(N371,tblChannels[Channel ID],0)),0),"Watched","Unwatched")) | E371: 45777.701 | F371: Super Carlin Brothers | G371: Which Bending Style Is Each Harry Potter Character? | Harry Potter Film Theory | H371: 0.013773148 | I371: 52134 | J371: 2789 | K371: 604 | N371: UCKZo4N0lVPccBkSiuyVh4yg | O371: 45777.867 | P371: 45777 | Q371: 2897 | R371: No Video ID yet | U371: Exclusive $35-off Carver Mat at AuraFrames.com. Promo Code [SCB] Go to and use code SCB to get $35-off plus free shipping on their best-selling Carver Mat frame. Today J dives off a Sky Bison into the worlds of both Harry Potter and Avatar the Last Airbender to find out which bending style each character in Harry Potter would excel in! Is Harry the Avatar? Are all Gryffindor’s Fire Benders? Does Bending run in families? Tickets go on-sale Friday, April 25 @ 10am Local Time! | V371: =IF(AND(P371>=Calendar!$K$2,P371<EDATE(Calendar!$K$2,1),OR(Calendar!$K$4="*",N371=Calendar!$K$4)),P371*100+COUNTIFS($P$6:$P$3267,P371,$Q$6:$Q$3267,"<="&Q371,$N$6:$N$3267,Calendar!$K$4),"") | W371: =IF(AND(B371=Queue!$C$4,OR(Queue!$K$4="*",N371=Queue!$K$4)),Q371,"")
...

Sheet Queue
B2: Watch Queue
C3: Show | D3: Channel | E3: Order
B4: =HYPERLINK("#Dashboard!A1","◄ Dashboard") | C4: Unwatched | D4: All channels | E4: Oldest first | K4: =IF($D$4="All channels","*",IFERROR(INDEX(tblChannels[Channel ID],MATCH($D$4,tblChannels[Display Name],0)),"none"))
B5: =COUNT(tblVideos[Queue Key])&" videos match · "&IF(ROUND((SUMIFS(tblVideos[Length],tblVideos[Queue Key],">0"))*1440,0)<60,ROUND((SUMIFS(tblVideos[Length],tblVideos[Queue Key],">0"))*1440,0)&" m",IF(MOD(ROUND((SUMIFS(tblVideos[Length],tblVideos[Queue Key],">0"))*1440,0),60)=0,INT(ROUND((SUMIFS(tblVideos[Length],tblVideos[Queue Key],">0"))*1440,0)/60)&" h",INT(ROUND((SUMIFS(tblVideos[Length],tblVideos[Queue Key],">0"))*1440,0)/60)&" h "&MOD(ROUND((SUMIFS(tblVideos[Length],tblVideos[Queue Key],">0"))*1440,0),60)&" m"))&" of runtime"
B6: Your next videos. Click a title to open it on YouTube; mark it watched in the Library.
B7: # | C7: Published | D7: Channel | E7: Title | F7: Length | G7: Status
B8: =IF($I8="","",1) | C8: =IF($I8="","",INDEX(tblVideos[Day],$I8)) | D8: =IF($I8="","",INDEX(tblVideos[Channel],$I8)) | E8: =IF($I8="","",IF(INDEX(tblVideos[Video ID],$I8)="",INDEX(tblVideos[Title],$I8),HYPERLINK("https://www.youtube.com/watch?v="&INDEX(tblVideos[Video ID],$I8),INDEX(tblVideos[Title],$I8)))) | F8: =IF($I8="","",INDEX(tblVideos[Length],$I8)) | G8: =IF($I8="","",INDEX(tblVideos[Status],$I8)) | I8: =IFERROR(MATCH(IF($E$4="Newest first",LARGE(tblVideos[Queue Key],1),SMALL(tblVideos[Queue Key],1)),tblVideos[Seq],0),"")
B9: =IF($I9="","",2) | C9: =IF($I9="","",INDEX(tblVideos[Day],$I9)) | D9: =IF($I9="","",INDEX(tblVideos[Channel],$I9)) | E9: =IF($I9="","",IF(INDEX(tblVideos[Video ID],$I9)="",INDEX(tblVideos[Title],$I9),HYPERLINK("https://www.youtube.com/watch?v="&INDEX(tblVideos[Video ID],$I9),INDEX(tblVideos[Title],$I9)))) | F9: =IF($I9="","",INDEX(tblVideos[Length],$I9)) | G9: =IF($I9="","",INDEX(tblVideos[Status],$I9)) | I9: =IFERROR(MATCH(IF($E$4="Newest first",LARGE(tblVideos[Queue Key],2),SMALL(tblVideos[Queue Key],2)),tblVideos[Seq],0),"")
B10: =IF($I10="","",3) | C10: =IF($I10="","",INDEX(tblVideos[Day],$I10)) | D10: =IF($I10="","",INDEX(tblVideos[Channel],$I10)) | E10: =IF($I10="","",IF(INDEX(tblVideos[Video ID],$I10)="",INDEX(tblVideos[Title],$I10),HYPERLINK("https://www.youtube.com/watch?v="&INDEX(tblVideos[Video ID],$I10),INDEX(tblVideos[Title],$I10)))) | F10: =IF($I10="","",INDEX(tblVideos[Length],$I10)) | G10: =IF($I10="","",INDEX(tblVideos[Status],$I10)) | I10: =IFERROR(MATCH(IF($E$4="Newest first",LARGE(tblVideos[Queue Key],3),SMALL(tblVideos[Queue Key],3)),tblVideos[Seq],0),"")
B11: =IF($I11="","",4) | C11: =IF($I11="","",INDEX(tblVideos[Day],$I11)) | D11: =IF($I11="","",INDEX(tblVideos[Channel],$I11)) | E11: =IF($I11="","",IF(INDEX(tblVideos[Video ID],$I11)="",INDEX(tblVideos[Title],$I11),HYPERLINK("https://www.youtube.com/watch?v="&INDEX(tblVideos[Video ID],$I11),INDEX(tblVideos[Title],$I11)))) | F11: =IF($I11="","",INDEX(tblVideos[Length],$I11)) | G11: =IF($I11="","",INDEX(tblVideos[Status],$I11)) | I11: =IFERROR(MATCH(IF($E$4="Newest first",LARGE(tblVideos[Queue Key],4),SMALL(tblVideos[Queue Key],4)),tblVideos[Seq],0),"")
B12: =IF($I12="","",5) | C12: =IF($I12="","",INDEX(tblVideos[Day],$I12)) | D12: =IF($I12="","",INDEX(tblVideos[Channel],$I12)) | E12: =IF($I12="","",IF(INDEX(tblVideos[Video ID],$I12)="",INDEX(tblVideos[Title],$I12),HYPERLINK("https://www.youtube.com/watch?v="&INDEX(tblVideos[Video ID],$I12),INDEX(tblVideos[Title],$I12)))) | F12: =IF($I12="","",INDEX(tblVideos[Length],$I12)) | G12: =IF($I12="","",INDEX(tblVideos[Status],$I12)) | I12: =IFERROR(MATCH(IF($E$4="Newest first",LARGE(tblVideos[Queue Key],5),SMALL(tblVideos[Queue Key],5)),tblVideos[Seq],0),"")
B13: =IF($I13="","",6) | C13: =IF($I13="","",INDEX(tblVideos[Day],$I13)) | D13: =IF($I13="","",INDEX(tblVideos[Channel],$I13)) | E13: =IF($I13="","",IF(INDEX(tblVideos[Video ID],$I13)="",INDEX(tblVideos[Title],$I13),HYPERLINK("https://www.youtube.com/watch?v="&INDEX(tblVideos[Video ID],$I13),INDEX(tblVideos[Title],$I13)))) | F13: =IF($I13="","",INDEX(tblVideos[Length],$I13)) | G13: =IF($I13="","",INDEX(tblVideos[Status],$I13)) | I13: =IFERROR(MATCH(IF($E$4="Newest first",LARGE(tblVideos[Queue Key],6),SMALL(tblVideos[Queue Key],6)),tblVideos[Seq],0),"")
B14: =IF($I14="","",7) | C14: =IF($I14="","",INDEX(tblVideos[Day],$I14)) | D14: =IF($I14="","",INDEX(tblVideos[Channel],$I14)) | E14: =IF($I14="","",IF(INDEX(tblVideos[Video ID],$I14)="",INDEX(tblVideos[Title],$I14),HYPERLINK("https://www.youtube.com/watch?v="&INDEX(tblVideos[Video ID],$I14),INDEX(tblVideos[Title],$I14)))) | F14: =IF($I14="","",INDEX(tblVideos[Length],$I14)) | G14: =IF($I14="","",INDEX(tblVideos[Status],$I14)) | I14: =IFERROR(MATCH(IF($E$4="Newest first",LARGE(tblVideos[Queue Key],7),SMALL(tblVideos[Queue Key],7)),tblVideos[Seq],0),"")
B15: =IF($I15="","",8) | C15: =IF($I15="","",INDEX(tblVideos[Day],$I15)) | D15: =IF($I15="","",INDEX(tblVideos[Channel],$I15)) | E15: =IF($I15="","",IF(INDEX(tblVideos[Video ID],$I15)="",INDEX(tblVideos[Title],$I15),HYPERLINK("https://www.youtube.com/watch?v="&INDEX(tblVideos[Video ID],$I15),INDEX(tblVideos[Title],$I15)))) | F15: =IF($I15="","",INDEX(tblVideos[Length],$I15)) | G15: =IF($I15="","",INDEX(tblVideos[Status],$I15)) | I15: =IFERROR(MATCH(IF($E$4="Newest first",LARGE(tblVideos[Queue Key],8),SMALL(tblVideos[Queue Key],8)),tblVideos[Seq],0),"")
B16: =IF($I16="","",9) | C16: =IF($I16="","",INDEX(tblVideos[Day],$I16)) | D16: =IF($I16="","",INDEX(tblVideos[Channel],$I16)) | E16: =IF($I16="","",IF(INDEX(tblVideos[Video ID],$I16)="",INDEX(tblVideos[Title],$I16),HYPERLINK("https://www.youtube.com/watch?v="&INDEX(tblVideos[Video ID],$I16),INDEX(tblVideos[Title],$I16)))) | F16: =IF($I16="","",INDEX(tblVideos[Length],$I16)) | G16: =IF($I16="","",INDEX(tblVideos[Status],$I16)) | I16: =IFERROR(MATCH(IF($E$4="Newest first",LARGE(tblVideos[Queue Key],9),SMALL(tblVideos[Queue Key],9)),tblVideos[Seq],0),"")
B17: =IF($I17="","",10) | C17: =IF($I17="","",INDEX(tblVideos[Day],$I17)) | D17: =IF($I17="","",INDEX(tblVideos[Channel],$I17)) | E17: =IF($I17="","",IF(INDEX(tblVideos[Video ID],$I17)="",INDEX(tblVideos[Title],$I17),HYPERLINK("https://www.youtube.com/watch?v="&INDEX(tblVideos[Video ID],$I17),INDEX(tblVideos[Title],$I17)))) | F17: =IF($I17="","",INDEX(tblVideos[Length],$I17)) | G17: =IF($I17="","",INDEX(tblVideos[Status],$I17)) | I17: =IFERROR(MATCH(IF($E$4="Newest first",LARGE(tblVideos[Queue Key],10),SMALL(tblVideos[Queue Key],10)),tblVideos[Seq],0),"")
B18: =IF($I18="","",11) | C18: =IF($I18="","",INDEX(tblVideos[Day],$I18)) | D18: =IF($I18="","",INDEX(tblVideos[Channel],$I18)) | E18: =IF($I18="","",IF(INDEX(tblVideos[Video ID],$I18)="",INDEX(tblVideos[Title],$I18),HYPERLINK("https://www.youtube.com/watch?v="&INDEX(tblVideos[Video ID],$I18),INDEX(tblVideos[Title],$I18)))) | F18: =IF($I18="","",INDEX(tblVideos[Length],$I18)) | G18: =IF($I18="","",INDEX(tblVideos[Status],$I18)) | I18: =IFERROR(MATCH(IF($E$4="Newest first",LARGE(tblVideos[Queue Key],11),SMALL(tblVideos[Queue Key],11)),tblVideos[Seq],0),"")
B19: =IF($I19="","",12) | C19: =IF($I19="","",INDEX(tblVideos[Day],$I19)) | D19: =IF($I19="","",INDEX(tblVideos[Channel],$I19)) | E19: =IF($I19="","",IF(INDEX(tblVideos[Video ID],$I19)="",INDEX(tblVideos[Title],$I19),HYPERLINK("https://www.youtube.com/watch?v="&INDEX(tblVideos[Video ID],$I19),INDEX(tblVideos[Title],$I19)))) | F19: =IF($I19="","",INDEX(tblVideos[Length],$I19)) | G19: =IF($I19="","",INDEX(tblVideos[Status],$I19)) | I19: =IFERROR(MATCH(IF($E$4="Newest first",LARGE(tblVideos[Queue Key],12),SMALL(tblVideos[Queue Key],12)),tblVideos[Seq],0),"")
B20: =IF($I20="","",13) | C20: =IF($I20="","",INDEX(tblVideos[Day],$I20)) | D20: =IF($I20="","",INDEX(tblVideos[Channel],$I20)) | E20: =IF($I20="","",IF(INDEX(tblVideos[Video ID],$I20)="",INDEX(tblVideos[Title],$I20),HYPERLINK("https://www.youtube.com/watch?v="&INDEX(tblVideos[Video ID],$I20),INDEX(tblVideos[Title],$I20)))) | F20: =IF($I20="","",INDEX(tblVideos[Length],$I20)) | G20: =IF($I20="","",INDEX(tblVideos[Status],$I20)) | I20: =IFERROR(MATCH(IF($E$4="Newest first",LARGE(tblVideos[Queue Key],13),SMALL(tblVideos[Queue Key],13)),tblVideos[Seq],0),"")
B21: =IF($I21="","",14) | C21: =IF($I21="","",INDEX(tblVideos[Day],$I21)) | D21: =IF($I21="","",INDEX(tblVideos[Channel],$I21)) | E21: =IF($I21="","",IF(INDEX(tblVideos[Video ID],$I21)="",INDEX(tblVideos[Title],$I21),HYPERLINK("https://www.youtube.com/watch?v="&INDEX(tblVideos[Video ID],$I21),INDEX(tblVideos[Title],$I21)))) | F21: =IF($I21="","",INDEX(tblVideos[Length],$I21)) | G21: =IF($I21="","",INDEX(tblVideos[Status],$I21)) | I21: =IFERROR(MATCH(IF($E$4="Newest first",LARGE(tblVideos[Queue Key],14),SMALL(tblVideos[Queue Key],14)),tblVideos[Seq],0),"")
B22: =IF($I22="","",15) | C22: =IF($I22="","",INDEX(tblVideos[Day],$I22)) | D22: =IF($I22="","",INDEX(tblVideos[Channel],$I22)) | E22: =IF($I22="","",IF(INDEX(tblVideos[Video ID],$I22)="",INDEX(tblVideos[Title],$I22),HYPERLINK("https://www.youtube.com/watch?v="&INDEX(tblVideos[Video ID],$I22),INDEX(tblVideos[Title],$I22)))) | F22: =IF($I22="","",INDEX(tblVideos[Length],$I22)) | G22: =IF($I22="","",INDEX(tblVideos[Status],$I22)) | I22: =IFERROR(MATCH(IF($E$4="Newest first",LARGE(tblVideos[Queue Key],15),SMALL(tblVideos[Queue Key],15)),tblVideos[Seq],0),"")
B23: =IF($I23="","",16) | C23: =IF($I23="","",INDEX(tblVideos[Day],$I23)) | D23: =IF($I23="","",INDEX(tblVideos[Channel],$I23)) | E23: =IF($I23="","",IF(INDEX(tblVideos[Video ID],$I23)="",INDEX(tblVideos[Title],$I23),HYPERLINK("https://www.youtube.com/watch?v="&INDEX(tblVideos[Video ID],$I23),INDEX(tblVideos[Title],$I23)))) | F23: =IF($I23="","",INDEX(tblVideos[Length],$I23)) | G23: =IF($I23="","",INDEX(tblVideos[Status],$I23)) | I23: =IFERROR(MATCH(IF($E$4="Newest first",LARGE(tblVideos[Queue Key],16),SMALL(tblVideos[Queue Key],16)),tblVideos[Seq],0),"")
B24: =IF($I24="","",17) | C24: =IF($I24="","",INDEX(tblVideos[Day],$I24)) | D24: =IF($I24="","",INDEX(tblVideos[Channel],$I24)) | E24: =IF($I24="","",IF(INDEX(tblVideos[Video ID],$I24)="",INDEX(tblVideos[Title],$I24),HYPERLINK("https://www.youtube.com/watch?v="&INDEX(tblVideos[Video ID],$I24),INDEX(tblVideos[Title],$I24)))) | F24: =IF($I24="","",INDEX(tblVideos[Length],$I24)) | G24: =IF($I24="","",INDEX(tblVideos[Status],$I24)) | I24: =IFERROR(MATCH(IF($E$4="Newest first",LARGE(tblVideos[Queue Key],17),SMALL(tblVideos[Queue Key],17)),tblVideos[Seq],0),"")
B25: =IF($I25="","",18) | C25: =IF($I25="","",INDEX(tblVideos[Day],$I25)) | D25: =IF($I25="","",INDEX(tblVideos[Channel],$I25)) | E25: =IF($I25="","",IF(INDEX(tblVideos[Video ID],$I25)="",INDEX(tblVideos[Title],$I25),HYPERLINK("https://www.youtube.com/watch?v="&INDEX(tblVideos[Video ID],$I25),INDEX(tblVideos[Title],$I25)))) | F25: =IF($I25="","",INDEX(tblVideos[Length],$I25)) | G25: =IF($I25="","",INDEX(tblVideos[Status],$I25)) | I25: =IFERROR(MATCH(IF($E$4="Newest first",LARGE(tblVideos[Queue Key],18),SMALL(tblVideos[Queue Key],18)),tblVideos[Seq],0),"")
B26: =IF($I26="","",19) | C26: =IF($I26="","",INDEX(tblVideos[Day],$I26)) | D26: =IF($I26="","",INDEX(tblVideos[Channel],$I26)) | E26: =IF($I26="","",IF(INDEX(tblVideos[Video ID],$I26)="",INDEX(tblVideos[Title],$I26),HYPERLINK("https://www.youtube.com/watch?v="&INDEX(tblVideos[Video ID],$I26),INDEX(tblVideos[Title],$I26)))) | F26: =IF($I26="","",INDEX(tblVideos[Length],$I26)) | G26: =IF($I26="","",INDEX(tblVideos[Status],$I26)) | I26: =IFERROR(MATCH(IF($E$4="Newest first",LARGE(tblVideos[Queue Key],19),SMALL(tblVideos[Queue Key],19)),tblVideos[Seq],0),"")
B27: =IF($I27="","",20) | C27: =IF($I27="","",INDEX(tblVideos[Day],$I27)) | D27: =IF($I27="","",INDEX(tblVideos[Channel],$I27)) | E27: =IF($I27="","",IF(INDEX(tblVideos[Video ID],$I27)="",INDEX(tblVideos[Title],$I27),HYPERLINK("https://www.youtube.com/watch?v="&INDEX(tblVideos[Video ID],$I27),INDEX(tblVideos[Title],$I27)))) | F27: =IF($I27="","",INDEX(tblVideos[Length],$I27)) | G27: =IF($I27="","",INDEX(tblVideos[Status],$I27)) | I27: =IFERROR(MATCH(IF($E$4="Newest first",LARGE(tblVideos[Queue Key],20),SMALL(tblVideos[Queue Key],20)),tblVideos[Seq],0),"")
B28: =IF($I28="","",21) | C28: =IF($I28="","",INDEX(tblVideos[Day],$I28)) | D28: =IF($I28="","",INDEX(tblVideos[Channel],$I28)) | E28: =IF($I28="","",IF(INDEX(tblVideos[Video ID],$I28)="",INDEX(tblVideos[Title],$I28),HYPERLINK("https://www.youtube.com/watch?v="&INDEX(tblVideos[Video ID],$I28),INDEX(tblVideos[Title],$I28)))) | F28: =IF($I28="","",INDEX(tblVideos[Length],$I28)) | G28: =IF($I28="","",INDEX(tblVideos[Status],$I28)) | I28: =IFERROR(MATCH(IF($E$4="Newest first",LARGE(tblVideos[Queue Key],21),SMALL(tblVideos[Queue Key],21)),tblVideos[Seq],0),"")
B29: =IF($I29="","",22) | C29: =IF($I29="","",INDEX(tblVideos[Day],$I29)) | D29: =IF($I29="","",INDEX(tblVideos[Channel],$I29)) | E29: =IF($I29="","",IF(INDEX(tblVideos[Video ID],$I29)="",INDEX(tblVideos[Title],$I29),HYPERLINK("https://www.youtube.com/watch?v="&INDEX(tblVideos[Video ID],$I29),INDEX(tblVideos[Title],$I29)))) | F29: =IF($I29="","",INDEX(tblVideos[Length],$I29)) | G29: =IF($I29="","",INDEX(tblVideos[Status],$I29)) | I29: =IFERROR(MATCH(IF($E$4="Newest first",LARGE(tblVideos[Queue Key],22),SMALL(tblVideos[Queue Key],22)),tblVideos[Seq],0),"")
B30: =IF($I30="","",23) | C30: =IF($I30="","",INDEX(tblVideos[Day],$I30)) | D30: =IF($I30="","",INDEX(tblVideos[Channel],$I30)) | E30: =IF($I30="","",IF(INDEX(tblVideos[Video ID],$I30)="",INDEX(tblVideos[Title],$I30),HYPERLINK("https://www.youtube.com/watch?v="&INDEX(tblVideos[Video ID],$I30),INDEX(tblVideos[Title],$I30)))) | F30: =IF($I30="","",INDEX(tblVideos[Length],$I30)) | G30: =IF($I30="","",INDEX(tblVideos[Status],$I30)) | I30: =IFERROR(MATCH(IF($E$4="Newest first",LARGE(tblVideos[Queue Key],23),SMALL(tblVideos[Queue Key],23)),tblVideos[Seq],0),"")
B31: =IF($I31="","",24) | C31: =IF($I31="","",INDEX(tblVideos[Day],$I31)) | D31: =IF($I31="","",INDEX(tblVideos[Channel],$I31)) | E31: =IF($I31="","",IF(INDEX(tblVideos[Video ID],$I31)="",INDEX(tblVideos[Title],$I31),HYPERLINK("https://www.youtube.com/watch?v="&INDEX(tblVideos[Video ID],$I31),INDEX(tblVideos[Title],$I31)))) | F31: =IF($I31="","",INDEX(tblVideos[Length],$I31)) | G31: =IF($I31="","",INDEX(tblVideos[Status],$I31)) | I31: =IFERROR(MATCH(IF($E$4="Newest first",LARGE(tblVideos[Queue Key],24),SMALL(tblVideos[Queue Key],24)),tblVideos[Seq],0),"")
B32: =IF($I32="","",25) | C32: =IF($I32="","",INDEX(tblVideos[Day],$I32)) | D32: =IF($I32="","",INDEX(tblVideos[Channel],$I32)) | E32: =IF($I32="","",IF(INDEX(tblVideos[Video ID],$I32)="",INDEX(tblVideos[Title],$I32),HYPERLINK("https://www.youtube.com/watch?v="&INDEX(tblVideos[Video ID],$I32),INDEX(tblVideos[Title],$I32)))) | F32: =IF($I32="","",INDEX(tblVideos[Length],$I32)) | G32: =IF($I32="","",INDEX(tblVideos[Status],$I32)) | I32: =IFERROR(MATCH(IF($E$4="Newest first",LARGE(tblVideos[Queue Key],25),SMALL(tblVideos[Queue Key],25)),tblVideos[Seq],0),"")
B33: =IF($I33="","",26) | C33: =IF($I33="","",INDEX(tblVideos[Day],$I33)) | D33: =IF($I33="","",INDEX(tblVideos[Channel],$I33)) | E33: =IF($I33="","",IF(INDEX(tblVideos[Video ID],$I33)="",INDEX(tblVideos[Title],$I33),HYPERLINK("https://www.youtube.com/watch?v="&INDEX(tblVideos[Video ID],$I33),INDEX(tblVideos[Title],$I33)))) | F33: =IF($I33="","",INDEX(tblVideos[Length],$I33)) | G33: =IF($I33="","",INDEX(tblVideos[Status],$I33)) | I33: =IFERROR(MATCH(IF($E$4="Newest first",LARGE(tblVideos[Queue Key],26),SMALL(tblVideos[Queue Key],26)),tblVideos[Seq],0),"")
B34: =IF($I34="","",27) | C34: =IF($I34="","",INDEX(tblVideos[Day],$I34)) | D34: =IF($I34="","",INDEX(tblVideos[Channel],$I34)) | E34: =IF($I34="","",IF(INDEX(tblVideos[Video ID],$I34)="",INDEX(tblVideos[Title],$I34),HYPERLINK("https://www.youtube.com/watch?v="&INDEX(tblVideos[Video ID],$I34),INDEX(tblVideos[Title],$I34)))) | F34: =IF($I34="","",INDEX(tblVideos[Length],$I34)) | G34: =IF($I34="","",INDEX(tblVideos[Status],$I34)) | I34: =IFERROR(MATCH(IF($E$4="Newest first",LARGE(tblVideos[Queue Key],27),SMALL(tblVideos[Queue Key],27)),tblVideos[Seq],0),"")
B35: =IF($I35="","",28) | C35: =IF($I35="","",INDEX(tblVideos[Day],$I35)) | D35: =IF($I35="","",INDEX(tblVideos[Channel],$I35)) | E35: =IF($I35="","",IF(INDEX(tblVideos[Video ID],$I35)="",INDEX(tblVideos[Title],$I35),HYPERLINK("https://www.youtube.com/watch?v="&INDEX(tblVideos[Video ID],$I35),INDEX(tblVideos[Title],$I35)))) | F35: =IF($I35="","",INDEX(tblVideos[Length],$I35)) | G35: =IF($I35="","",INDEX(tblVideos[Status],$I35)) | I35: =IFERROR(MATCH(IF($E$4="Newest first",LARGE(tblVideos[Queue Key],28),SMALL(tblVideos[Queue Key],28)),tblVideos[Seq],0),"")
B36: =IF($I36="","",29) | C36: =IF($I36="","",INDEX(tblVideos[Day],$I36)) | D36: =IF($I36="","",INDEX(tblVideos[Channel],$I36)) | E36: =IF($I36="","",IF(INDEX(tblVideos[Video ID],$I36)="",INDEX(tblVideos[Title],$I36),HYPERLINK("https://www.youtube.com/watch?v="&INDEX(tblVideos[Video ID],$I36),INDEX(tblVideos[Title],$I36)))) | F36: =IF($I36="","",INDEX(tblVideos[Length],$I36)) | G36: =IF($I36="","",INDEX(tblVideos[Status],$I36)) | I36: =IFERROR(MATCH(IF($E$4="Newest first",LARGE(tblVideos[Queue Key],29),SMALL(tblVideos[Queue Key],29)),tblVideos[Seq],0),"")
B37: =IF($I37="","",30) | C37: =IF($I37="","",INDEX(tblVideos[Day],$I37)) | D37: =IF($I37="","",INDEX(tblVideos[Channel],$I37)) | E37: =IF($I37="","",IF(INDEX(tblVideos[Video ID],$I37)="",INDEX(tblVideos[Title],$I37),HYPERLINK("https://www.youtube.com/watch?v="&INDEX(tblVideos[Video ID],$I37),INDEX(tblVideos[Title],$I37)))) | F37: =IF($I37="","",INDEX(tblVideos[Length],$I37)) | G37: =IF($I37="","",INDEX(tblVideos[Status],$I37)) | I37: =IFERROR(MATCH(IF($E$4="Newest first",LARGE(tblVideos[Queue Key],30),SMALL(tblVideos[Queue Key],30)),tblVideos[Seq],0),"")

Sheet Calendar
B2: Upload Calendar | J2: month start | K2: =DATE($C$4,MATCH($E$4,MonthList,0),1)
C3: Year | E3: Month | G3: Channel | J3: grid start | K3: =K2-(WEEKDAY(K2,1)-1)
B4: =HYPERLINK("#Dashboard!A1","◄ Dashboard") | C4: 2026 | E4: October | G4: All channels | J4: channel crit | K4: =IF($G$4="All channels","*",IFERROR(INDEX(tblChannels[Channel ID],MATCH($G$4,tblChannels[Display Name],0)),"none"))
B5: Pick a year, month and (optionally) a channel with the dropdowns. Click a title to open it on YouTube. ✓ = watched, dimmed.
B6: ="Videos: "&COUNTIFS(tblVideos[Day],">="&$K$2,tblVideos[Day],"<"&EDATE($K$2,1),tblVideos[Channel ID],$K$4)&" Runtime: "&IF(ROUND((SUMIFS(tblVideos[Length],tblVideos[Day],">="&$K$2,tblVideos[Day],"<"&EDATE($K$2,1),tblVideos[Channel ID],$K$4))*1440,0)<60,ROUND((SUMIFS(tblVideos[Length],tblVideos[Day],">="&$K$2,tblVideos[Day],"<"&EDATE($K$2,1),tblVideos[Channel ID],$K$4))*1440,0)&" m",IF(MOD(ROUND((SUMIFS(tblVideos[Length],tblVideos[Day],">="&$K$2,tblVideos[Day],"<"&EDATE($K$2,1),tblVideos[Channel ID],$K$4))*1440,0),60)=0,INT(ROUND((SUMIFS(tblVideos[Length],tblVideos[Day],">="&$K$2,tblVideos[Day],"<"&EDATE($K$2,1),tblVideos[Channel ID],$K$4))*1440,0)/60)&" h",INT(ROUND((SUMIFS(tblVideos[Length],tblVideos[Day],">="&$K$2,tblVideos[Day],"<"&EDATE($K$2,1),tblVideos[Channel ID],$K$4))*1440,0)/60)&" h "&MOD(ROUND((SUMIFS(tblVideos[Length],tblVideos[Day],">="&$K$2,tblVideos[Day],"<"&EDATE($K$2,1),tblVideos[Channel ID],$K$4))*1440,0),60)&" m"))&" Watched: "&COUNTIFS(tblVideos[Day],">="&$K$2,tblVideos[Day],"<"&EDATE($K$2,1),tblVideos[Channel ID],$K$4,tblVideos[Status],"Watched")&" of "&COUNTIFS(tblVideos[Day],">="&$K$2,tblVideos[Day],"<"&EDATE($K$2,1),tblVideos[Channel ID],$K$4)
B7: =Channels!$C$6&" ("&COUNTIFS(tblVideos[Day],">="&$K$2,tblVideos[Day],"<"&EDATE($K$2,1),tblVideos[Channel ID],Channels!$E$6)&")" | C7: =Channels!$C$7&" ("&COUNTIFS(tblVideos[Day],">="&$K$2,tblVideos[Day],"<"&EDATE($K$2,1),tblVideos[Channel ID],Channels!$E$7)&")" | D7: =Channels!$C$8&" ("&COUNTIFS(tblVideos[Day],">="&$K$2,tblVideos[Day],"<"&EDATE($K$2,1),tblVideos[Channel ID],Channels!$E$8)&")" | E7: =Channels!$C$9&" ("&COUNTIFS(tblVideos[Day],">="&$K$2,tblVideos[Day],"<"&EDATE($K$2,1),tblVideos[Channel ID],Channels!$E$9)&")" | F7: =Channels!$C$10&" ("&COUNTIFS(tblVideos[Day],">="&$K$2,tblVideos[Day],"<"&EDATE($K$2,1),tblVideos[Channel ID],Channels!$E$10)&")" | G7: =Channels!$C$11&" ("&COUNTIFS(tblVideos[Day],">="&$K$2,tblVideos[Day],"<"&EDATE($K$2,1),tblVideos[Channel ID],Channels!$E$11)&")"
B9: Sunday | C9: Monday | D9: Tuesday | E9: Wednesday | F9: Thursday | G9: Friday | H9: Saturday
B10: =IF(MONTH(K10)=MONTH($K$2),DAY(K10)&IF(S10>0," · "&S10&IF(S10=1," video"," videos")&" · "&IF(ROUND((AA10)*1440,0)<60,ROUND((AA10)*1440,0)&" m",IF(MOD(ROUND((AA10)*1440,0),60)=0,INT(ROUND((AA10)*1440,0)/60)&" h",INT(ROUND((AA10)*1440,0)/60)&" h "&MOD(ROUND((AA10)*1440,0),60)&" m"))&IF(S10>5," (+"&(S10-5)&" more)",""),""),"") | C10: =IF(MONTH(L10)=MONTH($K$2),DAY(L10)&IF(T10>0," · "&T10&IF(T10=1," video"," videos")&" · "&IF(ROUND((AB10)*1440,0)<60,ROUND((AB10)*1440,0)&" m",IF(MOD(ROUND((AB10)*1440,0),60)=0,INT(ROUND((AB10)*1440,0)/60)&" h",INT(ROUND((AB10)*1440,0)/60)&" h "&MOD(ROUND((AB10)*1440,0),60)&" m"))&IF(T10>5," (+"&(T10-5)&" more)",""),""),"") | D10: =IF(MONTH(M10)=MONTH($K$2),DAY(M10)&IF(U10>0," · "&U10&IF(U10=1," video"," videos")&" · "&IF(ROUND((AC10)*1440,0)<60,ROUND((AC10)*1440,0)&" m",IF(MOD(ROUND((AC10)*1440,0),60)=0,INT(ROUND((AC10)*1440,0)/60)&" h",INT(ROUND((AC10)*1440,0)/60)&" h "&MOD(ROUND((AC10)*1440,0),60)&" m"))&IF(U10>5," (+"&(U10-5)&" more)",""),""),"") | E10: =IF(MONTH(N10)=MONTH($K$2),DAY(N10)&IF(V10>0," · "&V10&IF(V10=1," video"," videos")&" · "&IF(ROUND((AD10)*1440,0)<60,ROUND((AD10)*1440,0)&" m",IF(MOD(ROUND((AD10)*1440,0),60)=0,INT(ROUND((AD10)*1440,0)/60)&" h",INT(ROUND((AD10)*1440,0)/60)&" h "&MOD(ROUND((AD10)*1440,0),60)&" m"))&IF(V10>5," (+"&(V10-5)&" more)",""),""),"") | F10: =IF(MONTH(O10)=MONTH($K$2),DAY(O10)&IF(W10>0," · "&W10&IF(W10=1," video"," videos")&" · "&IF(ROUND((AE10)*1440,0)<60,ROUND((AE10)*1440,0)&" m",IF(MOD(ROUND((AE10)*1440,0),60)=0,INT(ROUND((AE10)*1440,0)/60)&" h",INT(ROUND((AE10)*1440,0)/60)&" h "&MOD(ROUND((AE10)*1440,0),60)&" m"))&IF(W10>5," (+"&(W10-5)&" more)",""),""),"") | G10: =IF(MONTH(P10)=MONTH($K$2),DAY(P10)&IF(X10>0," · "&X10&IF(X10=1," video"," videos")&" · "&IF(ROUND((AF10)*1440,0)<60,ROUND((AF10)*1440,0)&" m",IF(MOD(ROUND((AF10)*1440,0),60)=0,INT(ROUND((AF10)*1440,0)/60)&" h",INT(ROUND((AF10)*1440,0)/60)&" h "&MOD(ROUND((AF10)*1440,0),60)&" m"))&IF(X10>5," (+"&(X10-5)&" more)",""),""),"") | H10: =IF(MONTH(Q10)=MONTH($K$2),DAY(Q10)&IF(Y10>0," · "&Y10&IF(Y10=1," video"," videos")&" · "&IF(ROUND((AG10)*1440,0)<60,ROUND((AG10)*1440,0)&" m",IF(MOD(ROUND((AG10)*1440,0),60)=0,INT(ROUND((AG10)*1440,0)/60)&" h",INT(ROUND((AG10)*1440,0)/60)&" h "&MOD(ROUND((AG10)*1440,0),60)&" m"))&IF(Y10>5," (+"&(Y10-5)&" more)",""),""),"") | K10: =$K$3+0 | L10: =$K$3+1 | M10: =$K$3+2 | N10: =$K$3+3 | O10: =$K$3+4 | P10: =$K$3+5 | Q10: =$K$3+6 | S10: =IF(MONTH(K10)=MONTH($K$2),COUNTIFS(tblVideos[Day],K10,tblVideos[Channel ID],$K$4),0) | T10: =IF(MONTH(L10)=MONTH($K$2),COUNTIFS(tblVideos[Day],L10,tblVideos[Channel ID],$K$4),0) | U10: =IF(MONTH(M10)=MONTH($K$2),COUNTIFS(tblVideos[Day],M10,tblVideos[Channel ID],$K$4),0) | V10: =IF(MONTH(N10)=MONTH($K$2),COUNTIFS(tblVideos[Day],N10,tblVideos[Channel ID],$K$4),0) | W10: =IF(MONTH(O10)=MONTH($K$2),COUNTIFS(tblVideos[Day],O10,tblVideos[Channel ID],$K$4),0) | X10: =IF(MONTH(P10)=MONTH($K$2),COUNTIFS(tblVideos[Day],P10,tblVideos[Channel ID],$K$4),0) | Y10: =IF(MONTH(Q10)=MONTH($K$2),COUNTIFS(tblVideos[Day],Q10,tblVideos[Channel ID],$K$4),0) | AA10: =IF(S10>0,SUMIFS(tblVideos[Length],tblVideos[Day],K10,tblVideos[Channel ID],$K$4),0) | AB10: =IF(T10>0,SUMIFS(tblVideos[Length],tblVideos[Day],L10,tblVideos[Channel ID],$K$4),0) | AC10: =IF(U10>0,SUMIFS(tblVideos[Length],tblVideos[Day],M10,tblVideos[Channel ID],$K$4),0) | AD10: =IF(V10>0,SUMIFS(tblVideos[Length],tblVideos[Day],N10,tblVideos[Channel ID],$K$4),0) | AE10: =IF(W10>0,SUMIFS(tblVideos[Length],tblVideos[Day],O10,tblVideos[Channel ID],$K$4),0) | AF10: =IF(X10>0,SUMIFS(tblVideos[Length],tblVideos[Day],P10,tblVideos[Channel ID],$K$4),0) | AG10: =IF(Y10>0,SUMIFS(tblVideos[Length],tblVideos[Day],Q10,tblVideos[Channel ID],$K$4),0)
B11: =IF(K11="","",IF(INDEX(tblVideos[Video ID],K11)="",IF(INDEX(tblVideos[Status],K11)="Watched","✓ ","▸ ")&INDEX(tblVideos[Title],K11),HYPERLINK("https://www.youtube.com/watch?v="&INDEX(tblVideos[Video ID],K11),IF(INDEX(tblVideos[Status],K11)="Watched","✓ ","▸ ")&INDEX(tblVideos[Title],K11)))) | C11: =IF(L11="","",IF(INDEX(tblVideos[Video ID],L11)="",IF(INDEX(tblVideos[Status],L11)="Watched","✓ ","▸ ")&INDEX(tblVideos[Title],L11),HYPERLINK("https://www.youtube.com/watch?v="&INDEX(tblVideos[Video ID],L11),IF(INDEX(tblVideos[Status],L11)="Watched","✓ ","▸ ")&INDEX(tblVideos[Title],L11)))) | D11: =IF(M11="","",IF(INDEX(tblVideos[Video ID],M11)="",IF(INDEX(tblVideos[Status],M11)="Watched","✓ ","▸ ")&INDEX(tblVideos[Title],M11),HYPERLINK("https://www.youtube.com/watch?v="&INDEX(tblVideos[Video ID],M11),IF(INDEX(tblVideos[Status],M11)="Watched","✓ ","▸ ")&INDEX(tblVideos[Title],M11)))) | E11: =IF(N11="","",IF(INDEX(tblVideos[Video ID],N11)="",IF(INDEX(tblVideos[Status],N11)="Watched","✓ ","▸ ")&INDEX(tblVideos[Title],N11),HYPERLINK("https://www.youtube.com/watch?v="&INDEX(tblVideos[Video ID],N11),IF(INDEX(tblVideos[Status],N11)="Watched","✓ ","▸ ")&INDEX(tblVideos[Title],N11)))) | F11: =IF(O11="","",IF(INDEX(tblVideos[Video ID],O11)="",IF(INDEX(tblVideos[Status],O11)="Watched","✓ ","▸ ")&INDEX(tblVideos[Title],O11),HYPERLINK("https://www.youtube.com/watch?v="&INDEX(tblVideos[Video ID],O11),IF(INDEX(tblVideos[Status],O11)="Watched","✓ ","▸ ")&INDEX(tblVideos[Title],O11)))) | G11: =IF(P11="","",IF(INDEX(tblVideos[Video ID],P11)="",IF(INDEX(tblVideos[Status],P11)="Watched","✓ ","▸ ")&INDEX(tblVideos[Title],P11),HYPERLINK("https://www.youtube.com/watch?v="&INDEX(tblVideos[Video ID],P11),IF(INDEX(tblVideos[Status],P11)="Watched","✓ ","▸ ")&INDEX(tblVideos[Title],P11)))) | H11: =IF(Q11="","",IF(INDEX(tblVideos[Video ID],Q11)="",IF(INDEX(tblVideos[Status],Q11)="Watched","✓ ","▸ ")&INDEX(tblVideos[Title],Q11),HYPERLINK("https://www.youtube.com/watch?v="&INDEX(tblVideos[Video ID],Q11),IF(INDEX(tblVideos[Status],Q11)="Watched","✓ ","▸ ")&INDEX(tblVideos[Title],Q11)))) | K11: =IF(S10>=1,MATCH(K10*100+1,tblVideos[Cal Key],0),"") | L11: =IF(T10>=1,MATCH(L10*100+1,tblVideos[Cal Key],0),"") | M11: =IF(U10>=1,MATCH(M10*100+1,tblVideos[Cal Key],0),"") | N11: =IF(V10>=1,MATCH(N10*100+1,tblVideos[Cal Key],0),"") | O11: =IF(W10>=1,MATCH(O10*100+1,tblVideos[Cal Key],0),"") | P11: =IF(X10>=1,MATCH(P10*100+1,tblVideos[Cal Key],0),"") | Q11: =IF(Y10>=1,MATCH(Q10*100+1,tblVideos[Cal Key],0),"") | S11: =IF(K11="","",IFERROR(MATCH(INDEX(tblVideos[Channel ID],K11),tblChannels[Channel ID],0),"")) | T11: =IF(L11="","",IFERROR(MATCH(INDEX(tblVideos[Channel ID],L11),tblChannels[Channel ID],0),"")) | U11: =IF(M11="","",IFERROR(MATCH(INDEX(tblVideos[Channel ID],M11),tblChannels[Channel ID],0),"")) | V11: =IF(N11="","",IFERROR(MATCH(INDEX(tblVideos[Channel ID],N11),tblChannels[Channel ID],0),"")) | W11: =IF(O11="","",IFERROR(MATCH(INDEX(tblVideos[Channel ID],O11),tblChannels[Channel ID],0),"")) | X11: =IF(P11="","",IFERROR(MATCH(INDEX(tblVideos[Channel ID],P11),tblChannels[Channel ID],0),"")) | Y11: =IF(Q11="","",IFERROR(MATCH(INDEX(tblVideos[Channel ID],Q11),tblChannels[Channel ID],0),""))
B12: =IF(K12="","",IF(INDEX(tblVideos[Video ID],K12)="",IF(INDEX(tblVideos[Status],K12)="Watched","✓ ","▸ ")&INDEX(tblVideos[Title],K12),HYPERLINK("https://www.youtube.com/watch?v="&INDEX(tblVideos[Video ID],K12),IF(INDEX(tblVideos[Status],K12)="Watched","✓ ","▸ ")&INDEX(tblVideos[Title],K12)))) | C12: =IF(L12="","",IF(INDEX(tblVideos[Video ID],L12)="",IF(INDEX(tblVideos[Status],L12)="Watched","✓ ","▸ ")&INDEX(tblVideos[Title],L12),HYPERLINK("https://www.youtube.com/watch?v="&INDEX(tblVideos[Video ID],L12),IF(INDEX(tblVideos[Status],L12)="Watched","✓ ","▸ ")&INDEX(tblVideos[Title],L12)))) | D12: =IF(M12="","",IF(INDEX(tblVideos[Video ID],M12)="",IF(INDEX(tblVideos[Status],M12)="Watched","✓ ","▸ ")&INDEX(tblVideos[Title],M12),HYPERLINK("https://www.youtube.com/watch?v="&INDEX(tblVideos[Video ID],M12),IF(INDEX(tblVideos[Status],M12)="Watched","✓ ","▸ ")&INDEX(tblVideos[Title],M12)))) | E12: =IF(N12="","",IF(INDEX(tblVideos[Video ID],N12)="",IF(INDEX(tblVideos[Status],N12)="Watched","✓ ","▸ ")&INDEX(tblVideos[Title],N12),HYPERLINK("https://www.youtube.com/watch?v="&INDEX(tblVideos[Video ID],N12),IF(INDEX(tblVideos[Status],N12)="Watched","✓ ","▸ ")&INDEX(tblVideos[Title],N12)))) | F12: =IF(O12="","",IF(INDEX(tblVideos[Video ID],O12)="",IF(INDEX(tblVideos[Status],O12)="Watched","✓ ","▸ ")&INDEX(tblVideos[Title],O12),HYPERLINK("https://www.youtube.com/watch?v="&INDEX(tblVideos[Video ID],O12),IF(INDEX(tblVideos[Status],O12)="Watched","✓ ","▸ ")&INDEX(tblVideos[Title],O12)))) | G12: =IF(P12="","",IF(INDEX(tblVideos[Video ID],P12)="",IF(INDEX(tblVideos[Status],P12)="Watched","✓ ","▸ ")&INDEX(tblVideos[Title],P12),HYPERLINK("https://www.youtube.com/watch?v="&INDEX(tblVideos[Video ID],P12),IF(INDEX(tblVideos[Status],P12)="Watched","✓ ","▸ ")&INDEX(tblVideos[Title],P12)))) | H12: =IF(Q12="","",IF(INDEX(tblVideos[Video ID],Q12)="",IF(INDEX(tblVideos[Status],Q12)="Watched","✓ ","▸ ")&INDEX(tblVideos[Title],Q12),HYPERLINK("https://www.youtube.com/watch?v="&INDEX(tblVideos[Video ID],Q12),IF(INDEX(tblVideos[Status],Q12)="Watched","✓ ","▸ ")&INDEX(tblVideos[Title],Q12)))) | K12: =IF(S10>=2,MATCH(K10*100+2,tblVideos[Cal Key],0),"") | L12: =IF(T10>=2,MATCH(L10*100+2,tblVideos[Cal Key],0),"") | M12: =IF(U10>=2,MATCH(M10*100+2,tblVideos[Cal Key],0),"") | N12: =IF(V10>=2,MATCH(N10*100+2,tblVideos[Cal Key],0),"") | O12: =IF(W10>=2,MATCH(O10*100+2,tblVideos[Cal Key],0),"") | P12: =IF(X10>=2,MATCH(P10*100+2,tblVideos[Cal Key],0),"") | Q12: =IF(Y10>=2,MATCH(Q10*100+2,tblVideos[Cal Key],0),"") | S12: =IF(K12="","",IFERROR(MATCH(INDEX(tblVideos[Channel ID],K12),tblChannels[Channel ID],0),"")) | T12: =IF(L12="","",IFERROR(MATCH(INDEX(tblVideos[Channel ID],L12),tblChannels[Channel ID],0),"")) | U12: =IF(M12="","",IFERROR(MATCH(INDEX(tblVideos[Channel ID],M12),tblChannels[Channel ID],0),"")) | V12: =IF(N12="","",IFERROR(MATCH(INDEX(tblVideos[Channel ID],N12),tblChannels[Channel ID],0),"")) | W12: =IF(O12="","",IFERROR(MATCH(INDEX(tblVideos[Channel ID],O12),tblChannels[Channel ID],0),"")) | X12: =IF(P12="","",IFERROR(MATCH(INDEX(tblVideos[Channel ID],P12),tblChannels[Channel ID],0),"")) | Y12: =IF(Q12="","",IFERROR(MATCH(INDEX(tblVideos[Channel ID],Q12),tblChannels[Channel ID],0),""))
B13: =IF(K13="","",IF(INDEX(tblVideos[Video ID],K13)="",IF(INDEX(tblVideos[Status],K13)="Watched","✓ ","▸ ")&INDEX(tblVideos[Title],K13),HYPERLINK("https://www.youtube.com/watch?v="&INDEX(tblVideos[Video ID],K13),IF(INDEX(tblVideos[Status],K13)="Watched","✓ ","▸ ")&INDEX(tblVideos[Title],K13)))) | C13: =IF(L13="","",IF(INDEX(tblVideos[Video ID],L13)="",IF(INDEX(tblVideos[Status],L13)="Watched","✓ ","▸ ")&INDEX(tblVideos[Title],L13),HYPERLINK("https://www.youtube.com/watch?v="&INDEX(tblVideos[Video ID],L13),IF(INDEX(tblVideos[Status],L13)="Watched","✓ ","▸ ")&INDEX(tblVideos[Title],L13)))) | D13: =IF(M13="","",IF(INDEX(tblVideos[Video ID],M13)="",IF(INDEX(tblVideos[Status],M13)="Watched","✓ ","▸ ")&INDEX(tblVideos[Title],M13),HYPERLINK("https://www.youtube.com/watch?v="&INDEX(tblVideos[Video ID],M13),IF(INDEX(tblVideos[Status],M13)="Watched","✓ ","▸ ")&INDEX(tblVideos[Title],M13)))) | E13: =IF(N13="","",IF(INDEX(tblVideos[Video ID],N13)="",IF(INDEX(tblVideos[Status],N13)="Watched","✓ ","▸ ")&INDEX(tblVideos[Title],N13),HYPERLINK("https://www.youtube.com/watch?v="&INDEX(tblVideos[Video ID],N13),IF(INDEX(tblVideos[Status],N13)="Watched","✓ ","▸ ")&INDEX(tblVideos[Title],N13)))) | F13: =IF(O13="","",IF(INDEX(tblVideos[Video ID],O13)="",IF(INDEX(tblVideos[Status],O13)="Watched","✓ ","▸ ")&INDEX(tblVideos[Title],O13),HYPERLINK("https://www.youtube.com/watch?v="&INDEX(tblVideos[Video ID],O13),IF(INDEX(tblVideos[Status],O13)="Watched","✓ ","▸ ")&INDEX(tblVideos[Title],O13)))) | G13: =IF(P13="","",IF(INDEX(tblVideos[Video ID],P13)="",IF(INDEX(tblVideos[Status],P13)="Watched","✓ ","▸ ")&INDEX(tblVideos[Title],P13),HYPERLINK("https://www.youtube.com/watch?v="&INDEX(tblVideos[Video ID],P13),IF(INDEX(tblVideos[Status],P13)="Watched","✓ ","▸ ")&INDEX(tblVideos[Title],P13)))) | H13: =IF(Q13="","",IF(INDEX(tblVideos[Video ID],Q13)="",IF(INDEX(tblVideos[Status],Q13)="Watched","✓ ","▸ ")&INDEX(tblVideos[Title],Q13),HYPERLINK("https://www.youtube.com/watch?v="&INDEX(tblVideos[Video ID],Q13),IF(INDEX(tblVideos[Status],Q13)="Watched","✓ ","▸ ")&INDEX(tblVideos[Title],Q13)))) | K13: =IF(S10>=3,MATCH(K10*100+3,tblVideos[Cal Key],0),"") | L13: =IF(T10>=3,MATCH(L10*100+3,tblVideos[Cal Key],0),"") | M13: =IF(U10>=3,MATCH(M10*100+3,tblVideos[Cal Key],0),"") | N13: =IF(V10>=3,MATCH(N10*100+3,tblVideos[Cal Key],0),"") | O13: =IF(W10>=3,MATCH(O10*100+3,tblVideos[Cal Key],0),"") | P13: =IF(X10>=3,MATCH(P10*100+3,tblVideos[Cal Key],0),"") | Q13: =IF(Y10>=3,MATCH(Q10*100+3,tblVideos[Cal Key],0),"") | S13: =IF(K13="","",IFERROR(MATCH(INDEX(tblVideos[Channel ID],K13),tblChannels[Channel ID],0),"")) | T13: =IF(L13="","",IFERROR(MATCH(INDEX(tblVideos[Channel ID],L13),tblChannels[Channel ID],0),"")) | U13: =IF(M13="","",IFERROR(MATCH(INDEX(tblVideos[Channel ID],M13),tblChannels[Channel ID],0),"")) | V13: =IF(N13="","",IFERROR(MATCH(INDEX(tblVideos[Channel ID],N13),tblChannels[Channel ID],0),"")) | W13: =IF(O13="","",IFERROR(MATCH(INDEX(tblVideos[Channel ID],O13),tblChannels[Channel ID],0),"")) | X13: =IF(P13="","",IFERROR(MATCH(INDEX(tblVideos[Channel ID],P13),tblChannels[Channel ID],0),"")) | Y13: =IF(Q13="","",IFERROR(MATCH(INDEX(tblVideos[Channel ID],Q13),tblChannels[Channel ID],0),""))
B14: =IF(K14="","",IF(INDEX(tblVideos[Video ID],K14)="",IF(INDEX(tblVideos[Status],K14)="Watched","✓ ","▸ ")&INDEX(tblVideos[Title],K14),HYPERLINK("https://www.youtube.com/watch?v="&INDEX(tblVideos[Video ID],K14),IF(INDEX(tblVideos[Status],K14)="Watched","✓ ","▸ ")&INDEX(tblVideos[Title],K14)))) | C14: =IF(L14="","",IF(INDEX(tblVideos[Video ID],L14)="",IF(INDEX(tblVideos[Status],L14)="Watched","✓ ","▸ ")&INDEX(tblVideos[Title],L14),HYPERLINK("https://www.youtube.com/watch?v="&INDEX(tblVideos[Video ID],L14),IF(INDEX(tblVideos[Status],L14)="Watched","✓ ","▸ ")&INDEX(tblVideos[Title],L14)))) | D14: =IF(M14="","",IF(INDEX(tblVideos[Video ID],M14)="",IF(INDEX(tblVideos[Status],M14)="Watched","✓ ","▸ ")&INDEX(tblVideos[Title],M14),HYPERLINK("https://www.youtube.com/watch?v="&INDEX(tblVideos[Video ID],M14),IF(INDEX(tblVideos[Status],M14)="Watched","✓ ","▸ ")&INDEX(tblVideos[Title],M14)))) | E14: =IF(N14="","",IF(INDEX(tblVideos[Video ID],N14)="",IF(INDEX(tblVideos[Status],N14)="Watched","✓ ","▸ ")&INDEX(tblVideos[Title],N14),HYPERLINK("https://www.youtube.com/watch?v="&INDEX(tblVideos[Video ID],N14),IF(INDEX(tblVideos[Status],N14)="Watched","✓ ","▸ ")&INDEX(tblVideos[Title],N14)))) | F14: =IF(O14="","",IF(INDEX(tblVideos[Video ID],O14)="",IF(INDEX(tblVideos[Status],O14)="Watched","✓ ","▸ ")&INDEX(tblVideos[Title],O14),HYPERLINK("https://www.youtube.com/watch?v="&INDEX(tblVideos[Video ID],O14),IF(INDEX(tblVideos[Status],O14)="Watched","✓ ","▸ ")&INDEX(tblVideos[Title],O14)))) | G14: =IF(P14="","",IF(INDEX(tblVideos[Video ID],P14)="",IF(INDEX(tblVideos[Status],P14)="Watched","✓ ","▸ ")&INDEX(tblVideos[Title],P14),HYPERLINK("https://www.youtube.com/watch?v="&INDEX(tblVideos[Video ID],P14),IF(INDEX(tblVideos[Status],P14)="Watched","✓ ","▸ ")&INDEX(tblVideos[Title],P14)))) | H14: =IF(Q14="","",IF(INDEX(tblVideos[Video ID],Q14)="",IF(INDEX(tblVideos[Status],Q14)="Watched","✓ ","▸ ")&INDEX(tblVideos[Title],Q14),HYPERLINK("https://www.youtube.com/watch?v="&INDEX(tblVideos[Video ID],Q14),IF(INDEX(tblVideos[Status],Q14)="Watched","✓ ","▸ ")&INDEX(tblVideos[Title],Q14)))) | K14: =IF(S10>=4,MATCH(K10*100+4,tblVideos[Cal Key],0),"") | L14: =IF(T10>=4,MATCH(L10*100+4,tblVideos[Cal Key],0),"") | M14: =IF(U10>=4,MATCH(M10*100+4,tblVideos[Cal Key],0),"") | N14: =IF(V10>=4,MATCH(N10*100+4,tblVideos[Cal Key],0),"") | O14: =IF(W10>=4,MATCH(O10*100+4,tblVideos[Cal Key],0),"") | P14: =IF(X10>=4,MATCH(P10*100+4,tblVideos[Cal Key],0),"") | Q14: =IF(Y10>=4,MATCH(Q10*100+4,tblVideos[Cal Key],0),"") | S14: =IF(K14="","",IFERROR(MATCH(INDEX(tblVideos[Channel ID],K14),tblChannels[Channel ID],0),"")) | T14: =IF(L14="","",IFERROR(MATCH(INDEX(tblVideos[Channel ID],L14),tblChannels[Channel ID],0),"")) | U14: =IF(M14="","",IFERROR(MATCH(INDEX(tblVideos[Channel ID],M14),tblChannels[Channel ID],0),"")) | V14: =IF(N14="","",IFERROR(MATCH(INDEX(tblVideos[Channel ID],N14),tblChannels[Channel ID],0),"")) | W14: =IF(O14="","",IFERROR(MATCH(INDEX(tblVideos[Channel ID],O14),tblChannels[Channel ID],0),"")) | X14: =IF(P14="","",IFERROR(MATCH(INDEX(tblVideos[Channel ID],P14),tblChannels[Channel ID],0),"")) | Y14: =IF(Q14="","",IFERROR(MATCH(INDEX(tblVideos[Channel ID],Q14),tblChannels[Channel ID],0),""))
B15: =IF(K15="","",IF(INDEX(tblVideos[Video ID],K15)="",IF(INDEX(tblVideos[Status],K15)="Watched","✓ ","▸ ")&INDEX(tblVideos[Title],K15),HYPERLINK("https://www.youtube.com/watch?v="&INDEX(tblVideos[Video ID],K15),IF(INDEX(tblVideos[Status],K15)="Watched","✓ ","▸ ")&INDEX(tblVideos[Title],K15)))) | C15: =IF(L15="","",IF(INDEX(tblVideos[Video ID],L15)="",IF(INDEX(tblVideos[Status],L15)="Watched","✓ ","▸ ")&INDEX(tblVideos[Title],L15),HYPERLINK("https://www.youtube.com/watch?v="&INDEX(tblVideos[Video ID],L15),IF(INDEX(tblVideos[Status],L15)="Watched","✓ ","▸ ")&INDEX(tblVideos[Title],L15)))) | D15: =IF(M15="","",IF(INDEX(tblVideos[Video ID],M15)="",IF(INDEX(tblVideos[Status],M15)="Watched","✓ ","▸ ")&INDEX(tblVideos[Title],M15),HYPERLINK("https://www.youtube.com/watch?v="&INDEX(tblVideos[Video ID],M15),IF(INDEX(tblVideos[Status],M15)="Watched","✓ ","▸ ")&INDEX(tblVideos[Title],M15)))) | E15: =IF(N15="","",IF(INDEX(tblVideos[Video ID],N15)="",IF(INDEX(tblVideos[Status],N15)="Watched","✓ ","▸ ")&INDEX(tblVideos[Title],N15),HYPERLINK("https://www.youtube.com/watch?v="&INDEX(tblVideos[Video ID],N15),IF(INDEX(tblVideos[Status],N15)="Watched","✓ ","▸ ")&INDEX(tblVideos[Title],N15)))) | F15: =IF(O15="","",IF(INDEX(tblVideos[Video ID],O15)="",IF(INDEX(tblVideos[Status],O15)="Watched","✓ ","▸ ")&INDEX(tblVideos[Title],O15),HYPERLINK("https://www.youtube.com/watch?v="&INDEX(tblVideos[Video ID],O15),IF(INDEX(tblVideos[Status],O15)="Watched","✓ ","▸ ")&INDEX(tblVideos[Title],O15)))) | G15: =IF(P15="","",IF(INDEX(tblVideos[Video ID],P15)="",IF(INDEX(tblVideos[Status],P15)="Watched","✓ ","▸ ")&INDEX(tblVideos[Title],P15),HYPERLINK("https://www.youtube.com/watch?v="&INDEX(tblVideos[Video ID],P15),IF(INDEX(tblVideos[Status],P15)="Watched","✓ ","▸ ")&INDEX(tblVideos[Title],P15)))) | H15: =IF(Q15="","",IF(INDEX(tblVideos[Video ID],Q15)="",IF(INDEX(tblVideos[Status],Q15)="Watched","✓ ","▸ ")&INDEX(tblVideos[Title],Q15),HYPERLINK("https://www.youtube.com/watch?v="&INDEX(tblVideos[Video ID],Q15),IF(INDEX(tblVideos[Status],Q15)="Watched","✓ ","▸ ")&INDEX(tblVideos[Title],Q15)))) | K15: =IF(S10>=5,MATCH(K10*100+5,tblVideos[Cal Key],0),"") | L15: =IF(T10>=5,MATCH(L10*100+5,tblVideos[Cal Key],0),"") | M15: =IF(U10>=5,MATCH(M10*100+5,tblVideos[Cal Key],0),"") | N15: =IF(V10>=5,MATCH(N10*100+5,tblVideos[Cal Key],0),"") | O15: =IF(W10>=5,MATCH(O10*100+5,tblVideos[Cal Key],0),"") | P15: =IF(X10>=5,MATCH(P10*100+5,tblVideos[Cal Key],0),"") | Q15: =IF(Y10>=5,MATCH(Q10*100+5,tblVideos[Cal Key],0),"") | S15: =IF(K15="","",IFERROR(MATCH(INDEX(tblVideos[Channel ID],K15),tblChannels[Channel ID],0),"")) | T15: =IF(L15="","",IFERROR(MATCH(INDEX(tblVideos[Channel ID],L15),tblChannels[Channel ID],0),"")) | U15: =IF(M15="","",IFERROR(MATCH(INDEX(tblVideos[Channel ID],M15),tblChannels[Channel ID],0),"")) | V15: =IF(N15="","",IFERROR(MATCH(INDEX(tblVideos[Channel ID],N15),tblChannels[Channel ID],0),"")) | W15: =IF(O15="","",IFERROR(MATCH(INDEX(tblVideos[Channel ID],O15),tblChannels[Channel ID],0),"")) | X15: =IF(P15="","",IFERROR(MATCH(INDEX(tblVideos[Channel ID],P15),tblChannels[Channel ID],0),"")) | Y15: =IF(Q15="","",IFERROR(MATCH(INDEX(tblVideos[Channel ID],Q15),tblChannels[Channel ID],0),""))
B16: =IF(MONTH(K16)=MONTH($K$2),DAY(K16)&IF(S16>0," · "&S16&IF(S16=1," video"," videos")&" · "&IF(ROUND((AA16)*1440,0)<60,ROUND((AA16)*1440,0)&" m",IF(MOD(ROUND((AA16)*1440,0),60)=0,INT(ROUND((AA16)*1440,0)/60)&" h",INT(ROUND((AA16)*1440,0)/60)&" h "&MOD(ROUND((AA16)*1440,0),60)&" m"))&IF(S16>5," (+"&(S16-5)&" more)",""),""),"") | C16: =IF(MONTH(L16)=MONTH($K$2),DAY(L16)&IF(T16>0," · "&T16&IF(T16=1," video"," videos")&" · "&IF(ROUND((AB16)*1440,0)<60,ROUND((AB16)*1440,0)&" m",IF(MOD(ROUND((AB16)*1440,0),60)=0,INT(ROUND((AB16)*1440,0)/60)&" h",INT(ROUND((AB16)*1440,0)/60)&" h "&MOD(ROUND((AB16)*1440,0),60)&" m"))&IF(T16>5," (+"&(T16-5)&" more)",""),""),"") | D16: =IF(MONTH(M16)=MONTH($K$2),DAY(M16)&IF(U16>0," · "&U16&IF(U16=1," video"," videos")&" · "&IF(ROUND((AC16)*1440,0)<60,ROUND((AC16)*1440,0)&" m",IF(MOD(ROUND((AC16)*1440,0),60)=0,INT(ROUND((AC16)*1440,0)/60)&" h",INT(ROUND((AC16)*1440,0)/60)&" h "&MOD(ROUND((AC16)*1440,0),60)&" m"))&IF(U16>5," (+"&(U16-5)&" more)",""),""),"") | E16: =IF(MONTH(N16)=MONTH($K$2),DAY(N16)&IF(V16>0," · "&V16&IF(V16=1," video"," videos")&" · "&IF(ROUND((AD16)*1440,0)<60,ROUND((AD16)*1440,0)&" m",IF(MOD(ROUND((AD16)*1440,0),60)=0,INT(ROUND((AD16)*1440,0)/60)&" h",INT(ROUND((AD16)*1440,0)/60)&" h "&MOD(ROUND((AD16)*1440,0),60)&" m"))&IF(V16>5," (+"&(V16-5)&" more)",""),""),"") | F16: =IF(MONTH(O16)=MONTH($K$2),DAY(O16)&IF(W16>0," · "&W16&IF(W16=1," video"," videos")&" · "&IF(ROUND((AE16)*1440,0)<60,ROUND((AE16)*1440,0)&" m",IF(MOD(ROUND((AE16)*1440,0),60)=0,INT(ROUND((AE16)*1440,0)/60)&" h",INT(ROUND((AE16)*1440,0)/60)&" h "&MOD(ROUND((AE16)*1440,0),60)&" m"))&IF(W16>5," (+"&(W16-5)&" more)",""),""),"") | G16: =IF(MONTH(P16)=MONTH($K$2),DAY(P16)&IF(X16>0," · "&X16&IF(X16=1," video"," videos")&" · "&IF(ROUND((AF16)*1440,0)<60,ROUND((AF16)*1440,0)&" m",IF(MOD(ROUND((AF16)*1440,0),60)=0,INT(ROUND((AF16)*1440,0)/60)&" h",INT(ROUND((AF16)*1440,0)/60)&" h "&MOD(ROUND((AF16)*1440,0),60)&" m"))&IF(X16>5," (+"&(X16-5)&" more)",""),""),"") | H16: =IF(MONTH(Q16)=MONTH($K$2),DAY(Q16)&IF(Y16>0," · "&Y16&IF(Y16=1," video"," videos")&" · "&IF(ROUND((AG16)*1440,0)<60,ROUND((AG16)*1440,0)&" m",IF(MOD(ROUND((AG16)*1440,0),60)=0,INT(ROUND((AG16)*1440,0)/60)&" h",INT(ROUND((AG16)*1440,0)/60)&" h "&MOD(ROUND((AG16)*1440,0),60)&" m"))&IF(Y16>5," (+"&(Y16-5)&" more)",""),""),"") | K16: =$K$3+7 | L16: =$K$3+8 | M16: =$K$3+9 | N16: =$K$3+10 | O16: =$K$3+11 | P16: =$K$3+12 | Q16: =$K$3+13 | S16: =IF(MONTH(K16)=MONTH($K$2),COUNTIFS(tblVideos[Day],K16,tblVideos[Channel ID],$K$4),0) | T16: =IF(MONTH(L16)=MONTH($K$2),COUNTIFS(tblVideos[Day],L16,tblVideos[Channel ID],$K$4),0) | U16: =IF(MONTH(M16)=MONTH($K$2),COUNTIFS(tblVideos[Day],M16,tblVideos[Channel ID],$K$4),0) | V16: =IF(MONTH(N16)=MONTH($K$2),COUNTIFS(tblVideos[Day],N16,tblVideos[Channel ID],$K$4),0) | W16: =IF(MONTH(O16)=MONTH($K$2),COUNTIFS(tblVideos[Day],O16,tblVideos[Channel ID],$K$4),0) | X16: =IF(MONTH(P16)=MONTH($K$2),COUNTIFS(tblVideos[Day],P16,tblVideos[Channel ID],$K$4),0) | Y16: =IF(MONTH(Q16)=MONTH($K$2),COUNTIFS(tblVideos[Day],Q16,tblVideos[Channel ID],$K$4),0) | AA16: =IF(S16>0,SUMIFS(tblVideos[Length],tblVideos[Day],K16,tblVideos[Channel ID],$K$4),0) | AB16: =IF(T16>0,SUMIFS(tblVideos[Length],tblVideos[Day],L16,tblVideos[Channel ID],$K$4),0) | AC16: =IF(U16>0,SUMIFS(tblVideos[Length],tblVideos[Day],M16,tblVideos[Channel ID],$K$4),0) | AD16: =IF(V16>0,SUMIFS(tblVideos[Length],tblVideos[Day],N16,tblVideos[Channel ID],$K$4),0) | AE16: =IF(W16>0,SUMIFS(tblVideos[Length],tblVideos[Day],O16,tblVideos[Channel ID],$K$4),0) | AF16: =IF(X16>0,SUMIFS(tblVideos[Length],tblVideos[Day],P16,tblVideos[Channel ID],$K$4),0) | AG16: =IF(Y16>0,SUMIFS(tblVideos[Length],tblVideos[Day],Q16,tblVideos[Channel ID],$K$4),0)
B17: =IF(K17="","",IF(INDEX(tblVideos[Video ID],K17)="",IF(INDEX(tblVideos[Status],K17)="Watched","✓ ","▸ ")&INDEX(tblVideos[Title],K17),HYPERLINK("https://www.youtube.com/watch?v="&INDEX(tblVideos[Video ID],K17),IF(INDEX(tblVideos[Status],K17)="Watched","✓ ","▸ ")&INDEX(tblVideos[Title],K17)))) | C17: =IF(L17="","",IF(INDEX(tblVideos[Video ID],L17)="",IF(INDEX(tblVideos[Status],L17)="Watched","✓ ","▸ ")&INDEX(tblVideos[Title],L17),HYPERLINK("https://www.youtube.com/watch?v="&INDEX(tblVideos[Video ID],L17),IF(INDEX(tblVideos[Status],L17)="Watched","✓ ","▸ ")&INDEX(tblVideos[Title],L17)))) | D17: =IF(M17="","",IF(INDEX(tblVideos[Video ID],M17)="",IF(INDEX(tblVideos[Status],M17)="Watched","✓ ","▸ ")&INDEX(tblVideos[Title],M17),HYPERLINK("https://www.youtube.com/watch?v="&INDEX(tblVideos[Video ID],M17),IF(INDEX(tblVideos[Status],M17)="Watched","✓ ","▸ ")&INDEX(tblVideos[Title],M17)))) | E17: =IF(N17="","",IF(INDEX(tblVideos[Video ID],N17)="",IF(INDEX(tblVideos[Status],N17)="Watched","✓ ","▸ ")&INDEX(tblVideos[Title],N17),HYPERLINK("https://www.youtube.com/watch?v="&INDEX(tblVideos[Video ID],N17),IF(INDEX(tblVideos[Status],N17)="Watched","✓ ","▸ ")&INDEX(tblVideos[Title],N17)))) | F17: =IF(O17="","",IF(INDEX(tblVideos[Video ID],O17)="",IF(INDEX(tblVideos[Status],O17)="Watched","✓ ","▸ ")&INDEX(tblVideos[Title],O17),HYPERLINK("https://www.youtube.com/watch?v="&INDEX(tblVideos[Video ID],O17),IF(INDEX(tblVideos[Status],O17)="Watched","✓ ","▸ ")&INDEX(tblVideos[Title],O17)))) | G17: =IF(P17="","",IF(INDEX(tblVideos[Video ID],P17)="",IF(INDEX(tblVideos[Status],P17)="Watched","✓ ","▸ ")&INDEX(tblVideos[Title],P17),HYPERLINK("https://www.youtube.com/watch?v="&INDEX(tblVideos[Video ID],P17),IF(INDEX(tblVideos[Status],P17)="Watched","✓ ","▸ ")&INDEX(tblVideos[Title],P17)))) | H17: =IF(Q17="","",IF(INDEX(tblVideos[Video ID],Q17)="",IF(INDEX(tblVideos[Status],Q17)="Watched","✓ ","▸ ")&INDEX(tblVideos[Title],Q17),HYPERLINK("https://www.youtube.com/watch?v="&INDEX(tblVideos[Video ID],Q17),IF(INDEX(tblVideos[Status],Q17)="Watched","✓ ","▸ ")&INDEX(tblVideos[Title],Q17)))) | K17: =IF(S16>=1,MATCH(K16*100+1,tblVideos[Cal Key],0),"") | L17: =IF(T16>=1,MATCH(L16*100+1,tblVideos[Cal Key],0),"") | M17: =IF(U16>=1,MATCH(M16*100+1,tblVideos[Cal Key],0),"") | N17: =IF(V16>=1,MATCH(N16*100+1,tblVideos[Cal Key],0),"") | O17: =IF(W16>=1,MATCH(O16*100+1,tblVideos[Cal Key],0),"") | P17: =IF(X16>=1,MATCH(P16*100+1,tblVideos[Cal Key],0),"") | Q17: =IF(Y16>=1,MATCH(Q16*100+1,tblVideos[Cal Key],0),"") | S17: =IF(K17="","",IFERROR(MATCH(INDEX(tblVideos[Channel ID],K17),tblChannels[Channel ID],0),"")) | T17: =IF(L17="","",IFERROR(MATCH(INDEX(tblVideos[Channel ID],L17),tblChannels[Channel ID],0),"")) | U17: =IF(M17="","",IFERROR(MATCH(INDEX(tblVideos[Channel ID],M17),tblChannels[Channel ID],0),"")) | V17: =IF(N17="","",IFERROR(MATCH(INDEX(tblVideos[Channel ID],N17),tblChannels[Channel ID],0),"")) | W17: =IF(O17="","",IFERROR(MATCH(INDEX(tblVideos[Channel ID],O17),tblChannels[Channel ID],0),"")) | X17: =IF(P17="","",IFERROR(MATCH(INDEX(tblVideos[Channel ID],P17),tblChannels[Channel ID],0),"")) | Y17: =IF(Q17="","",IFERROR(MATCH(INDEX(tblVideos[Channel ID],Q17),tblChannels[Channel ID],0),""))
B18: =IF(K18="","",IF(INDEX(tblVideos[Video ID],K18)="",IF(INDEX(tblVideos[Status],K18)="Watched","✓ ","▸ ")&INDEX(tblVideos[Title],K18),HYPERLINK("https://www.youtube.com/watch?v="&INDEX(tblVideos[Video ID],K18),IF(INDEX(tblVideos[Status],K18)="Watched","✓ ","▸ ")&INDEX(tblVideos[Title],K18)))) | C18: =IF(L18="","",IF(INDEX(tblVideos[Video ID],L18)="",IF(INDEX(tblVideos[Status],L18)="Watched","✓ ","▸ ")&INDEX(tblVideos[Title],L18),HYPERLINK("https://www.youtube.com/watch?v="&INDEX(tblVideos[Video ID],L18),IF(INDEX(tblVideos[Status],L18)="Watched","✓ ","▸ ")&INDEX(tblVideos[Title],L18)))) | D18: =IF(M18="","",IF(INDEX(tblVideos[Video ID],M18)="",IF(INDEX(tblVideos[Status],M18)="Watched","✓ ","▸ ")&INDEX(tblVideos[Title],M18),HYPERLINK("https://www.youtube.com/watch?v="&INDEX(tblVideos[Video ID],M18),IF(INDEX(tblVideos[Status],M18)="Watched","✓ ","▸ ")&INDEX(tblVideos[Title],M18)))) | E18: =IF(N18="","",IF(INDEX(tblVideos[Video ID],N18)="",IF(INDEX(tblVideos[Status],N18)="Watched","✓ ","▸ ")&INDEX(tblVideos[Title],N18),HYPERLINK("https://www.youtube.com/watch?v="&INDEX(tblVideos[Video ID],N18),IF(INDEX(tblVideos[Status],N18)="Watched","✓ ","▸ ")&INDEX(tblVideos[Title],N18)))) | F18: =IF(O18="","",IF(INDEX(tblVideos[Video ID],O18)="",IF(INDEX(tblVideos[Status],O18)="Watched","✓ ","▸ ")&INDEX(tblVideos[Title],O18),HYPERLINK("https://www.youtube.com/watch?v="&INDEX(tblVideos[Video ID],O18),IF(INDEX(tblVideos[Status],O18)="Watched","✓ ","▸ ")&INDEX(tblVideos[Title],O18)))) | G18: =IF(P18="","",IF(INDEX(tblVideos[Video ID],P18)="",IF(INDEX(tblVideos[Status],P18)="Watched","✓ ","▸ ")&INDEX(tblVideos[Title],P18),HYPERLINK("https://www.youtube.com/watch?v="&INDEX(tblVideos[Video ID],P18),IF(INDEX(tblVideos[Status],P18)="Watched","✓ ","▸ ")&INDEX(tblVideos[Title],P18)))) | H18: =IF(Q18="","",IF(INDEX(tblVideos[Video ID],Q18)="",IF(INDEX(tblVideos[Status],Q18)="Watched","✓ ","▸ ")&INDEX(tblVideos[Title],Q18),HYPERLINK("https://www.youtube.com/watch?v="&INDEX(tblVideos[Video ID],Q18),IF(INDEX(tblVideos[Status],Q18)="Watched","✓ ","▸ ")&INDEX(tblVideos[Title],Q18)))) | K18: =IF(S16>=2,MATCH(K16*100+2,tblVideos[Cal Key],0),"") | L18: =IF(T16>=2,MATCH(L16*100+2,tblVideos[Cal Key],0),"") | M18: =IF(U16>=2,MATCH(M16*100+2,tblVideos[Cal Key],0),"") | N18: =IF(V16>=2,MATCH(N16*100+2,tblVideos[Cal Key],0),"") | O18: =IF(W16>=2,MATCH(O16*100+2,tblVideos[Cal Key],0),"") | P18: =IF(X16>=2,MATCH(P16*100+2,tblVideos[Cal Key],0),"") | Q18: =IF(Y16>=2,MATCH(Q16*100+2,tblVideos[Cal Key],0),"") | S18: =IF(K18="","",IFERROR(MATCH(INDEX(tblVideos[Channel ID],K18),tblChannels[Channel ID],0),"")) | T18: =IF(L18="","",IFERROR(MATCH(INDEX(tblVideos[Channel ID],L18),tblChannels[Channel ID],0),"")) | U18: =IF(M18="","",IFERROR(MATCH(INDEX(tblVideos[Channel ID],M18),tblChannels[Channel ID],0),"")) | V18: =IF(N18="","",IFERROR(MATCH(INDEX(tblVideos[Channel ID],N18),tblChannels[Channel ID],0),"")) | W18: =IF(O18="","",IFERROR(MATCH(INDEX(tblVideos[Channel ID],O18),tblChannels[Channel ID],0),"")) | X18: =IF(P18="","",IFERROR(MATCH(INDEX(tblVideos[Channel ID],P18),tblChannels[Channel ID],0),"")) | Y18: =IF(Q18="","",IFERROR(MATCH(INDEX(tblVideos[Channel ID],Q18),tblChannels[Channel ID],0),""))
B19: =IF(K19="","",IF(INDEX(tblVideos[Video ID],K19)="",IF(INDEX(tblVideos[Status],K19)="Watched","✓ ","▸ ")&INDEX(tblVideos[Title],K19),HYPERLINK("https://www.youtube.com/watch?v="&INDEX(tblVideos[Video ID],K19),IF(INDEX(tblVideos[Status],K19)="Watched","✓ ","▸ ")&INDEX(tblVideos[Title],K19)))) | C19: =IF(L19="","",IF(INDEX(tblVideos[Video ID],L19)="",IF(INDEX(tblVideos[Status],L19)="Watched","✓ ","▸ ")&INDEX(tblVideos[Title],L19),HYPERLINK("https://www.youtube.com/watch?v="&INDEX(tblVideos[Video ID],L19),IF(INDEX(tblVideos[Status],L19)="Watched","✓ ","▸ ")&INDEX(tblVideos[Title],L19)))) | D19: =IF(M19="","",IF(INDEX(tblVideos[Video ID],M19)="",IF(INDEX(tblVideos[Status],M19)="Watched","✓ ","▸ ")&INDEX(tblVideos[Title],M19),HYPERLINK("https://www.youtube.com/watch?v="&INDEX(tblVideos[Video ID],M19),IF(INDEX(tblVideos[Status],M19)="Watched","✓ ","▸ ")&INDEX(tblVideos[Title],M19)))) | E19: =IF(N19="","",IF(INDEX(tblVideos[Video ID],N19)="",IF(INDEX(tblVideos[Status],N19)="Watched","✓ ","▸ ")&INDEX(tblVideos[Title],N19),HYPERLINK("https://www.youtube.com/watch?v="&INDEX(tblVideos[Video ID],N19),IF(INDEX(tblVideos[Status],N19)="Watched","✓ ","▸ ")&INDEX(tblVideos[Title],N19)))) | F19: =IF(O19="","",IF(INDEX(tblVideos[Video ID],O19)="",IF(INDEX(tblVideos[Status],O19)="Watched","✓ ","▸ ")&INDEX(tblVideos[Title],O19),HYPERLINK("https://www.youtube.com/watch?v="&INDEX(tblVideos[Video ID],O19),IF(INDEX(tblVideos[Status],O19)="Watched","✓ ","▸ ")&INDEX(tblVideos[Title],O19)))) | G19: =IF(P19="","",IF(INDEX(tblVideos[Video ID],P19)="",IF(INDEX(tblVideos[Status],P19)="Watched","✓ ","▸ ")&INDEX(tblVideos[Title],P19),HYPERLINK("https://www.youtube.com/watch?v="&INDEX(tblVideos[Video ID],P19),IF(INDEX(tblVideos[Status],P19)="Watched","✓ ","▸ ")&INDEX(tblVideos[Title],P19)))) | H19: =IF(Q19="","",IF(INDEX(tblVideos[Video ID],Q19)="",IF(INDEX(tblVideos[Status],Q19)="Watched","✓ ","▸ ")&INDEX(tblVideos[Title],Q19),HYPERLINK("https://www.youtube.com/watch?v="&INDEX(tblVideos[Video ID],Q19),IF(INDEX(tblVideos[Status],Q19)="Watched","✓ ","▸ ")&INDEX(tblVideos[Title],Q19)))) | K19: =IF(S16>=3,MATCH(K16*100+3,tblVideos[Cal Key],0),"") | L19: =IF(T16>=3,MATCH(L16*100+3,tblVideos[Cal Key],0),"") | M19: =IF(U16>=3,MATCH(M16*100+3,tblVideos[Cal Key],0),"") | N19: =IF(V16>=3,MATCH(N16*100+3,tblVideos[Cal Key],0),"") | O19: =IF(W16>=3,MATCH(O16*100+3,tblVideos[Cal Key],0),"") | P19: =IF(X16>=3,MATCH(P16*100+3,tblVideos[Cal Key],0),"") | Q19: =IF(Y16>=3,MATCH(Q16*100+3,tblVideos[Cal Key],0),"") | S19: =IF(K19="","",IFERROR(MATCH(INDEX(tblVideos[Channel ID],K19),tblChannels[Channel ID],0),"")) | T19: =IF(L19="","",IFERROR(MATCH(INDEX(tblVideos[Channel ID],L19),tblChannels[Channel ID],0),"")) | U19: =IF(M19="","",IFERROR(MATCH(INDEX(tblVideos[Channel ID],M19),tblChannels[Channel ID],0),"")) | V19: =IF(N19="","",IFERROR(MATCH(INDEX(tblVideos[Channel ID],N19),tblChannels[Channel ID],0),"")) | W19: =IF(O19="","",IFERROR(MATCH(INDEX(tblVideos[Channel ID],O19),tblChannels[Channel ID],0),"")) | X19: =IF(P19="","",IFERROR(MATCH(INDEX(tblVideos[Channel ID],P19),tblChannels[Channel ID],0),"")) | Y19: =IF(Q19="","",IFERROR(MATCH(INDEX(tblVideos[Channel ID],Q19),tblChannels[Channel ID],0),""))
B20: =IF(K20="","",IF(INDEX(tblVideos[Video ID],K20)="",IF(INDEX(tblVideos[Status],K20)="Watched","✓ ","▸ ")&INDEX(tblVideos[Title],K20),HYPERLINK("https://www.youtube.com/watch?v="&INDEX(tblVideos[Video ID],K20),IF(INDEX(tblVideos[Status],K20)="Watched","✓ ","▸ ")&INDEX(tblVideos[Title],K20)))) | C20: =IF(L20="","",IF(INDEX(tblVideos[Video ID],L20)="",IF(INDEX(tblVideos[Status],L20)="Watched","✓ ","▸ ")&INDEX(tblVideos[Title],L20),HYPERLINK("https://www.youtube.com/watch?v="&INDEX(tblVideos[Video ID],L20),IF(INDEX(tblVideos[Status],L20)="Watched","✓ ","▸ ")&INDEX(tblVideos[Title],L20)))) | D20: =IF(M20="","",IF(INDEX(tblVideos[Video ID],M20)="",IF(INDEX(tblVideos[Status],M20)="Watched","✓ ","▸ ")&INDEX(tblVideos[Title],M20),HYPERLINK("https://www.youtube.com/watch?v="&INDEX(tblVideos[Video ID],M20),IF(INDEX(tblVideos[Status],M20)="Watched","✓ ","▸ ")&INDEX(tblVideos[Title],M20)))) | E20: =IF(N20="","",IF(INDEX(tblVideos[Video ID],N20)="",IF(INDEX(tblVideos[Status],N20)="Watched","✓ ","▸ ")&INDEX(tblVideos[Title],N20),HYPERLINK("https://www.youtube.com/watch?v="&INDEX(tblVideos[Video ID],N20),IF(INDEX(tblVideos[Status],N20)="Watched","✓ ","▸ ")&INDEX(tblVideos[Title],N20)))) | F20: =IF(O20="","",IF(INDEX(tblVideos[Video ID],O20)="",IF(INDEX(tblVideos[Status],O20)="Watched","✓ ","▸ ")&INDEX(tblVideos[Title],O20),HYPERLINK("https://www.youtube.com/watch?v="&INDEX(tblVideos[Video ID],O20),IF(INDEX(tblVideos[Status],O20)="Watched","✓ ","▸ ")&INDEX(tblVideos[Title],O20)))) | G20: =IF(P20="","",IF(INDEX(tblVideos[Video ID],P20)="",IF(INDEX(tblVideos[Status],P20)="Watched","✓ ","▸ ")&INDEX(tblVideos[Title],P20),HYPERLINK("https://www.youtube.com/watch?v="&INDEX(tblVideos[Video ID],P20),IF(INDEX(tblVideos[Status],P20)="Watched","✓ ","▸ ")&INDEX(tblVideos[Title],P20)))) | H20: =IF(Q20="","",IF(INDEX(tblVideos[Video ID],Q20)="",IF(INDEX(tblVideos[Status],Q20)="Watched","✓ ","▸ ")&INDEX(tblVideos[Title],Q20),HYPERLINK("https://www.youtube.com/watch?v="&INDEX(tblVideos[Video ID],Q20),IF(INDEX(tblVideos[Status],Q20)="Watched","✓ ","▸ ")&INDEX(tblVideos[Title],Q20)))) | K20: =IF(S16>=4,MATCH(K16*100+4,tblVideos[Cal Key],0),"") | L20: =IF(T16>=4,MATCH(L16*100+4,tblVideos[Cal Key],0),"") | M20: =IF(U16>=4,MATCH(M16*100+4,tblVideos[Cal Key],0),"") | N20: =IF(V16>=4,MATCH(N16*100+4,tblVideos[Cal Key],0),"") | O20: =IF(W16>=4,MATCH(O16*100+4,tblVideos[Cal Key],0),"") | P20: =IF(X16>=4,MATCH(P16*100+4,tblVideos[Cal Key],0),"") | Q20: =IF(Y16>=4,MATCH(Q16*100+4,tblVideos[Cal Key],0),"") | S20: =IF(K20="","",IFERROR(MATCH(INDEX(tblVideos[Channel ID],K20),tblChannels[Channel ID],0),"")) | T20: =IF(L20="","",IFERROR(MATCH(INDEX(tblVideos[Channel ID],L20),tblChannels[Channel ID],0),"")) | U20: =IF(M20="","",IFERROR(MATCH(INDEX(tblVideos[Channel ID],M20),tblChannels[Channel ID],0),"")) | V20: =IF(N20="","",IFERROR(MATCH(INDEX(tblVideos[Channel ID],N20),tblChannels[Channel ID],0),"")) | W20: =IF(O20="","",IFERROR(MATCH(INDEX(tblVideos[Channel ID],O20),tblChannels[Channel ID],0),"")) | X20: =IF(P20="","",IFERROR(MATCH(INDEX(tblVideos[Channel ID],P20),tblChannels[Channel ID],0),"")) | Y20: =IF(Q20="","",IFERROR(MATCH(INDEX(tblVideos[Channel ID],Q20),tblChannels[Channel ID],0),""))
B21: =IF(K21="","",IF(INDEX(tblVideos[Video ID],K21)="",IF(INDEX(tblVideos[Status],K21)="Watched","✓ ","▸ ")&INDEX(tblVideos[Title],K21),HYPERLINK("https://www.youtube.com/watch?v="&INDEX(tblVideos[Video ID],K21),IF(INDEX(tblVideos[Status],K21)="Watched","✓ ","▸ ")&INDEX(tblVideos[Title],K21)))) | C21: =IF(L21="","",IF(INDEX(tblVideos[Video ID],L21)="",IF(INDEX(tblVideos[Status],L21)="Watched","✓ ","▸ ")&INDEX(tblVideos[Title],L21),HYPERLINK("https://www.youtube.com/watch?v="&INDEX(tblVideos[Video ID],L21),IF(INDEX(tblVideos[Status],L21)="Watched","✓ ","▸ ")&INDEX(tblVideos[Title],L21)))) | D21: =IF(M21="","",IF(INDEX(tblVideos[Video ID],M21)="",IF(INDEX(tblVideos[Status],M21)="Watched","✓ ","▸ ")&INDEX(tblVideos[Title],M21),HYPERLINK("https://www.youtube.com/watch?v="&INDEX(tblVideos[Video ID],M21),IF(INDEX(tblVideos[Status],M21)="Watched","✓ ","▸ ")&INDEX(tblVideos[Title],M21)))) | E21: =IF(N21="","",IF(INDEX(tblVideos[Video ID],N21)="",IF(INDEX(tblVideos[Status],N21)="Watched","✓ ","▸ ")&INDEX(tblVideos[Title],N21),HYPERLINK("https://www.youtube.com/watch?v="&INDEX(tblVideos[Video ID],N21),IF(INDEX(tblVideos[Status],N21)="Watched","✓ ","▸ ")&INDEX(tblVideos[Title],N21)))) | F21: =IF(O21="","",IF(INDEX(tblVideos[Video ID],O21)="",IF(INDEX(tblVideos[Status],O21)="Watched","✓ ","▸ ")&INDEX(tblVideos[Title],O21),HYPERLINK("https://www.youtube.com/watch?v="&INDEX(tblVideos[Video ID],O21),IF(INDEX(tblVideos[Status],O21)="Watched","✓ ","▸ ")&INDEX(tblVideos[Title],O21)))) | G21: =IF(P21="","",IF(INDEX(tblVideos[Video ID],P21)="",IF(INDEX(tblVideos[Status],P21)="Watched","✓ ","▸ ")&INDEX(tblVideos[Title],P21),HYPERLINK("https://www.youtube.com/watch?v="&INDEX(tblVideos[Video ID],P21),IF(INDEX(tblVideos[Status],P21)="Watched","✓ ","▸ ")&INDEX(tblVideos[Title],P21)))) | H21: =IF(Q21="","",IF(INDEX(tblVideos[Video ID],Q21)="",IF(INDEX(tblVideos[Status],Q21)="Watched","✓ ","▸ ")&INDEX(tblVideos[Title],Q21),HYPERLINK("https://www.youtube.com/watch?v="&INDEX(tblVideos[Video ID],Q21),IF(INDEX(tblVideos[Status],Q21)="Watched","✓ ","▸ ")&INDEX(tblVideos[Title],Q21)))) | K21: =IF(S16>=5,MATCH(K16*100+5,tblVideos[Cal Key],0),"") | L21: =IF(T16>=5,MATCH(L16*100+5,tblVideos[Cal Key],0),"") | M21: =IF(U16>=5,MATCH(M16*100+5,tblVideos[Cal Key],0),"") | N21: =IF(V16>=5,MATCH(N16*100+5,tblVideos[Cal Key],0),"") | O21: =IF(W16>=5,MATCH(O16*100+5,tblVideos[Cal Key],0),"") | P21: =IF(X16>=5,MATCH(P16*100+5,tblVideos[Cal Key],0),"") | Q21: =IF(Y16>=5,MATCH(Q16*100+5,tblVideos[Cal Key],0),"") | S21: =IF(K21="","",IFERROR(MATCH(INDEX(tblVideos[Channel ID],K21),tblChannels[Channel ID],0),"")) | T21: =IF(L21="","",IFERROR(MATCH(INDEX(tblVideos[Channel ID],L21),tblChannels[Channel ID],0),"")) | U21: =IF(M21="","",IFERROR(MATCH(INDEX(tblVideos[Channel ID],M21),tblChannels[Channel ID],0),"")) | V21: =IF(N21="","",IFERROR(MATCH(INDEX(tblVideos[Channel ID],N21),tblChannels[Channel ID],0),"")) | W21: =IF(O21="","",IFERROR(MATCH(INDEX(tblVideos[Channel ID],O21),tblChannels[Channel ID],0),"")) | X21: =IF(P21="","",IFERROR(MATCH(INDEX(tblVideos[Channel ID],P21),tblChannels[Channel ID],0),"")) | Y21: =IF(Q21="","",IFERROR(MATCH(INDEX(tblVideos[Channel ID],Q21),tblChannels[Channel ID],0),""))
B22: =IF(MONTH(K22)=MONTH($K$2),DAY(K22)&IF(S22>0," · "&S22&IF(S22=1," video"," videos")&" · "&IF(ROUND((AA22)*1440,0)<60,ROUND((AA22)*1440,0)&" m",IF(MOD(ROUND((AA22)*1440,0),60)=0,INT(ROUND((AA22)*1440,0)/60)&" h",INT(ROUND((AA22)*1440,0)/60)&" h "&MOD(ROUND((AA22)*1440,0),60)&" m"))&IF(S22>5," (+"&(S22-5)&" more)",""),""),"") | C22: =IF(MONTH(L22)=MONTH($K$2),DAY(L22)&IF(T22>0," · "&T22&IF(T22=1," video"," videos")&" · "&IF(ROUND((AB22)*1440,0)<60,ROUND((AB22)*1440,0)&" m",IF(MOD(ROUND((AB22)*1440,0),60)=0,INT(ROUND((AB22)*1440,0)/60)&" h",INT(ROUND((AB22)*1440,0)/60)&" h "&MOD(ROUND((AB22)*1440,0),60)&" m"))&IF(T22>5," (+"&(T22-5)&" more)",""),""),"") | D22: =IF(MONTH(M22)=MONTH($K$2),DAY(M22)&IF(U22>0," · "&U22&IF(U22=1," video"," videos")&" · "&IF(ROUND((AC22)*1440,0)<60,ROUND((AC22)*1440,0)&" m",IF(MOD(ROUND((AC22)*1440,0),60)=0,INT(ROUND((AC22)*1440,0)/60)&" h",INT(ROUND((AC22)*1440,0)/60)&" h "&MOD(ROUND((AC22)*1440,0),60)&" m"))&IF(U22>5," (+"&(U22-5)&" more)",""),""),"") | E22: =IF(MONTH(N22)=MONTH($K$2),DAY(N22)&IF(V22>0," · "&V22&IF(V22=1," video"," videos")&" · "&IF(ROUND((AD22)*1440,0)<60,ROUND((AD22)*1440,0)&" m",IF(MOD(ROUND((AD22)*1440,0),60)=0,INT(ROUND((AD22)*1440,0)/60)&" h",INT(ROUND((AD22)*1440,0)/60)&" h "&MOD(ROUND((AD22)*1440,0),60)&" m"))&IF(V22>5," (+"&(V22-5)&" more)",""),""),"") | F22: =IF(MONTH(O22)=MONTH($K$2),DAY(O22)&IF(W22>0," · "&W22&IF(W22=1," video"," videos")&" · "&IF(ROUND((AE22)*1440,0)<60,ROUND((AE22)*1440,0)&" m",IF(MOD(ROUND((AE22)*1440,0),60)=0,INT(ROUND((AE22)*1440,0)/60)&" h",INT(ROUND((AE22)*1440,0)/60)&" h "&MOD(ROUND((AE22)*1440,0),60)&" m"))&IF(W22>5," (+"&(W22-5)&" more)",""),""),"") | G22: =IF(MONTH(P22)=MONTH($K$2),DAY(P22)&IF(X22>0," · "&X22&IF(X22=1," video"," videos")&" · "&IF(ROUND((AF22)*1440,0)<60,ROUND((AF22)*1440,0)&" m",IF(MOD(ROUND((AF22)*1440,0),60)=0,INT(ROUND((AF22)*1440,0)/60)&" h",INT(ROUND((AF22)*1440,0)/60)&" h "&MOD(ROUND((AF22)*1440,0),60)&" m"))&IF(X22>5," (+"&(X22-5)&" more)",""),""),"") | H22: =IF(MONTH(Q22)=MONTH($K$2),DAY(Q22)&IF(Y22>0," · "&Y22&IF(Y22=1," video"," videos")&" · "&IF(ROUND((AG22)*1440,0)<60,ROUND((AG22)*1440,0)&" m",IF(MOD(ROUND((AG22)*1440,0),60)=0,INT(ROUND((AG22)*1440,0)/60)&" h",INT(ROUND((AG22)*1440,0)/60)&" h "&MOD(ROUND((AG22)*1440,0),60)&" m"))&IF(Y22>5," (+"&(Y22-5)&" more)",""),""),"") | K22: =$K$3+14 | L22: =$K$3+15 | M22: =$K$3+16 | N22: =$K$3+17 | O22: =$K$3+18 | P22: =$K$3+19 | Q22: =$K$3+20 | S22: =IF(MONTH(K22)=MONTH($K$2),COUNTIFS(tblVideos[Day],K22,tblVideos[Channel ID],$K$4),0) | T22: =IF(MONTH(L22)=MONTH($K$2),COUNTIFS(tblVideos[Day],L22,tblVideos[Channel ID],$K$4),0) | U22: =IF(MONTH(M22)=MONTH($K$2),COUNTIFS(tblVideos[Day],M22,tblVideos[Channel ID],$K$4),0) | V22: =IF(MONTH(N22)=MONTH($K$2),COUNTIFS(tblVideos[Day],N22,tblVideos[Channel ID],$K$4),0) | W22: =IF(MONTH(O22)=MONTH($K$2),COUNTIFS(tblVideos[Day],O22,tblVideos[Channel ID],$K$4),0) | X22: =IF(MONTH(P22)=MONTH($K$2),COUNTIFS(tblVideos[Day],P22,tblVideos[Channel ID],$K$4),0) | Y22: =IF(MONTH(Q22)=MONTH($K$2),COUNTIFS(tblVideos[Day],Q22,tblVideos[Channel ID],$K$4),0) | AA22: =IF(S22>0,SUMIFS(tblVideos[Length],tblVideos[Day],K22,tblVideos[Channel ID],$K$4),0) | AB22: =IF(T22>0,SUMIFS(tblVideos[Length],tblVideos[Day],L22,tblVideos[Channel ID],$K$4),0) | AC22: =IF(U22>0,SUMIFS(tblVideos[Length],tblVideos[Day],M22,tblVideos[Channel ID],$K$4),0) | AD22: =IF(V22>0,SUMIFS(tblVideos[Length],tblVideos[Day],N22,tblVideos[Channel ID],$K$4),0) | AE22: =IF(W22>0,SUMIFS(tblVideos[Length],tblVideos[Day],O22,tblVideos[Channel ID],$K$4),0) | AF22: =IF(X22>0,SUMIFS(tblVideos[Length],tblVideos[Day],P22,tblVideos[Channel ID],$K$4),0) | AG22: =IF(Y22>0,SUMIFS(tblVideos[Length],tblVideos[Day],Q22,tblVideos[Channel ID],$K$4),0)
B23: =IF(K23="","",IF(INDEX(tblVideos[Video ID],K23)="",IF(INDEX(tblVideos[Status],K23)="Watched","✓ ","▸ ")&INDEX(tblVideos[Title],K23),HYPERLINK("https://www.youtube.com/watch?v="&INDEX(tblVideos[Video ID],K23),IF(INDEX(tblVideos[Status],K23)="Watched","✓ ","▸ ")&INDEX(tblVideos[Title],K23)))) | C23: =IF(L23="","",IF(INDEX(tblVideos[Video ID],L23)="",IF(INDEX(tblVideos[Status],L23)="Watched","✓ ","▸ ")&INDEX(tblVideos[Title],L23),HYPERLINK("https://www.youtube.com/watch?v="&INDEX(tblVideos[Video ID],L23),IF(INDEX(tblVideos[Status],L23)="Watched","✓ ","▸ ")&INDEX(tblVideos[Title],L23)))) | D23: =IF(M23="","",IF(INDEX(tblVideos[Video ID],M23)="",IF(INDEX(tblVideos[Status],M23)="Watched","✓ ","▸ ")&INDEX(tblVideos[Title],M23),HYPERLINK("https://www.youtube.com/watch?v="&INDEX(tblVideos[Video ID],M23),IF(INDEX(tblVideos[Status],M23)="Watched","✓ ","▸ ")&INDEX(tblVideos[Title],M23)))) | E23: =IF(N23="","",IF(INDEX(tblVideos[Video ID],N23)="",IF(INDEX(tblVideos[Status],N23)="Watched","✓ ","▸ ")&INDEX(tblVideos[Title],N23),HYPERLINK("https://www.youtube.com/watch?v="&INDEX(tblVideos[Video ID],N23),IF(INDEX(tblVideos[Status],N23)="Watched","✓ ","▸ ")&INDEX(tblVideos[Title],N23)))) | F23: =IF(O23="","",IF(INDEX(tblVideos[Video ID],O23)="",IF(INDEX(tblVideos[Status],O23)="Watched","✓ ","▸ ")&INDEX(tblVideos[Title],O23),HYPERLINK("https://www.youtube.com/watch?v="&INDEX(tblVideos[Video ID],O23),IF(INDEX(tblVideos[Status],O23)="Watched","✓ ","▸ ")&INDEX(tblVideos[Title],O23)))) | G23: =IF(P23="","",IF(INDEX(tblVideos[Video ID],P23)="",IF(INDEX(tblVideos[Status],P23)="Watched","✓ ","▸ ")&INDEX(tblVideos[Title],P23),HYPERLINK("https://www.youtube.com/watch?v="&INDEX(tblVideos[Video ID],P23),IF(INDEX(tblVideos[Status],P23)="Watched","✓ ","▸ ")&INDEX(tblVideos[Title],P23)))) | H23: =IF(Q23="","",IF(INDEX(tblVideos[Video ID],Q23)="",IF(INDEX(tblVideos[Status],Q23)="Watched","✓ ","▸ ")&INDEX(tblVideos[Title],Q23),HYPERLINK("https://www.youtube.com/watch?v="&INDEX(tblVideos[Video ID],Q23),IF(INDEX(tblVideos[Status],Q23)="Watched","✓ ","▸ ")&INDEX(tblVideos[Title],Q23)))) | K23: =IF(S22>=1,MATCH(K22*100+1,tblVideos[Cal Key],0),"") | L23: =IF(T22>=1,MATCH(L22*100+1,tblVideos[Cal Key],0),"") | M23: =IF(U22>=1,MATCH(M22*100+1,tblVideos[Cal Key],0),"") | N23: =IF(V22>=1,MATCH(N22*100+1,tblVideos[Cal Key],0),"") | O23: =IF(W22>=1,MATCH(O22*100+1,tblVideos[Cal Key],0),"") | P23: =IF(X22>=1,MATCH(P22*100+1,tblVideos[Cal Key],0),"") | Q23: =IF(Y22>=1,MATCH(Q22*100+1,tblVideos[Cal Key],0),"") | S23: =IF(K23="","",IFERROR(MATCH(INDEX(tblVideos[Channel ID],K23),tblChannels[Channel ID],0),"")) | T23: =IF(L23="","",IFERROR(MATCH(INDEX(tblVideos[Channel ID],L23),tblChannels[Channel ID],0),"")) | U23: =IF(M23="","",IFERROR(MATCH(INDEX(tblVideos[Channel ID],M23),tblChannels[Channel ID],0),"")) | V23: =IF(N23="","",IFERROR(MATCH(INDEX(tblVideos[Channel ID],N23),tblChannels[Channel ID],0),"")) | W23: =IF(O23="","",IFERROR(MATCH(INDEX(tblVideos[Channel ID],O23),tblChannels[Channel ID],0),"")) | X23: =IF(P23="","",IFERROR(MATCH(INDEX(tblVideos[Channel ID],P23),tblChannels[Channel ID],0),"")) | Y23: =IF(Q23="","",IFERROR(MATCH(INDEX(tblVideos[Channel ID],Q23),tblChannels[Channel ID],0),""))
B24: =IF(K24="","",IF(INDEX(tblVideos[Video ID],K24)="",IF(INDEX(tblVideos[Status],K24)="Watched","✓ ","▸ ")&INDEX(tblVideos[Title],K24),HYPERLINK("https://www.youtube.com/watch?v="&INDEX(tblVideos[Video ID],K24),IF(INDEX(tblVideos[Status],K24)="Watched","✓ ","▸ ")&INDEX(tblVideos[Title],K24)))) | C24: =IF(L24="","",IF(INDEX(tblVideos[Video ID],L24)="",IF(INDEX(tblVideos[Status],L24)="Watched","✓ ","▸ ")&INDEX(tblVideos[Title],L24),HYPERLINK("https://www.youtube.com/watch?v="&INDEX(tblVideos[Video ID],L24),IF(INDEX(tblVideos[Status],L24)="Watched","✓ ","▸ ")&INDEX(tblVideos[Title],L24)))) | D24: =IF(M24="","",IF(INDEX(tblVideos[Video ID],M24)="",IF(INDEX(tblVideos[Status],M24)="Watched","✓ ","▸ ")&INDEX(tblVideos[Title],M24),HYPERLINK("https://www.youtube.com/watch?v="&INDEX(tblVideos[Video ID],M24),IF(INDEX(tblVideos[Status],M24)="Watched","✓ ","▸ ")&INDEX(tblVideos[Title],M24)))) | E24: =IF(N24="","",IF(INDEX(tblVideos[Video ID],N24)="",IF(INDEX(tblVideos[Status],N24)="Watched","✓ ","▸ ")&INDEX(tblVideos[Title],N24),HYPERLINK("https://www.youtube.com/watch?v="&INDEX(tblVideos[Video ID],N24),IF(INDEX(tblVideos[Status],N24)="Watched","✓ ","▸ ")&INDEX(tblVideos[Title],N24)))) | F24: =IF(O24="","",IF(INDEX(tblVideos[Video ID],O24)="",IF(INDEX(tblVideos[Status],O24)="Watched","✓ ","▸ ")&INDEX(tblVideos[Title],O24),HYPERLINK("https://www.youtube.com/watch?v="&INDEX(tblVideos[Video ID],O24),IF(INDEX(tblVideos[Status],O24)="Watched","✓ ","▸ ")&INDEX(tblVideos[Title],O24)))) | G24: =IF(P24="","",IF(INDEX(tblVideos[Video ID],P24)="",IF(INDEX(tblVideos[Status],P24)="Watched","✓ ","▸ ")&INDEX(tblVideos[Title],P24),HYPERLINK("https://www.youtube.com/watch?v="&INDEX(tblVideos[Video ID],P24),IF(INDEX(tblVideos[Status],P24)="Watched","✓ ","▸ ")&INDEX(tblVideos[Title],P24)))) | H24: =IF(Q24="","",IF(INDEX(tblVideos[Video ID],Q24)="",IF(INDEX(tblVideos[Status],Q24)="Watched","✓ ","▸ ")&INDEX(tblVideos[Title],Q24),HYPERLINK("https://www.youtube.com/watch?v="&INDEX(tblVideos[Video ID],Q24),IF(INDEX(tblVideos[Status],Q24)="Watched","✓ ","▸ ")&INDEX(tblVideos[Title],Q24)))) | K24: =IF(S22>=2,MATCH(K22*100+2,tblVideos[Cal Key],0),"") | L24: =IF(T22>=2,MATCH(L22*100+2,tblVideos[Cal Key],0),"") | M24: =IF(U22>=2,MATCH(M22*100+2,tblVideos[Cal Key],0),"") | N24: =IF(V22>=2,MATCH(N22*100+2,tblVideos[Cal Key],0),"") | O24: =IF(W22>=2,MATCH(O22*100+2,tblVideos[Cal Key],0),"") | P24: =IF(X22>=2,MATCH(P22*100+2,tblVideos[Cal Key],0),"") | Q24: =IF(Y22>=2,MATCH(Q22*100+2,tblVideos[Cal Key],0),"") | S24: =IF(K24="","",IFERROR(MATCH(INDEX(tblVideos[Channel ID],K24),tblChannels[Channel ID],0),"")) | T24: =IF(L24="","",IFERROR(MATCH(INDEX(tblVideos[Channel ID],L24),tblChannels[Channel ID],0),"")) | U24: =IF(M24="","",IFERROR(MATCH(INDEX(tblVideos[Channel ID],M24),tblChannels[Channel ID],0),"")) | V24: =IF(N24="","",IFERROR(MATCH(INDEX(tblVideos[Channel ID],N24),tblChannels[Channel ID],0),"")) | W24: =IF(O24="","",IFERROR(MATCH(INDEX(tblVideos[Channel ID],O24),tblChannels[Channel ID],0),"")) | X24: =IF(P24="","",IFERROR(MATCH(INDEX(tblVideos[Channel ID],P24),tblChannels[Channel ID],0),"")) | Y24: =IF(Q24="","",IFERROR(MATCH(INDEX(tblVideos[Channel ID],Q24),tblChannels[Channel ID],0),""))
B25: =IF(K25="","",IF(INDEX(tblVideos[Video ID],K25)="",IF(INDEX(tblVideos[Status],K25)="Watched","✓ ","▸ ")&INDEX(tblVideos[Title],K25),HYPERLINK("https://www.youtube.com/watch?v="&INDEX(tblVideos[Video ID],K25),IF(INDEX(tblVideos[Status],K25)="Watched","✓ ","▸ ")&INDEX(tblVideos[Title],K25)))) | C25: =IF(L25="","",IF(INDEX(tblVideos[Video ID],L25)="",IF(INDEX(tblVideos[Status],L25)="Watched","✓ ","▸ ")&INDEX(tblVideos[Title],L25),HYPERLINK("https://www.youtube.com/watch?v="&INDEX(tblVideos[Video ID],L25),IF(INDEX(tblVideos[Status],L25)="Watched","✓ ","▸ ")&INDEX(tblVideos[Title],L25)))) | D25: =IF(M25="","",IF(INDEX(tblVideos[Video ID],M25)="",IF(INDEX(tblVideos[Status],M25)="Watched","✓ ","▸ ")&INDEX(tblVideos[Title],M25),HYPERLINK("https://www.youtube.com/watch?v="&INDEX(tblVideos[Video ID],M25),IF(INDEX(tblVideos[Status],M25)="Watched","✓ ","▸ ")&INDEX(tblVideos[Title],M25)))) | E25: =IF(N25="","",IF(INDEX(tblVideos[Video ID],N25)="",IF(INDEX(tblVideos[Status],N25)="Watched","✓ ","▸ ")&INDEX(tblVideos[Title],N25),HYPERLINK("https://www.youtube.com/watch?v="&INDEX(tblVideos[Video ID],N25),IF(INDEX(tblVideos[Status],N25)="Watched","✓ ","▸ ")&INDEX(tblVideos[Title],N25)))) | F25: =IF(O25="","",IF(INDEX(tblVideos[Video ID],O25)="",IF(INDEX(tblVideos[Status],O25)="Watched","✓ ","▸ ")&INDEX(tblVideos[Title],O25),HYPERLINK("https://www.youtube.com/watch?v="&INDEX(tblVideos[Video ID],O25),IF(INDEX(tblVideos[Status],O25)="Watched","✓ ","▸ ")&INDEX(tblVideos[Title],O25)))) | G25: =IF(P25="","",IF(INDEX(tblVideos[Video ID],P25)="",IF(INDEX(tblVideos[Status],P25)="Watched","✓ ","▸ ")&INDEX(tblVideos[Title],P25),HYPERLINK("https://www.youtube.com/watch?v="&INDEX(tblVideos[Video ID],P25),IF(INDEX(tblVideos[Status],P25)="Watched","✓ ","▸ ")&INDEX(tblVideos[Title],P25)))) | H25: =IF(Q25="","",IF(INDEX(tblVideos[Video ID],Q25)="",IF(INDEX(tblVideos[Status],Q25)="Watched","✓ ","▸ ")&INDEX(tblVideos[Title],Q25),HYPERLINK("https://www.youtube.com/watch?v="&INDEX(tblVideos[Video ID],Q25),IF(INDEX(tblVideos[Status],Q25)="Watched","✓ ","▸ ")&INDEX(tblVideos[Title],Q25)))) | K25: =IF(S22>=3,MATCH(K22*100+3,tblVideos[Cal Key],0),"") | L25: =IF(T22>=3,MATCH(L22*100+3,tblVideos[Cal Key],0),"") | M25: =IF(U22>=3,MATCH(M22*100+3,tblVideos[Cal Key],0),"") | N25: =IF(V22>=3,MATCH(N22*100+3,tblVideos[Cal Key],0),"") | O25: =IF(W22>=3,MATCH(O22*100+3,tblVideos[Cal Key],0),"") | P25: =IF(X22>=3,MATCH(P22*100+3,tblVideos[Cal Key],0),"") | Q25: =IF(Y22>=3,MATCH(Q22*100+3,tblVideos[Cal Key],0),"") | S25: =IF(K25="","",IFERROR(MATCH(INDEX(tblVideos[Channel ID],K25),tblChannels[Channel ID],0),"")) | T25: =IF(L25="","",IFERROR(MATCH(INDEX(tblVideos[Channel ID],L25),tblChannels[Channel ID],0),"")) | U25: =IF(M25="","",IFERROR(MATCH(INDEX(tblVideos[Channel ID],M25),tblChannels[Channel ID],0),"")) | V25: =IF(N25="","",IFERROR(MATCH(INDEX(tblVideos[Channel ID],N25),tblChannels[Channel ID],0),"")) | W25: =IF(O25="","",IFERROR(MATCH(INDEX(tblVideos[Channel ID],O25),tblChannels[Channel ID],0),"")) | X25: =IF(P25="","",IFERROR(MATCH(INDEX(tblVideos[Channel ID],P25),tblChannels[Channel ID],0),"")) | Y25: =IF(Q25="","",IFERROR(MATCH(INDEX(tblVideos[Channel ID],Q25),tblChannels[Channel ID],0),""))
